Workbook

Sheet visão geral
B1: PAPEL | C1: SEGUIMENTO | D1: ATIVO | E1: PREÇO ATUAL | F1: QTD | G1: POSIÇÃO | H1: LUCRO | I1: VALORIZ. | J1: PM DESC. | K1: P. MÉDIO | L1: D.Y ON COST | M1: PESO | N1: P.IDEAL | O1: PL TOTAL | P1: =SUM(G2:G18) -> 352031.05
A2: 1 | B2: VALE3 | C2: MINÉRIO | D2: AÇÃO | E2: 26.25 | F2: =BBAS3.!E2 -> 830 | G2: =F2*E2 -> 21787.5 | H2: =G2-VALE3!D2 -> 487.5 | I2: =H2/VALE3!D2 -> 0.022887324 | J2: =K2/(1+L2) -> 70.503496 | K2: =VALE3!C2 -> 71 | L2: =M23/(K2*F2) -> 0.0070422535 | M2: =G2/P1 -> 0.061890847 | N2: 0.1 | O2: VALOR INVESTIDO | P2: =VALE3!D2+TAEE11!D2+ITSA4!D2+KLBN11!D2+PETR4.!D2+BBAS3.!D2+BRBl11!D2+TAEE11!D2+VALE3!D2+BBDC4!D2+MXRF11!D2+ITSA4!D2+CMIG4!D2+FIQE3!D2+XPML11!D2+XPLG11!D2 -> 1058564.4
A3: 2 | B3: TAEE11 | C3: ELÉTRICO | D3: AÇÃO | E3: =IFERROR(__xludf.DUMMYFUNCTION("GOOGLEFINANCE(B3)"),40.6) -> 40.6 | F3: =TAEE11!C5 -> 650 | G3: =F3*E3 -> 26390 | H3: =G3-TAEE11!F2 -> 8231.25 | I3: =H3/TAEE11!D2 -> 0.30151099 | J3: =K3/(1+L3) -> 19.973174 | K3: =TAEE11!C2 -> 42 | L3: =M24/(K3*F3) -> 1.1028205 | M3: =G2/P1 -> 0.061890847 | N3: 0.05 | O3: TOTAL AÇÕES | P3: =SUM(G2:G11) -> 344222.25
A4: 3 | B4: PETR4 | C4: MINÉRIO Gas & ENERGIA | D4: AÇÃO | E4: =IFERROR(__xludf.DUMMYFUNCTION("GOOGLEFINANCE(B4)"),31.08) -> 31.08 | F4: =ITSA4!E2 -> 1450 | G4: =F4*E4 -> 45066 | H4: =G4-PETR4.!D2 -> 34497 | I4: =H4/PETR4.!D2 -> 3.2639796 | J4: =K4/(1+L4) -> 34.257086 | K4: =PETR4.!C2 -> 35.23 | L4: =M25/(K4*F4) -> 0.028400364 | M4: =G4/P1 -> 0.12801712 | N4: 0.07 | O4: TOTAL FIIS | P4: =SUM(G13:G18) -> 7808.8
A5: 4 | B5: BBAS3 | C5: BANCO | D5: AÇÃO | E5: 22 | F5: =KLBN11!E2 -> 5000 | G5: =F5*E5 -> 110000 | H5: =G5-BBAS3.!D2 -> 91740 | I5: =H5/BBAS3.!D2 -> 5.0240964 | J5: =K5/(1+L5) -> 21.91914 | K5: =BBAS3.!C2 -> 22 | L5: =M26/(K5*F5) -> 0.003689 | M5: =G5/P1 -> 0.31247244 | N5: 0.06 | O5: LUCRO | P5: =P1-P2 -> -706533.3
A6: 5 | B6: BRBI11 | C6: ROUDING | D6: AÇÃO | E6: =IFERROR(__xludf.DUMMYFUNCTION("GOOGLEFINANCE(B6)"),18.38) -> 18.38 | F6: =PETR4.!E2 -> 300 | G6: =F6*E6 -> 5514 | H6: =G6-BRBl11!D2 -> -12746 | I6: =H6/BRBl11!D2 -> -0.69802848 | J6: =K6/(1+L6) -> 21.312197 | K6: =BRBl11!C2 -> 22 | L6: =M27/(K6*F6) -> 0.032272727 | M6: =G6/P1 -> 0.015663391 | N6: 0.05 | O6: VALORIZAÇÃO | P6: =P5/P2 -> -0.66744483 | Q6: PESO | R6: PESO IDEAL
A7: 6 | B7: BBDC4 | C7: BANCOS | D7: AÇÃO | E7: =IFERROR(__xludf.DUMMYFUNCTION("GOOGLEFINANCE(B7)"),18.25) -> 18.25 | F7: =BBDC4!C5 -> 995 | G7: =F7*E7 -> 18158.75 | H7: =G7-BBDC4!F2 -> -3628.75 | I7: =H7/BBDC4!D2 -> -0.19983479 | J7: =K7/(1+L7) -> 18.003378 | K7: =BBDC4!C2 -> 18.25 | L7: =M28/(K7*F7) -> 0.01369863 | M7: =G7/P1 -> 0.051582808 | N7: 0.05 | O7: RENDA FIXA | P7: 85000 | Q7: =P7/P11 -> 0.183573 | R7: 0.5
A8: 7 | B8: ITSA4 | C8: BANCOS | D8: AÇÃO | E8: =IFERROR(__xludf.DUMMYFUNCTION("GOOGLEFINANCE(B8)"),11.53) -> 11.53 | F8: =ITSA4!C5 -> 1450 | G8: =F8*E8 -> 16718.5 | H8: =G8-ITSA4!F2 -> -28347.5 | I8: =H8/ITSA4!D2 -> -1.3964286 | J8: =K8/(1+L8) -> 13.688799 | K8: =ITSA4!C2 -> 14 | L8: =M29/(K8*F8) -> 0.02273399 | M8: =G8/P1 -> 0.047491549 | N8: 0.1 | O8: RENDA VARIÁVEL | P8: =P1 -> 352031.05 | Q8: =P8/P11 -> 0.76027526 | R8: 0.32
A9: 8 | B9: CMIG4 | C9: ENERGIA | D9: AÇÃO | E9: =IFERROR(__xludf.DUMMYFUNCTION("GOOGLEFINANCE(B9)"),10.97) -> 10.97 | F9: =TAEE11!E2 -> 650 | G9: =F9*E9 -> 7130.5 | H9: =G9-CMIG4!D2 -> -792079.1 | I9: =H9/CMIG4!D2 -> -0.99107806 | J9: =K9/(1+L9) -> 10.532326 | K9: =CMIG4!C2 -> 11.2 | L9: =M30/(K9*F9) -> 0.063392857 | M9: =G9/P1 -> 0.020255316 | N9: 0.1 | O9: INTERNACIONAL | P9: 22000 | Q9: =P9/P11 -> 0.047513012 | R9: 0.15
A10: 9 | B10: FIQE3 | C10: TECNÓLOGO | D10: AÇÃO | E10: =IFERROR(__xludf.DUMMYFUNCTION("GOOGLEFINANCE(B10)"),5.69) -> 5.69 | F10: =VALE3!E2 -> 300 | G10: =F10*E10 -> 1707 | H10: =G10-FIQE3!D2 -> -29709 | I10: =H10/FIQE3!D2 -> -0.94566463 | J10: =K10/(1+L10) -> 2.5441696 | K10: =FIQE3!C2 -> 6 | L10: =M31/(K10*F10) -> 1.3583333 | M10: =G10/P1 -> 0.0048490041 | N10: 0.05 | O10: CRIPTO | P10: 4000 | Q10: =P10/P11 -> 0.0086387295 | R10: 0.03
A11: 10 | B11: KLBN11 | C11: INDUSTRIAL Cel | D11: AÇÃO | E11: =IFERROR(__xludf.DUMMYFUNCTION("GOOGLEFINANCE(B11)"),18.35) -> 18.35 | F11: =KLBN11!E2 -> 5000 | G11: =F11*E11 -> 91750 | H11: =G11-KLBN11!D2 -> 71750 | I11: =H11/KLBN11!D2 -> 3.5875 | J11: =K11/(1+L11) -> 1.4368074 | K11: =KLBN11!C2 -> 4 | L11: =M32/(K11*F11) -> 1.78395 | M11: =G11/P1 -> 0.26063042 | N11: 0.07 | O11: TOTAL | P11: =P7+P8+P9+P10 -> 463031.05 | Q11: =Q7+Q8+Q9+Q10 -> 1 | R11: =R7+R8+R9+R10 -> 1
M12: 0.65 | N12: =SUM(N2:N11) -> 0.7
A13: 1 | B13: MXRF11 | C13: PAPEL | D13: FII | E13: =IFERROR(__xludf.DUMMYFUNCTION("GOOGLEFINANCE(B13)"),9.47) -> 9.47 | F13: =MXRF11!E2 -> 298 | G13: =F13*E13 -> 2822.06 | H13: =G13-MXRF11!D2 -> 140.06 | I13: =H13/MXRF11!D2 -> 0.052222222 | J13: =K13/(1+L13) -> 8.7947883 | K13: =MXRF11!C2 -> 9 | L13: =M34/(K13*F13) -> 0.023333333 | M13: 0.09 | N13: 0.05
A14: 2 | B14: BRCR11 | C14: LAJE | D14: FII | E14: =IFERROR(__xludf.DUMMYFUNCTION("GOOGLEFINANCE(B14)"),44.55) -> 44.55 | F14: =BRCR11!E2 -> 13 | G14: =F14*E14 -> 579.15 | H14: =G14-BRCR11!D2 -> -70.85 | I14: =H14/BRCR11!D2 -> -0.109 | J14: =K14/(1+L14) -> 49.593335 | K14: =BRCR11!C2 -> 50 | L14: =M35/(K14*F14) -> 0.0082 | M14: 0.03 | N14: 0.04
A15: 3 | B15: XPLG11 | C15: LOGÍSTICO | D15: FII | E15: =IFERROR(__xludf.DUMMYFUNCTION("GOOGLEFINANCE(B15)"),103.13) -> 103.13 | F15: =XPLG11!E2 -> 19 | G15: =F15*E15 -> 1959.47 | H15: =G15-XPLG11!D2 -> 154.47 | I15: =H15/XPLG11!D2 -> 0.085578947 | J15: =K15/(1+L15) -> 94.631958 | K15: =XPLG11!C2 -> 95 | L15: =M36/(K15*F15) -> 0.0038891967 | M15: 0.08 | N15: 0.06
A16: 4 | B16: XPML11 | C16: SHOPPING | D16: FII | E16: =IFERROR(__xludf.DUMMYFUNCTION("GOOGLEFINANCE(B16)"),106.26) -> 106.26 | F16: =XPML11!E2 -> 4 | G16: =F16*E16 -> 425.04 | H16: =G16-XPML11!D2 -> 21.04 | I16: =H16/XPML11!D2 -> 0.052079208 | J16: =K16/(1+L16) -> 99.212216 | K16: =XPML11!C2 -> 101 | L16: =M37/(K16*F16) -> 0.018019802 | M16: 0.03 | N16: 0.05
A17: 5 | B17: SNAG11 | C17: AGRO | D17: FII | E17: =IFERROR(__xludf.DUMMYFUNCTION("GOOGLEFINANCE(B17)"),10.6) -> 10.6 | F17: =SNAG11!E2 -> 149 | G17: =F17*E17 -> 1579.4 | H17: =G17-SNAG11!D2 -> 74.5 | I17: =H17/XPML11!D2 -> 0.18440594 | J17: =K17/(1+L17) -> 100.93105 | K17: =XPML11!C2 -> 101 | L17: =M38/(K17*F17) -> 0.00068310187 | M17: 0.09 | N17: 0.06
A18: 6 | B18: CPTS11 | C18: HIBRIDO | D18: FII | E18: =IFERROR(__xludf.DUMMYFUNCTION("GOOGLEFINANCE(B18)"),7.52) -> 7.52 | F18: =CPTS11!E2 -> 59 | G18: =F18*E18 -> 443.68 | H18: =G18-CPTS11!D2 -> 0 | I18: =H18/CPTS11!D2 -> 0 | J18: =K18/(1+L18) -> 7.4506456 | K18: =CPTS11!C2 -> 7.52 | L18: =M39/(K18*F18) -> 0.0093085106 | M18: 0.03 | N18: 0.04
M19: =M13+M14+M15+M16+M17+M18 -> 0.35 | N19: =N13+N14+N15+N16+N17+N18 -> 0.3
L21: VALORIZAÇÃO + DIVIDENDOS POR ATIVO
J22: EMPRESA | K22: V. COMPRA | L22: POSIÇÃO | M22: DIVID. J/CP | N22: DIVID. SINT | O22: TOTAL | P22: VALORIZAÇÃO
J23: BBAS3 | K23: =K2*F2 -> 58930 | L23: =G2 -> 21787.5 | M23: =BBAS3.!K15 -> 415 | N23: =BBAS3.!P15 -> 0 | O23: =L23+M23+N23 -> 22202.5 | P23: =(O23-K23)/K23 -> -0.62323944
J24: FIQE3 | K24: =K3*F3 -> 27300 | L24: =G3 -> 26390 | M24: =FIQE3!K15 -> 30107 | N24: =FIQE3!Q15 | O24: =L24+M24+N24 -> 56497 | P24: =(O24-K24)/K24 -> 1.0694872
J25: ITSA3 | K25: =K4*F4 -> 51083.5 | L25: =G4 -> 45066 | M25: =ITSA4!K15 -> 1450.79 | N25: =ITSA4!Q15 -> 0 | O25: =L25+M25+N25 -> 46516.79 | P25: =(O25-K25)/K25 -> -0.089396968
J26: KLBN11 | K26: =K5*F5 -> 110000 | L26: =G5 -> 110000 | M26: =KLBN11!K15 -> 405.79 | N26: =KLBN11!Q15 -> 0 | O26: =L26+M26+N26 -> 110405.79 | P26: =(O26-K26)/K26 -> 0.003689
J27: PETR4 | K27: =K6*F6 -> 6600 | L27: =G6 -> 5514 | M27: =PETR4.!K15 -> 213 | N27: =PETR4.!Q15 -> -10569 | O27: =L27+M27+N27 -> -4842 | P27: =(O27-K27)/K27 -> -1.7336364
J28: BBDC4 | K28: =K7*F7 -> 18158.75 | L28: =G7 -> 18158.75 | M28: =BBDC4!K15 -> 248.75 | N28: =BBDC4!P15 -> 0 | O28: =L28+M28+N28 -> 18407.5 | P28: =(O28-K28)/K28 -> 0.01369863
J29: TAEE11 | K29: =K8*F8 -> 20300 | L29: =G8 -> 16718.5 | M29: =TAEE11!K15 -> 461.5 | N29: =TAEE11!Q15 -> 0 | O29: =L29+M29+N29 -> 17180 | P29: =(O29-K29)/K29 -> -0.15369458
J30: TAEE11 | K30: =K9*F9 -> 7280 | L30: =G9 -> 7130.5 | M30: =TAEE11!K15 -> 461.5 | N30: =TAEE11!Q15 -> 0 | O30: =L30+M30+N30 -> 7592 | P30: =(O30-K30)/K30 -> 0.042857143
J31: VALE3 | K31: =K10*F10 -> 1800 | L31: =G10 -> 1707 | M31: =VALE3!K15 -> 2445 | N31: =VALE3!Q15 -> 0 | O31: =L31+M31+N31 -> 4152 | P31: =(O31-K31)/K31 -> 1.3066667
J32: CMIG4 | K32: =K11*F11 -> 20000 | L32: =G11 -> 91750 | M32: =CMIG4!K15 -> 35679 | N32: =CMIG4!Q15 | O32: =L32+M32+N32 -> 127429 | P32: =(O32-K32)/K32 -> 5.37145
L33: =G12
J34: MXRF11 | K34: =K13*F13 -> 2682 | L34: =G13 -> 2822.06 | M34: =MXRF11!K15 -> 62.58 | O34: =L34+M34+N34 -> 2884.64 | P34: =(O34-K34)/K34 -> 0.075555556
J35: BRCR11 | K35: =K14*F14 -> 650 | L35: =G14 -> 579.15 | M35: =BRCR11!K15 -> 5.33 | O35: =L35+M35+N35 -> 584.48 | P35: =(O35-K35)/K35 -> -0.1008
J36: XPLG11 | K36: =K15*F15 -> 1805 | L36: =G15 -> 1959.47 | M36: =XPLG11!K15 -> 7.02 | O36: =L36+M36+N36 -> 1966.49 | P36: =(O36-K36)/K36 -> 0.089468144
J37: XPML11 | K37: =K16*F16 -> 404 | L37: =G16 -> 425.04 | M37: =XPML11!K15 -> 7.28 | O37: =L37+M37+N37 -> 432.32 | P37: =(O37-K37)/K37 -> 0.07009901
J38: SNAG11 | K38: =K17*F17 -> 15049 | L38: =G17 -> 1579.4 | M38: =SNAG11!K15 -> 10.28 | O38: =L38+M38+N38 -> 1589.68 | P38: =(O38-K38)/K38 -> -0.8943664
J39: CPTS11 | K39: =K18*F18 -> 443.68 | L39: =G18 -> 443.68 | M39: =CPTS11!K15 -> 4.13 | O39: =L39+M39+N39 -> 447.81 | P39: =(O39-K39)/K39 -> 0.0093085106
K41: =P2 -> 1058564.4 | L41: =SUM(L22:L40) -> 352031.05 | M41: =SUM(M22:M40) -> 71983.95 | O41: =L41+M41+N41 -> 424015 | P41: =(O41-K41)/K41 -> -0.59944334

Sheet BBAS3.
A1: PAPEL | B1: DATA INÍCIO | C1: PREÇO MÉDIO | D1: TOTAL INVESTIDO | E1: QUANTIDADE | F1: POSIÇÃO
A2: BBAS3 | C2: =F15 -> 22 | D2: =E15 -> 18260 | E2: =C15 -> 830 | F2: ='visão geral'!G2 -> 21787.5
B4: DATA | C4: QTD | D4: PREÇO | E4: INVESTIDO | G4: DATA | H4: DIVIDEND | I4: J/CP | J4: Qtd | K4: TOTAL | M4: DATA | N4: DIVID. SINT | O4: Qtd | P4: TOTAL
B5: 46008 | C5: 830 | D5: 22 | E5: =C5*D5 -> 18260 | G5: 46008 | H5: 0.5 | J5: 830 | K5: =SUM(H5*J5) -> 415 | P5: =N5*O5 -> 0
B6: 46009 | E6: =C6*D6 -> 0 | G6: 46009 | K6: 0 | P6: =N6*O6 -> 0
B7: 46010 | E7: =C7*D7 -> 0 | G7: 46010 | K7: 0 | P7: =N7*O7 -> 0
B8: 46011 | E8: =C8*D8 -> 0 | G8: 46011 | K8: 0 | P8: =N8*O8 -> 0
B9: 46012 | E9: =C9*D9 -> 0 | G9: 46012 | K9: =J9*(I9+H9) -> 0 | P9: =N9*O9 -> 0
B10: 46013 | E10: =C10*D10 -> 0 | G10: 46013 | K10: =J10*(I10+H10) -> 0 | P10: =N10*O10 -> 0
B11: 46014 | E11: =C11*D11 -> 0 | G11: 46014 | K11: =J11*(I11+H11) -> 0 | P11: =N11*O11 -> 0
B12: 46015 | E12: =C12*D12 -> 0 | G12: 46015 | K12: =J12*(I12+H12) -> 0 | P12: =N12*O12 -> 0
B13: 46016 | E13: =C13*D13 -> 0 | G13: 46016 | K13: =J13*(I13+H13) -> 0 | P13: =N13*O13 -> 0
B14: 46017 | E14: =C14*D14 -> 0 | F14: PREÇO MÉDIO | G14: 46017 | K14: =J14*(I14+H14) -> 0 | P14: =N14*O14 -> 0
A15: TOTAL | C15: =SUM(C5:C14) -> 830 | E15: =E5+E6+E7+E8+E9+E10+E11+E12+E13 -> 18260 | F15: =E15/C15 -> 22 | G15: TOTAL | K15: =K5+K6+K7+K8+K9+K10+K11+K12+K13+K14 -> 415 | M15: TOTAL | P15: =SUM(P5:P14) -> 0

Sheet FIQE3
A1: PAPEL | B1: DATA INÍCIO | C1: PREÇO MÉDIO | D1: TOTAL INVESTIDO | E1: QUANTIDADE | F1: POSIÇÃO
A2: FIQE3 | C2: =F15 -> 6 | D2: =E15 -> 31416 | E2: =C15 -> 5236 | F2: ='visão geral'!G2 -> 21787.5
B4: DATA | C4: QTD | D4: PREÇO | E4: INVESTIDO | G4: DATA | H4: DIVIDEND | I4: J/CP | J4: Qtd | K4: TOTAL | M4: DATA | N4: DIVID. SINT | O4: Qtd | P4: TOTAL
B5: 46008 | C5: 5236 | D5: 6 | E5: =C5*D5 -> 31416 | G5: 46008 | H5: 5.75 | J5: 5236 | K5: =SUM(H5*J5) -> 30107 | P5: =N5*O5 -> 0
B6: 46009 | E6: =C6*D6 -> 0 | G6: 46009 | K6: 0 | P6: =N6*O6 -> 0
B7: 46010 | E7: =C7*D7 -> 0 | G7: 46010 | K7: 0 | P7: =N7*O7 -> 0
B8: 46011 | E8: =C8*D8 -> 0 | G8: 46011 | K8: 0 | P8: =N8*O8 -> 0
B9: 46012 | E9: =C9*D9 -> 0 | G9: 46012 | K9: =J9*(I9+H9) -> 0 | P9: =N9*O9 -> 0
B10: 46013 | E10: =C10*D10 -> 0 | G10: 46013 | K10: =J10*(I10+H10) -> 0 | P10: =N10*O10 -> 0
B11: 46014 | E11: =C11*D11 -> 0 | G11: 46014 | K11: =J11*(I11+H11) -> 0 | P11: =N11*O11 -> 0
B12: 46015 | E12: =C12*D12 -> 0 | G12: 46015 | K12: =J12*(I12+H12) -> 0 | P12: =N12*O12 -> 0
B13: 46016 | E13: =C13*D13 -> 0 | G13: 46016 | K13: =J13*(I13+H13) -> 0 | P13: =N13*O13 -> 0
B14: 46017 | E14: =C14*D14 -> 0 | F14: PREÇO MÉDIO | G14: 46017 | K14: =J14*(I14+H14) -> 0 | P14: =N14*O14 -> 0
A15: TOTAL | C15: =SUM(C5:C14) -> 5236 | E15: =E5+E6+E7+E8+E9+E10+E11+E12+E13 -> 31416 | F15: =E15/C15 -> 6 | G15: TOTAL | K15: =K5+K6+K7+K8+K9+K10+K11+K12+K13+K14 -> 30107 | M15: TOTAL | P15: =SUM(P5:P14) -> 0

Sheet CMIG4
A1: PAPEL | B1: DATA INÍCIO | C1: PREÇO MÉDIO | D1: TOTAL INVESTIDO | E1: QUANTIDADE | F1: POSIÇÃO
A2: CMIG4 | C2: =F15 -> 11.2 | D2: =E15 -> 799209.6 | E2: =C15 -> 71358 | F2: ='visão geral'!G2 -> 21787.5
B4: DATA | C4: QTD | D4: PREÇO | E4: INVESTIDO | G4: DATA | H4: DIVIDEND | I4: J/CP | J4: Qtd | K4: TOTAL | M4: DATA | N4: DIVID. SINT | O4: Qtd | P4: TOTAL
B5: 46008 | C5: 71358 | D5: 11.2 | E5: =C5*D5 -> 799209.6 | G5: 46008 | H5: 0.5 | J5: 71358 | K5: =SUM(H5*J5) -> 35679 | P5: =N5*O5 -> 0
B6: 46009 | E6: =C6*D6 -> 0 | G6: 46009 | K6: 0 | P6: =N6*O6 -> 0
B7: 46010 | E7: =C7*D7 -> 0 | G7: 46010 | K7: 0 | P7: =N7*O7 -> 0
B8: 46011 | E8: =C8*D8 -> 0 | G8: 46011 | K8: 0 | P8: =N8*O8 -> 0
B9: 46012 | E9: =C9*D9 -> 0 | G9: 46012 | K9: =J9*(I9+H9) -> 0 | P9: =N9*O9 -> 0
B10: 46013 | E10: =C10*D10 -> 0 | G10: 46013 | K10: =J10*(I10+H10) -> 0 | P10: =N10*O10 -> 0
B11: 46014 | E11: =C11*D11 -> 0 | G11: 46014 | K11: =J11*(I11+H11) -> 0 | P11: =N11*O11 -> 0
B12: 46015 | E12: =C12*D12 -> 0 | G12: 46015 | K12: =J12*(I12+H12) -> 0 | P12: =N12*O12 -> 0
B13: 46016 | E13: =C13*D13 -> 0 | G13: 46016 | K13: =J13*(I13+H13) -> 0 | P13: =N13*O13 -> 0
B14: 46017 | E14: =C14*D14 -> 0 | F14: PREÇO MÉDIO | G14: 46017 | K14: =J14*(I14+H14) -> 0 | P14: =N14*O14 -> 0
A15: TOTAL | C15: =SUM(C5:C14) -> 71358 | E15: =E5+E6+E7+E8+E9+E10+E11+E12+E13 -> 799209.6 | F15: =E15/C15 -> 11.2 | G15: TOTAL | K15: =K5+K6+K7+K8+K9+K10+K11+K12+K13+K14 -> 35679 | M15: TOTAL | P15: =SUM(P5:P14) -> 0

Sheet BBDC4
A1: PAPEL | B1: DATA INÍCIO | C1: PREÇO MÉDIO | D1: TOTAL INVESTIDO | E1: QUANTIDADE | F1: POSIÇÃO
A2: BBDC4 | C2: =F15 -> 18.25 | D2: =E15 -> 18158.75 | E2: =C15 -> 995 | F2: ='visão geral'!G2 -> 21787.5
B4: DATA | C4: QTD | D4: PREÇO | E4: INVESTIDO | G4: DATA | H4: DIVIDEND | I4: J/CP | J4: Qtd | K4: TOTAL | M4: DATA | N4: DIVID. SINT | O4: Qtd | P4: TOTAL
B5: 46008 | C5: 995 | D5: 18.25 | E5: =C5*D5 -> 18158.75 | G5: 46008 | H5: 0.25 | J5: 995 | K5: =SUM(H5*J5) -> 248.75 | P5: =N5*O5 -> 0
B6: 46009 | E6: =C6*D6 -> 0 | G6: 46009 | K6: 0 | P6: =N6*O6 -> 0
B7: 46010 | E7: =C7*D7 -> 0 | G7: 46010 | K7: 0 | P7: =N7*O7 -> 0
B8: 46011 | E8: =C8*D8 -> 0 | G8: 46011 | K8: 0 | P8: =N8*O8 -> 0
B9: 46012 | E9: =C9*D9 -> 0 | G9: 46012 | K9: =J9*(I9+H9) -> 0 | P9: =N9*O9 -> 0
B10: 46013 | E10: =C10*D10 -> 0 | G10: 46013 | K10: =J10*(I10+H10) -> 0 | P10: =N10*O10 -> 0
B11: 46014 | E11: =C11*D11 -> 0 | G11: 46014 | K11: =J11*(I11+H11) -> 0 | P11: =N11*O11 -> 0
B12: 46015 | E12: =C12*D12 -> 0 | G12: 46015 | K12: =J12*(I12+H12) -> 0 | P12: =N12*O12 -> 0
B13: 46016 | E13: =C13*D13 -> 0 | G13: 46016 | K13: =J13*(I13+H13) -> 0 | P13: =N13*O13 -> 0
B14: 46017 | E14: =C14*D14 -> 0 | F14: PREÇO MÉDIO | G14: 46017 | K14: =J14*(I14+H14) -> 0 | P14: =N14*O14 -> 0
A15: TOTAL | C15: =SUM(C5:C14) -> 995 | E15: =E5+E6+E7+E8+E9+E10+E11+E12+E13 -> 18158.75 | F15: =E15/C15 -> 18.25 | G15: TOTAL | K15: =K5+K6+K7+K8+K9+K10+K11+K12+K13+K14 -> 248.75 | M15: TOTAL | P15: =SUM(P5:P14) -> 0

Sheet BRBl11
A1: PAPEL | B1: DATA INÍCIO | C1: PREÇO MÉDIO | D1: TOTAL INVESTIDO | E1: QUANTIDADE | F1: POSIÇÃO
A2: BRBI11 | C2: =F15 -> 22 | D2: =E15 -> 18260 | E2: =C15 -> 830 | F2: ='visão geral'!G2 -> 21787.5
B4: DATA | C4: QTD | D4: PREÇO | E4: INVESTIDO | G4: DATA | H4: DIVIDEND | I4: J/CP | J4: Qtd | K4: TOTAL | M4: DATA | N4: DIVID. SINT | O4: Qtd | P4: TOTAL
B5: 46008 | C5: 830 | D5: 22 | E5: =C5*D5 -> 18260 | G5: 46008 | H5: 0.78 | J5: 830 | K5: =SUM(H5*J5) -> 647.4 | P5: =N5*O5 -> 0
B6: 46009 | E6: =C6*D6 -> 0 | G6: 46009 | K6: 0 | P6: =N6*O6 -> 0
B7: 46010 | E7: =C7*D7 -> 0 | G7: 46010 | K7: 0 | P7: =N7*O7 -> 0
B8: 46011 | E8: =C8*D8 -> 0 | G8: 46011 | K8: 0 | P8: =N8*O8 -> 0
B9: 46012 | E9: =C9*D9 -> 0 | G9: 46012 | K9: =J9*(I9+H9) -> 0 | P9: =N9*O9 -> 0
B10: 46013 | E10: =C10*D10 -> 0 | G10: 46013 | K10: =J10*(I10+H10) -> 0 | P10: =N10*O10 -> 0
B11: 46014 | E11: =C11*D11 -> 0 | G11: 46014 | K11: =J11*(I11+H11) -> 0 | P11: =N11*O11 -> 0
B12: 46015 | E12: =C12*D12 -> 0 | G12: 46015 | K12: =J12*(I12+H12) -> 0 | P12: =N12*O12 -> 0
B13: 46016 | E13: =C13*D13 -> 0 | G13: 46016 | K13: =J13*(I13+H13) -> 0 | P13: =N13*O13 -> 0
B14: 46017 | E14: =C14*D14 -> 0 | F14: PREÇO MÉDIO | G14: 46017 | K14: =J14*(I14+H14) -> 0 | P14: =N14*O14 -> 0
A15: TOTAL | C15: =SUM(C5:C14) -> 830 | E15: =E5+E6+E7+E8+E9+E10+E11+E12+E13 -> 18260 | F15: =E15/C15 -> 22 | G15: TOTAL | K15: =K5+K6+K7+K8+K9+K10+K11+K12+K13+K14 -> 647.4 | M15: TOTAL | P15: =SUM(P5:P14) -> 0

Sheet ITSA4
A1: PAPEL | B1: DATA INÍCIO | C1: PREÇO MÉDIO | D1: TOTAL INVESTIDO | E1: QUANTIDADE | F1: POSIÇÃO
A2: ITSA4 | C2: =F15 -> 14 | D2: =E15 -> 20300 | E2: =C15 -> 1450 | F2: ='visão geral'!G4 -> 45066
B4: DATA | C4: QTD | D4: PREÇO | E4: INVESTIDO | G4: DATA | H4: DIVIDEN | I4: J/CP | J4: Qtd | K4: TOTAL | M4: DATA | N4: DIVID. SINT | O4: Qtd | P4: CUSTOS | Q4: TOTAL
C5: 1450 | D5: 14 | E5: =C5*D5 -> 20300 | G5: 46008 | H5: 0.79 | J5: 1450 | K5: =SUM(J5+H5) -> 1450.79 | Q5: =N5*O5-P5 -> 0
E6: =C6*D6 -> 0 | Q6: =N6*O6-P6 -> 0
E7: =C7*D7 -> 0 | K7: =J7*(I7+H7) -> 0 | Q7: =N7*O7-P7 -> 0
E8: =C8*D8 -> 0 | K8: =J8*(I8+H8) -> 0 | Q8: =N8*O8-P8 -> 0
E9: =C9*D9 -> 0 | K9: =J9*(I9+H9) -> 0 | Q9: =N9*O9-P9 -> 0
E10: =C10*D10 -> 0 | K10: =J10*(I10+H10) -> 0 | Q10: =N10*O10-P10 -> 0
E11: =C11*D11 -> 0 | K11: =J11*(I11+H11) -> 0 | Q11: =N11*O11-P11 -> 0
E12: =C12*D12 -> 0 | K12: =J12*(I12+H12) -> 0 | Q12: =N12*O12-P12 -> 0
E13: =C13*D13 -> 0 | K13: =J13*(I13+H13) -> 0 | Q13: =N13*O13-P13 -> 0
E14: =C14*D14 -> 0 | F14: PREÇO MÉDIO | K14: =J14*(I14+H14) -> 0 | Q14: =N14*O14-P14 -> 0
A15: TOTAL | C15: =C5+C6 -> 1450 | E15: =E5+E6+E7+E8+E9+E10+E11+E12+E13 -> 20300 | F15: =E15/C15 -> 14 | G15: TOTAL | K15: =K5+K6+K7+K8+K9+K10+K11+K12+K13+K14 -> 1450.79 | M15: TOTAL | Q15: =SUM(Q5:Q14) -> 0

Sheet KLBN11
A1: PAPEL | B1: DATA INÍCIO | C1: PREÇO MÉDIO | D1: TOTAL INVESTIDO | E1: QUANTIDADE | F1: POSIÇÃO
A2: IRBR3 | C2: =F15 -> 4 | D2: =E15 -> 20000 | E2: =C15 -> 5000 | F2: ='visão geral'!G5 -> 110000
B4: DATA | C4: QTD | D4: PREÇO | E4: INVESTIDO | G4: DATA | H4: DIVID | I4: J/CP | J4: Qtd | K4: TOTAL | M4: DATA | N4: DIVID. SINT | O4: Qtd | P4: CUSTOS | Q4: TOTAL
C5: 5000 | D5: 4 | E5: =C5*D5 -> 20000 | G5: 46008 | H5: 0.08 | J5: 5000 | K5: =SUM(H5*J5) -> 400 | Q5: =N5*O5-P5 -> 0
E6: =C6*D6 -> 0 | K6: 5.79 | Q6: =N6*O6-P6 -> 0
E7: =C7*D7 -> 0 | K7: =J7*(I7+H7) -> 0 | Q7: =N7*O7-P7 -> 0
E8: =C8*D8 -> 0 | K8: =J8*(I8+H8) -> 0 | Q8: =N8*O8-P8 -> 0
E9: =C9*D9 -> 0 | K9: =J9*(I9+H9) -> 0 | Q9: =N9*O9-P9 -> 0
E10: =C10*D10 -> 0 | K10: =J10*(I10+H10) -> 0 | Q10: =N10*O10-P10 -> 0
E11: =C11*D11 -> 0 | K11: =J11*(I11+H11) -> 0 | Q11: =N11*O11-P11 -> 0
E12: =C12*D12 -> 0 | K12: =J12*(I12+H12) -> 0 | Q12: =N12*O12-P12 -> 0
E13: =C13*D13 -> 0 | K13: =J13*(I13+H13) -> 0 | Q13: =N13*O13-P13 -> 0
E14: =C14*D14 -> 0 | F14: PREÇO MÉDIO | K14: =J14*(I14+H14) -> 0 | Q14: =N14*O14-P14 -> 0
A15: TOTAL | C15: =C5+C6 -> 5000 | E15: =E5+E6+E7+E8+E9+E10+E11+E12+E13 -> 20000 | F15: =E15/C15 -> 4 | G15: TOTAL | K15: =K5+K6+K7+K8+K9+K10+K11+K12+K13+K14 -> 405.79 | M15: TOTAL | Q15: =SUM(Q5:Q14) -> 0

Sheet PETR4.
A1: PAPEL | B1: DATA INÍCIO | C1: PREÇO MÉDIO | D1: TOTAL INVESTIDO | E1: QUANTIDADE | F1: POSIÇÃO
A2: PETR4 | C2: =F15 -> 35.23 | D2: =E15 -> 10569 | E2: =C15 -> 300 | F2: ='visão geral'!G6 -> 5514
B4: DATA | C4: QTD | D4: PREÇO | E4: INVESTIDO | G4: DATA | H4: DIVID | I4: J/CP | J4: Qtd | K4: TOTAL | M4: DATA | N4: DIVID. SINT | O4: Qtd | P4: CUSTOS | Q4: TOTAL
C5: 300 | D5: 35.23 | E5: =C5*D5 -> 10569 | H5: 0.71 | J5: 300 | K5: =SUM(H5*J5) -> 213 | O5: 300 | P5: =E5 -> 10569 | Q5: =N5*O5-P5 -> -10569
E6: =C6*D6 -> 0 | K6: =J6*(I6+H6) -> 0 | Q6: =N6*O6-P6 -> 0
E7: =C7*D7 -> 0 | K7: =J7*(I7+H7) -> 0 | Q7: =N7*O7-P7 -> 0
E8: =C8*D8 -> 0 | K8: =J8*(I8+H8) -> 0 | Q8: =N8*O8-P8 -> 0
E9: =C9*D9 -> 0 | K9: =J9*(I9+H9) -> 0 | Q9: =N9*O9-P9 -> 0
E10: =C10*D10 -> 0 | K10: =J10*(I10+H10) -> 0 | Q10: =N10*O10-P10 -> 0
E11: =C11*D11 -> 0 | K11: =J11*(I11+H11) -> 0 | Q11: =N11*O11-P11 -> 0
E12: =C12*D12 -> 0 | K12: =J12*(I12+H12) -> 0 | Q12: =N12*O12-P12 -> 0
E13: =C13*D13 -> 0 | K13: =J13*(I13+H13) -> 0 | Q13: =N13*O13-P13 -> 0
E14: =C14*D14 -> 0 | F14: PREÇO MÉDIO | K14: =J14*(I14+H14) -> 0 | Q14: =N14*O14-P14 -> 0
A15: TOTAL | C15: =SUM(C5:C14) -> 300 | E15: =SUM(E5:E14) -> 10569 | F15: =E15/C15 -> 35.23 | G15: TOTAL | K15: =K5+K6+K7+K8+K9+K10+K11+K12+K13+K14 -> 213 | M15: TOTAL | Q15: =SUM(Q5:Q14) -> -10569

Sheet TAEE11
A1: PAPEL | B1: DATA INÍCIO | C1: PREÇO MÉDIO | D1: TOTAL INVESTIDO | E1: QUANTIDADE | F1: POSIÇÃO
A2: TAEE11 | B2: 44056 | C2: =F15 -> 42 | D2: =E15 -> 27300 | E2: =C15 -> 650 | F2: ='visão geral'!G7 -> 18158.75
B4: DATA | C4: QTD | D4: PREÇO | E4: INVESTIDO | G4: DATA | H4: DIVID | I4: J/CP | J4: Qtd | K4: TOTAL | M4: DATA | N4: DIVID. SINT | O4: Qtd | P4: CUSTOS | Q4: TOTAL
C5: 650 | D5: 42 | E5: =C5*D5 -> 27300 | G5: 45307 | H5: 0.71 | J5: 650 | K5: =SUM(H5*J5) -> 461.5 | Q5: =N5*O5-P5 -> 0
E6: =C6*D6 -> 0 | K6: =J6*(I6+H6) -> 0 | Q6: =N6*O6-P6 -> 0
E7: =C7*D7 -> 0 | K7: =J7*(I7+H7) -> 0 | Q7: =N7*O7-P7 -> 0
E8: =C8*D8 -> 0 | K8: =J8*(I8+H8) -> 0 | Q8: =N8*O8-P8 -> 0
E9: =C9*D9 -> 0 | K9: =J9*(I9+H9) -> 0 | Q9: =N9*O9-P9 -> 0
E10: =C10*D10 -> 0 | K10: =J10*(I10+H10) -> 0 | Q10: =N10*O10-P10 -> 0
E11: =C11*D11 -> 0 | K11: =J11*(I11+H11) -> 0 | Q11: =N11*O11-P11 -> 0
E12: =C12*D12 -> 0 | K12: =J12*(I12+H12) -> 0 | Q12: =N12*O12-P12 -> 0
E13: =C13*D13 -> 0 | K13: =J13*(I13+H13) -> 0 | Q13: =N13*O13-P13 -> 0
E14: =C14*D14 -> 0 | F14: PREÇO MÉDIO | K14: =J14*(I14+H14) -> 0 | Q14: =N14*O14-P14 -> 0
A15: TOTAL | C15: =C5+C6 -> 650 | E15: =E5+E6+E7+E8+E9+E10+E11+E12+E13 -> 27300 | F15: =E15/C15 -> 42 | G15: TOTAL | K15: =K5+K6+K7+K8+K9+K10+K11+K12+K13+K14 -> 461.5 | M15: TOTAL | Q15: =SUM(Q5:Q14) -> 0

Sheet VALE3
A1: PAPEL | B1: DATA INÍCIO | C1: PREÇO MÉDIO | D1: TOTAL INVESTIDO | E1: QUANTIDADE | F1: POSIÇÃO
A2: VALE3 | B2: 44056 | C2: =F15 -> 71 | D2: =E15 -> 21300 | E2: =C15 -> 300 | F2: ='visão geral'!G7 -> 18158.75
B4: DATA | C4: QTD | D4: PREÇO | E4: INVESTIDO | G4: DATA | H4: DIVID | I4: J/CP | J4: Qtd | K4: TOTAL | M4: DATA | N4: DIVID. SINT | O4: Qtd | P4: CUSTOS | Q4: TOTAL
C5: 300 | D5: 71 | E5: =C5*D5 -> 21300 | H5: 8.15 | J5: 300 | K5: =SUM(H5*J5) -> 2445 | Q5: =N5*O5-P5 -> 0
E6: =C6*D6 -> 0 | K6: =J6*(I6+H6) -> 0 | Q6: =N6*O6-P6 -> 0
E7: =C7*D7 -> 0 | K7: =J7*(I7+H7) -> 0 | Q7: =N7*O7-P7 -> 0
E8: =C8*D8 -> 0 | K8: =J8*(I8+H8) -> 0 | Q8: =N8*O8-P8 -> 0
E9: =C9*D9 -> 0 | K9: =J9*(I9+H9) -> 0 | Q9: =N9*O9-P9 -> 0
E10: =C10*D10 -> 0 | K10: =J10*(I10+H10) -> 0 | Q10: =N10*O10-P10 -> 0
E11: =C11*D11 -> 0 | K11: =J11*(I11+H11) -> 0 | Q11: =N11*O11-P11 -> 0
E12: =C12*D12 -> 0 | K12: =J12*(I12+H12) -> 0 | Q12: =N12*O12-P12 -> 0
E13: =C13*D13 -> 0 | K13: =J13*(I13+H13) -> 0 | Q13: =N13*O13-P13 -> 0
E14: =C14*D14 -> 0 | F14: PREÇO MÉDIO | K14: =J14*(I14+H14) -> 0 | Q14: =N14*O14-P14 -> 0
A15: TOTAL | C15: =C5+C6 -> 300 | E15: =E5+E6+E7+E8+E9+E10+E11+E12+E13 -> 21300 | F15: =E15/C15 -> 71 | G15: TOTAL | K15: =K5+K6+K7+K8+K9+K10+K11+K12+K13+K14 -> 2445 | M15: TOTAL | Q15: =SUM(Q5:Q14) -> 0

Sheet MXRF11
A1: PAPEL | B1: DATA INÍCIO | C1: PREÇO MÉDIO | D1: TOTAL INVESTIDO | E1: QUANTIDADE | F1: POSIÇÃO
A2: MXRF11 | B2: 44056 | C2: =F15 -> 9 | D2: =E15 -> 2682 | E2: =C15 -> 298 | F2: ='visão geral'!G7 -> 18158.75
B4: DATA | C4: QTD | D4: PREÇO | E4: INVESTIDO | G4: DATA | H4: DIVID | I4: J/CP | J4: Qtd | K4: TOTAL | M4: DATA | N4: DIVID. SINT | O4: Qtd | P4: CUSTOS | Q4: TOTAL
C5: 298 | D5: 9 | E5: =C5*D5 -> 2682 | G5: 45306 | K5: 32.78 | Q5: =N5*O5-P5 -> 0
E6: =C6*D6 -> 0 | G6: 45338 | K6: 29.8 | Q6: =N6*O6-P6 -> 0
E7: =C7*D7 -> 0 | K7: =J7*(I7+H7) -> 0 | Q7: =N7*O7-P7 -> 0
E8: =C8*D8 -> 0 | K8: =J8*(I8+H8) -> 0 | Q8: =N8*O8-P8 -> 0
E9: =C9*D9 -> 0 | K9: =J9*(I9+H9) -> 0 | Q9: =N9*O9-P9 -> 0
E10: =C10*D10 -> 0 | K10: =J10*(I10+H10) -> 0 | Q10: =N10*O10-P10 -> 0
E11: =C11*D11 -> 0 | K11: =J11*(I11+H11) -> 0 | Q11: =N11*O11-P11 -> 0
E12: =C12*D12 -> 0 | K12: =J12*(I12+H12) -> 0 | Q12: =N12*O12-P12 -> 0
E13: =C13*D13 -> 0 | K13: =J13*(I13+H13) -> 0 | Q13: =N13*O13-P13 -> 0
E14: =C14*D14 -> 0 | F14: PREÇO MÉDIO | K14: =J14*(I14+H14) -> 0 | Q14: =N14*O14-P14 -> 0
A15: TOTAL | C15: =C5+C6 -> 298 | E15: =E5+E6+E7+E8+E9+E10+E11+E12+E13 -> 2682 | F15: =E15/C15 -> 9 | G15: TOTAL | K15: =K5+K6+K7+K8+K9+K10+K11+K12+K13+K14 -> 62.58 | M15: TOTAL | Q15: =SUM(Q5:Q14) -> 0

Sheet BRCR11
A1: PAPEL | B1: DATA INÍCIO | C1: PREÇO MÉDIO | D1: TOTAL INVESTIDO | E1: QUANTIDADE | F1: POSIÇÃO
B2: 44056 | C2: =F15 -> 50 | D2: =E15 -> 650 | E2: =C15 -> 13 | F2: ='visão geral'!G7 -> 18158.75
B4: DATA | C4: QTD | D4: PREÇO | E4: INVESTIDO | G4: DATA | H4: DIVID | I4: J/CP | J4: Qtd | K4: TOTAL | M4: DATA | N4: DIVID. SINT | O4: Qtd | P4: CUSTOS | Q4: TOTAL
C5: 13 | D5: 50 | E5: =C5*D5 -> 650 | G5: 45338 | K5: 5.33 | Q5: =N5*O5-P5 -> 0
E6: =C6*D6 -> 0 | K6: =J6*(I6+H6) -> 0 | Q6: =N6*O6-P6 -> 0
E7: =C7*D7 -> 0 | K7: =J7*(I7+H7) -> 0 | Q7: =N7*O7-P7 -> 0
E8: =C8*D8 -> 0 | K8: =J8*(I8+H8) -> 0 | Q8: =N8*O8-P8 -> 0
E9: =C9*D9 -> 0 | K9: =J9*(I9+H9) -> 0 | Q9: =N9*O9-P9 -> 0
E10: =C10*D10 -> 0 | K10: =J10*(I10+H10) -> 0 | Q10: =N10*O10-P10 -> 0
E11: =C11*D11 -> 0 | K11: =J11*(I11+H11) -> 0 | Q11: =N11*O11-P11 -> 0
E12: =C12*D12 -> 0 | K12: =J12*(I12+H12) -> 0 | Q12: =N12*O12-P12 -> 0
E13: =C13*D13 -> 0 | K13: =J13*(I13+H13) -> 0 | Q13: =N13*O13-P13 -> 0
E14: =C14*D14 -> 0 | F14: PREÇO MÉDIO | K14: =J14*(I14+H14) -> 0 | Q14: =N14*O14-P14 -> 0
A15: TOTAL | C15: =C5+C6 -> 13 | E15: =E5+E6+E7+E8+E9+E10+E11+E12+E13 -> 650 | F15: =E15/C15 -> 50 | G15: TOTAL | K15: =K5+K6+K7+K8+K9+K10+K11+K12+K13+K14 -> 5.33 | M15: TOTAL | Q15: =SUM(Q5:Q14) -> 0

Sheet SNAG11
A1: PAPEL | B1: DATA INÍCIO | C1: PREÇO MÉDIO | D1: TOTAL INVESTIDO | E1: QUANTIDADE | F1: POSIÇÃO
A2: MXRF11 | B2: 44056 | C2: =F15 -> 10.1 | D2: =E15 -> 1504.9 | E2: =C15 -> 149 | F2: ='visão geral'!G7 -> 18158.75
B4: DATA | C4: QTD | D4: PREÇO | E4: INVESTIDO | G4: DATA | H4: DIVID | I4: J/CP | J4: Qtd | K4: TOTAL | M4: DATA | N4: DIVID. SINT | O4: Qtd | P4: CUSTOS | Q4: TOTAL
C5: 149 | D5: 10.1 | E5: =C5*D5 -> 1504.9 | G5: 45316 | K5: 5.14 | Q5: =N5*O5-P5 -> 0
E6: =C6*D6 -> 0 | G6: 45345 | K6: 5.14 | Q6: =N6*O6-P6 -> 0
E7: =C7*D7 -> 0 | K7: =J7*(I7+H7) -> 0 | Q7: =N7*O7-P7 -> 0
E8: =C8*D8 -> 0 | K8: =J8*(I8+H8) -> 0 | Q8: =N8*O8-P8 -> 0
E9: =C9*D9 -> 0 | K9: =J9*(I9+H9) -> 0 | Q9: =N9*O9-P9 -> 0
E10: =C10*D10 -> 0 | K10: =J10*(I10+H10) -> 0 | Q10: =N10*O10-P10 -> 0
E11: =C11*D11 -> 0 | K11: =J11*(I11+H11) -> 0 | Q11: =N11*O11-P11 -> 0
E12: =C12*D12 -> 0 | K12: =J12*(I12+H12) -> 0 | Q12: =N12*O12-P12 -> 0
E13: =C13*D13 -> 0 | K13: =J13*(I13+H13) -> 0 | Q13: =N13*O13-P13 -> 0
E14: =C14*D14 -> 0 | F14: PREÇO MÉDIO | K14: =J14*(I14+H14) -> 0 | Q14: =N14*O14-P14 -> 0
A15: TOTAL | C15: =C5+C6 -> 149 | E15: =E5+E6+E7+E8+E9+E10+E11+E12+E13 -> 1504.9 | F15: =E15/C15 -> 10.1 | G15: TOTAL | K15: =K5+K6+K7+K8+K9+K10+K11+K12+K13+K14 -> 10.28 | M15: TOTAL | Q15: =SUM(Q5:Q14) -> 0

Sheet CPTS11
A1: PAPEL | B1: DATA INÍCIO | C1: PREÇO MÉDIO | D1: TOTAL INVESTIDO | E1: QUANTIDADE | F1: POSIÇÃO
A2: MXRF11 | B2: 44056 | C2: =F15 -> 7.52 | D2: =E15 -> 443.68 | E2: =C15 -> 59 | F2: ='visão geral'!G7 -> 18158.75
B4: DATA | C4: QTD | D4: PREÇO | E4: INVESTIDO | G4: DATA | H4: DIVID | I4: J/CP | J4: Qtd | K4: TOTAL | M4: DATA | N4: DIVID. SINT | O4: Qtd | P4: CUSTOS | Q4: TOTAL
C5: 59 | D5: 7.52 | E5: =C5*D5 -> 443.68 | G5: 45343 | K5: 4.13 | Q5: =N5*O5-P5 -> 0
E6: =C6*D6 -> 0 | K6: =J6*(I6+H6) -> 0 | Q6: =N6*O6-P6 -> 0
E7: =C7*D7 -> 0 | K7: =J7*(I7+H7) -> 0 | Q7: =N7*O7-P7 -> 0
E8: =C8*D8 -> 0 | K8: =J8*(I8+H8) -> 0 | Q8: =N8*O8-P8 -> 0
E9: =C9*D9 -> 0 | K9: =J9*(I9+H9) -> 0 | Q9: =N9*O9-P9 -> 0
E10: =C10*D10 -> 0 | K10: =J10*(I10+H10) -> 0 | Q10: =N10*O10-P10 -> 0
E11: =C11*D11 -> 0 | K11: =J11*(I11+H11) -> 0 | Q11: =N11*O11-P11 -> 0
E12: =C12*D12 -> 0 | K12: =J12*(I12+H12) -> 0 | Q12: =N12*O12-P12 -> 0
E13: =C13*D13 -> 0 | K13: =J13*(I13+H13) -> 0 | Q13: =N13*O13-P13 -> 0
E14: =C14*D14 -> 0 | F14: PREÇO MÉDIO | K14: =J14*(I14+H14) -> 0 | Q14: =N14*O14-P14 -> 0
A15: TOTAL | C15: =C5+C6 -> 59 | E15: =E5+E6+E7+E8+E9+E10+E11+E12+E13 -> 443.68 | F15: =E15/C15 -> 7.52 | G15: TOTAL | K15: =K5+K6+K7+K8+K9+K10+K11+K12+K13+K14 -> 4.13 | M15: TOTAL | Q15: =SUM(Q5:Q14) -> 0

Sheet XPML11
A1: PAPEL | B1: DATA INÍCIO | C1: PREÇO MÉDIO | D1: TOTAL INVESTIDO | E1: QUANTIDADE | F1: POSIÇÃO
A2: MXRF11 | B2: 44056 | C2: =F15 -> 101 | D2: =E15 -> 404 | E2: =C15 -> 4 | F2: ='visão geral'!G7 -> 18158.75
B4: DATA | C4: QTD | D4: PREÇO | E4: INVESTIDO | G4: DATA | H4: DIVID | I4: J/CP | J4: Qtd | K4: TOTAL | M4: DATA | N4: DIVID. SINT | O4: Qtd | P4: CUSTOS | Q4: TOTAL
C5: 4 | D5: 101 | E5: =C5*D5 -> 404 | G5: 45316 | K5: 3.68 | Q5: =N5*O5-P5 -> 0
E6: =C6*D6 -> 0 | G6: 45345 | K6: 3.6 | Q6: =N6*O6-P6 -> 0
E7: =C7*D7 -> 0 | K7: =J7*(I7+H7) -> 0 | Q7: =N7*O7-P7 -> 0
E8: =C8*D8 -> 0 | K8: =J8*(I8+H8) -> 0 | Q8: =N8*O8-P8 -> 0
E9: =C9*D9 -> 0 | K9: =J9*(I9+H9) -> 0 | Q9: =N9*O9-P9 -> 0
E10: =C10*D10 -> 0 | K10: =J10*(I10+H10) -> 0 | Q10: =N10*O10-P10 -> 0
E11: =C11*D11 -> 0 | K11: =J11*(I11+H11) -> 0 | Q11: =N11*O11-P11 -> 0
E12: =C12*D12 -> 0 | K12: =J12*(I12+H12) -> 0 | Q12: =N12*O12-P12 -> 0
E13: =C13*D13 -> 0 | K13: =J13*(I13+H13) -> 0 | Q13: =N13*O13-P13 -> 0
E14: =C14*D14 -> 0 | F14: PREÇO MÉDIO | K14: =J14*(I14+H14) -> 0 | Q14: =N14*O14-P14 -> 0
A15: TOTAL | C15: =C5+C6 -> 4 | E15: =E5+E6+E7+E8+E9+E10+E11+E12+E13 -> 404 | F15: =E15/C15 -> 101 | G15: TOTAL | K15: =K5+K6+K7+K8+K9+K10+K11+K12+K13+K14 -> 7.28 | M15: TOTAL | Q15: =SUM(Q5:Q14) -> 0

Sheet XPLG11
A1: PAPEL | B1: DATA INÍCIO | C1: PREÇO MÉDIO | D1: TOTAL INVESTIDO | E1: QUANTIDADE | F1: POSIÇÃO
A2: MXRF11 | B2: 44056 | C2: =F15 -> 95 | D2: =E15 -> 1805 | E2: =C15 -> 19 | F2: ='visão geral'!G7 -> 18158.75
B4: DATA | C4: QTD | D4: PREÇO | E4: INVESTIDO | G4: DATA | H4: DIVID | I4: J/CP | J4: Qtd | K4: TOTAL | M4: DATA | N4: DIVID. SINT | O4: Qtd | P4: CUSTOS | Q4: TOTAL
C5: 19 | D5: 95 | E5: =C5*D5 -> 1805 | G5: 45338 | K5: 7.02 | Q5: =N5*O5-P5 -> 0
E6: =C6*D6 -> 0 | K6: =J6*(I6+H6) -> 0 | Q6: =N6*O6-P6 -> 0
E7: =C7*D7 -> 0 | K7: =J7*(I7+H7) -> 0 | Q7: =N7*O7-P7 -> 0
E8: =C8*D8 -> 0 | K8: =J8*(I8+H8) -> 0 | Q8: =N8*O8-P8 -> 0
E9: =C9*D9 -> 0 | K9: =J9*(I9+H9) -> 0 | Q9: =N9*O9-P9 -> 0
E10: =C10*D10 -> 0 | K10: =J10*(I10+H10) -> 0 | Q10: =N10*O10-P10 -> 0
E11: =C11*D11 -> 0 | K11: =J11*(I11+H11) -> 0 | Q11: =N11*O11-P11 -> 0
E12: =C12*D12 -> 0 | K12: =J12*(I12+H12) -> 0 | Q12: =N12*O12-P12 -> 0
E13: =C13*D13 -> 0 | K13: =J13*(I13+H13) -> 0 | Q13: =N13*O13-P13 -> 0
E14: =C14*D14 -> 0 | F14: PREÇO MÉDIO | K14: =J14*(I14+H14) -> 0 | Q14: =N14*O14-P14 -> 0
A15: TOTAL | C15: =C5+C6 -> 19 | E15: =E5+E6+E7+E8+E9+E10+E11+E12+E13 -> 1805 | F15: =E15/C15 -> 95 | G15: TOTAL | K15: =K5+K6+K7+K8+K9+K10+K11+K12+K13+K14 -> 7.02 | M15: TOTAL | Q15: =SUM(Q5:Q14) -> 0
