Workbook
Name META_MENSAL: Premissas!$B$5
Name APORTE_MENSAL: Premissas!$B$6
Name PESO_RV: Premissas!$B$7
Name OUTRAS_CLASSES: Premissas!$B$11:$B$13
Name lc_data: Cadastro!$C$8
Name lc_ticker: Cadastro!$C$9
Name lc_op: Cadastro!$C$10
Name lc_qtd: Cadastro!$C$11
Name lc_preco: Cadastro!$C$12
Name lc_custos: Cadastro!$C$13
Name lc_ativo: Cadastro!$C$15
Name lc_cot: Cadastro!$C$16
Name lc_tem: Cadastro!$C$17
Name lc_tipo: Cadastro!$C$19
Name lc_seg: Cadastro!$C$20
Name lc_total: Cadastro!$C$22
Name lc_apos: Cadastro!$C$23
Name lc_status: Cadastro!$B$24
Name pv_data: Cadastro!$F$8
Name pv_ticker: Cadastro!$F$9
Name pv_tipo: Cadastro!$F$10
Name pv_valor: Cadastro!$F$11
Name pv_qtd: Cadastro!$F$12
Name pv_tem: Cadastro!$F$14
Name pv_total: Cadastro!$F$15
Name pv_status: Cadastro!$E$16
Name lc_registrar: Cadastro!$C$26
Name pv_registrar: Cadastro!$F$18

Sheet Painel
B1: ◆ InvestERP Painel Carteira Análises ✚ Lançar Lançamentos Proventos Premissas Verificar
C2: Visão geral da carteira | Y2: =TODAY()
C3: Início › Painel • ações e FIIs, meta de renda e alocação • cotações: Google Finance
C4: =IF(COUNTIF(Carteira!C5:C35,">0")=0,"✚ Nenhuma ação ou FII na carteira ainda — registre sua primeira compra na aba Cadastro (clique aqui)","")
C5: Patrimônio | O5: renda fixa (Premissas) + ações e FIIs (Carteira)
C7: PATRIMÔNIO TOTAL | H7: RENDA FIXA | M7: RENDA VARIÁVEL | R7: INVESTIDO EM AÇÕES/FIIS | W7: LUCRO / PREJUÍZO | AB7: PROVENTOS RECEBIDOS
C8: =(Carteira!G36+SUM(OUTRAS_CLASSES)) | H8: =SUMIF(Premissas!$A:$A,"Renda fixa*",Premissas!$B:$B) | M8: =Carteira!G36 | R8: =Carteira!E36 | W8: =Carteira!H36 | AB8: =Carteira!J36
C9: =COUNTIF(Carteira!C5:C35,">0") | H9: =IF((Carteira!G36+SUM(OUTRAS_CLASSES))>0,SUMIF(Premissas!$A:$A,"Renda fixa*",Premissas!$B:$B)/(Carteira!G36+SUM(OUTRAS_CLASSES)),0) | M9: =IF((Carteira!G36+SUM(OUTRAS_CLASSES))>0,Carteira!G36/(Carteira!G36+SUM(OUTRAS_CLASSES)),0) | R9: =Carteira!I36 | W9: =Carteira!L36 | AB9: =Carteira!O36
C11: Meta de renda | O11: cada ativo deve pagar R$ 1.000/mês
C13: RENDA MENSAL | H13: META MENSAL | M13: PROGRESSO DA META | R13: ATIVOS NA META | W13: APORTE P/ META | AB13: TEMPO ATÉ A META
C14: =Carteira!V36 | H14: =META_MENSAL*COUNTIF(Carteira!A5:A35,"?*") | M14: =Carteira!W36 | R14: =Carteira!X36 | W14: =Carteira!Z36 | AB14: =Carteira!AA36
C15: =Carteira!V36*12 | H15: =META_MENSAL | M15: =IF(META_MENSAL>0,Carteira!V36/(META_MENSAL*COUNTIF(Carteira!A5:A35,"?*")),0) | R15: =Carteira!Y36 | W15: =APORTE_MENSAL | AB15: =IF(APORTE_MENSAL>0,Carteira!Z36/APORTE_MENSAL/12,0)
C17: Destaques | O17: rankings atualizados automaticamente
C19: Maiores posições | M19: Maiores altas | W19: Maiores quedas
C20: # | D20: ATIVO | F20: POSIÇÃO | I20: PARTICIPAÇÃO | M20: # | N20: ATIVO | P20: VALORIZAÇÃO | S20: LUCRO | W20: # | X20: ATIVO | Z20: VALORIZAÇÃO | AC20: LUCRO
C21: 1 | D21: =IF(SUM(Carteira!$C$5:$C$35)=0,"",'Base Painel'!G5) | F21: =IF(SUM(Carteira!$C$5:$C$35)=0,"",'Base Painel'!H5) | I21: =IF(SUM(Carteira!$C$5:$C$35)=0,"",'Base Painel'!AJ5) | M21: 1 | N21: =IF(SUM(Carteira!$C$5:$C$35)=0,"",'Base Painel'!K5) | P21: =IF(SUM(Carteira!$C$5:$C$35)=0,"",'Base Painel'!L5) | S21: =IF(SUM(Carteira!$C$5:$C$35)=0,"",'Base Painel'!M5) | W21: 1 | X21: =IF(SUM(Carteira!$C$5:$C$35)=0,"",'Base Painel'!P5) | Z21: =IF(SUM(Carteira!$C$5:$C$35)=0,"",'Base Painel'!Q5) | AC21: =IF(SUM(Carteira!$C$5:$C$35)=0,"",'Base Painel'!R5)
C22: 2 | D22: =IF(SUM(Carteira!$C$5:$C$35)=0,"",'Base Painel'!G6) | F22: =IF(SUM(Carteira!$C$5:$C$35)=0,"",'Base Painel'!H6) | I22: =IF(SUM(Carteira!$C$5:$C$35)=0,"",'Base Painel'!AJ6) | M22: 2 | N22: =IF(SUM(Carteira!$C$5:$C$35)=0,"",'Base Painel'!K6) | P22: =IF(SUM(Carteira!$C$5:$C$35)=0,"",'Base Painel'!L6) | S22: =IF(SUM(Carteira!$C$5:$C$35)=0,"",'Base Painel'!M6) | W22: 2 | X22: =IF(SUM(Carteira!$C$5:$C$35)=0,"",'Base Painel'!P6) | Z22: =IF(SUM(Carteira!$C$5:$C$35)=0,"",'Base Painel'!Q6) | AC22: =IF(SUM(Carteira!$C$5:$C$35)=0,"",'Base Painel'!R6)
C23: 3 | D23: =IF(SUM(Carteira!$C$5:$C$35)=0,"",'Base Painel'!G7) | F23: =IF(SUM(Carteira!$C$5:$C$35)=0,"",'Base Painel'!H7) | I23: =IF(SUM(Carteira!$C$5:$C$35)=0,"",'Base Painel'!AJ7) | M23: 3 | N23: =IF(SUM(Carteira!$C$5:$C$35)=0,"",'Base Painel'!K7) | P23: =IF(SUM(Carteira!$C$5:$C$35)=0,"",'Base Painel'!L7) | S23: =IF(SUM(Carteira!$C$5:$C$35)=0,"",'Base Painel'!M7) | W23: 3 | X23: =IF(SUM(Carteira!$C$5:$C$35)=0,"",'Base Painel'!P7) | Z23: =IF(SUM(Carteira!$C$5:$C$35)=0,"",'Base Painel'!Q7) | AC23: =IF(SUM(Carteira!$C$5:$C$35)=0,"",'Base Painel'!R7)
C24: 4 | D24: =IF(SUM(Carteira!$C$5:$C$35)=0,"",'Base Painel'!G8) | F24: =IF(SUM(Carteira!$C$5:$C$35)=0,"",'Base Painel'!H8) | I24: =IF(SUM(Carteira!$C$5:$C$35)=0,"",'Base Painel'!AJ8) | M24: 4 | N24: =IF(SUM(Carteira!$C$5:$C$35)=0,"",'Base Painel'!K8) | P24: =IF(SUM(Carteira!$C$5:$C$35)=0,"",'Base Painel'!L8) | S24: =IF(SUM(Carteira!$C$5:$C$35)=0,"",'Base Painel'!M8) | W24: 4 | X24: =IF(SUM(Carteira!$C$5:$C$35)=0,"",'Base Painel'!P8) | Z24: =IF(SUM(Carteira!$C$5:$C$35)=0,"",'Base Painel'!Q8) | AC24: =IF(SUM(Carteira!$C$5:$C$35)=0,"",'Base Painel'!R8)
C25: 5 | D25: =IF(SUM(Carteira!$C$5:$C$35)=0,"",'Base Painel'!G9) | F25: =IF(SUM(Carteira!$C$5:$C$35)=0,"",'Base Painel'!H9) | I25: =IF(SUM(Carteira!$C$5:$C$35)=0,"",'Base Painel'!AJ9) | M25: 5 | N25: =IF(SUM(Carteira!$C$5:$C$35)=0,"",'Base Painel'!K9) | P25: =IF(SUM(Carteira!$C$5:$C$35)=0,"",'Base Painel'!L9) | S25: =IF(SUM(Carteira!$C$5:$C$35)=0,"",'Base Painel'!M9) | W25: 5 | X25: =IF(SUM(Carteira!$C$5:$C$35)=0,"",'Base Painel'!P9) | Z25: =IF(SUM(Carteira!$C$5:$C$35)=0,"",'Base Painel'!Q9) | AC25: =IF(SUM(Carteira!$C$5:$C$35)=0,"",'Base Painel'!R9)
C27: Composição e resultado | O27: barras ordenadas da maior para a menor
C45: Meta de renda por ativo
C63: Proventos e rebalanceamento
C81: Alocação por classe | O81: valores de outras classes e pesos ideais: aba Premissas
C83: Classe | H83: Valor (R$) | M83: Peso atual | Q83: Peso ideal | U83: Desvio | Y83: Aporte p/ ideal (R$)
C84: Ações | H84: =Carteira!G38 | M84: =IF($H$89>0,H84/$H$89,0) | Q84: =PESO_RV*SUMIFS(Ativos!$F$5:$F$35,Ativos!$B$5:$B$35,"AÇÃO")/Ativos!$F$36 | U84: =M84-Q84 | Y84: =MAX(0,Q84*$H$89-H84)
C85: FIIs | H85: =Carteira!G39 | M85: =IF($H$89>0,H85/$H$89,0) | Q85: =PESO_RV*SUMIFS(Ativos!$F$5:$F$35,Ativos!$B$5:$B$35,"FII")/Ativos!$F$36 | U85: =M85-Q85 | Y85: =MAX(0,Q85*$H$89-H85)
C86: =Premissas!A11 | H86: =Premissas!B11 | M86: =IF($H$89>0,H86/$H$89,0) | Q86: =Premissas!C11 | U86: =M86-Q86 | Y86: =MAX(0,Q86*$H$89-H86)
C87: =Premissas!A12 | H87: =Premissas!B12 | M87: =IF($H$89>0,H87/$H$89,0) | Q87: =Premissas!C12 | U87: =M87-Q87 | Y87: =MAX(0,Q87*$H$89-H87)
C88: =Premissas!A13 | H88: =Premissas!B13 | M88: =IF($H$89>0,H88/$H$89,0) | Q88: =Premissas!C13 | U88: =M88-Q88 | Y88: =MAX(0,Q88*$H$89-H88)
C89: TOTAL | H89: =SUM(H84:H88) | M89: =SUM(M84:M88) | Q89: =SUM(Q84:Q88) | Y89: =SUM(Y84:Y88)

Sheet Carteira
B1: ◆ InvestERP Painel Carteira Análises ✚ Lançar Lançamentos Proventos Premissas Verificar
A2: Carteira
A3: Cada ação/FII em uma linha só: posição, proventos, peso e meta de renda — calculado, não digite aqui.
A4: Ticker | B4: Tipo | C4: Qtd atual | D4: Preço médio (R$) | E4: Valor investido (R$) | F4: Cotação (R$) | G4: Posição atual (R$) | H4: Lucro / prejuízo (R$) | I4: Valorização | J4: Proventos recebidos (R$) | K4: Proventos 12m (R$) | L4: Retorno total (R$) | M4: Retorno total % | N4: Yield on cost | O4: DY atual | P4: Peso atual | Q4: Peso ideal | R4: Desvio do peso | S4: Aporte p/ peso ideal (R$) | T4: Provento 12m por cota (R$) | U4: Provento mensal por cota (R$) | V4: Renda mensal (R$) | W4: % da meta | X4: Cotas p/ meta | Y4: Cotas faltantes | Z4: Aporte p/ meta (R$) | AA4: Meses p/ meta | AB4: Segmento
A5: =IF(Ativos!A5="","",Ativos!A5) | B5: =IF(Ativos!B5="","",Ativos!B5) | C5: =SUMIFS('Lançamentos'!$D$5:$D$5000,'Lançamentos'!$B$5:$B$5000,A5,'Lançamentos'!$C$5:$C$5000,"COMPRA")-SUMIFS('Lançamentos'!$D$5:$D$5000,'Lançamentos'!$B$5:$B$5000,A5,'Lançamentos'!$C$5:$C$5000,"VENDA") | D5: =IFERROR(SUMIFS('Lançamentos'!$G$5:$G$5000,'Lançamentos'!$B$5:$B$5000,A5,'Lançamentos'!$C$5:$C$5000,"COMPRA")/SUMIFS('Lançamentos'!$D$5:$D$5000,'Lançamentos'!$B$5:$B$5000,A5,'Lançamentos'!$C$5:$C$5000,"COMPRA"),0) | E5: =C5*D5 | F5: =N(Ativos!D5) | G5: =C5*F5 | H5: =G5-E5 | I5: =IF(E5>0,H5/E5,0) | J5: =SUMIFS(Proventos!$F$5:$F$5000,Proventos!$B$5:$B$5000,A5) | K5: =SUMIFS(Proventos!$F$5:$F$5000,Proventos!$B$5:$B$5000,A5,Proventos!$A$5:$A$5000,">="&(TODAY()-365)) | L5: =H5+J5 | M5: =IF(E5>0,L5/E5,0) | N5: =IF(D5>0,T5/D5,0) | O5: =IF(F5>0,T5/F5,0) | P5: =IF($G$36>0,G5/$G$36,0) | Q5: =N(Ativos!F5) | R5: =P5-Q5 | S5: =MAX(0,Q5*$G$36-G5) | T5: =N(Ativos!E5) | U5: =T5/12 | V5: =C5*U5 | W5: =IF(META_MENSAL>0,MIN(1,V5/META_MENSAL),0) | X5: =IF(U5>0,ROUNDUP(META_MENSAL/U5,0),0) | Y5: =MAX(0,X5-C5) | Z5: =Y5*F5 | AA5: =IF(APORTE_MENSAL>0,ROUNDUP(Z5/APORTE_MENSAL,0),0) | AB5: =IF(Ativos!C5="","",Ativos!C5)
A6: =IF(Ativos!A6="","",Ativos!A6) | B6: =IF(Ativos!B6="","",Ativos!B6) | C6: =SUMIFS('Lançamentos'!$D$5:$D$5000,'Lançamentos'!$B$5:$B$5000,A6,'Lançamentos'!$C$5:$C$5000,"COMPRA")-SUMIFS('Lançamentos'!$D$5:$D$5000,'Lançamentos'!$B$5:$B$5000,A6,'Lançamentos'!$C$5:$C$5000,"VENDA") | D6: =IFERROR(SUMIFS('Lançamentos'!$G$5:$G$5000,'Lançamentos'!$B$5:$B$5000,A6,'Lançamentos'!$C$5:$C$5000,"COMPRA")/SUMIFS('Lançamentos'!$D$5:$D$5000,'Lançamentos'!$B$5:$B$5000,A6,'Lançamentos'!$C$5:$C$5000,"COMPRA"),0) | E6: =C6*D6 | F6: =N(Ativos!D6) | G6: =C6*F6 | H6: =G6-E6 | I6: =IF(E6>0,H6/E6,0) | J6: =SUMIFS(Proventos!$F$5:$F$5000,Proventos!$B$5:$B$5000,A6) | K6: =SUMIFS(Proventos!$F$5:$F$5000,Proventos!$B$5:$B$5000,A6,Proventos!$A$5:$A$5000,">="&(TODAY()-365)) | L6: =H6+J6 | M6: =IF(E6>0,L6/E6,0) | N6: =IF(D6>0,T6/D6,0) | O6: =IF(F6>0,T6/F6,0) | P6: =IF($G$36>0,G6/$G$36,0) | Q6: =N(Ativos!F6) | R6: =P6-Q6 | S6: =MAX(0,Q6*$G$36-G6) | T6: =N(Ativos!E6) | U6: =T6/12 | V6: =C6*U6 | W6: =IF(META_MENSAL>0,MIN(1,V6/META_MENSAL),0) | X6: =IF(U6>0,ROUNDUP(META_MENSAL/U6,0),0) | Y6: =MAX(0,X6-C6) | Z6: =Y6*F6 | AA6: =IF(APORTE_MENSAL>0,ROUNDUP(Z6/APORTE_MENSAL,0),0) | AB6: =IF(Ativos!C6="","",Ativos!C6)
A7: =IF(Ativos!A7="","",Ativos!A7) | B7: =IF(Ativos!B7="","",Ativos!B7) | C7: =SUMIFS('Lançamentos'!$D$5:$D$5000,'Lançamentos'!$B$5:$B$5000,A7,'Lançamentos'!$C$5:$C$5000,"COMPRA")-SUMIFS('Lançamentos'!$D$5:$D$5000,'Lançamentos'!$B$5:$B$5000,A7,'Lançamentos'!$C$5:$C$5000,"VENDA") | D7: =IFERROR(SUMIFS('Lançamentos'!$G$5:$G$5000,'Lançamentos'!$B$5:$B$5000,A7,'Lançamentos'!$C$5:$C$5000,"COMPRA")/SUMIFS('Lançamentos'!$D$5:$D$5000,'Lançamentos'!$B$5:$B$5000,A7,'Lançamentos'!$C$5:$C$5000,"COMPRA"),0) | E7: =C7*D7 | F7: =N(Ativos!D7) | G7: =C7*F7 | H7: =G7-E7 | I7: =IF(E7>0,H7/E7,0) | J7: =SUMIFS(Proventos!$F$5:$F$5000,Proventos!$B$5:$B$5000,A7) | K7: =SUMIFS(Proventos!$F$5:$F$5000,Proventos!$B$5:$B$5000,A7,Proventos!$A$5:$A$5000,">="&(TODAY()-365)) | L7: =H7+J7 | M7: =IF(E7>0,L7/E7,0) | N7: =IF(D7>0,T7/D7,0) | O7: =IF(F7>0,T7/F7,0) | P7: =IF($G$36>0,G7/$G$36,0) | Q7: =N(Ativos!F7) | R7: =P7-Q7 | S7: =MAX(0,Q7*$G$36-G7) | T7: =N(Ativos!E7) | U7: =T7/12 | V7: =C7*U7 | W7: =IF(META_MENSAL>0,MIN(1,V7/META_MENSAL),0) | X7: =IF(U7>0,ROUNDUP(META_MENSAL/U7,0),0) | Y7: =MAX(0,X7-C7) | Z7: =Y7*F7 | AA7: =IF(APORTE_MENSAL>0,ROUNDUP(Z7/APORTE_MENSAL,0),0) | AB7: =IF(Ativos!C7="","",Ativos!C7)
A8: =IF(Ativos!A8="","",Ativos!A8) | B8: =IF(Ativos!B8="","",Ativos!B8) | C8: =SUMIFS('Lançamentos'!$D$5:$D$5000,'Lançamentos'!$B$5:$B$5000,A8,'Lançamentos'!$C$5:$C$5000,"COMPRA")-SUMIFS('Lançamentos'!$D$5:$D$5000,'Lançamentos'!$B$5:$B$5000,A8,'Lançamentos'!$C$5:$C$5000,"VENDA") | D8: =IFERROR(SUMIFS('Lançamentos'!$G$5:$G$5000,'Lançamentos'!$B$5:$B$5000,A8,'Lançamentos'!$C$5:$C$5000,"COMPRA")/SUMIFS('Lançamentos'!$D$5:$D$5000,'Lançamentos'!$B$5:$B$5000,A8,'Lançamentos'!$C$5:$C$5000,"COMPRA"),0) | E8: =C8*D8 | F8: =N(Ativos!D8) | G8: =C8*F8 | H8: =G8-E8 | I8: =IF(E8>0,H8/E8,0) | J8: =SUMIFS(Proventos!$F$5:$F$5000,Proventos!$B$5:$B$5000,A8) | K8: =SUMIFS(Proventos!$F$5:$F$5000,Proventos!$B$5:$B$5000,A8,Proventos!$A$5:$A$5000,">="&(TODAY()-365)) | L8: =H8+J8 | M8: =IF(E8>0,L8/E8,0) | N8: =IF(D8>0,T8/D8,0) | O8: =IF(F8>0,T8/F8,0) | P8: =IF($G$36>0,G8/$G$36,0) | Q8: =N(Ativos!F8) | R8: =P8-Q8 | S8: =MAX(0,Q8*$G$36-G8) | T8: =N(Ativos!E8) | U8: =T8/12 | V8: =C8*U8 | W8: =IF(META_MENSAL>0,MIN(1,V8/META_MENSAL),0) | X8: =IF(U8>0,ROUNDUP(META_MENSAL/U8,0),0) | Y8: =MAX(0,X8-C8) | Z8: =Y8*F8 | AA8: =IF(APORTE_MENSAL>0,ROUNDUP(Z8/APORTE_MENSAL,0),0) | AB8: =IF(Ativos!C8="","",Ativos!C8)
A9: =IF(Ativos!A9="","",Ativos!A9) | B9: =IF(Ativos!B9="","",Ativos!B9) | C9: =SUMIFS('Lançamentos'!$D$5:$D$5000,'Lançamentos'!$B$5:$B$5000,A9,'Lançamentos'!$C$5:$C$5000,"COMPRA")-SUMIFS('Lançamentos'!$D$5:$D$5000,'Lançamentos'!$B$5:$B$5000,A9,'Lançamentos'!$C$5:$C$5000,"VENDA") | D9: =IFERROR(SUMIFS('Lançamentos'!$G$5:$G$5000,'Lançamentos'!$B$5:$B$5000,A9,'Lançamentos'!$C$5:$C$5000,"COMPRA")/SUMIFS('Lançamentos'!$D$5:$D$5000,'Lançamentos'!$B$5:$B$5000,A9,'Lançamentos'!$C$5:$C$5000,"COMPRA"),0) | E9: =C9*D9 | F9: =N(Ativos!D9) | G9: =C9*F9 | H9: =G9-E9 | I9: =IF(E9>0,H9/E9,0) | J9: =SUMIFS(Proventos!$F$5:$F$5000,Proventos!$B$5:$B$5000,A9) | K9: =SUMIFS(Proventos!$F$5:$F$5000,Proventos!$B$5:$B$5000,A9,Proventos!$A$5:$A$5000,">="&(TODAY()-365)) | L9: =H9+J9 | M9: =IF(E9>0,L9/E9,0) | N9: =IF(D9>0,T9/D9,0) | O9: =IF(F9>0,T9/F9,0) | P9: =IF($G$36>0,G9/$G$36,0) | Q9: =N(Ativos!F9) | R9: =P9-Q9 | S9: =MAX(0,Q9*$G$36-G9) | T9: =N(Ativos!E9) | U9: =T9/12 | V9: =C9*U9 | W9: =IF(META_MENSAL>0,MIN(1,V9/META_MENSAL),0) | X9: =IF(U9>0,ROUNDUP(META_MENSAL/U9,0),0) | Y9: =MAX(0,X9-C9) | Z9: =Y9*F9 | AA9: =IF(APORTE_MENSAL>0,ROUNDUP(Z9/APORTE_MENSAL,0),0) | AB9: =IF(Ativos!C9="","",Ativos!C9)
A10: =IF(Ativos!A10="","",Ativos!A10) | B10: =IF(Ativos!B10="","",Ativos!B10) | C10: =SUMIFS('Lançamentos'!$D$5:$D$5000,'Lançamentos'!$B$5:$B$5000,A10,'Lançamentos'!$C$5:$C$5000,"COMPRA")-SUMIFS('Lançamentos'!$D$5:$D$5000,'Lançamentos'!$B$5:$B$5000,A10,'Lançamentos'!$C$5:$C$5000,"VENDA") | D10: =IFERROR(SUMIFS('Lançamentos'!$G$5:$G$5000,'Lançamentos'!$B$5:$B$5000,A10,'Lançamentos'!$C$5:$C$5000,"COMPRA")/SUMIFS('Lançamentos'!$D$5:$D$5000,'Lançamentos'!$B$5:$B$5000,A10,'Lançamentos'!$C$5:$C$5000,"COMPRA"),0) | E10: =C10*D10 | F10: =N(Ativos!D10) | G10: =C10*F10 | H10: =G10-E10 | I10: =IF(E10>0,H10/E10,0) | J10: =SUMIFS(Proventos!$F$5:$F$5000,Proventos!$B$5:$B$5000,A10) | K10: =SUMIFS(Proventos!$F$5:$F$5000,Proventos!$B$5:$B$5000,A10,Proventos!$A$5:$A$5000,">="&(TODAY()-365)) | L10: =H10+J10 | M10: =IF(E10>0,L10/E10,0) | N10: =IF(D10>0,T10/D10,0) | O10: =IF(F10>0,T10/F10,0) | P10: =IF($G$36>0,G10/$G$36,0) | Q10: =N(Ativos!F10) | R10: =P10-Q10 | S10: =MAX(0,Q10*$G$36-G10) | T10: =N(Ativos!E10) | U10: =T10/12 | V10: =C10*U10 | W10: =IF(META_MENSAL>0,MIN(1,V10/META_MENSAL),0) | X10: =IF(U10>0,ROUNDUP(META_MENSAL/U10,0),0) | Y10: =MAX(0,X10-C10) | Z10: =Y10*F10 | AA10: =IF(APORTE_MENSAL>0,ROUNDUP(Z10/APORTE_MENSAL,0),0) | AB10: =IF(Ativos!C10="","",Ativos!C10)
A11: =IF(Ativos!A11="","",Ativos!A11) | B11: =IF(Ativos!B11="","",Ativos!B11) | C11: =SUMIFS('Lançamentos'!$D$5:$D$5000,'Lançamentos'!$B$5:$B$5000,A11,'Lançamentos'!$C$5:$C$5000,"COMPRA")-SUMIFS('Lançamentos'!$D$5:$D$5000,'Lançamentos'!$B$5:$B$5000,A11,'Lançamentos'!$C$5:$C$5000,"VENDA") | D11: =IFERROR(SUMIFS('Lançamentos'!$G$5:$G$5000,'Lançamentos'!$B$5:$B$5000,A11,'Lançamentos'!$C$5:$C$5000,"COMPRA")/SUMIFS('Lançamentos'!$D$5:$D$5000,'Lançamentos'!$B$5:$B$5000,A11,'Lançamentos'!$C$5:$C$5000,"COMPRA"),0) | E11: =C11*D11 | F11: =N(Ativos!D11) | G11: =C11*F11 | H11: =G11-E11 | I11: =IF(E11>0,H11/E11,0) | J11: =SUMIFS(Proventos!$F$5:$F$5000,Proventos!$B$5:$B$5000,A11) | K11: =SUMIFS(Proventos!$F$5:$F$5000,Proventos!$B$5:$B$5000,A11,Proventos!$A$5:$A$5000,">="&(TODAY()-365)) | L11: =H11+J11 | M11: =IF(E11>0,L11/E11,0) | N11: =IF(D11>0,T11/D11,0) | O11: =IF(F11>0,T11/F11,0) | P11: =IF($G$36>0,G11/$G$36,0) | Q11: =N(Ativos!F11) | R11: =P11-Q11 | S11: =MAX(0,Q11*$G$36-G11) | T11: =N(Ativos!E11) | U11: =T11/12 | V11: =C11*U11 | W11: =IF(META_MENSAL>0,MIN(1,V11/META_MENSAL),0) | X11: =IF(U11>0,ROUNDUP(META_MENSAL/U11,0),0) | Y11: =MAX(0,X11-C11) | Z11: =Y11*F11 | AA11: =IF(APORTE_MENSAL>0,ROUNDUP(Z11/APORTE_MENSAL,0),0) | AB11: =IF(Ativos!C11="","",Ativos!C11)
A12: =IF(Ativos!A12="","",Ativos!A12) | B12: =IF(Ativos!B12="","",Ativos!B12) | C12: =SUMIFS('Lançamentos'!$D$5:$D$5000,'Lançamentos'!$B$5:$B$5000,A12,'Lançamentos'!$C$5:$C$5000,"COMPRA")-SUMIFS('Lançamentos'!$D$5:$D$5000,'Lançamentos'!$B$5:$B$5000,A12,'Lançamentos'!$C$5:$C$5000,"VENDA") | D12: =IFERROR(SUMIFS('Lançamentos'!$G$5:$G$5000,'Lançamentos'!$B$5:$B$5000,A12,'Lançamentos'!$C$5:$C$5000,"COMPRA")/SUMIFS('Lançamentos'!$D$5:$D$5000,'Lançamentos'!$B$5:$B$5000,A12,'Lançamentos'!$C$5:$C$5000,"COMPRA"),0) | E12: =C12*D12 | F12: =N(Ativos!D12) | G12: =C12*F12 | H12: =G12-E12 | I12: =IF(E12>0,H12/E12,0) | J12: =SUMIFS(Proventos!$F$5:$F$5000,Proventos!$B$5:$B$5000,A12) | K12: =SUMIFS(Proventos!$F$5:$F$5000,Proventos!$B$5:$B$5000,A12,Proventos!$A$5:$A$5000,">="&(TODAY()-365)) | L12: =H12+J12 | M12: =IF(E12>0,L12/E12,0) | N12: =IF(D12>0,T12/D12,0) | O12: =IF(F12>0,T12/F12,0) | P12: =IF($G$36>0,G12/$G$36,0) | Q12: =N(Ativos!F12) | R12: =P12-Q12 | S12: =MAX(0,Q12*$G$36-G12) | T12: =N(Ativos!E12) | U12: =T12/12 | V12: =C12*U12 | W12: =IF(META_MENSAL>0,MIN(1,V12/META_MENSAL),0) | X12: =IF(U12>0,ROUNDUP(META_MENSAL/U12,0),0) | Y12: =MAX(0,X12-C12) | Z12: =Y12*F12 | AA12: =IF(APORTE_MENSAL>0,ROUNDUP(Z12/APORTE_MENSAL,0),0) | AB12: =IF(Ativos!C12="","",Ativos!C12)
A13: =IF(Ativos!A13="","",Ativos!A13) | B13: =IF(Ativos!B13="","",Ativos!B13) | C13: =SUMIFS('Lançamentos'!$D$5:$D$5000,'Lançamentos'!$B$5:$B$5000,A13,'Lançamentos'!$C$5:$C$5000,"COMPRA")-SUMIFS('Lançamentos'!$D$5:$D$5000,'Lançamentos'!$B$5:$B$5000,A13,'Lançamentos'!$C$5:$C$5000,"VENDA") | D13: =IFERROR(SUMIFS('Lançamentos'!$G$5:$G$5000,'Lançamentos'!$B$5:$B$5000,A13,'Lançamentos'!$C$5:$C$5000,"COMPRA")/SUMIFS('Lançamentos'!$D$5:$D$5000,'Lançamentos'!$B$5:$B$5000,A13,'Lançamentos'!$C$5:$C$5000,"COMPRA"),0) | E13: =C13*D13 | F13: =N(Ativos!D13) | G13: =C13*F13 | H13: =G13-E13 | I13: =IF(E13>0,H13/E13,0) | J13: =SUMIFS(Proventos!$F$5:$F$5000,Proventos!$B$5:$B$5000,A13) | K13: =SUMIFS(Proventos!$F$5:$F$5000,Proventos!$B$5:$B$5000,A13,Proventos!$A$5:$A$5000,">="&(TODAY()-365)) | L13: =H13+J13 | M13: =IF(E13>0,L13/E13,0) | N13: =IF(D13>0,T13/D13,0) | O13: =IF(F13>0,T13/F13,0) | P13: =IF($G$36>0,G13/$G$36,0) | Q13: =N(Ativos!F13) | R13: =P13-Q13 | S13: =MAX(0,Q13*$G$36-G13) | T13: =N(Ativos!E13) | U13: =T13/12 | V13: =C13*U13 | W13: =IF(META_MENSAL>0,MIN(1,V13/META_MENSAL),0) | X13: =IF(U13>0,ROUNDUP(META_MENSAL/U13,0),0) | Y13: =MAX(0,X13-C13) | Z13: =Y13*F13 | AA13: =IF(APORTE_MENSAL>0,ROUNDUP(Z13/APORTE_MENSAL,0),0) | AB13: =IF(Ativos!C13="","",Ativos!C13)
A14: =IF(Ativos!A14="","",Ativos!A14) | B14: =IF(Ativos!B14="","",Ativos!B14) | C14: =SUMIFS('Lançamentos'!$D$5:$D$5000,'Lançamentos'!$B$5:$B$5000,A14,'Lançamentos'!$C$5:$C$5000,"COMPRA")-SUMIFS('Lançamentos'!$D$5:$D$5000,'Lançamentos'!$B$5:$B$5000,A14,'Lançamentos'!$C$5:$C$5000,"VENDA") | D14: =IFERROR(SUMIFS('Lançamentos'!$G$5:$G$5000,'Lançamentos'!$B$5:$B$5000,A14,'Lançamentos'!$C$5:$C$5000,"COMPRA")/SUMIFS('Lançamentos'!$D$5:$D$5000,'Lançamentos'!$B$5:$B$5000,A14,'Lançamentos'!$C$5:$C$5000,"COMPRA"),0) | E14: =C14*D14 | F14: =N(Ativos!D14) | G14: =C14*F14 | H14: =G14-E14 | I14: =IF(E14>0,H14/E14,0) | J14: =SUMIFS(Proventos!$F$5:$F$5000,Proventos!$B$5:$B$5000,A14) | K14: =SUMIFS(Proventos!$F$5:$F$5000,Proventos!$B$5:$B$5000,A14,Proventos!$A$5:$A$5000,">="&(TODAY()-365)) | L14: =H14+J14 | M14: =IF(E14>0,L14/E14,0) | N14: =IF(D14>0,T14/D14,0) | O14: =IF(F14>0,T14/F14,0) | P14: =IF($G$36>0,G14/$G$36,0) | Q14: =N(Ativos!F14) | R14: =P14-Q14 | S14: =MAX(0,Q14*$G$36-G14) | T14: =N(Ativos!E14) | U14: =T14/12 | V14: =C14*U14 | W14: =IF(META_MENSAL>0,MIN(1,V14/META_MENSAL),0) | X14: =IF(U14>0,ROUNDUP(META_MENSAL/U14,0),0) | Y14: =MAX(0,X14-C14) | Z14: =Y14*F14 | AA14: =IF(APORTE_MENSAL>0,ROUNDUP(Z14/APORTE_MENSAL,0),0) | AB14: =IF(Ativos!C14="","",Ativos!C14)
A15: =IF(Ativos!A15="","",Ativos!A15) | B15: =IF(Ativos!B15="","",Ativos!B15) | C15: =SUMIFS('Lançamentos'!$D$5:$D$5000,'Lançamentos'!$B$5:$B$5000,A15,'Lançamentos'!$C$5:$C$5000,"COMPRA")-SUMIFS('Lançamentos'!$D$5:$D$5000,'Lançamentos'!$B$5:$B$5000,A15,'Lançamentos'!$C$5:$C$5000,"VENDA") | D15: =IFERROR(SUMIFS('Lançamentos'!$G$5:$G$5000,'Lançamentos'!$B$5:$B$5000,A15,'Lançamentos'!$C$5:$C$5000,"COMPRA")/SUMIFS('Lançamentos'!$D$5:$D$5000,'Lançamentos'!$B$5:$B$5000,A15,'Lançamentos'!$C$5:$C$5000,"COMPRA"),0) | E15: =C15*D15 | F15: =N(Ativos!D15) | G15: =C15*F15 | H15: =G15-E15 | I15: =IF(E15>0,H15/E15,0) | J15: =SUMIFS(Proventos!$F$5:$F$5000,Proventos!$B$5:$B$5000,A15) | K15: =SUMIFS(Proventos!$F$5:$F$5000,Proventos!$B$5:$B$5000,A15,Proventos!$A$5:$A$5000,">="&(TODAY()-365)) | L15: =H15+J15 | M15: =IF(E15>0,L15/E15,0) | N15: =IF(D15>0,T15/D15,0) | O15: =IF(F15>0,T15/F15,0) | P15: =IF($G$36>0,G15/$G$36,0) | Q15: =N(Ativos!F15) | R15: =P15-Q15 | S15: =MAX(0,Q15*$G$36-G15) | T15: =N(Ativos!E15) | U15: =T15/12 | V15: =C15*U15 | W15: =IF(META_MENSAL>0,MIN(1,V15/META_MENSAL),0) | X15: =IF(U15>0,ROUNDUP(META_MENSAL/U15,0),0) | Y15: =MAX(0,X15-C15) | Z15: =Y15*F15 | AA15: =IF(APORTE_MENSAL>0,ROUNDUP(Z15/APORTE_MENSAL,0),0) | AB15: =IF(Ativos!C15="","",Ativos!C15)
A16: =IF(Ativos!A16="","",Ativos!A16) | B16: =IF(Ativos!B16="","",Ativos!B16) | C16: =SUMIFS('Lançamentos'!$D$5:$D$5000,'Lançamentos'!$B$5:$B$5000,A16,'Lançamentos'!$C$5:$C$5000,"COMPRA")-SUMIFS('Lançamentos'!$D$5:$D$5000,'Lançamentos'!$B$5:$B$5000,A16,'Lançamentos'!$C$5:$C$5000,"VENDA") | D16: =IFERROR(SUMIFS('Lançamentos'!$G$5:$G$5000,'Lançamentos'!$B$5:$B$5000,A16,'Lançamentos'!$C$5:$C$5000,"COMPRA")/SUMIFS('Lançamentos'!$D$5:$D$5000,'Lançamentos'!$B$5:$B$5000,A16,'Lançamentos'!$C$5:$C$5000,"COMPRA"),0) | E16: =C16*D16 | F16: =N(Ativos!D16) | G16: =C16*F16 | H16: =G16-E16 | I16: =IF(E16>0,H16/E16,0) | J16: =SUMIFS(Proventos!$F$5:$F$5000,Proventos!$B$5:$B$5000,A16) | K16: =SUMIFS(Proventos!$F$5:$F$5000,Proventos!$B$5:$B$5000,A16,Proventos!$A$5:$A$5000,">="&(TODAY()-365)) | L16: =H16+J16 | M16: =IF(E16>0,L16/E16,0) | N16: =IF(D16>0,T16/D16,0) | O16: =IF(F16>0,T16/F16,0) | P16: =IF($G$36>0,G16/$G$36,0) | Q16: =N(Ativos!F16) | R16: =P16-Q16 | S16: =MAX(0,Q16*$G$36-G16) | T16: =N(Ativos!E16) | U16: =T16/12 | V16: =C16*U16 | W16: =IF(META_MENSAL>0,MIN(1,V16/META_MENSAL),0) | X16: =IF(U16>0,ROUNDUP(META_MENSAL/U16,0),0) | Y16: =MAX(0,X16-C16) | Z16: =Y16*F16 | AA16: =IF(APORTE_MENSAL>0,ROUNDUP(Z16/APORTE_MENSAL,0),0) | AB16: =IF(Ativos!C16="","",Ativos!C16)
... A35: =IF(Ativos!A35="","",Ativos!A35) | B35: =IF(Ativos!B35="","",Ativos!B35) | C35: =SUMIFS('Lançamentos'!$D$5:$D$5000,'Lançamentos'!$B$5:$B$5000,A35,'Lançamentos'!$C$5:$C$5000,"COMPRA")-SUMIFS('Lançamentos'!$D$5:$D$5000,'Lançamentos'!$B$5:$B$5000,A35,'Lançamentos'!$C$5:$C$5000,"VENDA") | D35: =IFERROR(SUMIFS('Lançamentos'!$G$5:$G$5000,'Lançamentos'!$B$5:$B$5000,A35,'Lançamentos'!$C$5:$C$5000,"COMPRA")/SUMIFS('Lançamentos'!$D$5:$D$5000,'Lançamentos'!$B$5:$B$5000,A35,'Lançamentos'!$C$5:$C$5000,"COMPRA"),0) | E35: =C35*D35 | F35: =N(Ativos!D35) | G35: =C35*F35 | H35: =G35-E35 | I35: =IF(E35>0,H35/E35,0) | J35: =SUMIFS(Proventos!$F$5:$F$5000,Proventos!$B$5:$B$5000,A35) | K35: =SUMIFS(Proventos!$F$5:$F$5000,Proventos!$B$5:$B$5000,A35,Proventos!$A$5:$A$5000,">="&(TODAY()-365)) | L35: =H35+J35 | M35: =IF(E35>0,L35/E35,0) | N35: =IF(D35>0,T35/D35,0) | O35: =IF(F35>0,T35/F35,0) | P35: =IF($G$36>0,G35/$G$36,0) | Q35: =N(Ativos!F35) | R35: =P35-Q35 | S35: =MAX(0,Q35*$G$36-G35) | T35: =N(Ativos!E35) | U35: =T35/12 | V35: =C35*U35 | W35: =IF(META_MENSAL>0,MIN(1,V35/META_MENSAL),0) | X35: =IF(U35>0,ROUNDUP(META_MENSAL/U35,0),0) | Y35: =MAX(0,X35-C35) | Z35: =Y35*F35 | AA35: =IF(APORTE_MENSAL>0,ROUNDUP(Z35/APORTE_MENSAL,0),0) | AB35: =IF(Ativos!C35="","",Ativos!C35)
A36: TOTAL | E36: =SUM(E5:E35) | G36: =SUM(G5:G35) | H36: =SUM(H5:H35) | I36: =IF(E36>0,H36/E36,0) | J36: =SUM(J5:J35) | K36: =SUM(K5:K35) | L36: =SUM(L5:L35) | M36: =IF(E36>0,L36/E36,0) | N36: =IF(E36>0,SUMPRODUCT(C5:C35,T5:T35)/E36,0) | O36: =IF(G36>0,SUMPRODUCT(C5:C35,T5:T35)/G36,0) | P36: =SUM(P5:P35) | Q36: =SUM(Q5:Q35) | S36: =SUM(S5:S35) | V36: =SUM(V5:V35) | W36: =IFERROR(AVERAGEIF(A5:A35,"?*",W5:W35),0) | X36: =COUNTIF(W5:W35,">=1")&" de "&COUNTIF(A5:A35,"?*")&" na meta" | Y36: =SUM(Y5:Y35) | Z36: =SUM(Z5:Z35) | AA36: =IF(APORTE_MENSAL>0,ROUNDUP(Z36/APORTE_MENSAL,0),0)
A38: Subtotal ações | E38: =SUMIFS(E5:E35,$B$5:$B$35,"AÇÃO") | G38: =SUMIFS(G5:G35,$B$5:$B$35,"AÇÃO") | H38: =SUMIFS(H5:H35,$B$5:$B$35,"AÇÃO") | I38: =IF(E38>0,H38/E38,0) | J38: =SUMIFS(J5:J35,$B$5:$B$35,"AÇÃO") | L38: =SUMIFS(L5:L35,$B$5:$B$35,"AÇÃO") | P38: =SUMIFS(P5:P35,$B$5:$B$35,"AÇÃO") | V38: =SUMIFS(V5:V35,$B$5:$B$35,"AÇÃO")
A39: Subtotal FIIs | E39: =SUMIFS(E5:E35,$B$5:$B$35,"FII") | G39: =SUMIFS(G5:G35,$B$5:$B$35,"FII") | H39: =SUMIFS(H5:H35,$B$5:$B$35,"FII") | I39: =IF(E39>0,H39/E39,0) | J39: =SUMIFS(J5:J35,$B$5:$B$35,"FII") | L39: =SUMIFS(L5:L35,$B$5:$B$35,"FII") | P39: =SUMIFS(P5:P35,$B$5:$B$35,"FII") | V39: =SUMIFS(V5:V35,$B$5:$B$35,"FII")
A41: Como ler
A42: • Linhas em cinza: ativos do catálogo que você ainda não tem (a mesma lista serve de catálogo e de carteira).
A43: • Meta de renda: cotas p/ meta = meta mensal ÷ provento mensal por cota; aporte = cotas faltantes × cotação.
A44: • Tipo, segmento, cotação, provento 12m e peso ideal vêm de dados/ativos.csv (aba Ativos, oculta).

Sheet Análises
B1: ◆ InvestERP Painel Carteira Análises ✚ Lançar Lançamentos Proventos Premissas Verificar
A2: Análises Dinâmicas
A3: Consultas QUERY recalculadas automaticamente pelo Google Planilhas.
A5: Carteira por tipo de ativo | G5: Posição por ativo
A7: =IFERROR(QUERY(Carteira!A5:AB200,"select B, sum(E), sum(G), sum(H), sum(J) where C > 0 group by B label B 'Tipo', sum(E) 'Investido', sum(G) 'Posição', sum(H) 'Lucro', sum(J) 'Proventos'",0),"Nenhuma ação ou FII na carteira ainda") | G7: =IFERROR(QUERY(Carteira!A5:G200,"select A, G where C > 0 order by G desc label A 'Ticker', G 'Posição'",0),"Sem posições")
A20: Proventos por ativo | G20: Lançamentos por ativo e operação
A22: =IFERROR(QUERY(Proventos!A5:F5000,"select B, sum(F) where B is not null group by B order by sum(F) desc label B 'Ticker', sum(F) 'Proventos'",0),"Sem proventos registrados") | G22: =IFERROR(QUERY('Lançamentos'!A5:G5000,"select B, sum(G) where B is not null group by B pivot C label B 'Ticker'",0),"Sem lançamentos")

Sheet Cadastro
B1: ◆ InvestERP Painel Carteira Análises ✚ Lançar Lançamentos Proventos Premissas Verificar
A2: Novo Lançamento
A3: Escolha o ticker, informe a quantidade e clique em Registrar — o resto vem do cadastro do ativo. | L3: cadastro-formulario-v3
B5: Amarelo = você preenche • Cinza ⟲ = automático • Marque a caixa Registrar (ou menu InvestERP › Registrar)
B7: ✚ Compra / venda de cotas | E7: ◈ Provento recebido | H7: Últimos lançamentos
B8: Data (vazio = hoje) | E8: Data pagamento (vazio = hoje) | H8: Data | I8: Ticker | J8: Operação | K8: Cotas | L8: Preço (R$)
B9: Ticker | E9: Ticker | H9: =IF((COUNTA('Lançamentos'!$B:$B)+3-0)<5,"",INDEX('Lançamentos'!$A:$A,(COUNTA('Lançamentos'!$B:$B)+3-0))) | I9: =IF((COUNTA('Lançamentos'!$B:$B)+3-0)<5,"",INDEX('Lançamentos'!$B:$B,(COUNTA('Lançamentos'!$B:$B)+3-0))) | J9: =IF((COUNTA('Lançamentos'!$B:$B)+3-0)<5,"",INDEX('Lançamentos'!$C:$C,(COUNTA('Lançamentos'!$B:$B)+3-0))) | K9: =IF((COUNTA('Lançamentos'!$B:$B)+3-0)<5,"",INDEX('Lançamentos'!$D:$D,(COUNTA('Lançamentos'!$B:$B)+3-0))) | L9: =IF((COUNTA('Lançamentos'!$B:$B)+3-0)<5,"",INDEX('Lançamentos'!$E:$E,(COUNTA('Lançamentos'!$B:$B)+3-0)))
B10: Operação (vazio = compra) | E10: Tipo de provento | H10: =IF((COUNTA('Lançamentos'!$B:$B)+3-1)<5,"",INDEX('Lançamentos'!$A:$A,(COUNTA('Lançamentos'!$B:$B)+3-1))) | I10: =IF((COUNTA('Lançamentos'!$B:$B)+3-1)<5,"",INDEX('Lançamentos'!$B:$B,(COUNTA('Lançamentos'!$B:$B)+3-1))) | J10: =IF((COUNTA('Lançamentos'!$B:$B)+3-1)<5,"",INDEX('Lançamentos'!$C:$C,(COUNTA('Lançamentos'!$B:$B)+3-1))) | K10: =IF((COUNTA('Lançamentos'!$B:$B)+3-1)<5,"",INDEX('Lançamentos'!$D:$D,(COUNTA('Lançamentos'!$B:$B)+3-1))) | L10: =IF((COUNTA('Lançamentos'!$B:$B)+3-1)<5,"",INDEX('Lançamentos'!$E:$E,(COUNTA('Lançamentos'!$B:$B)+3-1)))
B11: Quantidade de cotas | E11: Valor por cota (R$) | H11: =IF((COUNTA('Lançamentos'!$B:$B)+3-2)<5,"",INDEX('Lançamentos'!$A:$A,(COUNTA('Lançamentos'!$B:$B)+3-2))) | I11: =IF((COUNTA('Lançamentos'!$B:$B)+3-2)<5,"",INDEX('Lançamentos'!$B:$B,(COUNTA('Lançamentos'!$B:$B)+3-2))) | J11: =IF((COUNTA('Lançamentos'!$B:$B)+3-2)<5,"",INDEX('Lançamentos'!$C:$C,(COUNTA('Lançamentos'!$B:$B)+3-2))) | K11: =IF((COUNTA('Lançamentos'!$B:$B)+3-2)<5,"",INDEX('Lançamentos'!$D:$D,(COUNTA('Lançamentos'!$B:$B)+3-2))) | L11: =IF((COUNTA('Lançamentos'!$B:$B)+3-2)<5,"",INDEX('Lançamentos'!$E:$E,(COUNTA('Lançamentos'!$B:$B)+3-2)))
B12: Preço por cota (vazio = cotação) | E12: Qtd de cotas (vazio = suas cotas) | H12: =IF((COUNTA('Lançamentos'!$B:$B)+3-3)<5,"",INDEX('Lançamentos'!$A:$A,(COUNTA('Lançamentos'!$B:$B)+3-3))) | I12: =IF((COUNTA('Lançamentos'!$B:$B)+3-3)<5,"",INDEX('Lançamentos'!$B:$B,(COUNTA('Lançamentos'!$B:$B)+3-3))) | J12: =IF((COUNTA('Lançamentos'!$B:$B)+3-3)<5,"",INDEX('Lançamentos'!$C:$C,(COUNTA('Lançamentos'!$B:$B)+3-3))) | K12: =IF((COUNTA('Lançamentos'!$B:$B)+3-3)<5,"",INDEX('Lançamentos'!$D:$D,(COUNTA('Lançamentos'!$B:$B)+3-3))) | L12: =IF((COUNTA('Lançamentos'!$B:$B)+3-3)<5,"",INDEX('Lançamentos'!$E:$E,(COUNTA('Lançamentos'!$B:$B)+3-3)))
B13: Custos / taxas (R$) | E13: AUTOMÁTICO ⟲ | H13: =IF((COUNTA('Lançamentos'!$B:$B)+3-4)<5,"",INDEX('Lançamentos'!$A:$A,(COUNTA('Lançamentos'!$B:$B)+3-4))) | I13: =IF((COUNTA('Lançamentos'!$B:$B)+3-4)<5,"",INDEX('Lançamentos'!$B:$B,(COUNTA('Lançamentos'!$B:$B)+3-4))) | J13: =IF((COUNTA('Lançamentos'!$B:$B)+3-4)<5,"",INDEX('Lançamentos'!$C:$C,(COUNTA('Lançamentos'!$B:$B)+3-4))) | K13: =IF((COUNTA('Lançamentos'!$B:$B)+3-4)<5,"",INDEX('Lançamentos'!$D:$D,(COUNTA('Lançamentos'!$B:$B)+3-4))) | L13: =IF((COUNTA('Lançamentos'!$B:$B)+3-4)<5,"",INDEX('Lançamentos'!$E:$E,(COUNTA('Lançamentos'!$B:$B)+3-4)))
B14: DADOS DO ATIVO ⟲ automático | E14: Cotas que você tem | F14: =IF(pv_ticker="","",IFERROR(INDEX(Carteira!$C$5:$C$35,MATCH(pv_ticker,Carteira!$A$5:$A$35,0)),0)) | H14: =IF((COUNTA('Lançamentos'!$B:$B)+3-5)<5,"",INDEX('Lançamentos'!$A:$A,(COUNTA('Lançamentos'!$B:$B)+3-5))) | I14: =IF((COUNTA('Lançamentos'!$B:$B)+3-5)<5,"",INDEX('Lançamentos'!$B:$B,(COUNTA('Lançamentos'!$B:$B)+3-5))) | J14: =IF((COUNTA('Lançamentos'!$B:$B)+3-5)<5,"",INDEX('Lançamentos'!$C:$C,(COUNTA('Lançamentos'!$B:$B)+3-5))) | K14: =IF((COUNTA('Lançamentos'!$B:$B)+3-5)<5,"",INDEX('Lançamentos'!$D:$D,(COUNTA('Lançamentos'!$B:$B)+3-5))) | L14: =IF((COUNTA('Lançamentos'!$B:$B)+3-5)<5,"",INDEX('Lançamentos'!$E:$E,(COUNTA('Lançamentos'!$B:$B)+3-5)))
B15: Ativo | C15: =IF(lc_ticker="","",IFERROR(INDEX(Ativos!$B$5:$B$35,MATCH(lc_ticker,Ativos!$A$5:$A$35,0))&" • "&INDEX(Ativos!$C$5:$C$35,MATCH(lc_ticker,Ativos!$A$5:$A$35,0)),"Ticker novo — preencha Tipo e Segmento abaixo")) | E15: Total recebido | F15: =IF(pv_valor="","",pv_valor*IF(pv_qtd="",N(pv_tem),pv_qtd)) | H15: =IF((COUNTA('Lançamentos'!$B:$B)+3-6)<5,"",INDEX('Lançamentos'!$A:$A,(COUNTA('Lançamentos'!$B:$B)+3-6))) | I15: =IF((COUNTA('Lançamentos'!$B:$B)+3-6)<5,"",INDEX('Lançamentos'!$B:$B,(COUNTA('Lançamentos'!$B:$B)+3-6))) | J15: =IF((COUNTA('Lançamentos'!$B:$B)+3-6)<5,"",INDEX('Lançamentos'!$C:$C,(COUNTA('Lançamentos'!$B:$B)+3-6))) | K15: =IF((COUNTA('Lançamentos'!$B:$B)+3-6)<5,"",INDEX('Lançamentos'!$D:$D,(COUNTA('Lançamentos'!$B:$B)+3-6))) | L15: =IF((COUNTA('Lançamentos'!$B:$B)+3-6)<5,"",INDEX('Lançamentos'!$E:$E,(COUNTA('Lançamentos'!$B:$B)+3-6)))
B16: Cotação atual (R$) | C16: =IF(lc_ticker="","",IFERROR(INDEX(Ativos!$D$5:$D$35,MATCH(lc_ticker,Ativos!$A$5:$A$35,0)),"")) | H16: =IF((COUNTA('Lançamentos'!$B:$B)+3-7)<5,"",INDEX('Lançamentos'!$A:$A,(COUNTA('Lançamentos'!$B:$B)+3-7))) | I16: =IF((COUNTA('Lançamentos'!$B:$B)+3-7)<5,"",INDEX('Lançamentos'!$B:$B,(COUNTA('Lançamentos'!$B:$B)+3-7))) | J16: =IF((COUNTA('Lançamentos'!$B:$B)+3-7)<5,"",INDEX('Lançamentos'!$C:$C,(COUNTA('Lançamentos'!$B:$B)+3-7))) | K16: =IF((COUNTA('Lançamentos'!$B:$B)+3-7)<5,"",INDEX('Lançamentos'!$D:$D,(COUNTA('Lançamentos'!$B:$B)+3-7))) | L16: =IF((COUNTA('Lançamentos'!$B:$B)+3-7)<5,"",INDEX('Lançamentos'!$E:$E,(COUNTA('Lançamentos'!$B:$B)+3-7)))
B17: Cotas que você tem | C17: =IF(lc_ticker="","",IFERROR(INDEX(Carteira!$C$5:$C$35,MATCH(lc_ticker,Carteira!$A$5:$A$35,0)),0)) | H17: =IF((COUNTA('Lançamentos'!$B:$B)+3-8)<5,"",INDEX('Lançamentos'!$A:$A,(COUNTA('Lançamentos'!$B:$B)+3-8))) | I17: =IF((COUNTA('Lançamentos'!$B:$B)+3-8)<5,"",INDEX('Lançamentos'!$B:$B,(COUNTA('Lançamentos'!$B:$B)+3-8))) | J17: =IF((COUNTA('Lançamentos'!$B:$B)+3-8)<5,"",INDEX('Lançamentos'!$C:$C,(COUNTA('Lançamentos'!$B:$B)+3-8))) | K17: =IF((COUNTA('Lançamentos'!$B:$B)+3-8)<5,"",INDEX('Lançamentos'!$D:$D,(COUNTA('Lançamentos'!$B:$B)+3-8))) | L17: =IF((COUNTA('Lançamentos'!$B:$B)+3-8)<5,"",INDEX('Lançamentos'!$E:$E,(COUNTA('Lançamentos'!$B:$B)+3-8)))
B18: SÓ PARA TICKER NOVO | E18: ✔ Registrar provento → | F18: FALSE | H18: =IF((COUNTA('Lançamentos'!$B:$B)+3-9)<5,"",INDEX('Lançamentos'!$A:$A,(COUNTA('Lançamentos'!$B:$B)+3-9))) | I18: =IF((COUNTA('Lançamentos'!$B:$B)+3-9)<5,"",INDEX('Lançamentos'!$B:$B,(COUNTA('Lançamentos'!$B:$B)+3-9))) | J18: =IF((COUNTA('Lançamentos'!$B:$B)+3-9)<5,"",INDEX('Lançamentos'!$C:$C,(COUNTA('Lançamentos'!$B:$B)+3-9))) | K18: =IF((COUNTA('Lançamentos'!$B:$B)+3-9)<5,"",INDEX('Lançamentos'!$D:$D,(COUNTA('Lançamentos'!$B:$B)+3-9))) | L18: =IF((COUNTA('Lançamentos'!$B:$B)+3-9)<5,"",INDEX('Lançamentos'!$E:$E,(COUNTA('Lançamentos'!$B:$B)+3-9)))
B19: Tipo do ativo (AÇÃO / FII) | H19: =IF((COUNTA('Lançamentos'!$B:$B)+3-10)<5,"",INDEX('Lançamentos'!$A:$A,(COUNTA('Lançamentos'!$B:$B)+3-10))) | I19: =IF((COUNTA('Lançamentos'!$B:$B)+3-10)<5,"",INDEX('Lançamentos'!$B:$B,(COUNTA('Lançamentos'!$B:$B)+3-10))) | J19: =IF((COUNTA('Lançamentos'!$B:$B)+3-10)<5,"",INDEX('Lançamentos'!$C:$C,(COUNTA('Lançamentos'!$B:$B)+3-10))) | K19: =IF((COUNTA('Lançamentos'!$B:$B)+3-10)<5,"",INDEX('Lançamentos'!$D:$D,(COUNTA('Lançamentos'!$B:$B)+3-10))) | L19: =IF((COUNTA('Lançamentos'!$B:$B)+3-10)<5,"",INDEX('Lançamentos'!$E:$E,(COUNTA('Lançamentos'!$B:$B)+3-10)))
B20: Segmento | H20: =IF((COUNTA('Lançamentos'!$B:$B)+3-11)<5,"",INDEX('Lançamentos'!$A:$A,(COUNTA('Lançamentos'!$B:$B)+3-11))) | I20: =IF((COUNTA('Lançamentos'!$B:$B)+3-11)<5,"",INDEX('Lançamentos'!$B:$B,(COUNTA('Lançamentos'!$B:$B)+3-11))) | J20: =IF((COUNTA('Lançamentos'!$B:$B)+3-11)<5,"",INDEX('Lançamentos'!$C:$C,(COUNTA('Lançamentos'!$B:$B)+3-11))) | K20: =IF((COUNTA('Lançamentos'!$B:$B)+3-11)<5,"",INDEX('Lançamentos'!$D:$D,(COUNTA('Lançamentos'!$B:$B)+3-11))) | L20: =IF((COUNTA('Lançamentos'!$B:$B)+3-11)<5,"",INDEX('Lançamentos'!$E:$E,(COUNTA('Lançamentos'!$B:$B)+3-11)))
B21: RESUMO | H21: =IF((COUNTA('Lançamentos'!$B:$B)+3-12)<5,"",INDEX('Lançamentos'!$A:$A,(COUNTA('Lançamentos'!$B:$B)+3-12))) | I21: =IF((COUNTA('Lançamentos'!$B:$B)+3-12)<5,"",INDEX('Lançamentos'!$B:$B,(COUNTA('Lançamentos'!$B:$B)+3-12))) | J21: =IF((COUNTA('Lançamentos'!$B:$B)+3-12)<5,"",INDEX('Lançamentos'!$C:$C,(COUNTA('Lançamentos'!$B:$B)+3-12))) | K21: =IF((COUNTA('Lançamentos'!$B:$B)+3-12)<5,"",INDEX('Lançamentos'!$D:$D,(COUNTA('Lançamentos'!$B:$B)+3-12))) | L21: =IF((COUNTA('Lançamentos'!$B:$B)+3-12)<5,"",INDEX('Lançamentos'!$E:$E,(COUNTA('Lançamentos'!$B:$B)+3-12)))
B22: Total do lançamento | C22: =IF(lc_qtd="","",lc_qtd*IF(lc_preco="",N(lc_cot),lc_preco)+N(lc_custos)) | H22: =IF((COUNTA('Lançamentos'!$B:$B)+3-13)<5,"",INDEX('Lançamentos'!$A:$A,(COUNTA('Lançamentos'!$B:$B)+3-13))) | I22: =IF((COUNTA('Lançamentos'!$B:$B)+3-13)<5,"",INDEX('Lançamentos'!$B:$B,(COUNTA('Lançamentos'!$B:$B)+3-13))) | J22: =IF((COUNTA('Lançamentos'!$B:$B)+3-13)<5,"",INDEX('Lançamentos'!$C:$C,(COUNTA('Lançamentos'!$B:$B)+3-13))) | K22: =IF((COUNTA('Lançamentos'!$B:$B)+3-13)<5,"",INDEX('Lançamentos'!$D:$D,(COUNTA('Lançamentos'!$B:$B)+3-13))) | L22: =IF((COUNTA('Lançamentos'!$B:$B)+3-13)<5,"",INDEX('Lançamentos'!$E:$E,(COUNTA('Lançamentos'!$B:$B)+3-13)))
B23: Cotas após o lançamento | C23: =IF(lc_qtd="","",N(lc_tem)+IF(UPPER(lc_op)="VENDA",-1,1)*lc_qtd) | H23: =IF((COUNTA('Lançamentos'!$B:$B)+3-14)<5,"",INDEX('Lançamentos'!$A:$A,(COUNTA('Lançamentos'!$B:$B)+3-14))) | I23: =IF((COUNTA('Lançamentos'!$B:$B)+3-14)<5,"",INDEX('Lançamentos'!$B:$B,(COUNTA('Lançamentos'!$B:$B)+3-14))) | J23: =IF((COUNTA('Lançamentos'!$B:$B)+3-14)<5,"",INDEX('Lançamentos'!$C:$C,(COUNTA('Lançamentos'!$B:$B)+3-14))) | K23: =IF((COUNTA('Lançamentos'!$B:$B)+3-14)<5,"",INDEX('Lançamentos'!$D:$D,(COUNTA('Lançamentos'!$B:$B)+3-14))) | L23: =IF((COUNTA('Lançamentos'!$B:$B)+3-14)<5,"",INDEX('Lançamentos'!$E:$E,(COUNTA('Lançamentos'!$B:$B)+3-14)))
H24: Histórico completo na aba Lançamentos • posição de cada ativo na aba Carteira
B26: ✔ Registrar lançamento → | C26: FALSE

Sheet Ativos
B1: ◆ InvestERP Painel Carteira Análises ✚ Lançar Lançamentos Proventos Premissas Verificar
A2: Cadastro de Ativos
A3: Gerado a partir de dados/ativos.csv — edite lá e rode gestao.py (ou atualizar.bat).
A4: Ticker | B4: Tipo | C4: Segmento | D4: Cotação (R$) | E4: Provento 12m por cota (R$) | F4: Peso ideal | G4: Atualizado em | H4: Cotação base (R$)
A5: VALE3 | B5: AÇÃO | C5: Mineração | D5: =IF(A5="","",IFERROR(GOOGLEFINANCE("BVMF:"&A5),H5)) | E5: 5.6125 | F5: 0.1 | G5: 25/09/2026 | H5: 70.77
A6: TAEE11 | B6: AÇÃO | C6: Energia – Transmissão | D6: =IF(A6="","",IFERROR(GOOGLEFINANCE("BVMF:"&A6),H6)) | E6: 3.0065 | F6: 0.05 | G6: 25/09/2026 | H6: 40.79
A7: PETR4 | B7: AÇÃO | C7: Petróleo & Gás | D7: =IF(A7="","",IFERROR(GOOGLEFINANCE("BVMF:"&A7),H7)) | E7: 3.6643 | F7: 0.07 | G7: 25/09/2026 | H7: 48.07
A8: BBAS3 | B8: AÇÃO | C8: Bancos | D8: =IF(A8="","",IFERROR(GOOGLEFINANCE("BVMF:"&A8),H8)) | E8: 0.655 | F8: 0.06 | G8: 25/09/2026 | H8: 21.59
A9: BRBI11 | B9: AÇÃO | C9: Banco de investimento | D9: =IF(A9="","",IFERROR(GOOGLEFINANCE("BVMF:"&A9),H9)) | E9: 1.38 | F9: 0.05 | G9: 25/09/2026 | H9: 14.83
A10: BBDC4 | B10: AÇÃO | C10: Bancos | D10: =IF(A10="","",IFERROR(GOOGLEFINANCE("BVMF:"&A10),H10)) | E10: 1.5528 | F10: 0.05 | G10: 25/09/2026 | H10: 17.88
A11: ITSA4 | B11: AÇÃO | C11: Holding – Bancos | D11: =IF(A11="","",IFERROR(GOOGLEFINANCE("BVMF:"&A11),H11)) | E11: 1.1278 | F11: 0.1 | G11: 25/09/2026 | H11: 13.99
A12: CMIG4 | B12: AÇÃO | C12: Energia – Utilities | D12: =IF(A12="","",IFERROR(GOOGLEFINANCE("BVMF:"&A12),H12)) | E12: 1.3507 | F12: 0.1 | G12: 25/09/2026 | H12: 10.89
A13: FIQE3 | B13: AÇÃO | C13: Telecom / Tecnologia | D13: =IF(A13="","",IFERROR(GOOGLEFINANCE("BVMF:"&A13),H13)) | E13: 0.682 | F13: 0.05 | G13: 25/09/2026 | H13: 5.07
A14: KLBN11 | B14: AÇÃO | C14: Papel & Celulose | D14: =IF(A14="","",IFERROR(GOOGLEFINANCE("BVMF:"&A14),H14)) | E14: 1.1611 | F14: 0.07 | G14: 25/09/2026 | H14: 18.15
A15: MXRF11 | B15: FII | C15: Papel (recebíveis) | D15: =IF(A15="","",IFERROR(GOOGLEFINANCE("BVMF:"&A15),H15)) | E15: 1.1943 | F15: 0.05 | G15: 25/09/2026 | H15: 9.1
A16: BRCR11 | B16: FII | C16: Lajes corporativas | D16: =IF(A16="","",IFERROR(GOOGLEFINANCE("BVMF:"&A16),H16)) | E16: 4.92 | F16: 0.04 | G16: 25/09/2026 | H16: 41.16
... A20: CPTS11 | B20: FII | C20: Híbrido (papel) | D20: =IF(A20="","",IFERROR(GOOGLEFINANCE("BVMF:"&A20),H20)) | E20: 1.08 | F20: 0.04 | G20: 25/09/2026 | H20: 7.45
D21: =IF(A21="","",IFERROR(GOOGLEFINANCE("BVMF:"&A21),H21))
D22: =IF(A22="","",IFERROR(GOOGLEFINANCE("BVMF:"&A22),H22))
D23: =IF(A23="","",IFERROR(GOOGLEFINANCE("BVMF:"&A23),H23))
D24: =IF(A24="","",IFERROR(GOOGLEFINANCE("BVMF:"&A24),H24))
D25: =IF(A25="","",IFERROR(GOOGLEFINANCE("BVMF:"&A25),H25))
D26: =IF(A26="","",IFERROR(GOOGLEFINANCE("BVMF:"&A26),H26))
D27: =IF(A27="","",IFERROR(GOOGLEFINANCE("BVMF:"&A27),H27))
D28: =IF(A28="","",IFERROR(GOOGLEFINANCE("BVMF:"&A28),H28))
D29: =IF(A29="","",IFERROR(GOOGLEFINANCE("BVMF:"&A29),H29))
D30: =IF(A30="","",IFERROR(GOOGLEFINANCE("BVMF:"&A30),H30))
D31: =IF(A31="","",IFERROR(GOOGLEFINANCE("BVMF:"&A31),H31))
D32: =IF(A32="","",IFERROR(GOOGLEFINANCE("BVMF:"&A32),H32))
... D35: =IF(A35="","",IFERROR(GOOGLEFINANCE("BVMF:"&A35),H35))
A36: TOTAL | F36: =SUM(F5:F35)
A38: Observações
A39: • Cotação, provento 12m e 'Atualizado em' são preenchidos pelo Yahoo Finance a cada execução; 'manual' = não atualizado online.
A40: • Peso ideal: participação desejada de cada ativo dentro da renda variável — deve somar 100%.

Sheet Lançamentos
B1: ◆ InvestERP Painel Carteira Análises ✚ Lançar Lançamentos Proventos Premissas Verificar
A2: Lançamentos de Compra e Venda
A3: Gerado a partir de dados/lancamentos.csv — edite lá e rode gestao.py (ou atualizar.bat).
A4: Data | B4: Ticker | C4: Operação | D4: Quantidade | E4: Preço (R$) | F4: Custos (R$) | G4: Total (R$)

Sheet Proventos
B1: ◆ InvestERP Painel Carteira Análises ✚ Lançar Lançamentos Proventos Premissas Verificar
A2: Proventos Recebidos
A3: Gerado a partir de dados/proventos.csv — edite lá e rode gestao.py (ou atualizar.bat).
A4: Data pagamento | B4: Ticker | C4: Tipo | D4: Valor por cota (R$) | E4: Qtd de cotas | F4: Total (R$)

Sheet Premissas
B1: ◆ InvestERP Painel Carteira Análises ✚ Lançar Lançamentos Proventos Premissas Verificar
A2: Premissas
A3: Gerado a partir de dados/config.json — edite lá e rode gestao.py (ou atualizar.bat).
A4: Parâmetro | B4: Valor | C4: Uso
A5: Meta mensal por ativo | B5: 1000 | C5: Renda que cada ativo deve pagar por mês
A6: Aporte mensal | B6: 3000 | C6: Quanto você investe por mês (tempo até a meta)
A7: Peso ideal da renda variável | B7: 0.32 | C7: Ações + FIIs no patrimônio total
A10: Outras classes | B10: Valor (R$) | C10: Peso ideal no patrimônio
A11: Renda fixa (CDB Nubank) | B11: 1000 | C11: 0.5
A12: Internacional | B12: 0 | C12: 0.15
A13: Cripto | B13: 0 | C13: 0.03

Sheet Verificar
B1: ◆ InvestERP Painel Carteira Análises ✚ Lançar Lançamentos Proventos Premissas Verificar
A2: Pontos a Conferir
A3: Checagens automáticas feitas a cada geração — corrija em dados/.
A4: Gravidade | B4: Ativo | C4: O que foi encontrado
A5: Nenhuma inconsistência encontrada.

Sheet Base Painel
A1: Mês | B1: Proventos
A2: =DATE(YEAR(TODAY()),MONTH(TODAY())-11,1) | B2: =SUMIFS(Proventos!$F:$F,Proventos!$A:$A,">="&A2,Proventos!$A:$A,"<"&DATE(YEAR(A2),MONTH(A2)+1,1))
A3: =DATE(YEAR(TODAY()),MONTH(TODAY())-10,1) | B3: =SUMIFS(Proventos!$F:$F,Proventos!$A:$A,">="&A3,Proventos!$A:$A,"<"&DATE(YEAR(A3),MONTH(A3)+1,1))
A4: =DATE(YEAR(TODAY()),MONTH(TODAY())-9,1) | B4: =SUMIFS(Proventos!$F:$F,Proventos!$A:$A,">="&A4,Proventos!$A:$A,"<"&DATE(YEAR(A4),MONTH(A4)+1,1)) | D4: Ticker | G4: Ticker | H4: Posição | K4: Ticker | L4: Valorização | M4: Lucro | P4: Ticker | Q4: Valorização | R4: Lucro | U4: Ticker | V4: Lucro / prejuízo | Y4: Ticker | Z4: % da meta | AC4: Ticker | AD4: Aporte necessário | AG4: Ticker | AH4: Proventos | AJ4: Participação
A5: =DATE(YEAR(TODAY()),MONTH(TODAY())-8,1) | B5: =SUMIFS(Proventos!$F:$F,Proventos!$A:$A,">="&A5,Proventos!$A:$A,"<"&DATE(YEAR(A5),MONTH(A5)+1,1)) | D5: =Carteira!A5 | F5: =IF(OR(Carteira!C5>0,AND(SUM(Carteira!$C$5:$C$35)=0,Carteira!A5<>"")),N(Carteira!G5)+ROW()/1E9,"") | G5: =IFERROR(INDEX($D$5:$D$35,MATCH(LARGE($F$5:$F$35,1),$F$5:$F$35,0)),"") | H5: =IFERROR(INDEX(Carteira!$G$5:$G$35,MATCH(G5,Carteira!$A$5:$A$35,0)),"") | J5: =IF(OR(Carteira!C5>0,AND(SUM(Carteira!$C$5:$C$35)=0,Carteira!A5<>"")),N(Carteira!I5)+ROW()/1E9,"") | K5: =IFERROR(INDEX($D$5:$D$35,MATCH(LARGE($J$5:$J$35,1),$J$5:$J$35,0)),"") | L5: =IFERROR(INDEX(Carteira!$I$5:$I$35,MATCH(K5,Carteira!$A$5:$A$35,0)),"") | M5: =IFERROR(INDEX(Carteira!$H$5:$H$35,MATCH(K5,Carteira!$A$5:$A$35,0)),"") | O5: =IF(OR(Carteira!C5>0,AND(SUM(Carteira!$C$5:$C$35)=0,Carteira!A5<>"")),N(Carteira!I5)+ROW()/1E9,"") | P5: =IFERROR(INDEX($D$5:$D$35,MATCH(SMALL($O$5:$O$35,1),$O$5:$O$35,0)),"") | Q5: =IFERROR(INDEX(Carteira!$I$5:$I$35,MATCH(P5,Carteira!$A$5:$A$35,0)),"") | R5: =IFERROR(INDEX(Carteira!$H$5:$H$35,MATCH(P5,Carteira!$A$5:$A$35,0)),"") | T5: =IF(OR(Carteira!C5>0,AND(SUM(Carteira!$C$5:$C$35)=0,Carteira!A5<>"")),N(Carteira!H5)+ROW()/1E9,"") | U5: =IFERROR(INDEX($D$5:$D$35,MATCH(LARGE($T$5:$T$35,1),$T$5:$T$35,0)),"") | V5: =IFERROR(INDEX(Carteira!$H$5:$H$35,MATCH(U5,Carteira!$A$5:$A$35,0)),"") | X5: =IF(OR(Carteira!C5>0,AND(SUM(Carteira!$C$5:$C$35)=0,Carteira!A5<>"")),N(Carteira!W5)+ROW()/1E9,"") | Y5: =IFERROR(INDEX($D$5:$D$35,MATCH(LARGE($X$5:$X$35,1),$X$5:$X$35,0)),"") | Z5: =IFERROR(INDEX(Carteira!$W$5:$W$35,MATCH(Y5,Carteira!$A$5:$A$35,0)),"") | AB5: =IF(OR(Carteira!C5>0,AND(SUM(Carteira!$C$5:$C$35)=0,Carteira!A5<>"")),N(Carteira!Z5)+ROW()/1E9,"") | AC5: =IFERROR(INDEX($D$5:$D$35,MATCH(LARGE($AB$5:$AB$35,1),$AB$5:$AB$35,0)),"") | AD5: =IFERROR(INDEX(Carteira!$Z$5:$Z$35,MATCH(AC5,Carteira!$A$5:$A$35,0)),"") | AF5: =IF(OR(Carteira!C5>0,AND(SUM(Carteira!$C$5:$C$35)=0,Carteira!A5<>"")),N(Carteira!J5)+ROW()/1E9,"") | AG5: =IFERROR(INDEX($D$5:$D$35,MATCH(LARGE($AF$5:$AF$35,1),$AF$5:$AF$35,0)),"") | AH5: =IFERROR(INDEX(Carteira!$J$5:$J$35,MATCH(AG5,Carteira!$A$5:$A$35,0)),"") | AJ5: =IF(ISNUMBER(H5),IF(Carteira!$G$36>0,H5/Carteira!$G$36,0),"")
A6: =DATE(YEAR(TODAY()),MONTH(TODAY())-7,1) | B6: =SUMIFS(Proventos!$F:$F,Proventos!$A:$A,">="&A6,Proventos!$A:$A,"<"&DATE(YEAR(A6),MONTH(A6)+1,1)) | D6: =Carteira!A6 | F6: =IF(OR(Carteira!C6>0,AND(SUM(Carteira!$C$5:$C$35)=0,Carteira!A6<>"")),N(Carteira!G6)+ROW()/1E9,"") | G6: =IFERROR(INDEX($D$5:$D$35,MATCH(LARGE($F$5:$F$35,2),$F$5:$F$35,0)),"") | H6: =IFERROR(INDEX(Carteira!$G$5:$G$35,MATCH(G6,Carteira!$A$5:$A$35,0)),"") | J6: =IF(OR(Carteira!C6>0,AND(SUM(Carteira!$C$5:$C$35)=0,Carteira!A6<>"")),N(Carteira!I6)+ROW()/1E9,"") | K6: =IFERROR(INDEX($D$5:$D$35,MATCH(LARGE($J$5:$J$35,2),$J$5:$J$35,0)),"") | L6: =IFERROR(INDEX(Carteira!$I$5:$I$35,MATCH(K6,Carteira!$A$5:$A$35,0)),"") | M6: =IFERROR(INDEX(Carteira!$H$5:$H$35,MATCH(K6,Carteira!$A$5:$A$35,0)),"") | O6: =IF(OR(Carteira!C6>0,AND(SUM(Carteira!$C$5:$C$35)=0,Carteira!A6<>"")),N(Carteira!I6)+ROW()/1E9,"") | P6: =IFERROR(INDEX($D$5:$D$35,MATCH(SMALL($O$5:$O$35,2),$O$5:$O$35,0)),"") | Q6: =IFERROR(INDEX(Carteira!$I$5:$I$35,MATCH(P6,Carteira!$A$5:$A$35,0)),"") | R6: =IFERROR(INDEX(Carteira!$H$5:$H$35,MATCH(P6,Carteira!$A$5:$A$35,0)),"") | T6: =IF(OR(Carteira!C6>0,AND(SUM(Carteira!$C$5:$C$35)=0,Carteira!A6<>"")),N(Carteira!H6)+ROW()/1E9,"") | U6: =IFERROR(INDEX($D$5:$D$35,MATCH(LARGE($T$5:$T$35,2),$T$5:$T$35,0)),"") | V6: =IFERROR(INDEX(Carteira!$H$5:$H$35,MATCH(U6,Carteira!$A$5:$A$35,0)),"") | X6: =IF(OR(Carteira!C6>0,AND(SUM(Carteira!$C$5:$C$35)=0,Carteira!A6<>"")),N(Carteira!W6)+ROW()/1E9,"") | Y6: =IFERROR(INDEX($D$5:$D$35,MATCH(LARGE($X$5:$X$35,2),$X$5:$X$35,0)),"") | Z6: =IFERROR(INDEX(Carteira!$W$5:$W$35,MATCH(Y6,Carteira!$A$5:$A$35,0)),"") | AB6: =IF(OR(Carteira!C6>0,AND(SUM(Carteira!$C$5:$C$35)=0,Carteira!A6<>"")),N(Carteira!Z6)+ROW()/1E9,"") | AC6: =IFERROR(INDEX($D$5:$D$35,MATCH(LARGE($AB$5:$AB$35,2),$AB$5:$AB$35,0)),"") | AD6: =IFERROR(INDEX(Carteira!$Z$5:$Z$35,MATCH(AC6,Carteira!$A$5:$A$35,0)),"") | AF6: =IF(OR(Carteira!C6>0,AND(SUM(Carteira!$C$5:$C$35)=0,Carteira!A6<>"")),N(Carteira!J6)+ROW()/1E9,"") | AG6: =IFERROR(INDEX($D$5:$D$35,MATCH(LARGE($AF$5:$AF$35,2),$AF$5:$AF$35,0)),"") | AH6: =IFERROR(INDEX(Carteira!$J$5:$J$35,MATCH(AG6,Carteira!$A$5:$A$35,0)),"") | AJ6: =IF(ISNUMBER(H6),IF(Carteira!$G$36>0,H6/Carteira!$G$36,0),"")
A7: =DATE(YEAR(TODAY()),MONTH(TODAY())-6,1) | B7: =SUMIFS(Proventos!$F:$F,Proventos!$A:$A,">="&A7,Proventos!$A:$A,"<"&DATE(YEAR(A7),MONTH(A7)+1,1)) | D7: =Carteira!A7 | F7: =IF(OR(Carteira!C7>0,AND(SUM(Carteira!$C$5:$C$35)=0,Carteira!A7<>"")),N(Carteira!G7)+ROW()/1E9,"") | G7: =IFERROR(INDEX($D$5:$D$35,MATCH(LARGE($F$5:$F$35,3),$F$5:$F$35,0)),"") | H7: =IFERROR(INDEX(Carteira!$G$5:$G$35,MATCH(G7,Carteira!$A$5:$A$35,0)),"") | J7: =IF(OR(Carteira!C7>0,AND(SUM(Carteira!$C$5:$C$35)=0,Carteira!A7<>"")),N(Carteira!I7)+ROW()/1E9,"") | K7: =IFERROR(INDEX($D$5:$D$35,MATCH(LARGE($J$5:$J$35,3),$J$5:$J$35,0)),"") | L7: =IFERROR(INDEX(Carteira!$I$5:$I$35,MATCH(K7,Carteira!$A$5:$A$35,0)),"") | M7: =IFERROR(INDEX(Carteira!$H$5:$H$35,MATCH(K7,Carteira!$A$5:$A$35,0)),"") | O7: =IF(OR(Carteira!C7>0,AND(SUM(Carteira!$C$5:$C$35)=0,Carteira!A7<>"")),N(Carteira!I7)+ROW()/1E9,"") | P7: =IFERROR(INDEX($D$5:$D$35,MATCH(SMALL($O$5:$O$35,3),$O$5:$O$35,0)),"") | Q7: =IFERROR(INDEX(Carteira!$I$5:$I$35,MATCH(P7,Carteira!$A$5:$A$35,0)),"") | R7: =IFERROR(INDEX(Carteira!$H$5:$H$35,MATCH(P7,Carteira!$A$5:$A$35,0)),"") | T7: =IF(OR(Carteira!C7>0,AND(SUM(Carteira!$C$5:$C$35)=0,Carteira!A7<>"")),N(Carteira!H7)+ROW()/1E9,"") | U7: =IFERROR(INDEX($D$5:$D$35,MATCH(LARGE($T$5:$T$35,3),$T$5:$T$35,0)),"") | V7: =IFERROR(INDEX(Carteira!$H$5:$H$35,MATCH(U7,Carteira!$A$5:$A$35,0)),"") | X7: =IF(OR(Carteira!C7>0,AND(SUM(Carteira!$C$5:$C$35)=0,Carteira!A7<>"")),N(Carteira!W7)+ROW()/1E9,"") | Y7: =IFERROR(INDEX($D$5:$D$35,MATCH(LARGE($X$5:$X$35,3),$X$5:$X$35,0)),"") | Z7: =IFERROR(INDEX(Carteira!$W$5:$W$35,MATCH(Y7,Carteira!$A$5:$A$35,0)),"") | AB7: =IF(OR(Carteira!C7>0,AND(SUM(Carteira!$C$5:$C$35)=0,Carteira!A7<>"")),N(Carteira!Z7)+ROW()/1E9,"") | AC7: =IFERROR(INDEX($D$5:$D$35,MATCH(LARGE($AB$5:$AB$35,3),$AB$5:$AB$35,0)),"") | AD7: =IFERROR(INDEX(Carteira!$Z$5:$Z$35,MATCH(AC7,Carteira!$A$5:$A$35,0)),"") | AF7: =IF(OR(Carteira!C7>0,AND(SUM(Carteira!$C$5:$C$35)=0,Carteira!A7<>"")),N(Carteira!J7)+ROW()/1E9,"") | AG7: =IFERROR(INDEX($D$5:$D$35,MATCH(LARGE($AF$5:$AF$35,3),$AF$5:$AF$35,0)),"") | AH7: =IFERROR(INDEX(Carteira!$J$5:$J$35,MATCH(AG7,Carteira!$A$5:$A$35,0)),"") | AJ7: =IF(ISNUMBER(H7),IF(Carteira!$G$36>0,H7/Carteira!$G$36,0),"")
A8: =DATE(YEAR(TODAY()),MONTH(TODAY())-5,1) | B8: =SUMIFS(Proventos!$F:$F,Proventos!$A:$A,">="&A8,Proventos!$A:$A,"<"&DATE(YEAR(A8),MONTH(A8)+1,1)) | D8: =Carteira!A8 | F8: =IF(OR(Carteira!C8>0,AND(SUM(Carteira!$C$5:$C$35)=0,Carteira!A8<>"")),N(Carteira!G8)+ROW()/1E9,"") | G8: =IFERROR(INDEX($D$5:$D$35,MATCH(LARGE($F$5:$F$35,4),$F$5:$F$35,0)),"") | H8: =IFERROR(INDEX(Carteira!$G$5:$G$35,MATCH(G8,Carteira!$A$5:$A$35,0)),"") | J8: =IF(OR(Carteira!C8>0,AND(SUM(Carteira!$C$5:$C$35)=0,Carteira!A8<>"")),N(Carteira!I8)+ROW()/1E9,"") | K8: =IFERROR(INDEX($D$5:$D$35,MATCH(LARGE($J$5:$J$35,4),$J$5:$J$35,0)),"") | L8: =IFERROR(INDEX(Carteira!$I$5:$I$35,MATCH(K8,Carteira!$A$5:$A$35,0)),"") | M8: =IFERROR(INDEX(Carteira!$H$5:$H$35,MATCH(K8,Carteira!$A$5:$A$35,0)),"") | O8: =IF(OR(Carteira!C8>0,AND(SUM(Carteira!$C$5:$C$35)=0,Carteira!A8<>"")),N(Carteira!I8)+ROW()/1E9,"") | P8: =IFERROR(INDEX($D$5:$D$35,MATCH(SMALL($O$5:$O$35,4),$O$5:$O$35,0)),"") | Q8: =IFERROR(INDEX(Carteira!$I$5:$I$35,MATCH(P8,Carteira!$A$5:$A$35,0)),"") | R8: =IFERROR(INDEX(Carteira!$H$5:$H$35,MATCH(P8,Carteira!$A$5:$A$35,0)),"") | T8: =IF(OR(Carteira!C8>0,AND(SUM(Carteira!$C$5:$C$35)=0,Carteira!A8<>"")),N(Carteira!H8)+ROW()/1E9,"") | U8: =IFERROR(INDEX($D$5:$D$35,MATCH(LARGE($T$5:$T$35,4),$T$5:$T$35,0)),"") | V8: =IFERROR(INDEX(Carteira!$H$5:$H$35,MATCH(U8,Carteira!$A$5:$A$35,0)),"") | X8: =IF(OR(Carteira!C8>0,AND(SUM(Carteira!$C$5:$C$35)=0,Carteira!A8<>"")),N(Carteira!W8)+ROW()/1E9,"") | Y8: =IFERROR(INDEX($D$5:$D$35,MATCH(LARGE($X$5:$X$35,4),$X$5:$X$35,0)),"") | Z8: =IFERROR(INDEX(Carteira!$W$5:$W$35,MATCH(Y8,Carteira!$A$5:$A$35,0)),"") | AB8: =IF(OR(Carteira!C8>0,AND(SUM(Carteira!$C$5:$C$35)=0,Carteira!A8<>"")),N(Carteira!Z8)+ROW()/1E9,"") | AC8: =IFERROR(INDEX($D$5:$D$35,MATCH(LARGE($AB$5:$AB$35,4),$AB$5:$AB$35,0)),"") | AD8: =IFERROR(INDEX(Carteira!$Z$5:$Z$35,MATCH(AC8,Carteira!$A$5:$A$35,0)),"") | AF8: =IF(OR(Carteira!C8>0,AND(SUM(Carteira!$C$5:$C$35)=0,Carteira!A8<>"")),N(Carteira!J8)+ROW()/1E9,"") | AG8: =IFERROR(INDEX($D$5:$D$35,MATCH(LARGE($AF$5:$AF$35,4),$AF$5:$AF$35,0)),"") | AH8: =IFERROR(INDEX(Carteira!$J$5:$J$35,MATCH(AG8,Carteira!$A$5:$A$35,0)),"") | AJ8: =IF(ISNUMBER(H8),IF(Carteira!$G$36>0,H8/Carteira!$G$36,0),"")
A9: =DATE(YEAR(TODAY()),MONTH(TODAY())-4,1) | B9: =SUMIFS(Proventos!$F:$F,Proventos!$A:$A,">="&A9,Proventos!$A:$A,"<"&DATE(YEAR(A9),MONTH(A9)+1,1)) | D9: =Carteira!A9 | F9: =IF(OR(Carteira!C9>0,AND(SUM(Carteira!$C$5:$C$35)=0,Carteira!A9<>"")),N(Carteira!G9)+ROW()/1E9,"") | G9: =IFERROR(INDEX($D$5:$D$35,MATCH(LARGE($F$5:$F$35,5),$F$5:$F$35,0)),"") | H9: =IFERROR(INDEX(Carteira!$G$5:$G$35,MATCH(G9,Carteira!$A$5:$A$35,0)),"") | J9: =IF(OR(Carteira!C9>0,AND(SUM(Carteira!$C$5:$C$35)=0,Carteira!A9<>"")),N(Carteira!I9)+ROW()/1E9,"") | K9: =IFERROR(INDEX($D$5:$D$35,MATCH(LARGE($J$5:$J$35,5),$J$5:$J$35,0)),"") | L9: =IFERROR(INDEX(Carteira!$I$5:$I$35,MATCH(K9,Carteira!$A$5:$A$35,0)),"") | M9: =IFERROR(INDEX(Carteira!$H$5:$H$35,MATCH(K9,Carteira!$A$5:$A$35,0)),"") | O9: =IF(OR(Carteira!C9>0,AND(SUM(Carteira!$C$5:$C$35)=0,Carteira!A9<>"")),N(Carteira!I9)+ROW()/1E9,"") | P9: =IFERROR(INDEX($D$5:$D$35,MATCH(SMALL($O$5:$O$35,5),$O$5:$O$35,0)),"") | Q9: =IFERROR(INDEX(Carteira!$I$5:$I$35,MATCH(P9,Carteira!$A$5:$A$35,0)),"") | R9: =IFERROR(INDEX(Carteira!$H$5:$H$35,MATCH(P9,Carteira!$A$5:$A$35,0)),"") | T9: =IF(OR(Carteira!C9>0,AND(SUM(Carteira!$C$5:$C$35)=0,Carteira!A9<>"")),N(Carteira!H9)+ROW()/1E9,"") | U9: =IFERROR(INDEX($D$5:$D$35,MATCH(LARGE($T$5:$T$35,5),$T$5:$T$35,0)),"") | V9: =IFERROR(INDEX(Carteira!$H$5:$H$35,MATCH(U9,Carteira!$A$5:$A$35,0)),"") | X9: =IF(OR(Carteira!C9>0,AND(SUM(Carteira!$C$5:$C$35)=0,Carteira!A9<>"")),N(Carteira!W9)+ROW()/1E9,"") | Y9: =IFERROR(INDEX($D$5:$D$35,MATCH(LARGE($X$5:$X$35,5),$X$5:$X$35,0)),"") | Z9: =IFERROR(INDEX(Carteira!$W$5:$W$35,MATCH(Y9,Carteira!$A$5:$A$35,0)),"") | AB9: =IF(OR(Carteira!C9>0,AND(SUM(Carteira!$C$5:$C$35)=0,Carteira!A9<>"")),N(Carteira!Z9)+ROW()/1E9,"") | AC9: =IFERROR(INDEX($D$5:$D$35,MATCH(LARGE($AB$5:$AB$35,5),$AB$5:$AB$35,0)),"") | AD9: =IFERROR(INDEX(Carteira!$Z$5:$Z$35,MATCH(AC9,Carteira!$A$5:$A$35,0)),"") | AF9: =IF(OR(Carteira!C9>0,AND(SUM(Carteira!$C$5:$C$35)=0,Carteira!A9<>"")),N(Carteira!J9)+ROW()/1E9,"") | AG9: =IFERROR(INDEX($D$5:$D$35,MATCH(LARGE($AF$5:$AF$35,5),$AF$5:$AF$35,0)),"") | AH9: =IFERROR(INDEX(Carteira!$J$5:$J$35,MATCH(AG9,Carteira!$A$5:$A$35,0)),"") | AJ9: =IF(ISNUMBER(H9),IF(Carteira!$G$36>0,H9/Carteira!$G$36,0),"")
A10: =DATE(YEAR(TODAY()),MONTH(TODAY())-3,1) | B10: =SUMIFS(Proventos!$F:$F,Proventos!$A:$A,">="&A10,Proventos!$A:$A,"<"&DATE(YEAR(A10),MONTH(A10)+1,1)) | D10: =Carteira!A10 | F10: =IF(OR(Carteira!C10>0,AND(SUM(Carteira!$C$5:$C$35)=0,Carteira!A10<>"")),N(Carteira!G10)+ROW()/1E9,"") | G10: =IFERROR(INDEX($D$5:$D$35,MATCH(LARGE($F$5:$F$35,6),$F$5:$F$35,0)),"") | H10: =IFERROR(INDEX(Carteira!$G$5:$G$35,MATCH(G10,Carteira!$A$5:$A$35,0)),"") | J10: =IF(OR(Carteira!C10>0,AND(SUM(Carteira!$C$5:$C$35)=0,Carteira!A10<>"")),N(Carteira!I10)+ROW()/1E9,"") | K10: =IFERROR(INDEX($D$5:$D$35,MATCH(LARGE($J$5:$J$35,6),$J$5:$J$35,0)),"") | L10: =IFERROR(INDEX(Carteira!$I$5:$I$35,MATCH(K10,Carteira!$A$5:$A$35,0)),"") | M10: =IFERROR(INDEX(Carteira!$H$5:$H$35,MATCH(K10,Carteira!$A$5:$A$35,0)),"") | O10: =IF(OR(Carteira!C10>0,AND(SUM(Carteira!$C$5:$C$35)=0,Carteira!A10<>"")),N(Carteira!I10)+ROW()/1E9,"") | P10: =IFERROR(INDEX($D$5:$D$35,MATCH(SMALL($O$5:$O$35,6),$O$5:$O$35,0)),"") | Q10: =IFERROR(INDEX(Carteira!$I$5:$I$35,MATCH(P10,Carteira!$A$5:$A$35,0)),"") | R10: =IFERROR(INDEX(Carteira!$H$5:$H$35,MATCH(P10,Carteira!$A$5:$A$35,0)),"") | T10: =IF(OR(Carteira!C10>0,AND(SUM(Carteira!$C$5:$C$35)=0,Carteira!A10<>"")),N(Carteira!H10)+ROW()/1E9,"") | U10: =IFERROR(INDEX($D$5:$D$35,MATCH(LARGE($T$5:$T$35,6),$T$5:$T$35,0)),"") | V10: =IFERROR(INDEX(Carteira!$H$5:$H$35,MATCH(U10,Carteira!$A$5:$A$35,0)),"") | X10: =IF(OR(Carteira!C10>0,AND(SUM(Carteira!$C$5:$C$35)=0,Carteira!A10<>"")),N(Carteira!W10)+ROW()/1E9,"") | Y10: =IFERROR(INDEX($D$5:$D$35,MATCH(LARGE($X$5:$X$35,6),$X$5:$X$35,0)),"") | Z10: =IFERROR(INDEX(Carteira!$W$5:$W$35,MATCH(Y10,Carteira!$A$5:$A$35,0)),"") | AB10: =IF(OR(Carteira!C10>0,AND(SUM(Carteira!$C$5:$C$35)=0,Carteira!A10<>"")),N(Carteira!Z10)+ROW()/1E9,"") | AC10: =IFERROR(INDEX($D$5:$D$35,MATCH(LARGE($AB$5:$AB$35,6),$AB$5:$AB$35,0)),"") | AD10: =IFERROR(INDEX(Carteira!$Z$5:$Z$35,MATCH(AC10,Carteira!$A$5:$A$35,0)),"") | AF10: =IF(OR(Carteira!C10>0,AND(SUM(Carteira!$C$5:$C$35)=0,Carteira!A10<>"")),N(Carteira!J10)+ROW()/1E9,"") | AG10: =IFERROR(INDEX($D$5:$D$35,MATCH(LARGE($AF$5:$AF$35,6),$AF$5:$AF$35,0)),"") | AH10: =IFERROR(INDEX(Carteira!$J$5:$J$35,MATCH(AG10,Carteira!$A$5:$A$35,0)),"") | AJ10: =IF(ISNUMBER(H10),IF(Carteira!$G$36>0,H10/Carteira!$G$36,0),"")
A11: =DATE(YEAR(TODAY()),MONTH(TODAY())-2,1) | B11: =SUMIFS(Proventos!$F:$F,Proventos!$A:$A,">="&A11,Proventos!$A:$A,"<"&DATE(YEAR(A11),MONTH(A11)+1,1)) | D11: =Carteira!A11 | F11: =IF(OR(Carteira!C11>0,AND(SUM(Carteira!$C$5:$C$35)=0,Carteira!A11<>"")),N(Carteira!G11)+ROW()/1E9,"") | G11: =IFERROR(INDEX($D$5:$D$35,MATCH(LARGE($F$5:$F$35,7),$F$5:$F$35,0)),"") | H11: =IFERROR(INDEX(Carteira!$G$5:$G$35,MATCH(G11,Carteira!$A$5:$A$35,0)),"") | J11: =IF(OR(Carteira!C11>0,AND(SUM(Carteira!$C$5:$C$35)=0,Carteira!A11<>"")),N(Carteira!I11)+ROW()/1E9,"") | K11: =IFERROR(INDEX($D$5:$D$35,MATCH(LARGE($J$5:$J$35,7),$J$5:$J$35,0)),"") | L11: =IFERROR(INDEX(Carteira!$I$5:$I$35,MATCH(K11,Carteira!$A$5:$A$35,0)),"") | M11: =IFERROR(INDEX(Carteira!$H$5:$H$35,MATCH(K11,Carteira!$A$5:$A$35,0)),"") | O11: =IF(OR(Carteira!C11>0,AND(SUM(Carteira!$C$5:$C$35)=0,Carteira!A11<>"")),N(Carteira!I11)+ROW()/1E9,"") | P11: =IFERROR(INDEX($D$5:$D$35,MATCH(SMALL($O$5:$O$35,7),$O$5:$O$35,0)),"") | Q11: =IFERROR(INDEX(Carteira!$I$5:$I$35,MATCH(P11,Carteira!$A$5:$A$35,0)),"") | R11: =IFERROR(INDEX(Carteira!$H$5:$H$35,MATCH(P11,Carteira!$A$5:$A$35,0)),"") | T11: =IF(OR(Carteira!C11>0,AND(SUM(Carteira!$C$5:$C$35)=0,Carteira!A11<>"")),N(Carteira!H11)+ROW()/1E9,"") | U11: =IFERROR(INDEX($D$5:$D$35,MATCH(LARGE($T$5:$T$35,7),$T$5:$T$35,0)),"") | V11: =IFERROR(INDEX(Carteira!$H$5:$H$35,MATCH(U11,Carteira!$A$5:$A$35,0)),"") | X11: =IF(OR(Carteira!C11>0,AND(SUM(Carteira!$C$5:$C$35)=0,Carteira!A11<>"")),N(Carteira!W11)+ROW()/1E9,"") | Y11: =IFERROR(INDEX($D$5:$D$35,MATCH(LARGE($X$5:$X$35,7),$X$5:$X$35,0)),"") | Z11: =IFERROR(INDEX(Carteira!$W$5:$W$35,MATCH(Y11,Carteira!$A$5:$A$35,0)),"") | AB11: =IF(OR(Carteira!C11>0,AND(SUM(Carteira!$C$5:$C$35)=0,Carteira!A11<>"")),N(Carteira!Z11)+ROW()/1E9,"") | AC11: =IFERROR(INDEX($D$5:$D$35,MATCH(LARGE($AB$5:$AB$35,7),$AB$5:$AB$35,0)),"") | AD11: =IFERROR(INDEX(Carteira!$Z$5:$Z$35,MATCH(AC11,Carteira!$A$5:$A$35,0)),"") | AF11: =IF(OR(Carteira!C11>0,AND(SUM(Carteira!$C$5:$C$35)=0,Carteira!A11<>"")),N(Carteira!J11)+ROW()/1E9,"") | AG11: =IFERROR(INDEX($D$5:$D$35,MATCH(LARGE($AF$5:$AF$35,7),$AF$5:$AF$35,0)),"") | AH11: =IFERROR(INDEX(Carteira!$J$5:$J$35,MATCH(AG11,Carteira!$A$5:$A$35,0)),"") | AJ11: =IF(ISNUMBER(H11),IF(Carteira!$G$36>0,H11/Carteira!$G$36,0),"")
A12: =DATE(YEAR(TODAY()),MONTH(TODAY())-1,1) | B12: =SUMIFS(Proventos!$F:$F,Proventos!$A:$A,">="&A12,Proventos!$A:$A,"<"&DATE(YEAR(A12),MONTH(A12)+1,1)) | D12: =Carteira!A12 | F12: =IF(OR(Carteira!C12>0,AND(SUM(Carteira!$C$5:$C$35)=0,Carteira!A12<>"")),N(Carteira!G12)+ROW()/1E9,"") | G12: =IFERROR(INDEX($D$5:$D$35,MATCH(LARGE($F$5:$F$35,8),$F$5:$F$35,0)),"") | H12: =IFERROR(INDEX(Carteira!$G$5:$G$35,MATCH(G12,Carteira!$A$5:$A$35,0)),"") | J12: =IF(OR(Carteira!C12>0,AND(SUM(Carteira!$C$5:$C$35)=0,Carteira!A12<>"")),N(Carteira!I12)+ROW()/1E9,"") | K12: =IFERROR(INDEX($D$5:$D$35,MATCH(LARGE($J$5:$J$35,8),$J$5:$J$35,0)),"") | L12: =IFERROR(INDEX(Carteira!$I$5:$I$35,MATCH(K12,Carteira!$A$5:$A$35,0)),"") | M12: =IFERROR(INDEX(Carteira!$H$5:$H$35,MATCH(K12,Carteira!$A$5:$A$35,0)),"") | O12: =IF(OR(Carteira!C12>0,AND(SUM(Carteira!$C$5:$C$35)=0,Carteira!A12<>"")),N(Carteira!I12)+ROW()/1E9,"") | P12: =IFERROR(INDEX($D$5:$D$35,MATCH(SMALL($O$5:$O$35,8),$O$5:$O$35,0)),"") | Q12: =IFERROR(INDEX(Carteira!$I$5:$I$35,MATCH(P12,Carteira!$A$5:$A$35,0)),"") | R12: =IFERROR(INDEX(Carteira!$H$5:$H$35,MATCH(P12,Carteira!$A$5:$A$35,0)),"") | T12: =IF(OR(Carteira!C12>0,AND(SUM(Carteira!$C$5:$C$35)=0,Carteira!A12<>"")),N(Carteira!H12)+ROW()/1E9,"") | U12: =IFERROR(INDEX($D$5:$D$35,MATCH(LARGE($T$5:$T$35,8),$T$5:$T$35,0)),"") | V12: =IFERROR(INDEX(Carteira!$H$5:$H$35,MATCH(U12,Carteira!$A$5:$A$35,0)),"") | X12: =IF(OR(Carteira!C12>0,AND(SUM(Carteira!$C$5:$C$35)=0,Carteira!A12<>"")),N(Carteira!W12)+ROW()/1E9,"") | Y12: =IFERROR(INDEX($D$5:$D$35,MATCH(LARGE($X$5:$X$35,8),$X$5:$X$35,0)),"") | Z12: =IFERROR(INDEX(Carteira!$W$5:$W$35,MATCH(Y12,Carteira!$A$5:$A$35,0)),"") | AB12: =IF(OR(Carteira!C12>0,AND(SUM(Carteira!$C$5:$C$35)=0,Carteira!A12<>"")),N(Carteira!Z12)+ROW()/1E9,"") | AC12: =IFERROR(INDEX($D$5:$D$35,MATCH(LARGE($AB$5:$AB$35,8),$AB$5:$AB$35,0)),"") | AD12: =IFERROR(INDEX(Carteira!$Z$5:$Z$35,MATCH(AC12,Carteira!$A$5:$A$35,0)),"") | AF12: =IF(OR(Carteira!C12>0,AND(SUM(Carteira!$C$5:$C$35)=0,Carteira!A12<>"")),N(Carteira!J12)+ROW()/1E9,"") | AG12: =IFERROR(INDEX($D$5:$D$35,MATCH(LARGE($AF$5:$AF$35,8),$AF$5:$AF$35,0)),"") | AH12: =IFERROR(INDEX(Carteira!$J$5:$J$35,MATCH(AG12,Carteira!$A$5:$A$35,0)),"") | AJ12: =IF(ISNUMBER(H12),IF(Carteira!$G$36>0,H12/Carteira!$G$36,0),"")
A13: =DATE(YEAR(TODAY()),MONTH(TODAY())-0,1) | B13: =SUMIFS(Proventos!$F:$F,Proventos!$A:$A,">="&A13,Proventos!$A:$A,"<"&DATE(YEAR(A13),MONTH(A13)+1,1)) | D13: =Carteira!A13 | F13: =IF(OR(Carteira!C13>0,AND(SUM(Carteira!$C$5:$C$35)=0,Carteira!A13<>"")),N(Carteira!G13)+ROW()/1E9,"") | G13: =IFERROR(INDEX($D$5:$D$35,MATCH(LARGE($F$5:$F$35,9),$F$5:$F$35,0)),"") | H13: =IFERROR(INDEX(Carteira!$G$5:$G$35,MATCH(G13,Carteira!$A$5:$A$35,0)),"") | J13: =IF(OR(Carteira!C13>0,AND(SUM(Carteira!$C$5:$C$35)=0,Carteira!A13<>"")),N(Carteira!I13)+ROW()/1E9,"") | K13: =IFERROR(INDEX($D$5:$D$35,MATCH(LARGE($J$5:$J$35,9),$J$5:$J$35,0)),"") | L13: =IFERROR(INDEX(Carteira!$I$5:$I$35,MATCH(K13,Carteira!$A$5:$A$35,0)),"") | M13: =IFERROR(INDEX(Carteira!$H$5:$H$35,MATCH(K13,Carteira!$A$5:$A$35,0)),"") | O13: =IF(OR(Carteira!C13>0,AND(SUM(Carteira!$C$5:$C$35)=0,Carteira!A13<>"")),N(Carteira!I13)+ROW()/1E9,"") | P13: =IFERROR(INDEX($D$5:$D$35,MATCH(SMALL($O$5:$O$35,9),$O$5:$O$35,0)),"") | Q13: =IFERROR(INDEX(Carteira!$I$5:$I$35,MATCH(P13,Carteira!$A$5:$A$35,0)),"") | R13: =IFERROR(INDEX(Carteira!$H$5:$H$35,MATCH(P13,Carteira!$A$5:$A$35,0)),"") | T13: =IF(OR(Carteira!C13>0,AND(SUM(Carteira!$C$5:$C$35)=0,Carteira!A13<>"")),N(Carteira!H13)+ROW()/1E9,"") | U13: =IFERROR(INDEX($D$5:$D$35,MATCH(LARGE($T$5:$T$35,9),$T$5:$T$35,0)),"") | V13: =IFERROR(INDEX(Carteira!$H$5:$H$35,MATCH(U13,Carteira!$A$5:$A$35,0)),"") | X13: =IF(OR(Carteira!C13>0,AND(SUM(Carteira!$C$5:$C$35)=0,Carteira!A13<>"")),N(Carteira!W13)+ROW()/1E9,"") | Y13: =IFERROR(INDEX($D$5:$D$35,MATCH(LARGE($X$5:$X$35,9),$X$5:$X$35,0)),"") | Z13: =IFERROR(INDEX(Carteira!$W$5:$W$35,MATCH(Y13,Carteira!$A$5:$A$35,0)),"") | AB13: =IF(OR(Carteira!C13>0,AND(SUM(Carteira!$C$5:$C$35)=0,Carteira!A13<>"")),N(Carteira!Z13)+ROW()/1E9,"") | AC13: =IFERROR(INDEX($D$5:$D$35,MATCH(LARGE($AB$5:$AB$35,9),$AB$5:$AB$35,0)),"") | AD13: =IFERROR(INDEX(Carteira!$Z$5:$Z$35,MATCH(AC13,Carteira!$A$5:$A$35,0)),"") | AF13: =IF(OR(Carteira!C13>0,AND(SUM(Carteira!$C$5:$C$35)=0,Carteira!A13<>"")),N(Carteira!J13)+ROW()/1E9,"") | AG13: =IFERROR(INDEX($D$5:$D$35,MATCH(LARGE($AF$5:$AF$35,9),$AF$5:$AF$35,0)),"") | AH13: =IFERROR(INDEX(Carteira!$J$5:$J$35,MATCH(AG13,Carteira!$A$5:$A$35,0)),"") | AJ13: =IF(ISNUMBER(H13),IF(Carteira!$G$36>0,H13/Carteira!$G$36,0),"")
D14: =Carteira!A14 | F14: =IF(OR(Carteira!C14>0,AND(SUM(Carteira!$C$5:$C$35)=0,Carteira!A14<>"")),N(Carteira!G14)+ROW()/1E9,"") | G14: =IFERROR(INDEX($D$5:$D$35,MATCH(LARGE($F$5:$F$35,10),$F$5:$F$35,0)),"") | H14: =IFERROR(INDEX(Carteira!$G$5:$G$35,MATCH(G14,Carteira!$A$5:$A$35,0)),"") | J14: =IF(OR(Carteira!C14>0,AND(SUM(Carteira!$C$5:$C$35)=0,Carteira!A14<>"")),N(Carteira!I14)+ROW()/1E9,"") | K14: =IFERROR(INDEX($D$5:$D$35,MATCH(LARGE($J$5:$J$35,10),$J$5:$J$35,0)),"") | L14: =IFERROR(INDEX(Carteira!$I$5:$I$35,MATCH(K14,Carteira!$A$5:$A$35,0)),"") | M14: =IFERROR(INDEX(Carteira!$H$5:$H$35,MATCH(K14,Carteira!$A$5:$A$35,0)),"") | O14: =IF(OR(Carteira!C14>0,AND(SUM(Carteira!$C$5:$C$35)=0,Carteira!A14<>"")),N(Carteira!I14)+ROW()/1E9,"") | P14: =IFERROR(INDEX($D$5:$D$35,MATCH(SMALL($O$5:$O$35,10),$O$5:$O$35,0)),"") | Q14: =IFERROR(INDEX(Carteira!$I$5:$I$35,MATCH(P14,Carteira!$A$5:$A$35,0)),"") | R14: =IFERROR(INDEX(Carteira!$H$5:$H$35,MATCH(P14,Carteira!$A$5:$A$35,0)),"") | T14: =IF(OR(Carteira!C14>0,AND(SUM(Carteira!$C$5:$C$35)=0,Carteira!A14<>"")),N(Carteira!H14)+ROW()/1E9,"") | U14: =IFERROR(INDEX($D$5:$D$35,MATCH(LARGE($T$5:$T$35,10),$T$5:$T$35,0)),"") | V14: =IFERROR(INDEX(Carteira!$H$5:$H$35,MATCH(U14,Carteira!$A$5:$A$35,0)),"") | X14: =IF(OR(Carteira!C14>0,AND(SUM(Carteira!$C$5:$C$35)=0,Carteira!A14<>"")),N(Carteira!W14)+ROW()/1E9,"") | Y14: =IFERROR(INDEX($D$5:$D$35,MATCH(LARGE($X$5:$X$35,10),$X$5:$X$35,0)),"") | Z14: =IFERROR(INDEX(Carteira!$W$5:$W$35,MATCH(Y14,Carteira!$A$5:$A$35,0)),"") | AB14: =IF(OR(Carteira!C14>0,AND(SUM(Carteira!$C$5:$C$35)=0,Carteira!A14<>"")),N(Carteira!Z14)+ROW()/1E9,"") | AC14: =IFERROR(INDEX($D$5:$D$35,MATCH(LARGE($AB$5:$AB$35,10),$AB$5:$AB$35,0)),"") | AD14: =IFERROR(INDEX(Carteira!$Z$5:$Z$35,MATCH(AC14,Carteira!$A$5:$A$35,0)),"") | AF14: =IF(OR(Carteira!C14>0,AND(SUM(Carteira!$C$5:$C$35)=0,Carteira!A14<>"")),N(Carteira!J14)+ROW()/1E9,"") | AG14: =IFERROR(INDEX($D$5:$D$35,MATCH(LARGE($AF$5:$AF$35,10),$AF$5:$AF$35,0)),"") | AH14: =IFERROR(INDEX(Carteira!$J$5:$J$35,MATCH(AG14,Carteira!$A$5:$A$35,0)),"") | AJ14: =IF(ISNUMBER(H14),IF(Carteira!$G$36>0,H14/Carteira!$G$36,0),"")
D15: =Carteira!A15 | F15: =IF(OR(Carteira!C15>0,AND(SUM(Carteira!$C$5:$C$35)=0,Carteira!A15<>"")),N(Carteira!G15)+ROW()/1E9,"") | G15: =IFERROR(INDEX($D$5:$D$35,MATCH(LARGE($F$5:$F$35,11),$F$5:$F$35,0)),"") | H15: =IFERROR(INDEX(Carteira!$G$5:$G$35,MATCH(G15,Carteira!$A$5:$A$35,0)),"") | J15: =IF(OR(Carteira!C15>0,AND(SUM(Carteira!$C$5:$C$35)=0,Carteira!A15<>"")),N(Carteira!I15)+ROW()/1E9,"") | K15: =IFERROR(INDEX($D$5:$D$35,MATCH(LARGE($J$5:$J$35,11),$J$5:$J$35,0)),"") | L15: =IFERROR(INDEX(Carteira!$I$5:$I$35,MATCH(K15,Carteira!$A$5:$A$35,0)),"") | M15: =IFERROR(INDEX(Carteira!$H$5:$H$35,MATCH(K15,Carteira!$A$5:$A$35,0)),"") | O15: =IF(OR(Carteira!C15>0,AND(SUM(Carteira!$C$5:$C$35)=0,Carteira!A15<>"")),N(Carteira!I15)+ROW()/1E9,"") | P15: =IFERROR(INDEX($D$5:$D$35,MATCH(SMALL($O$5:$O$35,11),$O$5:$O$35,0)),"") | Q15: =IFERROR(INDEX(Carteira!$I$5:$I$35,MATCH(P15,Carteira!$A$5:$A$35,0)),"") | R15: =IFERROR(INDEX(Carteira!$H$5:$H$35,MATCH(P15,Carteira!$A$5:$A$35,0)),"") | T15: =IF(OR(Carteira!C15>0,AND(SUM(Carteira!$C$5:$C$35)=0,Carteira!A15<>"")),N(Carteira!H15)+ROW()/1E9,"") | U15: =IFERROR(INDEX($D$5:$D$35,MATCH(LARGE($T$5:$T$35,11),$T$5:$T$35,0)),"") | V15: =IFERROR(INDEX(Carteira!$H$5:$H$35,MATCH(U15,Carteira!$A$5:$A$35,0)),"") | X15: =IF(OR(Carteira!C15>0,AND(SUM(Carteira!$C$5:$C$35)=0,Carteira!A15<>"")),N(Carteira!W15)+ROW()/1E9,"") | Y15: =IFERROR(INDEX($D$5:$D$35,MATCH(LARGE($X$5:$X$35,11),$X$5:$X$35,0)),"") | Z15: =IFERROR(INDEX(Carteira!$W$5:$W$35,MATCH(Y15,Carteira!$A$5:$A$35,0)),"") | AB15: =IF(OR(Carteira!C15>0,AND(SUM(Carteira!$C$5:$C$35)=0,Carteira!A15<>"")),N(Carteira!Z15)+ROW()/1E9,"") | AC15: =IFERROR(INDEX($D$5:$D$35,MATCH(LARGE($AB$5:$AB$35,11),$AB$5:$AB$35,0)),"") | AD15: =IFERROR(INDEX(Carteira!$Z$5:$Z$35,MATCH(AC15,Carteira!$A$5:$A$35,0)),"") | AF15: =IF(OR(Carteira!C15>0,AND(SUM(Carteira!$C$5:$C$35)=0,Carteira!A15<>"")),N(Carteira!J15)+ROW()/1E9,"") | AG15: =IFERROR(INDEX($D$5:$D$35,MATCH(LARGE($AF$5:$AF$35,11),$AF$5:$AF$35,0)),"") | AH15: =IFERROR(INDEX(Carteira!$J$5:$J$35,MATCH(AG15,Carteira!$A$5:$A$35,0)),"") | AJ15: =IF(ISNUMBER(H15),IF(Carteira!$G$36>0,H15/Carteira!$G$36,0),"")
D16: =Carteira!A16 | F16: =IF(OR(Carteira!C16>0,AND(SUM(Carteira!$C$5:$C$35)=0,Carteira!A16<>"")),N(Carteira!G16)+ROW()/1E9,"") | G16: =IFERROR(INDEX($D$5:$D$35,MATCH(LARGE($F$5:$F$35,12),$F$5:$F$35,0)),"") | H16: =IFERROR(INDEX(Carteira!$G$5:$G$35,MATCH(G16,Carteira!$A$5:$A$35,0)),"") | J16: =IF(OR(Carteira!C16>0,AND(SUM(Carteira!$C$5:$C$35)=0,Carteira!A16<>"")),N(Carteira!I16)+ROW()/1E9,"") | K16: =IFERROR(INDEX($D$5:$D$35,MATCH(LARGE($J$5:$J$35,12),$J$5:$J$35,0)),"") | L16: =IFERROR(INDEX(Carteira!$I$5:$I$35,MATCH(K16,Carteira!$A$5:$A$35,0)),"") | M16: =IFERROR(INDEX(Carteira!$H$5:$H$35,MATCH(K16,Carteira!$A$5:$A$35,0)),"") | O16: =IF(OR(Carteira!C16>0,AND(SUM(Carteira!$C$5:$C$35)=0,Carteira!A16<>"")),N(Carteira!I16)+ROW()/1E9,"") | P16: =IFERROR(INDEX($D$5:$D$35,MATCH(SMALL($O$5:$O$35,12),$O$5:$O$35,0)),"") | Q16: =IFERROR(INDEX(Carteira!$I$5:$I$35,MATCH(P16,Carteira!$A$5:$A$35,0)),"") | R16: =IFERROR(INDEX(Carteira!$H$5:$H$35,MATCH(P16,Carteira!$A$5:$A$35,0)),"") | T16: =IF(OR(Carteira!C16>0,AND(SUM(Carteira!$C$5:$C$35)=0,Carteira!A16<>"")),N(Carteira!H16)+ROW()/1E9,"") | U16: =IFERROR(INDEX($D$5:$D$35,MATCH(LARGE($T$5:$T$35,12),$T$5:$T$35,0)),"") | V16: =IFERROR(INDEX(Carteira!$H$5:$H$35,MATCH(U16,Carteira!$A$5:$A$35,0)),"") | X16: =IF(OR(Carteira!C16>0,AND(SUM(Carteira!$C$5:$C$35)=0,Carteira!A16<>"")),N(Carteira!W16)+ROW()/1E9,"") | Y16: =IFERROR(INDEX($D$5:$D$35,MATCH(LARGE($X$5:$X$35,12),$X$5:$X$35,0)),"") | Z16: =IFERROR(INDEX(Carteira!$W$5:$W$35,MATCH(Y16,Carteira!$A$5:$A$35,0)),"") | AB16: =IF(OR(Carteira!C16>0,AND(SUM(Carteira!$C$5:$C$35)=0,Carteira!A16<>"")),N(Carteira!Z16)+ROW()/1E9,"") | AC16: =IFERROR(INDEX($D$5:$D$35,MATCH(LARGE($AB$5:$AB$35,12),$AB$5:$AB$35,0)),"") | AD16: =IFERROR(INDEX(Carteira!$Z$5:$Z$35,MATCH(AC16,Carteira!$A$5:$A$35,0)),"") | AF16: =IF(OR(Carteira!C16>0,AND(SUM(Carteira!$C$5:$C$35)=0,Carteira!A16<>"")),N(Carteira!J16)+ROW()/1E9,"") | AG16: =IFERROR(INDEX($D$5:$D$35,MATCH(LARGE($AF$5:$AF$35,12),$AF$5:$AF$35,0)),"") | AH16: =IFERROR(INDEX(Carteira!$J$5:$J$35,MATCH(AG16,Carteira!$A$5:$A$35,0)),"") | AJ16: =IF(ISNUMBER(H16),IF(Carteira!$G$36>0,H16/Carteira!$G$36,0),"")
D17: =Carteira!A17 | F17: =IF(OR(Carteira!C17>0,AND(SUM(Carteira!$C$5:$C$35)=0,Carteira!A17<>"")),N(Carteira!G17)+ROW()/1E9,"") | G17: =IFERROR(INDEX($D$5:$D$35,MATCH(LARGE($F$5:$F$35,13),$F$5:$F$35,0)),"") | H17: =IFERROR(INDEX(Carteira!$G$5:$G$35,MATCH(G17,Carteira!$A$5:$A$35,0)),"") | J17: =IF(OR(Carteira!C17>0,AND(SUM(Carteira!$C$5:$C$35)=0,Carteira!A17<>"")),N(Carteira!I17)+ROW()/1E9,"") | K17: =IFERROR(INDEX($D$5:$D$35,MATCH(LARGE($J$5:$J$35,13),$J$5:$J$35,0)),"") | L17: =IFERROR(INDEX(Carteira!$I$5:$I$35,MATCH(K17,Carteira!$A$5:$A$35,0)),"") | M17: =IFERROR(INDEX(Carteira!$H$5:$H$35,MATCH(K17,Carteira!$A$5:$A$35,0)),"") | O17: =IF(OR(Carteira!C17>0,AND(SUM(Carteira!$C$5:$C$35)=0,Carteira!A17<>"")),N(Carteira!I17)+ROW()/1E9,"") | P17: =IFERROR(INDEX($D$5:$D$35,MATCH(SMALL($O$5:$O$35,13),$O$5:$O$35,0)),"") | Q17: =IFERROR(INDEX(Carteira!$I$5:$I$35,MATCH(P17,Carteira!$A$5:$A$35,0)),"") | R17: =IFERROR(INDEX(Carteira!$H$5:$H$35,MATCH(P17,Carteira!$A$5:$A$35,0)),"") | T17: =IF(OR(Carteira!C17>0,AND(SUM(Carteira!$C$5:$C$35)=0,Carteira!A17<>"")),N(Carteira!H17)+ROW()/1E9,"") | U17: =IFERROR(INDEX($D$5:$D$35,MATCH(LARGE($T$5:$T$35,13),$T$5:$T$35,0)),"") | V17: =IFERROR(INDEX(Carteira!$H$5:$H$35,MATCH(U17,Carteira!$A$5:$A$35,0)),"") | X17: =IF(OR(Carteira!C17>0,AND(SUM(Carteira!$C$5:$C$35)=0,Carteira!A17<>"")),N(Carteira!W17)+ROW()/1E9,"") | Y17: =IFERROR(INDEX($D$5:$D$35,MATCH(LARGE($X$5:$X$35,13),$X$5:$X$35,0)),"") | Z17: =IFERROR(INDEX(Carteira!$W$5:$W$35,MATCH(Y17,Carteira!$A$5:$A$35,0)),"") | AB17: =IF(OR(Carteira!C17>0,AND(SUM(Carteira!$C$5:$C$35)=0,Carteira!A17<>"")),N(Carteira!Z17)+ROW()/1E9,"") | AC17: =IFERROR(INDEX($D$5:$D$35,MATCH(LARGE($AB$5:$AB$35,13),$AB$5:$AB$35,0)),"") | AD17: =IFERROR(INDEX(Carteira!$Z$5:$Z$35,MATCH(AC17,Carteira!$A$5:$A$35,0)),"") | AF17: =IF(OR(Carteira!C17>0,AND(SUM(Carteira!$C$5:$C$35)=0,Carteira!A17<>"")),N(Carteira!J17)+ROW()/1E9,"") | AG17: =IFERROR(INDEX($D$5:$D$35,MATCH(LARGE($AF$5:$AF$35,13),$AF$5:$AF$35,0)),"") | AH17: =IFERROR(INDEX(Carteira!$J$5:$J$35,MATCH(AG17,Carteira!$A$5:$A$35,0)),"") | AJ17: =IF(ISNUMBER(H17),IF(Carteira!$G$36>0,H17/Carteira!$G$36,0),"")
D18: =Carteira!A18 | F18: =IF(OR(Carteira!C18>0,AND(SUM(Carteira!$C$5:$C$35)=0,Carteira!A18<>"")),N(Carteira!G18)+ROW()/1E9,"") | G18: =IFERROR(INDEX($D$5:$D$35,MATCH(LARGE($F$5:$F$35,14),$F$5:$F$35,0)),"") | H18: =IFERROR(INDEX(Carteira!$G$5:$G$35,MATCH(G18,Carteira!$A$5:$A$35,0)),"") | J18: =IF(OR(Carteira!C18>0,AND(SUM(Carteira!$C$5:$C$35)=0,Carteira!A18<>"")),N(Carteira!I18)+ROW()/1E9,"") | K18: =IFERROR(INDEX($D$5:$D$35,MATCH(LARGE($J$5:$J$35,14),$J$5:$J$35,0)),"") | L18: =IFERROR(INDEX(Carteira!$I$5:$I$35,MATCH(K18,Carteira!$A$5:$A$35,0)),"") | M18: =IFERROR(INDEX(Carteira!$H$5:$H$35,MATCH(K18,Carteira!$A$5:$A$35,0)),"") | O18: =IF(OR(Carteira!C18>0,AND(SUM(Carteira!$C$5:$C$35)=0,Carteira!A18<>"")),N(Carteira!I18)+ROW()/1E9,"") | P18: =IFERROR(INDEX($D$5:$D$35,MATCH(SMALL($O$5:$O$35,14),$O$5:$O$35,0)),"") | Q18: =IFERROR(INDEX(Carteira!$I$5:$I$35,MATCH(P18,Carteira!$A$5:$A$35,0)),"") | R18: =IFERROR(INDEX(Carteira!$H$5:$H$35,MATCH(P18,Carteira!$A$5:$A$35,0)),"") | T18: =IF(OR(Carteira!C18>0,AND(SUM(Carteira!$C$5:$C$35)=0,Carteira!A18<>"")),N(Carteira!H18)+ROW()/1E9,"") | U18: =IFERROR(INDEX($D$5:$D$35,MATCH(LARGE($T$5:$T$35,14),$T$5:$T$35,0)),"") | V18: =IFERROR(INDEX(Carteira!$H$5:$H$35,MATCH(U18,Carteira!$A$5:$A$35,0)),"") | X18: =IF(OR(Carteira!C18>0,AND(SUM(Carteira!$C$5:$C$35)=0,Carteira!A18<>"")),N(Carteira!W18)+ROW()/1E9,"") | Y18: =IFERROR(INDEX($D$5:$D$35,MATCH(LARGE($X$5:$X$35,14),$X$5:$X$35,0)),"") | Z18: =IFERROR(INDEX(Carteira!$W$5:$W$35,MATCH(Y18,Carteira!$A$5:$A$35,0)),"") | AB18: =IF(OR(Carteira!C18>0,AND(SUM(Carteira!$C$5:$C$35)=0,Carteira!A18<>"")),N(Carteira!Z18)+ROW()/1E9,"") | AC18: =IFERROR(INDEX($D$5:$D$35,MATCH(LARGE($AB$5:$AB$35,14),$AB$5:$AB$35,0)),"") | AD18: =IFERROR(INDEX(Carteira!$Z$5:$Z$35,MATCH(AC18,Carteira!$A$5:$A$35,0)),"") | AF18: =IF(OR(Carteira!C18>0,AND(SUM(Carteira!$C$5:$C$35)=0,Carteira!A18<>"")),N(Carteira!J18)+ROW()/1E9,"") | AG18: =IFERROR(INDEX($D$5:$D$35,MATCH(LARGE($AF$5:$AF$35,14),$AF$5:$AF$35,0)),"") | AH18: =IFERROR(INDEX(Carteira!$J$5:$J$35,MATCH(AG18,Carteira!$A$5:$A$35,0)),"") | AJ18: =IF(ISNUMBER(H18),IF(Carteira!$G$36>0,H18/Carteira!$G$36,0),"")
D19: =Carteira!A19 | F19: =IF(OR(Carteira!C19>0,AND(SUM(Carteira!$C$5:$C$35)=0,Carteira!A19<>"")),N(Carteira!G19)+ROW()/1E9,"") | G19: =IFERROR(INDEX($D$5:$D$35,MATCH(LARGE($F$5:$F$35,15),$F$5:$F$35,0)),"") | H19: =IFERROR(INDEX(Carteira!$G$5:$G$35,MATCH(G19,Carteira!$A$5:$A$35,0)),"") | J19: =IF(OR(Carteira!C19>0,AND(SUM(Carteira!$C$5:$C$35)=0,Carteira!A19<>"")),N(Carteira!I19)+ROW()/1E9,"") | K19: =IFERROR(INDEX($D$5:$D$35,MATCH(LARGE($J$5:$J$35,15),$J$5:$J$35,0)),"") | L19: =IFERROR(INDEX(Carteira!$I$5:$I$35,MATCH(K19,Carteira!$A$5:$A$35,0)),"") | M19: =IFERROR(INDEX(Carteira!$H$5:$H$35,MATCH(K19,Carteira!$A$5:$A$35,0)),"") | O19: =IF(OR(Carteira!C19>0,AND(SUM(Carteira!$C$5:$C$35)=0,Carteira!A19<>"")),N(Carteira!I19)+ROW()/1E9,"") | P19: =IFERROR(INDEX($D$5:$D$35,MATCH(SMALL($O$5:$O$35,15),$O$5:$O$35,0)),"") | Q19: =IFERROR(INDEX(Carteira!$I$5:$I$35,MATCH(P19,Carteira!$A$5:$A$35,0)),"") | R19: =IFERROR(INDEX(Carteira!$H$5:$H$35,MATCH(P19,Carteira!$A$5:$A$35,0)),"") | T19: =IF(OR(Carteira!C19>0,AND(SUM(Carteira!$C$5:$C$35)=0,Carteira!A19<>"")),N(Carteira!H19)+ROW()/1E9,"") | U19: =IFERROR(INDEX($D$5:$D$35,MATCH(LARGE($T$5:$T$35,15),$T$5:$T$35,0)),"") | V19: =IFERROR(INDEX(Carteira!$H$5:$H$35,MATCH(U19,Carteira!$A$5:$A$35,0)),"") | X19: =IF(OR(Carteira!C19>0,AND(SUM(Carteira!$C$5:$C$35)=0,Carteira!A19<>"")),N(Carteira!W19)+ROW()/1E9,"") | Y19: =IFERROR(INDEX($D$5:$D$35,MATCH(LARGE($X$5:$X$35,15),$X$5:$X$35,0)),"") | Z19: =IFERROR(INDEX(Carteira!$W$5:$W$35,MATCH(Y19,Carteira!$A$5:$A$35,0)),"") | AB19: =IF(OR(Carteira!C19>0,AND(SUM(Carteira!$C$5:$C$35)=0,Carteira!A19<>"")),N(Carteira!Z19)+ROW()/1E9,"") | AC19: =IFERROR(INDEX($D$5:$D$35,MATCH(LARGE($AB$5:$AB$35,15),$AB$5:$AB$35,0)),"") | AD19: =IFERROR(INDEX(Carteira!$Z$5:$Z$35,MATCH(AC19,Carteira!$A$5:$A$35,0)),"") | AF19: =IF(OR(Carteira!C19>0,AND(SUM(Carteira!$C$5:$C$35)=0,Carteira!A19<>"")),N(Carteira!J19)+ROW()/1E9,"") | AG19: =IFERROR(INDEX($D$5:$D$35,MATCH(LARGE($AF$5:$AF$35,15),$AF$5:$AF$35,0)),"") | AH19: =IFERROR(INDEX(Carteira!$J$5:$J$35,MATCH(AG19,Carteira!$A$5:$A$35,0)),"") | AJ19: =IF(ISNUMBER(H19),IF(Carteira!$G$36>0,H19/Carteira!$G$36,0),"")
D20: =Carteira!A20 | F20: =IF(OR(Carteira!C20>0,AND(SUM(Carteira!$C$5:$C$35)=0,Carteira!A20<>"")),N(Carteira!G20)+ROW()/1E9,"") | G20: =IFERROR(INDEX($D$5:$D$35,MATCH(LARGE($F$5:$F$35,16),$F$5:$F$35,0)),"") | H20: =IFERROR(INDEX(Carteira!$G$5:$G$35,MATCH(G20,Carteira!$A$5:$A$35,0)),"") | J20: =IF(OR(Carteira!C20>0,AND(SUM(Carteira!$C$5:$C$35)=0,Carteira!A20<>"")),N(Carteira!I20)+ROW()/1E9,"") | K20: =IFERROR(INDEX($D$5:$D$35,MATCH(LARGE($J$5:$J$35,16),$J$5:$J$35,0)),"") | L20: =IFERROR(INDEX(Carteira!$I$5:$I$35,MATCH(K20,Carteira!$A$5:$A$35,0)),"") | M20: =IFERROR(INDEX(Carteira!$H$5:$H$35,MATCH(K20,Carteira!$A$5:$A$35,0)),"") | O20: =IF(OR(Carteira!C20>0,AND(SUM(Carteira!$C$5:$C$35)=0,Carteira!A20<>"")),N(Carteira!I20)+ROW()/1E9,"") | P20: =IFERROR(INDEX($D$5:$D$35,MATCH(SMALL($O$5:$O$35,16),$O$5:$O$35,0)),"") | Q20: =IFERROR(INDEX(Carteira!$I$5:$I$35,MATCH(P20,Carteira!$A$5:$A$35,0)),"") | R20: =IFERROR(INDEX(Carteira!$H$5:$H$35,MATCH(P20,Carteira!$A$5:$A$35,0)),"") | T20: =IF(OR(Carteira!C20>0,AND(SUM(Carteira!$C$5:$C$35)=0,Carteira!A20<>"")),N(Carteira!H20)+ROW()/1E9,"") | U20: =IFERROR(INDEX($D$5:$D$35,MATCH(LARGE($T$5:$T$35,16),$T$5:$T$35,0)),"") | V20: =IFERROR(INDEX(Carteira!$H$5:$H$35,MATCH(U20,Carteira!$A$5:$A$35,0)),"") | X20: =IF(OR(Carteira!C20>0,AND(SUM(Carteira!$C$5:$C$35)=0,Carteira!A20<>"")),N(Carteira!W20)+ROW()/1E9,"") | Y20: =IFERROR(INDEX($D$5:$D$35,MATCH(LARGE($X$5:$X$35,16),$X$5:$X$35,0)),"") | Z20: =IFERROR(INDEX(Carteira!$W$5:$W$35,MATCH(Y20,Carteira!$A$5:$A$35,0)),"") | AB20: =IF(OR(Carteira!C20>0,AND(SUM(Carteira!$C$5:$C$35)=0,Carteira!A20<>"")),N(Carteira!Z20)+ROW()/1E9,"") | AC20: =IFERROR(INDEX($D$5:$D$35,MATCH(LARGE($AB$5:$AB$35,16),$AB$5:$AB$35,0)),"") | AD20: =IFERROR(INDEX(Carteira!$Z$5:$Z$35,MATCH(AC20,Carteira!$A$5:$A$35,0)),"") | AF20: =IF(OR(Carteira!C20>0,AND(SUM(Carteira!$C$5:$C$35)=0,Carteira!A20<>"")),N(Carteira!J20)+ROW()/1E9,"") | AG20: =IFERROR(INDEX($D$5:$D$35,MATCH(LARGE($AF$5:$AF$35,16),$AF$5:$AF$35,0)),"") | AH20: =IFERROR(INDEX(Carteira!$J$5:$J$35,MATCH(AG20,Carteira!$A$5:$A$35,0)),"") | AJ20: =IF(ISNUMBER(H20),IF(Carteira!$G$36>0,H20/Carteira!$G$36,0),"")
D21: =Carteira!A21 | F21: =IF(OR(Carteira!C21>0,AND(SUM(Carteira!$C$5:$C$35)=0,Carteira!A21<>"")),N(Carteira!G21)+ROW()/1E9,"") | G21: =IFERROR(INDEX($D$5:$D$35,MATCH(LARGE($F$5:$F$35,17),$F$5:$F$35,0)),"") | H21: =IFERROR(INDEX(Carteira!$G$5:$G$35,MATCH(G21,Carteira!$A$5:$A$35,0)),"") | J21: =IF(OR(Carteira!C21>0,AND(SUM(Carteira!$C$5:$C$35)=0,Carteira!A21<>"")),N(Carteira!I21)+ROW()/1E9,"") | K21: =IFERROR(INDEX($D$5:$D$35,MATCH(LARGE($J$5:$J$35,17),$J$5:$J$35,0)),"") | L21: =IFERROR(INDEX(Carteira!$I$5:$I$35,MATCH(K21,Carteira!$A$5:$A$35,0)),"") | M21: =IFERROR(INDEX(Carteira!$H$5:$H$35,MATCH(K21,Carteira!$A$5:$A$35,0)),"") | O21: =IF(OR(Carteira!C21>0,AND(SUM(Carteira!$C$5:$C$35)=0,Carteira!A21<>"")),N(Carteira!I21)+ROW()/1E9,"") | P21: =IFERROR(INDEX($D$5:$D$35,MATCH(SMALL($O$5:$O$35,17),$O$5:$O$35,0)),"") | Q21: =IFERROR(INDEX(Carteira!$I$5:$I$35,MATCH(P21,Carteira!$A$5:$A$35,0)),"") | R21: =IFERROR(INDEX(Carteira!$H$5:$H$35,MATCH(P21,Carteira!$A$5:$A$35,0)),"") | T21: =IF(OR(Carteira!C21>0,AND(SUM(Carteira!$C$5:$C$35)=0,Carteira!A21<>"")),N(Carteira!H21)+ROW()/1E9,"") | U21: =IFERROR(INDEX($D$5:$D$35,MATCH(LARGE($T$5:$T$35,17),$T$5:$T$35,0)),"") | V21: =IFERROR(INDEX(Carteira!$H$5:$H$35,MATCH(U21,Carteira!$A$5:$A$35,0)),"") | X21: =IF(OR(Carteira!C21>0,AND(SUM(Carteira!$C$5:$C$35)=0,Carteira!A21<>"")),N(Carteira!W21)+ROW()/1E9,"") | Y21: =IFERROR(INDEX($D$5:$D$35,MATCH(LARGE($X$5:$X$35,17),$X$5:$X$35,0)),"") | Z21: =IFERROR(INDEX(Carteira!$W$5:$W$35,MATCH(Y21,Carteira!$A$5:$A$35,0)),"") | AB21: =IF(OR(Carteira!C21>0,AND(SUM(Carteira!$C$5:$C$35)=0,Carteira!A21<>"")),N(Carteira!Z21)+ROW()/1E9,"") | AC21: =IFERROR(INDEX($D$5:$D$35,MATCH(LARGE($AB$5:$AB$35,17),$AB$5:$AB$35,0)),"") | AD21: =IFERROR(INDEX(Carteira!$Z$5:$Z$35,MATCH(AC21,Carteira!$A$5:$A$35,0)),"") | AF21: =IF(OR(Carteira!C21>0,AND(SUM(Carteira!$C$5:$C$35)=0,Carteira!A21<>"")),N(Carteira!J21)+ROW()/1E9,"") | AG21: =IFERROR(INDEX($D$5:$D$35,MATCH(LARGE($AF$5:$AF$35,17),$AF$5:$AF$35,0)),"") | AH21: =IFERROR(INDEX(Carteira!$J$5:$J$35,MATCH(AG21,Carteira!$A$5:$A$35,0)),"") | AJ21: =IF(ISNUMBER(H21),IF(Carteira!$G$36>0,H21/Carteira!$G$36,0),"")
D22: =Carteira!A22 | F22: =IF(OR(Carteira!C22>0,AND(SUM(Carteira!$C$5:$C$35)=0,Carteira!A22<>"")),N(Carteira!G22)+ROW()/1E9,"") | G22: =IFERROR(INDEX($D$5:$D$35,MATCH(LARGE($F$5:$F$35,18),$F$5:$F$35,0)),"") | H22: =IFERROR(INDEX(Carteira!$G$5:$G$35,MATCH(G22,Carteira!$A$5:$A$35,0)),"") | J22: =IF(OR(Carteira!C22>0,AND(SUM(Carteira!$C$5:$C$35)=0,Carteira!A22<>"")),N(Carteira!I22)+ROW()/1E9,"") | K22: =IFERROR(INDEX($D$5:$D$35,MATCH(LARGE($J$5:$J$35,18),$J$5:$J$35,0)),"") | L22: =IFERROR(INDEX(Carteira!$I$5:$I$35,MATCH(K22,Carteira!$A$5:$A$35,0)),"") | M22: =IFERROR(INDEX(Carteira!$H$5:$H$35,MATCH(K22,Carteira!$A$5:$A$35,0)),"") | O22: =IF(OR(Carteira!C22>0,AND(SUM(Carteira!$C$5:$C$35)=0,Carteira!A22<>"")),N(Carteira!I22)+ROW()/1E9,"") | P22: =IFERROR(INDEX($D$5:$D$35,MATCH(SMALL($O$5:$O$35,18),$O$5:$O$35,0)),"") | Q22: =IFERROR(INDEX(Carteira!$I$5:$I$35,MATCH(P22,Carteira!$A$5:$A$35,0)),"") | R22: =IFERROR(INDEX(Carteira!$H$5:$H$35,MATCH(P22,Carteira!$A$5:$A$35,0)),"") | T22: =IF(OR(Carteira!C22>0,AND(SUM(Carteira!$C$5:$C$35)=0,Carteira!A22<>"")),N(Carteira!H22)+ROW()/1E9,"") | U22: =IFERROR(INDEX($D$5:$D$35,MATCH(LARGE($T$5:$T$35,18),$T$5:$T$35,0)),"") | V22: =IFERROR(INDEX(Carteira!$H$5:$H$35,MATCH(U22,Carteira!$A$5:$A$35,0)),"") | X22: =IF(OR(Carteira!C22>0,AND(SUM(Carteira!$C$5:$C$35)=0,Carteira!A22<>"")),N(Carteira!W22)+ROW()/1E9,"") | Y22: =IFERROR(INDEX($D$5:$D$35,MATCH(LARGE($X$5:$X$35,18),$X$5:$X$35,0)),"") | Z22: =IFERROR(INDEX(Carteira!$W$5:$W$35,MATCH(Y22,Carteira!$A$5:$A$35,0)),"") | AB22: =IF(OR(Carteira!C22>0,AND(SUM(Carteira!$C$5:$C$35)=0,Carteira!A22<>"")),N(Carteira!Z22)+ROW()/1E9,"") | AC22: =IFERROR(INDEX($D$5:$D$35,MATCH(LARGE($AB$5:$AB$35,18),$AB$5:$AB$35,0)),"") | AD22: =IFERROR(INDEX(Carteira!$Z$5:$Z$35,MATCH(AC22,Carteira!$A$5:$A$35,0)),"") | AF22: =IF(OR(Carteira!C22>0,AND(SUM(Carteira!$C$5:$C$35)=0,Carteira!A22<>"")),N(Carteira!J22)+ROW()/1E9,"") | AG22: =IFERROR(INDEX($D$5:$D$35,MATCH(LARGE($AF$5:$AF$35,18),$AF$5:$AF$35,0)),"") | AH22: =IFERROR(INDEX(Carteira!$J$5:$J$35,MATCH(AG22,Carteira!$A$5:$A$35,0)),"") | AJ22: =IF(ISNUMBER(H22),IF(Carteira!$G$36>0,H22/Carteira!$G$36,0),"")
D23: =Carteira!A23 | F23: =IF(OR(Carteira!C23>0,AND(SUM(Carteira!$C$5:$C$35)=0,Carteira!A23<>"")),N(Carteira!G23)+ROW()/1E9,"") | G23: =IFERROR(INDEX($D$5:$D$35,MATCH(LARGE($F$5:$F$35,19),$F$5:$F$35,0)),"") | H23: =IFERROR(INDEX(Carteira!$G$5:$G$35,MATCH(G23,Carteira!$A$5:$A$35,0)),"") | J23: =IF(OR(Carteira!C23>0,AND(SUM(Carteira!$C$5:$C$35)=0,Carteira!A23<>"")),N(Carteira!I23)+ROW()/1E9,"") | K23: =IFERROR(INDEX($D$5:$D$35,MATCH(LARGE($J$5:$J$35,19),$J$5:$J$35,0)),"") | L23: =IFERROR(INDEX(Carteira!$I$5:$I$35,MATCH(K23,Carteira!$A$5:$A$35,0)),"") | M23: =IFERROR(INDEX(Carteira!$H$5:$H$35,MATCH(K23,Carteira!$A$5:$A$35,0)),"") | O23: =IF(OR(Carteira!C23>0,AND(SUM(Carteira!$C$5:$C$35)=0,Carteira!A23<>"")),N(Carteira!I23)+ROW()/1E9,"") | P23: =IFERROR(INDEX($D$5:$D$35,MATCH(SMALL($O$5:$O$35,19),$O$5:$O$35,0)),"") | Q23: =IFERROR(INDEX(Carteira!$I$5:$I$35,MATCH(P23,Carteira!$A$5:$A$35,0)),"") | R23: =IFERROR(INDEX(Carteira!$H$5:$H$35,MATCH(P23,Carteira!$A$5:$A$35,0)),"") | T23: =IF(OR(Carteira!C23>0,AND(SUM(Carteira!$C$5:$C$35)=0,Carteira!A23<>"")),N(Carteira!H23)+ROW()/1E9,"") | U23: =IFERROR(INDEX($D$5:$D$35,MATCH(LARGE($T$5:$T$35,19),$T$5:$T$35,0)),"") | V23: =IFERROR(INDEX(Carteira!$H$5:$H$35,MATCH(U23,Carteira!$A$5:$A$35,0)),"") | X23: =IF(OR(Carteira!C23>0,AND(SUM(Carteira!$C$5:$C$35)=0,Carteira!A23<>"")),N(Carteira!W23)+ROW()/1E9,"") | Y23: =IFERROR(INDEX($D$5:$D$35,MATCH(LARGE($X$5:$X$35,19),$X$5:$X$35,0)),"") | Z23: =IFERROR(INDEX(Carteira!$W$5:$W$35,MATCH(Y23,Carteira!$A$5:$A$35,0)),"") | AB23: =IF(OR(Carteira!C23>0,AND(SUM(Carteira!$C$5:$C$35)=0,Carteira!A23<>"")),N(Carteira!Z23)+ROW()/1E9,"") | AC23: =IFERROR(INDEX($D$5:$D$35,MATCH(LARGE($AB$5:$AB$35,19),$AB$5:$AB$35,0)),"") | AD23: =IFERROR(INDEX(Carteira!$Z$5:$Z$35,MATCH(AC23,Carteira!$A$5:$A$35,0)),"") | AF23: =IF(OR(Carteira!C23>0,AND(SUM(Carteira!$C$5:$C$35)=0,Carteira!A23<>"")),N(Carteira!J23)+ROW()/1E9,"") | AG23: =IFERROR(INDEX($D$5:$D$35,MATCH(LARGE($AF$5:$AF$35,19),$AF$5:$AF$35,0)),"") | AH23: =IFERROR(INDEX(Carteira!$J$5:$J$35,MATCH(AG23,Carteira!$A$5:$A$35,0)),"") | AJ23: =IF(ISNUMBER(H23),IF(Carteira!$G$36>0,H23/Carteira!$G$36,0),"")
D24: =Carteira!A24 | F24: =IF(OR(Carteira!C24>0,AND(SUM(Carteira!$C$5:$C$35)=0,Carteira!A24<>"")),N(Carteira!G24)+ROW()/1E9,"") | G24: =IFERROR(INDEX($D$5:$D$35,MATCH(LARGE($F$5:$F$35,20),$F$5:$F$35,0)),"") | H24: =IFERROR(INDEX(Carteira!$G$5:$G$35,MATCH(G24,Carteira!$A$5:$A$35,0)),"") | J24: =IF(OR(Carteira!C24>0,AND(SUM(Carteira!$C$5:$C$35)=0,Carteira!A24<>"")),N(Carteira!I24)+ROW()/1E9,"") | K24: =IFERROR(INDEX($D$5:$D$35,MATCH(LARGE($J$5:$J$35,20),$J$5:$J$35,0)),"") | L24: =IFERROR(INDEX(Carteira!$I$5:$I$35,MATCH(K24,Carteira!$A$5:$A$35,0)),"") | M24: =IFERROR(INDEX(Carteira!$H$5:$H$35,MATCH(K24,Carteira!$A$5:$A$35,0)),"") | O24: =IF(OR(Carteira!C24>0,AND(SUM(Carteira!$C$5:$C$35)=0,Carteira!A24<>"")),N(Carteira!I24)+ROW()/1E9,"") | P24: =IFERROR(INDEX($D$5:$D$35,MATCH(SMALL($O$5:$O$35,20),$O$5:$O$35,0)),"") | Q24: =IFERROR(INDEX(Carteira!$I$5:$I$35,MATCH(P24,Carteira!$A$5:$A$35,0)),"") | R24: =IFERROR(INDEX(Carteira!$H$5:$H$35,MATCH(P24,Carteira!$A$5:$A$35,0)),"") | T24: =IF(OR(Carteira!C24>0,AND(SUM(Carteira!$C$5:$C$35)=0,Carteira!A24<>"")),N(Carteira!H24)+ROW()/1E9,"") | U24: =IFERROR(INDEX($D$5:$D$35,MATCH(LARGE($T$5:$T$35,20),$T$5:$T$35,0)),"") | V24: =IFERROR(INDEX(Carteira!$H$5:$H$35,MATCH(U24,Carteira!$A$5:$A$35,0)),"") | X24: =IF(OR(Carteira!C24>0,AND(SUM(Carteira!$C$5:$C$35)=0,Carteira!A24<>"")),N(Carteira!W24)+ROW()/1E9,"") | Y24: =IFERROR(INDEX($D$5:$D$35,MATCH(LARGE($X$5:$X$35,20),$X$5:$X$35,0)),"") | Z24: =IFERROR(INDEX(Carteira!$W$5:$W$35,MATCH(Y24,Carteira!$A$5:$A$35,0)),"") | AB24: =IF(OR(Carteira!C24>0,AND(SUM(Carteira!$C$5:$C$35)=0,Carteira!A24<>"")),N(Carteira!Z24)+ROW()/1E9,"") | AC24: =IFERROR(INDEX($D$5:$D$35,MATCH(LARGE($AB$5:$AB$35,20),$AB$5:$AB$35,0)),"") | AD24: =IFERROR(INDEX(Carteira!$Z$5:$Z$35,MATCH(AC24,Carteira!$A$5:$A$35,0)),"") | AF24: =IF(OR(Carteira!C24>0,AND(SUM(Carteira!$C$5:$C$35)=0,Carteira!A24<>"")),N(Carteira!J24)+ROW()/1E9,"") | AG24: =IFERROR(INDEX($D$5:$D$35,MATCH(LARGE($AF$5:$AF$35,20),$AF$5:$AF$35,0)),"") | AH24: =IFERROR(INDEX(Carteira!$J$5:$J$35,MATCH(AG24,Carteira!$A$5:$A$35,0)),"") | AJ24: =IF(ISNUMBER(H24),IF(Carteira!$G$36>0,H24/Carteira!$G$36,0),"")
D25: =Carteira!A25 | F25: =IF(OR(Carteira!C25>0,AND(SUM(Carteira!$C$5:$C$35)=0,Carteira!A25<>"")),N(Carteira!G25)+ROW()/1E9,"") | G25: =IFERROR(INDEX($D$5:$D$35,MATCH(LARGE($F$5:$F$35,21),$F$5:$F$35,0)),"") | H25: =IFERROR(INDEX(Carteira!$G$5:$G$35,MATCH(G25,Carteira!$A$5:$A$35,0)),"") | J25: =IF(OR(Carteira!C25>0,AND(SUM(Carteira!$C$5:$C$35)=0,Carteira!A25<>"")),N(Carteira!I25)+ROW()/1E9,"") | K25: =IFERROR(INDEX($D$5:$D$35,MATCH(LARGE($J$5:$J$35,21),$J$5:$J$35,0)),"") | L25: =IFERROR(INDEX(Carteira!$I$5:$I$35,MATCH(K25,Carteira!$A$5:$A$35,0)),"") | M25: =IFERROR(INDEX(Carteira!$H$5:$H$35,MATCH(K25,Carteira!$A$5:$A$35,0)),"") | O25: =IF(OR(Carteira!C25>0,AND(SUM(Carteira!$C$5:$C$35)=0,Carteira!A25<>"")),N(Carteira!I25)+ROW()/1E9,"") | P25: =IFERROR(INDEX($D$5:$D$35,MATCH(SMALL($O$5:$O$35,21),$O$5:$O$35,0)),"") | Q25: =IFERROR(INDEX(Carteira!$I$5:$I$35,MATCH(P25,Carteira!$A$5:$A$35,0)),"") | R25: =IFERROR(INDEX(Carteira!$H$5:$H$35,MATCH(P25,Carteira!$A$5:$A$35,0)),"") | T25: =IF(OR(Carteira!C25>0,AND(SUM(Carteira!$C$5:$C$35)=0,Carteira!A25<>"")),N(Carteira!H25)+ROW()/1E9,"") | U25: =IFERROR(INDEX($D$5:$D$35,MATCH(LARGE($T$5:$T$35,21),$T$5:$T$35,0)),"") | V25: =IFERROR(INDEX(Carteira!$H$5:$H$35,MATCH(U25,Carteira!$A$5:$A$35,0)),"") | X25: =IF(OR(Carteira!C25>0,AND(SUM(Carteira!$C$5:$C$35)=0,Carteira!A25<>"")),N(Carteira!W25)+ROW()/1E9,"") | Y25: =IFERROR(INDEX($D$5:$D$35,MATCH(LARGE($X$5:$X$35,21),$X$5:$X$35,0)),"") | Z25: =IFERROR(INDEX(Carteira!$W$5:$W$35,MATCH(Y25,Carteira!$A$5:$A$35,0)),"") | AB25: =IF(OR(Carteira!C25>0,AND(SUM(Carteira!$C$5:$C$35)=0,Carteira!A25<>"")),N(Carteira!Z25)+ROW()/1E9,"") | AC25: =IFERROR(INDEX($D$5:$D$35,MATCH(LARGE($AB$5:$AB$35,21),$AB$5:$AB$35,0)),"") | AD25: =IFERROR(INDEX(Carteira!$Z$5:$Z$35,MATCH(AC25,Carteira!$A$5:$A$35,0)),"") | AF25: =IF(OR(Carteira!C25>0,AND(SUM(Carteira!$C$5:$C$35)=0,Carteira!A25<>"")),N(Carteira!J25)+ROW()/1E9,"") | AG25: =IFERROR(INDEX($D$5:$D$35,MATCH(LARGE($AF$5:$AF$35,21),$AF$5:$AF$35,0)),"") | AH25: =IFERROR(INDEX(Carteira!$J$5:$J$35,MATCH(AG25,Carteira!$A$5:$A$35,0)),"") | AJ25: =IF(ISNUMBER(H25),IF(Carteira!$G$36>0,H25/Carteira!$G$36,0),"")
D26: =Carteira!A26 | F26: =IF(OR(Carteira!C26>0,AND(SUM(Carteira!$C$5:$C$35)=0,Carteira!A26<>"")),N(Carteira!G26)+ROW()/1E9,"") | G26: =IFERROR(INDEX($D$5:$D$35,MATCH(LARGE($F$5:$F$35,22),$F$5:$F$35,0)),"") | H26: =IFERROR(INDEX(Carteira!$G$5:$G$35,MATCH(G26,Carteira!$A$5:$A$35,0)),"") | J26: =IF(OR(Carteira!C26>0,AND(SUM(Carteira!$C$5:$C$35)=0,Carteira!A26<>"")),N(Carteira!I26)+ROW()/1E9,"") | K26: =IFERROR(INDEX($D$5:$D$35,MATCH(LARGE($J$5:$J$35,22),$J$5:$J$35,0)),"") | L26: =IFERROR(INDEX(Carteira!$I$5:$I$35,MATCH(K26,Carteira!$A$5:$A$35,0)),"") | M26: =IFERROR(INDEX(Carteira!$H$5:$H$35,MATCH(K26,Carteira!$A$5:$A$35,0)),"") | O26: =IF(OR(Carteira!C26>0,AND(SUM(Carteira!$C$5:$C$35)=0,Carteira!A26<>"")),N(Carteira!I26)+ROW()/1E9,"") | P26: =IFERROR(INDEX($D$5:$D$35,MATCH(SMALL($O$5:$O$35,22),$O$5:$O$35,0)),"") | Q26: =IFERROR(INDEX(Carteira!$I$5:$I$35,MATCH(P26,Carteira!$A$5:$A$35,0)),"") | R26: =IFERROR(INDEX(Carteira!$H$5:$H$35,MATCH(P26,Carteira!$A$5:$A$35,0)),"") | T26: =IF(OR(Carteira!C26>0,AND(SUM(Carteira!$C$5:$C$35)=0,Carteira!A26<>"")),N(Carteira!H26)+ROW()/1E9,"") | U26: =IFERROR(INDEX($D$5:$D$35,MATCH(LARGE($T$5:$T$35,22),$T$5:$T$35,0)),"") | V26: =IFERROR(INDEX(Carteira!$H$5:$H$35,MATCH(U26,Carteira!$A$5:$A$35,0)),"") | X26: =IF(OR(Carteira!C26>0,AND(SUM(Carteira!$C$5:$C$35)=0,Carteira!A26<>"")),N(Carteira!W26)+ROW()/1E9,"") | Y26: =IFERROR(INDEX($D$5:$D$35,MATCH(LARGE($X$5:$X$35,22),$X$5:$X$35,0)),"") | Z26: =IFERROR(INDEX(Carteira!$W$5:$W$35,MATCH(Y26,Carteira!$A$5:$A$35,0)),"") | AB26: =IF(OR(Carteira!C26>0,AND(SUM(Carteira!$C$5:$C$35)=0,Carteira!A26<>"")),N(Carteira!Z26)+ROW()/1E9,"") | AC26: =IFERROR(INDEX($D$5:$D$35,MATCH(LARGE($AB$5:$AB$35,22),$AB$5:$AB$35,0)),"") | AD26: =IFERROR(INDEX(Carteira!$Z$5:$Z$35,MATCH(AC26,Carteira!$A$5:$A$35,0)),"") | AF26: =IF(OR(Carteira!C26>0,AND(SUM(Carteira!$C$5:$C$35)=0,Carteira!A26<>"")),N(Carteira!J26)+ROW()/1E9,"") | AG26: =IFERROR(INDEX($D$5:$D$35,MATCH(LARGE($AF$5:$AF$35,22),$AF$5:$AF$35,0)),"") | AH26: =IFERROR(INDEX(Carteira!$J$5:$J$35,MATCH(AG26,Carteira!$A$5:$A$35,0)),"") | AJ26: =IF(ISNUMBER(H26),IF(Carteira!$G$36>0,H26/Carteira!$G$36,0),"")
D27: =Carteira!A27 | F27: =IF(OR(Carteira!C27>0,AND(SUM(Carteira!$C$5:$C$35)=0,Carteira!A27<>"")),N(Carteira!G27)+ROW()/1E9,"") | G27: =IFERROR(INDEX($D$5:$D$35,MATCH(LARGE($F$5:$F$35,23),$F$5:$F$35,0)),"") | H27: =IFERROR(INDEX(Carteira!$G$5:$G$35,MATCH(G27,Carteira!$A$5:$A$35,0)),"") | J27: =IF(OR(Carteira!C27>0,AND(SUM(Carteira!$C$5:$C$35)=0,Carteira!A27<>"")),N(Carteira!I27)+ROW()/1E9,"") | K27: =IFERROR(INDEX($D$5:$D$35,MATCH(LARGE($J$5:$J$35,23),$J$5:$J$35,0)),"") | L27: =IFERROR(INDEX(Carteira!$I$5:$I$35,MATCH(K27,Carteira!$A$5:$A$35,0)),"") | M27: =IFERROR(INDEX(Carteira!$H$5:$H$35,MATCH(K27,Carteira!$A$5:$A$35,0)),"") | O27: =IF(OR(Carteira!C27>0,AND(SUM(Carteira!$C$5:$C$35)=0,Carteira!A27<>"")),N(Carteira!I27)+ROW()/1E9,"") | P27: =IFERROR(INDEX($D$5:$D$35,MATCH(SMALL($O$5:$O$35,23),$O$5:$O$35,0)),"") | Q27: =IFERROR(INDEX(Carteira!$I$5:$I$35,MATCH(P27,Carteira!$A$5:$A$35,0)),"") | R27: =IFERROR(INDEX(Carteira!$H$5:$H$35,MATCH(P27,Carteira!$A$5:$A$35,0)),"") | T27: =IF(OR(Carteira!C27>0,AND(SUM(Carteira!$C$5:$C$35)=0,Carteira!A27<>"")),N(Carteira!H27)+ROW()/1E9,"") | U27: =IFERROR(INDEX($D$5:$D$35,MATCH(LARGE($T$5:$T$35,23),$T$5:$T$35,0)),"") | V27: =IFERROR(INDEX(Carteira!$H$5:$H$35,MATCH(U27,Carteira!$A$5:$A$35,0)),"") | X27: =IF(OR(Carteira!C27>0,AND(SUM(Carteira!$C$5:$C$35)=0,Carteira!A27<>"")),N(Carteira!W27)+ROW()/1E9,"") | Y27: =IFERROR(INDEX($D$5:$D$35,MATCH(LARGE($X$5:$X$35,23),$X$5:$X$35,0)),"") | Z27: =IFERROR(INDEX(Carteira!$W$5:$W$35,MATCH(Y27,Carteira!$A$5:$A$35,0)),"") | AB27: =IF(OR(Carteira!C27>0,AND(SUM(Carteira!$C$5:$C$35)=0,Carteira!A27<>"")),N(Carteira!Z27)+ROW()/1E9,"") | AC27: =IFERROR(INDEX($D$5:$D$35,MATCH(LARGE($AB$5:$AB$35,23),$AB$5:$AB$35,0)),"") | AD27: =IFERROR(INDEX(Carteira!$Z$5:$Z$35,MATCH(AC27,Carteira!$A$5:$A$35,0)),"") | AF27: =IF(OR(Carteira!C27>0,AND(SUM(Carteira!$C$5:$C$35)=0,Carteira!A27<>"")),N(Carteira!J27)+ROW()/1E9,"") | AG27: =IFERROR(INDEX($D$5:$D$35,MATCH(LARGE($AF$5:$AF$35,23),$AF$5:$AF$35,0)),"") | AH27: =IFERROR(INDEX(Carteira!$J$5:$J$35,MATCH(AG27,Carteira!$A$5:$A$35,0)),"") | AJ27: =IF(ISNUMBER(H27),IF(Carteira!$G$36>0,H27/Carteira!$G$36,0),"")
D28: =Carteira!A28 | F28: =IF(OR(Carteira!C28>0,AND(SUM(Carteira!$C$5:$C$35)=0,Carteira!A28<>"")),N(Carteira!G28)+ROW()/1E9,"") | G28: =IFERROR(INDEX($D$5:$D$35,MATCH(LARGE($F$5:$F$35,24),$F$5:$F$35,0)),"") | H28: =IFERROR(INDEX(Carteira!$G$5:$G$35,MATCH(G28,Carteira!$A$5:$A$35,0)),"") | J28: =IF(OR(Carteira!C28>0,AND(SUM(Carteira!$C$5:$C$35)=0,Carteira!A28<>"")),N(Carteira!I28)+ROW()/1E9,"") | K28: =IFERROR(INDEX($D$5:$D$35,MATCH(LARGE($J$5:$J$35,24),$J$5:$J$35,0)),"") | L28: =IFERROR(INDEX(Carteira!$I$5:$I$35,MATCH(K28,Carteira!$A$5:$A$35,0)),"") | M28: =IFERROR(INDEX(Carteira!$H$5:$H$35,MATCH(K28,Carteira!$A$5:$A$35,0)),"") | O28: =IF(OR(Carteira!C28>0,AND(SUM(Carteira!$C$5:$C$35)=0,Carteira!A28<>"")),N(Carteira!I28)+ROW()/1E9,"") | P28: =IFERROR(INDEX($D$5:$D$35,MATCH(SMALL($O$5:$O$35,24),$O$5:$O$35,0)),"") | Q28: =IFERROR(INDEX(Carteira!$I$5:$I$35,MATCH(P28,Carteira!$A$5:$A$35,0)),"") | R28: =IFERROR(INDEX(Carteira!$H$5:$H$35,MATCH(P28,Carteira!$A$5:$A$35,0)),"") | T28: =IF(OR(Carteira!C28>0,AND(SUM(Carteira!$C$5:$C$35)=0,Carteira!A28<>"")),N(Carteira!H28)+ROW()/1E9,"") | U28: =IFERROR(INDEX($D$5:$D$35,MATCH(LARGE($T$5:$T$35,24),$T$5:$T$35,0)),"") | V28: =IFERROR(INDEX(Carteira!$H$5:$H$35,MATCH(U28,Carteira!$A$5:$A$35,0)),"") | X28: =IF(OR(Carteira!C28>0,AND(SUM(Carteira!$C$5:$C$35)=0,Carteira!A28<>"")),N(Carteira!W28)+ROW()/1E9,"") | Y28: =IFERROR(INDEX($D$5:$D$35,MATCH(LARGE($X$5:$X$35,24),$X$5:$X$35,0)),"") | Z28: =IFERROR(INDEX(Carteira!$W$5:$W$35,MATCH(Y28,Carteira!$A$5:$A$35,0)),"") | AB28: =IF(OR(Carteira!C28>0,AND(SUM(Carteira!$C$5:$C$35)=0,Carteira!A28<>"")),N(Carteira!Z28)+ROW()/1E9,"") | AC28: =IFERROR(INDEX($D$5:$D$35,MATCH(LARGE($AB$5:$AB$35,24),$AB$5:$AB$35,0)),"") | AD28: =IFERROR(INDEX(Carteira!$Z$5:$Z$35,MATCH(AC28,Carteira!$A$5:$A$35,0)),"") | AF28: =IF(OR(Carteira!C28>0,AND(SUM(Carteira!$C$5:$C$35)=0,Carteira!A28<>"")),N(Carteira!J28)+ROW()/1E9,"") | AG28: =IFERROR(INDEX($D$5:$D$35,MATCH(LARGE($AF$5:$AF$35,24),$AF$5:$AF$35,0)),"") | AH28: =IFERROR(INDEX(Carteira!$J$5:$J$35,MATCH(AG28,Carteira!$A$5:$A$35,0)),"") | AJ28: =IF(ISNUMBER(H28),IF(Carteira!$G$36>0,H28/Carteira!$G$36,0),"")
D29: =Carteira!A29 | F29: =IF(OR(Carteira!C29>0,AND(SUM(Carteira!$C$5:$C$35)=0,Carteira!A29<>"")),N(Carteira!G29)+ROW()/1E9,"") | G29: =IFERROR(INDEX($D$5:$D$35,MATCH(LARGE($F$5:$F$35,25),$F$5:$F$35,0)),"") | H29: =IFERROR(INDEX(Carteira!$G$5:$G$35,MATCH(G29,Carteira!$A$5:$A$35,0)),"") | J29: =IF(OR(Carteira!C29>0,AND(SUM(Carteira!$C$5:$C$35)=0,Carteira!A29<>"")),N(Carteira!I29)+ROW()/1E9,"") | K29: =IFERROR(INDEX($D$5:$D$35,MATCH(LARGE($J$5:$J$35,25),$J$5:$J$35,0)),"") | L29: =IFERROR(INDEX(Carteira!$I$5:$I$35,MATCH(K29,Carteira!$A$5:$A$35,0)),"") | M29: =IFERROR(INDEX(Carteira!$H$5:$H$35,MATCH(K29,Carteira!$A$5:$A$35,0)),"") | O29: =IF(OR(Carteira!C29>0,AND(SUM(Carteira!$C$5:$C$35)=0,Carteira!A29<>"")),N(Carteira!I29)+ROW()/1E9,"") | P29: =IFERROR(INDEX($D$5:$D$35,MATCH(SMALL($O$5:$O$35,25),$O$5:$O$35,0)),"") | Q29: =IFERROR(INDEX(Carteira!$I$5:$I$35,MATCH(P29,Carteira!$A$5:$A$35,0)),"") | R29: =IFERROR(INDEX(Carteira!$H$5:$H$35,MATCH(P29,Carteira!$A$5:$A$35,0)),"") | T29: =IF(OR(Carteira!C29>0,AND(SUM(Carteira!$C$5:$C$35)=0,Carteira!A29<>"")),N(Carteira!H29)+ROW()/1E9,"") | U29: =IFERROR(INDEX($D$5:$D$35,MATCH(LARGE($T$5:$T$35,25),$T$5:$T$35,0)),"") | V29: =IFERROR(INDEX(Carteira!$H$5:$H$35,MATCH(U29,Carteira!$A$5:$A$35,0)),"") | X29: =IF(OR(Carteira!C29>0,AND(SUM(Carteira!$C$5:$C$35)=0,Carteira!A29<>"")),N(Carteira!W29)+ROW()/1E9,"") | Y29: =IFERROR(INDEX($D$5:$D$35,MATCH(LARGE($X$5:$X$35,25),$X$5:$X$35,0)),"") | Z29: =IFERROR(INDEX(Carteira!$W$5:$W$35,MATCH(Y29,Carteira!$A$5:$A$35,0)),"") | AB29: =IF(OR(Carteira!C29>0,AND(SUM(Carteira!$C$5:$C$35)=0,Carteira!A29<>"")),N(Carteira!Z29)+ROW()/1E9,"") | AC29: =IFERROR(INDEX($D$5:$D$35,MATCH(LARGE($AB$5:$AB$35,25),$AB$5:$AB$35,0)),"") | AD29: =IFERROR(INDEX(Carteira!$Z$5:$Z$35,MATCH(AC29,Carteira!$A$5:$A$35,0)),"") | AF29: =IF(OR(Carteira!C29>0,AND(SUM(Carteira!$C$5:$C$35)=0,Carteira!A29<>"")),N(Carteira!J29)+ROW()/1E9,"") | AG29: =IFERROR(INDEX($D$5:$D$35,MATCH(LARGE($AF$5:$AF$35,25),$AF$5:$AF$35,0)),"") | AH29: =IFERROR(INDEX(Carteira!$J$5:$J$35,MATCH(AG29,Carteira!$A$5:$A$35,0)),"") | AJ29: =IF(ISNUMBER(H29),IF(Carteira!$G$36>0,H29/Carteira!$G$36,0),"")
D30: =Carteira!A30 | F30: =IF(OR(Carteira!C30>0,AND(SUM(Carteira!$C$5:$C$35)=0,Carteira!A30<>"")),N(Carteira!G30)+ROW()/1E9,"") | G30: =IFERROR(INDEX($D$5:$D$35,MATCH(LARGE($F$5:$F$35,26),$F$5:$F$35,0)),"") | H30: =IFERROR(INDEX(Carteira!$G$5:$G$35,MATCH(G30,Carteira!$A$5:$A$35,0)),"") | J30: =IF(OR(Carteira!C30>0,AND(SUM(Carteira!$C$5:$C$35)=0,Carteira!A30<>"")),N(Carteira!I30)+ROW()/1E9,"") | K30: =IFERROR(INDEX($D$5:$D$35,MATCH(LARGE($J$5:$J$35,26),$J$5:$J$35,0)),"") | L30: =IFERROR(INDEX(Carteira!$I$5:$I$35,MATCH(K30,Carteira!$A$5:$A$35,0)),"") | M30: =IFERROR(INDEX(Carteira!$H$5:$H$35,MATCH(K30,Carteira!$A$5:$A$35,0)),"") | O30: =IF(OR(Carteira!C30>0,AND(SUM(Carteira!$C$5:$C$35)=0,Carteira!A30<>"")),N(Carteira!I30)+ROW()/1E9,"") | P30: =IFERROR(INDEX($D$5:$D$35,MATCH(SMALL($O$5:$O$35,26),$O$5:$O$35,0)),"") | Q30: =IFERROR(INDEX(Carteira!$I$5:$I$35,MATCH(P30,Carteira!$A$5:$A$35,0)),"") | R30: =IFERROR(INDEX(Carteira!$H$5:$H$35,MATCH(P30,Carteira!$A$5:$A$35,0)),"") | T30: =IF(OR(Carteira!C30>0,AND(SUM(Carteira!$C$5:$C$35)=0,Carteira!A30<>"")),N(Carteira!H30)+ROW()/1E9,"") | U30: =IFERROR(INDEX($D$5:$D$35,MATCH(LARGE($T$5:$T$35,26),$T$5:$T$35,0)),"") | V30: =IFERROR(INDEX(Carteira!$H$5:$H$35,MATCH(U30,Carteira!$A$5:$A$35,0)),"") | X30: =IF(OR(Carteira!C30>0,AND(SUM(Carteira!$C$5:$C$35)=0,Carteira!A30<>"")),N(Carteira!W30)+ROW()/1E9,"") | Y30: =IFERROR(INDEX($D$5:$D$35,MATCH(LARGE($X$5:$X$35,26),$X$5:$X$35,0)),"") | Z30: =IFERROR(INDEX(Carteira!$W$5:$W$35,MATCH(Y30,Carteira!$A$5:$A$35,0)),"") | AB30: =IF(OR(Carteira!C30>0,AND(SUM(Carteira!$C$5:$C$35)=0,Carteira!A30<>"")),N(Carteira!Z30)+ROW()/1E9,"") | AC30: =IFERROR(INDEX($D$5:$D$35,MATCH(LARGE($AB$5:$AB$35,26),$AB$5:$AB$35,0)),"") | AD30: =IFERROR(INDEX(Carteira!$Z$5:$Z$35,MATCH(AC30,Carteira!$A$5:$A$35,0)),"") | AF30: =IF(OR(Carteira!C30>0,AND(SUM(Carteira!$C$5:$C$35)=0,Carteira!A30<>"")),N(Carteira!J30)+ROW()/1E9,"") | AG30: =IFERROR(INDEX($D$5:$D$35,MATCH(LARGE($AF$5:$AF$35,26),$AF$5:$AF$35,0)),"") | AH30: =IFERROR(INDEX(Carteira!$J$5:$J$35,MATCH(AG30,Carteira!$A$5:$A$35,0)),"") | AJ30: =IF(ISNUMBER(H30),IF(Carteira!$G$36>0,H30/Carteira!$G$36,0),"")
D31: =Carteira!A31 | F31: =IF(OR(Carteira!C31>0,AND(SUM(Carteira!$C$5:$C$35)=0,Carteira!A31<>"")),N(Carteira!G31)+ROW()/1E9,"") | G31: =IFERROR(INDEX($D$5:$D$35,MATCH(LARGE($F$5:$F$35,27),$F$5:$F$35,0)),"") | H31: =IFERROR(INDEX(Carteira!$G$5:$G$35,MATCH(G31,Carteira!$A$5:$A$35,0)),"") | J31: =IF(OR(Carteira!C31>0,AND(SUM(Carteira!$C$5:$C$35)=0,Carteira!A31<>"")),N(Carteira!I31)+ROW()/1E9,"") | K31: =IFERROR(INDEX($D$5:$D$35,MATCH(LARGE($J$5:$J$35,27),$J$5:$J$35,0)),"") | L31: =IFERROR(INDEX(Carteira!$I$5:$I$35,MATCH(K31,Carteira!$A$5:$A$35,0)),"") | M31: =IFERROR(INDEX(Carteira!$H$5:$H$35,MATCH(K31,Carteira!$A$5:$A$35,0)),"") | O31: =IF(OR(Carteira!C31>0,AND(SUM(Carteira!$C$5:$C$35)=0,Carteira!A31<>"")),N(Carteira!I31)+ROW()/1E9,"") | P31: =IFERROR(INDEX($D$5:$D$35,MATCH(SMALL($O$5:$O$35,27),$O$5:$O$35,0)),"") | Q31: =IFERROR(INDEX(Carteira!$I$5:$I$35,MATCH(P31,Carteira!$A$5:$A$35,0)),"") | R31: =IFERROR(INDEX(Carteira!$H$5:$H$35,MATCH(P31,Carteira!$A$5:$A$35,0)),"") | T31: =IF(OR(Carteira!C31>0,AND(SUM(Carteira!$C$5:$C$35)=0,Carteira!A31<>"")),N(Carteira!H31)+ROW()/1E9,"") | U31: =IFERROR(INDEX($D$5:$D$35,MATCH(LARGE($T$5:$T$35,27),$T$5:$T$35,0)),"") | V31: =IFERROR(INDEX(Carteira!$H$5:$H$35,MATCH(U31,Carteira!$A$5:$A$35,0)),"") | X31: =IF(OR(Carteira!C31>0,AND(SUM(Carteira!$C$5:$C$35)=0,Carteira!A31<>"")),N(Carteira!W31)+ROW()/1E9,"") | Y31: =IFERROR(INDEX($D$5:$D$35,MATCH(LARGE($X$5:$X$35,27),$X$5:$X$35,0)),"") | Z31: =IFERROR(INDEX(Carteira!$W$5:$W$35,MATCH(Y31,Carteira!$A$5:$A$35,0)),"") | AB31: =IF(OR(Carteira!C31>0,AND(SUM(Carteira!$C$5:$C$35)=0,Carteira!A31<>"")),N(Carteira!Z31)+ROW()/1E9,"") | AC31: =IFERROR(INDEX($D$5:$D$35,MATCH(LARGE($AB$5:$AB$35,27),$AB$5:$AB$35,0)),"") | AD31: =IFERROR(INDEX(Carteira!$Z$5:$Z$35,MATCH(AC31,Carteira!$A$5:$A$35,0)),"") | AF31: =IF(OR(Carteira!C31>0,AND(SUM(Carteira!$C$5:$C$35)=0,Carteira!A31<>"")),N(Carteira!J31)+ROW()/1E9,"") | AG31: =IFERROR(INDEX($D$5:$D$35,MATCH(LARGE($AF$5:$AF$35,27),$AF$5:$AF$35,0)),"") | AH31: =IFERROR(INDEX(Carteira!$J$5:$J$35,MATCH(AG31,Carteira!$A$5:$A$35,0)),"") | AJ31: =IF(ISNUMBER(H31),IF(Carteira!$G$36>0,H31/Carteira!$G$36,0),"")
D32: =Carteira!A32 | F32: =IF(OR(Carteira!C32>0,AND(SUM(Carteira!$C$5:$C$35)=0,Carteira!A32<>"")),N(Carteira!G32)+ROW()/1E9,"") | G32: =IFERROR(INDEX($D$5:$D$35,MATCH(LARGE($F$5:$F$35,28),$F$5:$F$35,0)),"") | H32: =IFERROR(INDEX(Carteira!$G$5:$G$35,MATCH(G32,Carteira!$A$5:$A$35,0)),"") | J32: =IF(OR(Carteira!C32>0,AND(SUM(Carteira!$C$5:$C$35)=0,Carteira!A32<>"")),N(Carteira!I32)+ROW()/1E9,"") | K32: =IFERROR(INDEX($D$5:$D$35,MATCH(LARGE($J$5:$J$35,28),$J$5:$J$35,0)),"") | L32: =IFERROR(INDEX(Carteira!$I$5:$I$35,MATCH(K32,Carteira!$A$5:$A$35,0)),"") | M32: =IFERROR(INDEX(Carteira!$H$5:$H$35,MATCH(K32,Carteira!$A$5:$A$35,0)),"") | O32: =IF(OR(Carteira!C32>0,AND(SUM(Carteira!$C$5:$C$35)=0,Carteira!A32<>"")),N(Carteira!I32)+ROW()/1E9,"") | P32: =IFERROR(INDEX($D$5:$D$35,MATCH(SMALL($O$5:$O$35,28),$O$5:$O$35,0)),"") | Q32: =IFERROR(INDEX(Carteira!$I$5:$I$35,MATCH(P32,Carteira!$A$5:$A$35,0)),"") | R32: =IFERROR(INDEX(Carteira!$H$5:$H$35,MATCH(P32,Carteira!$A$5:$A$35,0)),"") | T32: =IF(OR(Carteira!C32>0,AND(SUM(Carteira!$C$5:$C$35)=0,Carteira!A32<>"")),N(Carteira!H32)+ROW()/1E9,"") | U32: =IFERROR(INDEX($D$5:$D$35,MATCH(LARGE($T$5:$T$35,28),$T$5:$T$35,0)),"") | V32: =IFERROR(INDEX(Carteira!$H$5:$H$35,MATCH(U32,Carteira!$A$5:$A$35,0)),"") | X32: =IF(OR(Carteira!C32>0,AND(SUM(Carteira!$C$5:$C$35)=0,Carteira!A32<>"")),N(Carteira!W32)+ROW()/1E9,"") | Y32: =IFERROR(INDEX($D$5:$D$35,MATCH(LARGE($X$5:$X$35,28),$X$5:$X$35,0)),"") | Z32: =IFERROR(INDEX(Carteira!$W$5:$W$35,MATCH(Y32,Carteira!$A$5:$A$35,0)),"") | AB32: =IF(OR(Carteira!C32>0,AND(SUM(Carteira!$C$5:$C$35)=0,Carteira!A32<>"")),N(Carteira!Z32)+ROW()/1E9,"") | AC32: =IFERROR(INDEX($D$5:$D$35,MATCH(LARGE($AB$5:$AB$35,28),$AB$5:$AB$35,0)),"") | AD32: =IFERROR(INDEX(Carteira!$Z$5:$Z$35,MATCH(AC32,Carteira!$A$5:$A$35,0)),"") | AF32: =IF(OR(Carteira!C32>0,AND(SUM(Carteira!$C$5:$C$35)=0,Carteira!A32<>"")),N(Carteira!J32)+ROW()/1E9,"") | AG32: =IFERROR(INDEX($D$5:$D$35,MATCH(LARGE($AF$5:$AF$35,28),$AF$5:$AF$35,0)),"") | AH32: =IFERROR(INDEX(Carteira!$J$5:$J$35,MATCH(AG32,Carteira!$A$5:$A$35,0)),"") | AJ32: =IF(ISNUMBER(H32),IF(Carteira!$G$36>0,H32/Carteira!$G$36,0),"")
D33: =Carteira!A33 | F33: =IF(OR(Carteira!C33>0,AND(SUM(Carteira!$C$5:$C$35)=0,Carteira!A33<>"")),N(Carteira!G33)+ROW()/1E9,"") | G33: =IFERROR(INDEX($D$5:$D$35,MATCH(LARGE($F$5:$F$35,29),$F$5:$F$35,0)),"") | H33: =IFERROR(INDEX(Carteira!$G$5:$G$35,MATCH(G33,Carteira!$A$5:$A$35,0)),"") | J33: =IF(OR(Carteira!C33>0,AND(SUM(Carteira!$C$5:$C$35)=0,Carteira!A33<>"")),N(Carteira!I33)+ROW()/1E9,"") | K33: =IFERROR(INDEX($D$5:$D$35,MATCH(LARGE($J$5:$J$35,29),$J$5:$J$35,0)),"") | L33: =IFERROR(INDEX(Carteira!$I$5:$I$35,MATCH(K33,Carteira!$A$5:$A$35,0)),"") | M33: =IFERROR(INDEX(Carteira!$H$5:$H$35,MATCH(K33,Carteira!$A$5:$A$35,0)),"") | O33: =IF(OR(Carteira!C33>0,AND(SUM(Carteira!$C$5:$C$35)=0,Carteira!A33<>"")),N(Carteira!I33)+ROW()/1E9,"") | P33: =IFERROR(INDEX($D$5:$D$35,MATCH(SMALL($O$5:$O$35,29),$O$5:$O$35,0)),"") | Q33: =IFERROR(INDEX(Carteira!$I$5:$I$35,MATCH(P33,Carteira!$A$5:$A$35,0)),"") | R33: =IFERROR(INDEX(Carteira!$H$5:$H$35,MATCH(P33,Carteira!$A$5:$A$35,0)),"") | T33: =IF(OR(Carteira!C33>0,AND(SUM(Carteira!$C$5:$C$35)=0,Carteira!A33<>"")),N(Carteira!H33)+ROW()/1E9,"") | U33: =IFERROR(INDEX($D$5:$D$35,MATCH(LARGE($T$5:$T$35,29),$T$5:$T$35,0)),"") | V33: =IFERROR(INDEX(Carteira!$H$5:$H$35,MATCH(U33,Carteira!$A$5:$A$35,0)),"") | X33: =IF(OR(Carteira!C33>0,AND(SUM(Carteira!$C$5:$C$35)=0,Carteira!A33<>"")),N(Carteira!W33)+ROW()/1E9,"") | Y33: =IFERROR(INDEX($D$5:$D$35,MATCH(LARGE($X$5:$X$35,29),$X$5:$X$35,0)),"") | Z33: =IFERROR(INDEX(Carteira!$W$5:$W$35,MATCH(Y33,Carteira!$A$5:$A$35,0)),"") | AB33: =IF(OR(Carteira!C33>0,AND(SUM(Carteira!$C$5:$C$35)=0,Carteira!A33<>"")),N(Carteira!Z33)+ROW()/1E9,"") | AC33: =IFERROR(INDEX($D$5:$D$35,MATCH(LARGE($AB$5:$AB$35,29),$AB$5:$AB$35,0)),"") | AD33: =IFERROR(INDEX(Carteira!$Z$5:$Z$35,MATCH(AC33,Carteira!$A$5:$A$35,0)),"") | AF33: =IF(OR(Carteira!C33>0,AND(SUM(Carteira!$C$5:$C$35)=0,Carteira!A33<>"")),N(Carteira!J33)+ROW()/1E9,"") | AG33: =IFERROR(INDEX($D$5:$D$35,MATCH(LARGE($AF$5:$AF$35,29),$AF$5:$AF$35,0)),"") | AH33: =IFERROR(INDEX(Carteira!$J$5:$J$35,MATCH(AG33,Carteira!$A$5:$A$35,0)),"") | AJ33: =IF(ISNUMBER(H33),IF(Carteira!$G$36>0,H33/Carteira!$G$36,0),"")
D34: =Carteira!A34 | F34: =IF(OR(Carteira!C34>0,AND(SUM(Carteira!$C$5:$C$35)=0,Carteira!A34<>"")),N(Carteira!G34)+ROW()/1E9,"") | G34: =IFERROR(INDEX($D$5:$D$35,MATCH(LARGE($F$5:$F$35,30),$F$5:$F$35,0)),"") | H34: =IFERROR(INDEX(Carteira!$G$5:$G$35,MATCH(G34,Carteira!$A$5:$A$35,0)),"") | J34: =IF(OR(Carteira!C34>0,AND(SUM(Carteira!$C$5:$C$35)=0,Carteira!A34<>"")),N(Carteira!I34)+ROW()/1E9,"") | K34: =IFERROR(INDEX($D$5:$D$35,MATCH(LARGE($J$5:$J$35,30),$J$5:$J$35,0)),"") | L34: =IFERROR(INDEX(Carteira!$I$5:$I$35,MATCH(K34,Carteira!$A$5:$A$35,0)),"") | M34: =IFERROR(INDEX(Carteira!$H$5:$H$35,MATCH(K34,Carteira!$A$5:$A$35,0)),"") | O34: =IF(OR(Carteira!C34>0,AND(SUM(Carteira!$C$5:$C$35)=0,Carteira!A34<>"")),N(Carteira!I34)+ROW()/1E9,"") | P34: =IFERROR(INDEX($D$5:$D$35,MATCH(SMALL($O$5:$O$35,30),$O$5:$O$35,0)),"") | Q34: =IFERROR(INDEX(Carteira!$I$5:$I$35,MATCH(P34,Carteira!$A$5:$A$35,0)),"") | R34: =IFERROR(INDEX(Carteira!$H$5:$H$35,MATCH(P34,Carteira!$A$5:$A$35,0)),"") | T34: =IF(OR(Carteira!C34>0,AND(SUM(Carteira!$C$5:$C$35)=0,Carteira!A34<>"")),N(Carteira!H34)+ROW()/1E9,"") | U34: =IFERROR(INDEX($D$5:$D$35,MATCH(LARGE($T$5:$T$35,30),$T$5:$T$35,0)),"") | V34: =IFERROR(INDEX(Carteira!$H$5:$H$35,MATCH(U34,Carteira!$A$5:$A$35,0)),"") | X34: =IF(OR(Carteira!C34>0,AND(SUM(Carteira!$C$5:$C$35)=0,Carteira!A34<>"")),N(Carteira!W34)+ROW()/1E9,"") | Y34: =IFERROR(INDEX($D$5:$D$35,MATCH(LARGE($X$5:$X$35,30),$X$5:$X$35,0)),"") | Z34: =IFERROR(INDEX(Carteira!$W$5:$W$35,MATCH(Y34,Carteira!$A$5:$A$35,0)),"") | AB34: =IF(OR(Carteira!C34>0,AND(SUM(Carteira!$C$5:$C$35)=0,Carteira!A34<>"")),N(Carteira!Z34)+ROW()/1E9,"") | AC34: =IFERROR(INDEX($D$5:$D$35,MATCH(LARGE($AB$5:$AB$35,30),$AB$5:$AB$35,0)),"") | AD34: =IFERROR(INDEX(Carteira!$Z$5:$Z$35,MATCH(AC34,Carteira!$A$5:$A$35,0)),"") | AF34: =IF(OR(Carteira!C34>0,AND(SUM(Carteira!$C$5:$C$35)=0,Carteira!A34<>"")),N(Carteira!J34)+ROW()/1E9,"") | AG34: =IFERROR(INDEX($D$5:$D$35,MATCH(LARGE($AF$5:$AF$35,30),$AF$5:$AF$35,0)),"") | AH34: =IFERROR(INDEX(Carteira!$J$5:$J$35,MATCH(AG34,Carteira!$A$5:$A$35,0)),"") | AJ34: =IF(ISNUMBER(H34),IF(Carteira!$G$36>0,H34/Carteira!$G$36,0),"")
D35: =Carteira!A35 | F35: =IF(OR(Carteira!C35>0,AND(SUM(Carteira!$C$5:$C$35)=0,Carteira!A35<>"")),N(Carteira!G35)+ROW()/1E9,"") | G35: =IFERROR(INDEX($D$5:$D$35,MATCH(LARGE($F$5:$F$35,31),$F$5:$F$35,0)),"") | H35: =IFERROR(INDEX(Carteira!$G$5:$G$35,MATCH(G35,Carteira!$A$5:$A$35,0)),"") | J35: =IF(OR(Carteira!C35>0,AND(SUM(Carteira!$C$5:$C$35)=0,Carteira!A35<>"")),N(Carteira!I35)+ROW()/1E9,"") | K35: =IFERROR(INDEX($D$5:$D$35,MATCH(LARGE($J$5:$J$35,31),$J$5:$J$35,0)),"") | L35: =IFERROR(INDEX(Carteira!$I$5:$I$35,MATCH(K35,Carteira!$A$5:$A$35,0)),"") | M35: =IFERROR(INDEX(Carteira!$H$5:$H$35,MATCH(K35,Carteira!$A$5:$A$35,0)),"") | O35: =IF(OR(Carteira!C35>0,AND(SUM(Carteira!$C$5:$C$35)=0,Carteira!A35<>"")),N(Carteira!I35)+ROW()/1E9,"") | P35: =IFERROR(INDEX($D$5:$D$35,MATCH(SMALL($O$5:$O$35,31),$O$5:$O$35,0)),"") | Q35: =IFERROR(INDEX(Carteira!$I$5:$I$35,MATCH(P35,Carteira!$A$5:$A$35,0)),"") | R35: =IFERROR(INDEX(Carteira!$H$5:$H$35,MATCH(P35,Carteira!$A$5:$A$35,0)),"") | T35: =IF(OR(Carteira!C35>0,AND(SUM(Carteira!$C$5:$C$35)=0,Carteira!A35<>"")),N(Carteira!H35)+ROW()/1E9,"") | U35: =IFERROR(INDEX($D$5:$D$35,MATCH(LARGE($T$5:$T$35,31),$T$5:$T$35,0)),"") | V35: =IFERROR(INDEX(Carteira!$H$5:$H$35,MATCH(U35,Carteira!$A$5:$A$35,0)),"") | X35: =IF(OR(Carteira!C35>0,AND(SUM(Carteira!$C$5:$C$35)=0,Carteira!A35<>"")),N(Carteira!W35)+ROW()/1E9,"") | Y35: =IFERROR(INDEX($D$5:$D$35,MATCH(LARGE($X$5:$X$35,31),$X$5:$X$35,0)),"") | Z35: =IFERROR(INDEX(Carteira!$W$5:$W$35,MATCH(Y35,Carteira!$A$5:$A$35,0)),"") | AB35: =IF(OR(Carteira!C35>0,AND(SUM(Carteira!$C$5:$C$35)=0,Carteira!A35<>"")),N(Carteira!Z35)+ROW()/1E9,"") | AC35: =IFERROR(INDEX($D$5:$D$35,MATCH(LARGE($AB$5:$AB$35,31),$AB$5:$AB$35,0)),"") | AD35: =IFERROR(INDEX(Carteira!$Z$5:$Z$35,MATCH(AC35,Carteira!$A$5:$A$35,0)),"") | AF35: =IF(OR(Carteira!C35>0,AND(SUM(Carteira!$C$5:$C$35)=0,Carteira!A35<>"")),N(Carteira!J35)+ROW()/1E9,"") | AG35: =IFERROR(INDEX($D$5:$D$35,MATCH(LARGE($AF$5:$AF$35,31),$AF$5:$AF$35,0)),"") | AH35: =IFERROR(INDEX(Carteira!$J$5:$J$35,MATCH(AG35,Carteira!$A$5:$A$35,0)),"") | AJ35: =IF(ISNUMBER(H35),IF(Carteira!$G$36>0,H35/Carteira!$G$36,0),"")
