Workbook
Name META_MENSAL: Premissas!$B$5
Name PRAZO_META: Premissas!$B$6
Name APORTE_MENSAL: Premissas!$B$7
Name PESO_RV: Premissas!$B$8
Name OUTRAS_CLASSES: Premissas!$B$12:$B$14
Name PJ_INICIAL: 'Projeção'!$B$5
Name PJ_APORTE: 'Projeção'!$B$6
Name PJ_DY: 'Projeção'!$B$7
Name PJ_REINV: 'Projeção'!$B$8
Name PJ_G_PESS: 'Projeção'!$B$9
Name PJ_G_BASE: 'Projeção'!$B$10
Name PJ_G_OTIM: 'Projeção'!$B$11
Name PJ_CDI: 'Projeção'!$B$12
Name PJ_META: 'Projeção'!$B$13
Name lc_data: Cadastro!$C$8
Name lc_ticker: Cadastro!$C$9
Name lc_op: Cadastro!$C$10
Name lc_qtd: Cadastro!$C$11
Name lc_preco: Cadastro!$C$12
Name lc_custos: Cadastro!$C$13
Name lc_ativo: Cadastro!$C$15
Name lc_cot: Cadastro!$C$16
Name lc_tem: Cadastro!$C$17
Name lc_tipo: Cadastro!$C$19
Name lc_seg: Cadastro!$C$20
Name lc_total: Cadastro!$C$22
Name lc_apos: Cadastro!$C$23
Name lc_status: Cadastro!$B$24
Name pv_data: Cadastro!$F$8
Name pv_ticker: Cadastro!$F$9
Name pv_tipo: Cadastro!$F$10
Name pv_valor: Cadastro!$F$11
Name pv_qtd: Cadastro!$F$12
Name pv_tem: Cadastro!$F$14
Name pv_total: Cadastro!$F$15
Name pv_status: Cadastro!$E$16
Name FILTRO_TIPO: Painel!$D$10

Sheet Painel
A1: InvestERP Painel de investimentos | Q1: =IF(COUNTIF(Verificar!A:A,"ERRO")>0,"⚠ Há erros nos dados — ver Verificar",IF(COUNTIF(Verificar!A:A,"AVISO")>0,"● "&COUNTIF(Verificar!A:A,"AVISO")&" pontos a conferir","✓ Dados consistentes"))
B3: =TODAY()
B5: Filtros | I5: =IF(COUNTIF(Carteira!C5:C20,">0")=0,"✚ Nenhuma ação ou FII na carteira ainda — registre sua primeira compra em ✚ Lançar (clique aqui)","")
I6: PATRIMÔNIO TOTAL | N6: RENDA VARIÁVEL | S6: LUCRO / PREJUÍZO | X6: PROVENTOS RECEBIDOS | AC6: MAIOR POSIÇÃO | AH6: MELHOR ATIVO
B7: Tipo de ativo | I7: =(Carteira!G21+SUM(OUTRAS_CLASSES)) | N7: =SUMIFS(Carteira!$G$5:$G$20,Carteira!$AC$5:$AC$20,1) | S7: =SUMIFS(Carteira!$H$5:$H$20,Carteira!$AC$5:$AC$20,1) | X7: =SUMIFS(Carteira!$J$5:$J$20,Carteira!$AC$5:$AC$20,1) | AC7: =IF(SUMIFS(Carteira!$C$5:$C$20,Carteira!$AC$5:$AC$20,1)=0,0,'Base Painel'!H5) | AH7: =IF(SUMIFS(Carteira!$C$5:$C$20,Carteira!$AC$5:$AC$20,1)=0,"—",'Base Painel'!K5)
I8: =TEXT(IF((Carteira!G21+SUM(OUTRAS_CLASSES))>0,Carteira!G21/(Carteira!G21+SUM(OUTRAS_CLASSES)),0),"0%")&" em renda variável" | N8: =SUMIFS(Carteira!$C$5:$C$20,Carteira!$AC$5:$AC$20,1) | S8: =IF(SUMIFS(Carteira!$E$5:$E$20,Carteira!$AC$5:$AC$20,1)>0,SUMIFS(Carteira!$H$5:$H$20,Carteira!$AC$5:$AC$20,1)/SUMIFS(Carteira!$E$5:$E$20,Carteira!$AC$5:$AC$20,1),0) | X8: =SUMIFS(Carteira!$V$5:$V$20,Carteira!$AC$5:$AC$20,1) | AC8: =IF(SUMIFS(Carteira!$C$5:$C$20,Carteira!$AC$5:$AC$20,1)=0,"—",'Base Painel'!G5) | AH8: =IF(SUMIFS(Carteira!$C$5:$C$20,Carteira!$AC$5:$AC$20,1)=0,"",'Base Painel'!L5)
B10: Selecionado | D10: Todos | I10: Carteira e proventos
B12: Atalhos
B13: ✚ Lançar compra ou provento
B14: ◧ Carteira completa
B15: ◎ Meta de renda por ativo
B16: ∑ Análise quantitativa
B17: λ Modelos matemáticos
B18: ↗ Projeção futura
B19: ⚙ Premissas e metas
B20: ⚠ Verificar dados
B22: Meta de renda
B23: =Carteira!W21
B24: =Carteira!W21
B25: ="Renda de R$ "&FIXED(Carteira!V21,0)&" por mês"
I27: Alocação e meta de renda
I44: Meta de renda | U44: meta e prazo de cada ativo: aba Meta (padrão nas Premissas)
I45: RENDA MENSAL | N45: META MENSAL | S45: PROGRESSO DA META | X45: ATIVOS NA META | AC45: APORTE P/ META | AH45: TEMPO ATÉ A META
I46: =Carteira!V21 | N46: =SUM(Meta!G5:G20) | S46: =Carteira!W21 | X46: =Carteira!X21 | AC46: =Carteira!Z21 | AH46: =Carteira!AA21
I47: =Carteira!V21*12 | N47: =Meta!S21 | S47: =IF(SUM(Meta!G5:G20)>0,Carteira!V21/SUM(Meta!G5:G20),0) | X47: =Carteira!Y21 | AC47: =APORTE_MENSAL | AH47: =IF(APORTE_MENSAL>0,Carteira!Z21/APORTE_MENSAL/12,0)
I49: Destaques | U49: rankings no filtro escolhido
I50: Maiores posições | S50: Maiores altas | AC50: Maiores quedas
I51: # | J51: ATIVO | L51: POSIÇÃO | O51: PARTICIPAÇÃO | S51: # | T51: ATIVO | V51: VALORIZAÇÃO | Y51: LUCRO | AC51: # | AD51: ATIVO | AF51: VALORIZAÇÃO | AI51: LUCRO
I52: 1 | J52: =IF(SUMIFS(Carteira!$C$5:$C$20,Carteira!$AC$5:$AC$20,1)=0,"",'Base Painel'!G5) | L52: =IF(SUMIFS(Carteira!$C$5:$C$20,Carteira!$AC$5:$AC$20,1)=0,"",'Base Painel'!H5) | O52: =IF(OR(SUMIFS(Carteira!$C$5:$C$20,Carteira!$AC$5:$AC$20,1)=0,Carteira!$G$21=0),"",'Base Painel'!H5/Carteira!$G$21) | S52: 1 | T52: =IF(SUMIFS(Carteira!$C$5:$C$20,Carteira!$AC$5:$AC$20,1)=0,"",'Base Painel'!K5) | V52: =IF(SUMIFS(Carteira!$C$5:$C$20,Carteira!$AC$5:$AC$20,1)=0,"",'Base Painel'!L5) | Y52: =IF(SUMIFS(Carteira!$C$5:$C$20,Carteira!$AC$5:$AC$20,1)=0,"",'Base Painel'!M5) | AC52: 1 | AD52: =IF(SUMIFS(Carteira!$C$5:$C$20,Carteira!$AC$5:$AC$20,1)=0,"",'Base Painel'!P5) | AF52: =IF(SUMIFS(Carteira!$C$5:$C$20,Carteira!$AC$5:$AC$20,1)=0,"",'Base Painel'!Q5) | AI52: =IF(SUMIFS(Carteira!$C$5:$C$20,Carteira!$AC$5:$AC$20,1)=0,"",'Base Painel'!R5)
I53: 2 | J53: =IF(SUMIFS(Carteira!$C$5:$C$20,Carteira!$AC$5:$AC$20,1)=0,"",'Base Painel'!G6) | L53: =IF(SUMIFS(Carteira!$C$5:$C$20,Carteira!$AC$5:$AC$20,1)=0,"",'Base Painel'!H6) | O53: =IF(OR(SUMIFS(Carteira!$C$5:$C$20,Carteira!$AC$5:$AC$20,1)=0,Carteira!$G$21=0),"",'Base Painel'!H6/Carteira!$G$21) | S53: 2 | T53: =IF(SUMIFS(Carteira!$C$5:$C$20,Carteira!$AC$5:$AC$20,1)=0,"",'Base Painel'!K6) | V53: =IF(SUMIFS(Carteira!$C$5:$C$20,Carteira!$AC$5:$AC$20,1)=0,"",'Base Painel'!L6) | Y53: =IF(SUMIFS(Carteira!$C$5:$C$20,Carteira!$AC$5:$AC$20,1)=0,"",'Base Painel'!M6) | AC53: 2 | AD53: =IF(SUMIFS(Carteira!$C$5:$C$20,Carteira!$AC$5:$AC$20,1)=0,"",'Base Painel'!P6) | AF53: =IF(SUMIFS(Carteira!$C$5:$C$20,Carteira!$AC$5:$AC$20,1)=0,"",'Base Painel'!Q6) | AI53: =IF(SUMIFS(Carteira!$C$5:$C$20,Carteira!$AC$5:$AC$20,1)=0,"",'Base Painel'!R6)
I54: 3 | J54: =IF(SUMIFS(Carteira!$C$5:$C$20,Carteira!$AC$5:$AC$20,1)=0,"",'Base Painel'!G7) | L54: =IF(SUMIFS(Carteira!$C$5:$C$20,Carteira!$AC$5:$AC$20,1)=0,"",'Base Painel'!H7) | O54: =IF(OR(SUMIFS(Carteira!$C$5:$C$20,Carteira!$AC$5:$AC$20,1)=0,Carteira!$G$21=0),"",'Base Painel'!H7/Carteira!$G$21) | S54: 3 | T54: =IF(SUMIFS(Carteira!$C$5:$C$20,Carteira!$AC$5:$AC$20,1)=0,"",'Base Painel'!K7) | V54: =IF(SUMIFS(Carteira!$C$5:$C$20,Carteira!$AC$5:$AC$20,1)=0,"",'Base Painel'!L7) | Y54: =IF(SUMIFS(Carteira!$C$5:$C$20,Carteira!$AC$5:$AC$20,1)=0,"",'Base Painel'!M7) | AC54: 3 | AD54: =IF(SUMIFS(Carteira!$C$5:$C$20,Carteira!$AC$5:$AC$20,1)=0,"",'Base Painel'!P7) | AF54: =IF(SUMIFS(Carteira!$C$5:$C$20,Carteira!$AC$5:$AC$20,1)=0,"",'Base Painel'!Q7) | AI54: =IF(SUMIFS(Carteira!$C$5:$C$20,Carteira!$AC$5:$AC$20,1)=0,"",'Base Painel'!R7)
I55: 4 | J55: =IF(SUMIFS(Carteira!$C$5:$C$20,Carteira!$AC$5:$AC$20,1)=0,"",'Base Painel'!G8) | L55: =IF(SUMIFS(Carteira!$C$5:$C$20,Carteira!$AC$5:$AC$20,1)=0,"",'Base Painel'!H8) | O55: =IF(OR(SUMIFS(Carteira!$C$5:$C$20,Carteira!$AC$5:$AC$20,1)=0,Carteira!$G$21=0),"",'Base Painel'!H8/Carteira!$G$21) | S55: 4 | T55: =IF(SUMIFS(Carteira!$C$5:$C$20,Carteira!$AC$5:$AC$20,1)=0,"",'Base Painel'!K8) | V55: =IF(SUMIFS(Carteira!$C$5:$C$20,Carteira!$AC$5:$AC$20,1)=0,"",'Base Painel'!L8) | Y55: =IF(SUMIFS(Carteira!$C$5:$C$20,Carteira!$AC$5:$AC$20,1)=0,"",'Base Painel'!M8) | AC55: 4 | AD55: =IF(SUMIFS(Carteira!$C$5:$C$20,Carteira!$AC$5:$AC$20,1)=0,"",'Base Painel'!P8) | AF55: =IF(SUMIFS(Carteira!$C$5:$C$20,Carteira!$AC$5:$AC$20,1)=0,"",'Base Painel'!Q8) | AI55: =IF(SUMIFS(Carteira!$C$5:$C$20,Carteira!$AC$5:$AC$20,1)=0,"",'Base Painel'!R8)
I56: 5 | J56: =IF(SUMIFS(Carteira!$C$5:$C$20,Carteira!$AC$5:$AC$20,1)=0,"",'Base Painel'!G9) | L56: =IF(SUMIFS(Carteira!$C$5:$C$20,Carteira!$AC$5:$AC$20,1)=0,"",'Base Painel'!H9) | O56: =IF(OR(SUMIFS(Carteira!$C$5:$C$20,Carteira!$AC$5:$AC$20,1)=0,Carteira!$G$21=0),"",'Base Painel'!H9/Carteira!$G$21) | S56: 5 | T56: =IF(SUMIFS(Carteira!$C$5:$C$20,Carteira!$AC$5:$AC$20,1)=0,"",'Base Painel'!K9) | V56: =IF(SUMIFS(Carteira!$C$5:$C$20,Carteira!$AC$5:$AC$20,1)=0,"",'Base Painel'!L9) | Y56: =IF(SUMIFS(Carteira!$C$5:$C$20,Carteira!$AC$5:$AC$20,1)=0,"",'Base Painel'!M9) | AC56: 5 | AD56: =IF(SUMIFS(Carteira!$C$5:$C$20,Carteira!$AC$5:$AC$20,1)=0,"",'Base Painel'!P9) | AF56: =IF(SUMIFS(Carteira!$C$5:$C$20,Carteira!$AC$5:$AC$20,1)=0,"",'Base Painel'!Q9) | AI56: =IF(SUMIFS(Carteira!$C$5:$C$20,Carteira!$AC$5:$AC$20,1)=0,"",'Base Painel'!R9)
I78: Alocação por classe | U78: valores de outras classes e pesos ideais: aba Premissas
I79: CLASSE | N79: VALOR (R$) | S79: PESO ATUAL | W79: PESO IDEAL | AA79: DESVIO | AE79: APORTE P/ IDEAL (R$)
I80: Ações | N80: =Carteira!G23 | S80: =IF($N$85>0,N80/$N$85,0) | W80: =PESO_RV*SUMIFS(Ativos!$F$5:$F$20,Ativos!$B$5:$B$20,"AÇÃO")/Ativos!$F$21 | AA80: =S80-W80 | AE80: =MAX(0,W80*$N$85-N80)
I81: FIIs | N81: =Carteira!G24 | S81: =IF($N$85>0,N81/$N$85,0) | W81: =PESO_RV*SUMIFS(Ativos!$F$5:$F$20,Ativos!$B$5:$B$20,"FII")/Ativos!$F$21 | AA81: =S81-W81 | AE81: =MAX(0,W81*$N$85-N81)
I82: =Premissas!A12 | N82: =Premissas!B12 | S82: =IF($N$85>0,N82/$N$85,0) | W82: =Premissas!C12 | AA82: =S82-W82 | AE82: =MAX(0,W82*$N$85-N82)
I83: =Premissas!A13 | N83: =Premissas!B13 | S83: =IF($N$85>0,N83/$N$85,0) | W83: =Premissas!C13 | AA83: =S83-W83 | AE83: =MAX(0,W83*$N$85-N83)
I84: =Premissas!A14 | N84: =Premissas!B14 | S84: =IF($N$85>0,N84/$N$85,0) | W84: =Premissas!C14 | AA84: =S84-W84 | AE84: =MAX(0,W84*$N$85-N84)
I85: TOTAL | N85: =SUM(N80:N84) | S85: =SUM(S80:S84) | W85: =SUM(W80:W84) | AE85: =SUM(AE80:AE84)

Sheet Carteira
A1: InvestERP Carteira
A3: Cada ação/FII em uma linha só: posição, proventos, peso e meta de renda — calculado, não digite aqui.
A4: Ticker | B4: Tipo | C4: Qtd atual | D4: Preço médio (R$) | E4: Valor investido (R$) | F4: Cotação (R$) | G4: Posição atual (R$) | H4: Lucro / prejuízo (R$) | I4: Valorização | J4: Proventos recebidos (R$) | K4: Proventos 12m (R$) | L4: Retorno total (R$) | M4: Retorno total % | N4: Yield on cost | O4: DY atual | P4: Peso atual | Q4: Peso ideal | R4: Desvio do peso | S4: Aporte p/ peso ideal (R$) | T4: Provento 12m por cota (R$) | U4: Provento mensal por cota (R$) | V4: Renda mensal (R$) | W4: % da meta | X4: Cotas p/ meta | Y4: Cotas faltantes | Z4: Aporte p/ meta (R$) | AA4: Meses p/ meta | AB4: Segmento | AC4: No filtro
A5: =IF(Ativos!A5="","",Ativos!A5) | B5: =IF(Ativos!B5="","",Ativos!B5) | C5: =SUMIFS('Lançamentos'!$D$5:$D$5000,'Lançamentos'!$B$5:$B$5000,A5,'Lançamentos'!$C$5:$C$5000,"COMPRA")-SUMIFS('Lançamentos'!$D$5:$D$5000,'Lançamentos'!$B$5:$B$5000,A5,'Lançamentos'!$C$5:$C$5000,"VENDA") | D5: =IFERROR(SUMIFS('Lançamentos'!$G$5:$G$5000,'Lançamentos'!$B$5:$B$5000,A5,'Lançamentos'!$C$5:$C$5000,"COMPRA")/SUMIFS('Lançamentos'!$D$5:$D$5000,'Lançamentos'!$B$5:$B$5000,A5,'Lançamentos'!$C$5:$C$5000,"COMPRA"),0) | E5: =C5*D5 | F5: =N(Ativos!D5) | G5: =C5*F5 | H5: =G5-E5 | I5: =IF(E5>0,H5/E5,0) | J5: =SUMIFS(Proventos!$F$5:$F$5000,Proventos!$B$5:$B$5000,A5) | K5: =SUMIFS(Proventos!$F$5:$F$5000,Proventos!$B$5:$B$5000,A5,Proventos!$A$5:$A$5000,">="&(TODAY()-365)) | L5: =H5+J5 | M5: =IF(E5>0,L5/E5,0) | N5: =IF(D5>0,T5/D5,0) | O5: =IF(F5>0,T5/F5,0) | P5: =IF($G$21>0,G5/$G$21,0) | Q5: =N(Ativos!F5) | R5: =P5-Q5 | S5: =MAX(0,Q5*$G$21-G5) | T5: =N(Ativos!E5) | U5: =T5/12 | V5: =C5*U5 | W5: =IF(N(Meta!G5)>0,MIN(1,V5/Meta!G5),0) | X5: =IF(U5>0,ROUNDUP(N(Meta!G5)/U5,0),0) | Y5: =MAX(0,X5-C5) | Z5: =Y5*F5 | AA5: =IF(APORTE_MENSAL>0,ROUNDUP(Z5/APORTE_MENSAL,0),0) | AB5: =IF(Ativos!C5="","",Ativos!C5) | AC5: =IF(A5="",0,IF(OR(FILTRO_TIPO="Todos",B5=FILTRO_TIPO),1,0))
A6: =IF(Ativos!A6="","",Ativos!A6) | B6: =IF(Ativos!B6="","",Ativos!B6) | C6: =SUMIFS('Lançamentos'!$D$5:$D$5000,'Lançamentos'!$B$5:$B$5000,A6,'Lançamentos'!$C$5:$C$5000,"COMPRA")-SUMIFS('Lançamentos'!$D$5:$D$5000,'Lançamentos'!$B$5:$B$5000,A6,'Lançamentos'!$C$5:$C$5000,"VENDA") | D6: =IFERROR(SUMIFS('Lançamentos'!$G$5:$G$5000,'Lançamentos'!$B$5:$B$5000,A6,'Lançamentos'!$C$5:$C$5000,"COMPRA")/SUMIFS('Lançamentos'!$D$5:$D$5000,'Lançamentos'!$B$5:$B$5000,A6,'Lançamentos'!$C$5:$C$5000,"COMPRA"),0) | E6: =C6*D6 | F6: =N(Ativos!D6) | G6: =C6*F6 | H6: =G6-E6 | I6: =IF(E6>0,H6/E6,0) | J6: =SUMIFS(Proventos!$F$5:$F$5000,Proventos!$B$5:$B$5000,A6) | K6: =SUMIFS(Proventos!$F$5:$F$5000,Proventos!$B$5:$B$5000,A6,Proventos!$A$5:$A$5000,">="&(TODAY()-365)) | L6: =H6+J6 | M6: =IF(E6>0,L6/E6,0) | N6: =IF(D6>0,T6/D6,0) | O6: =IF(F6>0,T6/F6,0) | P6: =IF($G$21>0,G6/$G$21,0) | Q6: =N(Ativos!F6) | R6: =P6-Q6 | S6: =MAX(0,Q6*$G$21-G6) | T6: =N(Ativos!E6) | U6: =T6/12 | V6: =C6*U6 | W6: =IF(N(Meta!G6)>0,MIN(1,V6/Meta!G6),0) | X6: =IF(U6>0,ROUNDUP(N(Meta!G6)/U6,0),0) | Y6: =MAX(0,X6-C6) | Z6: =Y6*F6 | AA6: =IF(APORTE_MENSAL>0,ROUNDUP(Z6/APORTE_MENSAL,0),0) | AB6: =IF(Ativos!C6="","",Ativos!C6) | AC6: =IF(A6="",0,IF(OR(FILTRO_TIPO="Todos",B6=FILTRO_TIPO),1,0))
A7: =IF(Ativos!A7="","",Ativos!A7) | B7: =IF(Ativos!B7="","",Ativos!B7) | C7: =SUMIFS('Lançamentos'!$D$5:$D$5000,'Lançamentos'!$B$5:$B$5000,A7,'Lançamentos'!$C$5:$C$5000,"COMPRA")-SUMIFS('Lançamentos'!$D$5:$D$5000,'Lançamentos'!$B$5:$B$5000,A7,'Lançamentos'!$C$5:$C$5000,"VENDA") | D7: =IFERROR(SUMIFS('Lançamentos'!$G$5:$G$5000,'Lançamentos'!$B$5:$B$5000,A7,'Lançamentos'!$C$5:$C$5000,"COMPRA")/SUMIFS('Lançamentos'!$D$5:$D$5000,'Lançamentos'!$B$5:$B$5000,A7,'Lançamentos'!$C$5:$C$5000,"COMPRA"),0) | E7: =C7*D7 | F7: =N(Ativos!D7) | G7: =C7*F7 | H7: =G7-E7 | I7: =IF(E7>0,H7/E7,0) | J7: =SUMIFS(Proventos!$F$5:$F$5000,Proventos!$B$5:$B$5000,A7) | K7: =SUMIFS(Proventos!$F$5:$F$5000,Proventos!$B$5:$B$5000,A7,Proventos!$A$5:$A$5000,">="&(TODAY()-365)) | L7: =H7+J7 | M7: =IF(E7>0,L7/E7,0) | N7: =IF(D7>0,T7/D7,0) | O7: =IF(F7>0,T7/F7,0) | P7: =IF($G$21>0,G7/$G$21,0) | Q7: =N(Ativos!F7) | R7: =P7-Q7 | S7: =MAX(0,Q7*$G$21-G7) | T7: =N(Ativos!E7) | U7: =T7/12 | V7: =C7*U7 | W7: =IF(N(Meta!G7)>0,MIN(1,V7/Meta!G7),0) | X7: =IF(U7>0,ROUNDUP(N(Meta!G7)/U7,0),0) | Y7: =MAX(0,X7-C7) | Z7: =Y7*F7 | AA7: =IF(APORTE_MENSAL>0,ROUNDUP(Z7/APORTE_MENSAL,0),0) | AB7: =IF(Ativos!C7="","",Ativos!C7) | AC7: =IF(A7="",0,IF(OR(FILTRO_TIPO="Todos",B7=FILTRO_TIPO),1,0))
A8: =IF(Ativos!A8="","",Ativos!A8) | B8: =IF(Ativos!B8="","",Ativos!B8) | C8: =SUMIFS('Lançamentos'!$D$5:$D$5000,'Lançamentos'!$B$5:$B$5000,A8,'Lançamentos'!$C$5:$C$5000,"COMPRA")-SUMIFS('Lançamentos'!$D$5:$D$5000,'Lançamentos'!$B$5:$B$5000,A8,'Lançamentos'!$C$5:$C$5000,"VENDA") | D8: =IFERROR(SUMIFS('Lançamentos'!$G$5:$G$5000,'Lançamentos'!$B$5:$B$5000,A8,'Lançamentos'!$C$5:$C$5000,"COMPRA")/SUMIFS('Lançamentos'!$D$5:$D$5000,'Lançamentos'!$B$5:$B$5000,A8,'Lançamentos'!$C$5:$C$5000,"COMPRA"),0) | E8: =C8*D8 | F8: =N(Ativos!D8) | G8: =C8*F8 | H8: =G8-E8 | I8: =IF(E8>0,H8/E8,0) | J8: =SUMIFS(Proventos!$F$5:$F$5000,Proventos!$B$5:$B$5000,A8) | K8: =SUMIFS(Proventos!$F$5:$F$5000,Proventos!$B$5:$B$5000,A8,Proventos!$A$5:$A$5000,">="&(TODAY()-365)) | L8: =H8+J8 | M8: =IF(E8>0,L8/E8,0) | N8: =IF(D8>0,T8/D8,0) | O8: =IF(F8>0,T8/F8,0) | P8: =IF($G$21>0,G8/$G$21,0) | Q8: =N(Ativos!F8) | R8: =P8-Q8 | S8: =MAX(0,Q8*$G$21-G8) | T8: =N(Ativos!E8) | U8: =T8/12 | V8: =C8*U8 | W8: =IF(N(Meta!G8)>0,MIN(1,V8/Meta!G8),0) | X8: =IF(U8>0,ROUNDUP(N(Meta!G8)/U8,0),0) | Y8: =MAX(0,X8-C8) | Z8: =Y8*F8 | AA8: =IF(APORTE_MENSAL>0,ROUNDUP(Z8/APORTE_MENSAL,0),0) | AB8: =IF(Ativos!C8="","",Ativos!C8) | AC8: =IF(A8="",0,IF(OR(FILTRO_TIPO="Todos",B8=FILTRO_TIPO),1,0))
A9: =IF(Ativos!A9="","",Ativos!A9) | B9: =IF(Ativos!B9="","",Ativos!B9) | C9: =SUMIFS('Lançamentos'!$D$5:$D$5000,'Lançamentos'!$B$5:$B$5000,A9,'Lançamentos'!$C$5:$C$5000,"COMPRA")-SUMIFS('Lançamentos'!$D$5:$D$5000,'Lançamentos'!$B$5:$B$5000,A9,'Lançamentos'!$C$5:$C$5000,"VENDA") | D9: =IFERROR(SUMIFS('Lançamentos'!$G$5:$G$5000,'Lançamentos'!$B$5:$B$5000,A9,'Lançamentos'!$C$5:$C$5000,"COMPRA")/SUMIFS('Lançamentos'!$D$5:$D$5000,'Lançamentos'!$B$5:$B$5000,A9,'Lançamentos'!$C$5:$C$5000,"COMPRA"),0) | E9: =C9*D9 | F9: =N(Ativos!D9) | G9: =C9*F9 | H9: =G9-E9 | I9: =IF(E9>0,H9/E9,0) | J9: =SUMIFS(Proventos!$F$5:$F$5000,Proventos!$B$5:$B$5000,A9) | K9: =SUMIFS(Proventos!$F$5:$F$5000,Proventos!$B$5:$B$5000,A9,Proventos!$A$5:$A$5000,">="&(TODAY()-365)) | L9: =H9+J9 | M9: =IF(E9>0,L9/E9,0) | N9: =IF(D9>0,T9/D9,0) | O9: =IF(F9>0,T9/F9,0) | P9: =IF($G$21>0,G9/$G$21,0) | Q9: =N(Ativos!F9) | R9: =P9-Q9 | S9: =MAX(0,Q9*$G$21-G9) | T9: =N(Ativos!E9) | U9: =T9/12 | V9: =C9*U9 | W9: =IF(N(Meta!G9)>0,MIN(1,V9/Meta!G9),0) | X9: =IF(U9>0,ROUNDUP(N(Meta!G9)/U9,0),0) | Y9: =MAX(0,X9-C9) | Z9: =Y9*F9 | AA9: =IF(APORTE_MENSAL>0,ROUNDUP(Z9/APORTE_MENSAL,0),0) | AB9: =IF(Ativos!C9="","",Ativos!C9) | AC9: =IF(A9="",0,IF(OR(FILTRO_TIPO="Todos",B9=FILTRO_TIPO),1,0))
A10: =IF(Ativos!A10="","",Ativos!A10) | B10: =IF(Ativos!B10="","",Ativos!B10) | C10: =SUMIFS('Lançamentos'!$D$5:$D$5000,'Lançamentos'!$B$5:$B$5000,A10,'Lançamentos'!$C$5:$C$5000,"COMPRA")-SUMIFS('Lançamentos'!$D$5:$D$5000,'Lançamentos'!$B$5:$B$5000,A10,'Lançamentos'!$C$5:$C$5000,"VENDA") | D10: =IFERROR(SUMIFS('Lançamentos'!$G$5:$G$5000,'Lançamentos'!$B$5:$B$5000,A10,'Lançamentos'!$C$5:$C$5000,"COMPRA")/SUMIFS('Lançamentos'!$D$5:$D$5000,'Lançamentos'!$B$5:$B$5000,A10,'Lançamentos'!$C$5:$C$5000,"COMPRA"),0) | E10: =C10*D10 | F10: =N(Ativos!D10) | G10: =C10*F10 | H10: =G10-E10 | I10: =IF(E10>0,H10/E10,0) | J10: =SUMIFS(Proventos!$F$5:$F$5000,Proventos!$B$5:$B$5000,A10) | K10: =SUMIFS(Proventos!$F$5:$F$5000,Proventos!$B$5:$B$5000,A10,Proventos!$A$5:$A$5000,">="&(TODAY()-365)) | L10: =H10+J10 | M10: =IF(E10>0,L10/E10,0) | N10: =IF(D10>0,T10/D10,0) | O10: =IF(F10>0,T10/F10,0) | P10: =IF($G$21>0,G10/$G$21,0) | Q10: =N(Ativos!F10) | R10: =P10-Q10 | S10: =MAX(0,Q10*$G$21-G10) | T10: =N(Ativos!E10) | U10: =T10/12 | V10: =C10*U10 | W10: =IF(N(Meta!G10)>0,MIN(1,V10/Meta!G10),0) | X10: =IF(U10>0,ROUNDUP(N(Meta!G10)/U10,0),0) | Y10: =MAX(0,X10-C10) | Z10: =Y10*F10 | AA10: =IF(APORTE_MENSAL>0,ROUNDUP(Z10/APORTE_MENSAL,0),0) | AB10: =IF(Ativos!C10="","",Ativos!C10) | AC10: =IF(A10="",0,IF(OR(FILTRO_TIPO="Todos",B10=FILTRO_TIPO),1,0))
A11: =IF(Ativos!A11="","",Ativos!A11) | B11: =IF(Ativos!B11="","",Ativos!B11) | C11: =SUMIFS('Lançamentos'!$D$5:$D$5000,'Lançamentos'!$B$5:$B$5000,A11,'Lançamentos'!$C$5:$C$5000,"COMPRA")-SUMIFS('Lançamentos'!$D$5:$D$5000,'Lançamentos'!$B$5:$B$5000,A11,'Lançamentos'!$C$5:$C$5000,"VENDA") | D11: =IFERROR(SUMIFS('Lançamentos'!$G$5:$G$5000,'Lançamentos'!$B$5:$B$5000,A11,'Lançamentos'!$C$5:$C$5000,"COMPRA")/SUMIFS('Lançamentos'!$D$5:$D$5000,'Lançamentos'!$B$5:$B$5000,A11,'Lançamentos'!$C$5:$C$5000,"COMPRA"),0) | E11: =C11*D11 | F11: =N(Ativos!D11) | G11: =C11*F11 | H11: =G11-E11 | I11: =IF(E11>0,H11/E11,0) | J11: =SUMIFS(Proventos!$F$5:$F$5000,Proventos!$B$5:$B$5000,A11) | K11: =SUMIFS(Proventos!$F$5:$F$5000,Proventos!$B$5:$B$5000,A11,Proventos!$A$5:$A$5000,">="&(TODAY()-365)) | L11: =H11+J11 | M11: =IF(E11>0,L11/E11,0) | N11: =IF(D11>0,T11/D11,0) | O11: =IF(F11>0,T11/F11,0) | P11: =IF($G$21>0,G11/$G$21,0) | Q11: =N(Ativos!F11) | R11: =P11-Q11 | S11: =MAX(0,Q11*$G$21-G11) | T11: =N(Ativos!E11) | U11: =T11/12 | V11: =C11*U11 | W11: =IF(N(Meta!G11)>0,MIN(1,V11/Meta!G11),0) | X11: =IF(U11>0,ROUNDUP(N(Meta!G11)/U11,0),0) | Y11: =MAX(0,X11-C11) | Z11: =Y11*F11 | AA11: =IF(APORTE_MENSAL>0,ROUNDUP(Z11/APORTE_MENSAL,0),0) | AB11: =IF(Ativos!C11="","",Ativos!C11) | AC11: =IF(A11="",0,IF(OR(FILTRO_TIPO="Todos",B11=FILTRO_TIPO),1,0))
A12: =IF(Ativos!A12="","",Ativos!A12) | B12: =IF(Ativos!B12="","",Ativos!B12) | C12: =SUMIFS('Lançamentos'!$D$5:$D$5000,'Lançamentos'!$B$5:$B$5000,A12,'Lançamentos'!$C$5:$C$5000,"COMPRA")-SUMIFS('Lançamentos'!$D$5:$D$5000,'Lançamentos'!$B$5:$B$5000,A12,'Lançamentos'!$C$5:$C$5000,"VENDA") | D12: =IFERROR(SUMIFS('Lançamentos'!$G$5:$G$5000,'Lançamentos'!$B$5:$B$5000,A12,'Lançamentos'!$C$5:$C$5000,"COMPRA")/SUMIFS('Lançamentos'!$D$5:$D$5000,'Lançamentos'!$B$5:$B$5000,A12,'Lançamentos'!$C$5:$C$5000,"COMPRA"),0) | E12: =C12*D12 | F12: =N(Ativos!D12) | G12: =C12*F12 | H12: =G12-E12 | I12: =IF(E12>0,H12/E12,0) | J12: =SUMIFS(Proventos!$F$5:$F$5000,Proventos!$B$5:$B$5000,A12) | K12: =SUMIFS(Proventos!$F$5:$F$5000,Proventos!$B$5:$B$5000,A12,Proventos!$A$5:$A$5000,">="&(TODAY()-365)) | L12: =H12+J12 | M12: =IF(E12>0,L12/E12,0) | N12: =IF(D12>0,T12/D12,0) | O12: =IF(F12>0,T12/F12,0) | P12: =IF($G$21>0,G12/$G$21,0) | Q12: =N(Ativos!F12) | R12: =P12-Q12 | S12: =MAX(0,Q12*$G$21-G12) | T12: =N(Ativos!E12) | U12: =T12/12 | V12: =C12*U12 | W12: =IF(N(Meta!G12)>0,MIN(1,V12/Meta!G12),0) | X12: =IF(U12>0,ROUNDUP(N(Meta!G12)/U12,0),0) | Y12: =MAX(0,X12-C12) | Z12: =Y12*F12 | AA12: =IF(APORTE_MENSAL>0,ROUNDUP(Z12/APORTE_MENSAL,0),0) | AB12: =IF(Ativos!C12="","",Ativos!C12) | AC12: =IF(A12="",0,IF(OR(FILTRO_TIPO="Todos",B12=FILTRO_TIPO),1,0))
A13: =IF(Ativos!A13="","",Ativos!A13) | B13: =IF(Ativos!B13="","",Ativos!B13) | C13: =SUMIFS('Lançamentos'!$D$5:$D$5000,'Lançamentos'!$B$5:$B$5000,A13,'Lançamentos'!$C$5:$C$5000,"COMPRA")-SUMIFS('Lançamentos'!$D$5:$D$5000,'Lançamentos'!$B$5:$B$5000,A13,'Lançamentos'!$C$5:$C$5000,"VENDA") | D13: =IFERROR(SUMIFS('Lançamentos'!$G$5:$G$5000,'Lançamentos'!$B$5:$B$5000,A13,'Lançamentos'!$C$5:$C$5000,"COMPRA")/SUMIFS('Lançamentos'!$D$5:$D$5000,'Lançamentos'!$B$5:$B$5000,A13,'Lançamentos'!$C$5:$C$5000,"COMPRA"),0) | E13: =C13*D13 | F13: =N(Ativos!D13) | G13: =C13*F13 | H13: =G13-E13 | I13: =IF(E13>0,H13/E13,0) | J13: =SUMIFS(Proventos!$F$5:$F$5000,Proventos!$B$5:$B$5000,A13) | K13: =SUMIFS(Proventos!$F$5:$F$5000,Proventos!$B$5:$B$5000,A13,Proventos!$A$5:$A$5000,">="&(TODAY()-365)) | L13: =H13+J13 | M13: =IF(E13>0,L13/E13,0) | N13: =IF(D13>0,T13/D13,0) | O13: =IF(F13>0,T13/F13,0) | P13: =IF($G$21>0,G13/$G$21,0) | Q13: =N(Ativos!F13) | R13: =P13-Q13 | S13: =MAX(0,Q13*$G$21-G13) | T13: =N(Ativos!E13) | U13: =T13/12 | V13: =C13*U13 | W13: =IF(N(Meta!G13)>0,MIN(1,V13/Meta!G13),0) | X13: =IF(U13>0,ROUNDUP(N(Meta!G13)/U13,0),0) | Y13: =MAX(0,X13-C13) | Z13: =Y13*F13 | AA13: =IF(APORTE_MENSAL>0,ROUNDUP(Z13/APORTE_MENSAL,0),0) | AB13: =IF(Ativos!C13="","",Ativos!C13) | AC13: =IF(A13="",0,IF(OR(FILTRO_TIPO="Todos",B13=FILTRO_TIPO),1,0))
A14: =IF(Ativos!A14="","",Ativos!A14) | B14: =IF(Ativos!B14="","",Ativos!B14) | C14: =SUMIFS('Lançamentos'!$D$5:$D$5000,'Lançamentos'!$B$5:$B$5000,A14,'Lançamentos'!$C$5:$C$5000,"COMPRA")-SUMIFS('Lançamentos'!$D$5:$D$5000,'Lançamentos'!$B$5:$B$5000,A14,'Lançamentos'!$C$5:$C$5000,"VENDA") | D14: =IFERROR(SUMIFS('Lançamentos'!$G$5:$G$5000,'Lançamentos'!$B$5:$B$5000,A14,'Lançamentos'!$C$5:$C$5000,"COMPRA")/SUMIFS('Lançamentos'!$D$5:$D$5000,'Lançamentos'!$B$5:$B$5000,A14,'Lançamentos'!$C$5:$C$5000,"COMPRA"),0) | E14: =C14*D14 | F14: =N(Ativos!D14) | G14: =C14*F14 | H14: =G14-E14 | I14: =IF(E14>0,H14/E14,0) | J14: =SUMIFS(Proventos!$F$5:$F$5000,Proventos!$B$5:$B$5000,A14) | K14: =SUMIFS(Proventos!$F$5:$F$5000,Proventos!$B$5:$B$5000,A14,Proventos!$A$5:$A$5000,">="&(TODAY()-365)) | L14: =H14+J14 | M14: =IF(E14>0,L14/E14,0) | N14: =IF(D14>0,T14/D14,0) | O14: =IF(F14>0,T14/F14,0) | P14: =IF($G$21>0,G14/$G$21,0) | Q14: =N(Ativos!F14) | R14: =P14-Q14 | S14: =MAX(0,Q14*$G$21-G14) | T14: =N(Ativos!E14) | U14: =T14/12 | V14: =C14*U14 | W14: =IF(N(Meta!G14)>0,MIN(1,V14/Meta!G14),0) | X14: =IF(U14>0,ROUNDUP(N(Meta!G14)/U14,0),0) | Y14: =MAX(0,X14-C14) | Z14: =Y14*F14 | AA14: =IF(APORTE_MENSAL>0,ROUNDUP(Z14/APORTE_MENSAL,0),0) | AB14: =IF(Ativos!C14="","",Ativos!C14) | AC14: =IF(A14="",0,IF(OR(FILTRO_TIPO="Todos",B14=FILTRO_TIPO),1,0))
A15: =IF(Ativos!A15="","",Ativos!A15) | B15: =IF(Ativos!B15="","",Ativos!B15) | C15: =SUMIFS('Lançamentos'!$D$5:$D$5000,'Lançamentos'!$B$5:$B$5000,A15,'Lançamentos'!$C$5:$C$5000,"COMPRA")-SUMIFS('Lançamentos'!$D$5:$D$5000,'Lançamentos'!$B$5:$B$5000,A15,'Lançamentos'!$C$5:$C$5000,"VENDA") | D15: =IFERROR(SUMIFS('Lançamentos'!$G$5:$G$5000,'Lançamentos'!$B$5:$B$5000,A15,'Lançamentos'!$C$5:$C$5000,"COMPRA")/SUMIFS('Lançamentos'!$D$5:$D$5000,'Lançamentos'!$B$5:$B$5000,A15,'Lançamentos'!$C$5:$C$5000,"COMPRA"),0) | E15: =C15*D15 | F15: =N(Ativos!D15) | G15: =C15*F15 | H15: =G15-E15 | I15: =IF(E15>0,H15/E15,0) | J15: =SUMIFS(Proventos!$F$5:$F$5000,Proventos!$B$5:$B$5000,A15) | K15: =SUMIFS(Proventos!$F$5:$F$5000,Proventos!$B$5:$B$5000,A15,Proventos!$A$5:$A$5000,">="&(TODAY()-365)) | L15: =H15+J15 | M15: =IF(E15>0,L15/E15,0) | N15: =IF(D15>0,T15/D15,0) | O15: =IF(F15>0,T15/F15,0) | P15: =IF($G$21>0,G15/$G$21,0) | Q15: =N(Ativos!F15) | R15: =P15-Q15 | S15: =MAX(0,Q15*$G$21-G15) | T15: =N(Ativos!E15) | U15: =T15/12 | V15: =C15*U15 | W15: =IF(N(Meta!G15)>0,MIN(1,V15/Meta!G15),0) | X15: =IF(U15>0,ROUNDUP(N(Meta!G15)/U15,0),0) | Y15: =MAX(0,X15-C15) | Z15: =Y15*F15 | AA15: =IF(APORTE_MENSAL>0,ROUNDUP(Z15/APORTE_MENSAL,0),0) | AB15: =IF(Ativos!C15="","",Ativos!C15) | AC15: =IF(A15="",0,IF(OR(FILTRO_TIPO="Todos",B15=FILTRO_TIPO),1,0))
A16: =IF(Ativos!A16="","",Ativos!A16) | B16: =IF(Ativos!B16="","",Ativos!B16) | C16: =SUMIFS('Lançamentos'!$D$5:$D$5000,'Lançamentos'!$B$5:$B$5000,A16,'Lançamentos'!$C$5:$C$5000,"COMPRA")-SUMIFS('Lançamentos'!$D$5:$D$5000,'Lançamentos'!$B$5:$B$5000,A16,'Lançamentos'!$C$5:$C$5000,"VENDA") | D16: =IFERROR(SUMIFS('Lançamentos'!$G$5:$G$5000,'Lançamentos'!$B$5:$B$5000,A16,'Lançamentos'!$C$5:$C$5000,"COMPRA")/SUMIFS('Lançamentos'!$D$5:$D$5000,'Lançamentos'!$B$5:$B$5000,A16,'Lançamentos'!$C$5:$C$5000,"COMPRA"),0) | E16: =C16*D16 | F16: =N(Ativos!D16) | G16: =C16*F16 | H16: =G16-E16 | I16: =IF(E16>0,H16/E16,0) | J16: =SUMIFS(Proventos!$F$5:$F$5000,Proventos!$B$5:$B$5000,A16) | K16: =SUMIFS(Proventos!$F$5:$F$5000,Proventos!$B$5:$B$5000,A16,Proventos!$A$5:$A$5000,">="&(TODAY()-365)) | L16: =H16+J16 | M16: =IF(E16>0,L16/E16,0) | N16: =IF(D16>0,T16/D16,0) | O16: =IF(F16>0,T16/F16,0) | P16: =IF($G$21>0,G16/$G$21,0) | Q16: =N(Ativos!F16) | R16: =P16-Q16 | S16: =MAX(0,Q16*$G$21-G16) | T16: =N(Ativos!E16) | U16: =T16/12 | V16: =C16*U16 | W16: =IF(N(Meta!G16)>0,MIN(1,V16/Meta!G16),0) | X16: =IF(U16>0,ROUNDUP(N(Meta!G16)/U16,0),0) | Y16: =MAX(0,X16-C16) | Z16: =Y16*F16 | AA16: =IF(APORTE_MENSAL>0,ROUNDUP(Z16/APORTE_MENSAL,0),0) | AB16: =IF(Ativos!C16="","",Ativos!C16) | AC16: =IF(A16="",0,IF(OR(FILTRO_TIPO="Todos",B16=FILTRO_TIPO),1,0))
... A20: =IF(Ativos!A20="","",Ativos!A20) | B20: =IF(Ativos!B20="","",Ativos!B20) | C20: =SUMIFS('Lançamentos'!$D$5:$D$5000,'Lançamentos'!$B$5:$B$5000,A20,'Lançamentos'!$C$5:$C$5000,"COMPRA")-SUMIFS('Lançamentos'!$D$5:$D$5000,'Lançamentos'!$B$5:$B$5000,A20,'Lançamentos'!$C$5:$C$5000,"VENDA") | D20: =IFERROR(SUMIFS('Lançamentos'!$G$5:$G$5000,'Lançamentos'!$B$5:$B$5000,A20,'Lançamentos'!$C$5:$C$5000,"COMPRA")/SUMIFS('Lançamentos'!$D$5:$D$5000,'Lançamentos'!$B$5:$B$5000,A20,'Lançamentos'!$C$5:$C$5000,"COMPRA"),0) | E20: =C20*D20 | F20: =N(Ativos!D20) | G20: =C20*F20 | H20: =G20-E20 | I20: =IF(E20>0,H20/E20,0) | J20: =SUMIFS(Proventos!$F$5:$F$5000,Proventos!$B$5:$B$5000,A20) | K20: =SUMIFS(Proventos!$F$5:$F$5000,Proventos!$B$5:$B$5000,A20,Proventos!$A$5:$A$5000,">="&(TODAY()-365)) | L20: =H20+J20 | M20: =IF(E20>0,L20/E20,0) | N20: =IF(D20>0,T20/D20,0) | O20: =IF(F20>0,T20/F20,0) | P20: =IF($G$21>0,G20/$G$21,0) | Q20: =N(Ativos!F20) | R20: =P20-Q20 | S20: =MAX(0,Q20*$G$21-G20) | T20: =N(Ativos!E20) | U20: =T20/12 | V20: =C20*U20 | W20: =IF(N(Meta!G20)>0,MIN(1,V20/Meta!G20),0) | X20: =IF(U20>0,ROUNDUP(N(Meta!G20)/U20,0),0) | Y20: =MAX(0,X20-C20) | Z20: =Y20*F20 | AA20: =IF(APORTE_MENSAL>0,ROUNDUP(Z20/APORTE_MENSAL,0),0) | AB20: =IF(Ativos!C20="","",Ativos!C20) | AC20: =IF(A20="",0,IF(OR(FILTRO_TIPO="Todos",B20=FILTRO_TIPO),1,0))
A21: TOTAL | E21: =SUM(E5:E20) | G21: =SUM(G5:G20) | H21: =SUM(H5:H20) | I21: =IF(E21>0,H21/E21,0) | J21: =SUM(J5:J20) | K21: =SUM(K5:K20) | L21: =SUM(L5:L20) | M21: =IF(E21>0,L21/E21,0) | N21: =IF(E21>0,SUMPRODUCT(C5:C20,T5:T20)/E21,0) | O21: =IF(G21>0,SUMPRODUCT(C5:C20,T5:T20)/G21,0) | P21: =SUM(P5:P20) | Q21: =SUM(Q5:Q20) | S21: =SUM(S5:S20) | V21: =SUM(V5:V20) | W21: =IFERROR(AVERAGEIF(A5:A20,"?*",W5:W20),0) | X21: =COUNTIF(W5:W20,">=1")&" de "&COUNTIF(A5:A20,"?*")&" na meta" | Y21: =SUM(Y5:Y20) | Z21: =SUM(Z5:Z20) | AA21: =IF(APORTE_MENSAL>0,ROUNDUP(Z21/APORTE_MENSAL,0),0)
A23: Subtotal ações | E23: =SUMIFS(E5:E20,$B$5:$B$20,"AÇÃO") | G23: =SUMIFS(G5:G20,$B$5:$B$20,"AÇÃO") | H23: =SUMIFS(H5:H20,$B$5:$B$20,"AÇÃO") | I23: =IF(E23>0,H23/E23,0) | J23: =SUMIFS(J5:J20,$B$5:$B$20,"AÇÃO") | L23: =SUMIFS(L5:L20,$B$5:$B$20,"AÇÃO") | P23: =SUMIFS(P5:P20,$B$5:$B$20,"AÇÃO") | V23: =SUMIFS(V5:V20,$B$5:$B$20,"AÇÃO")
A24: Subtotal FIIs | E24: =SUMIFS(E5:E20,$B$5:$B$20,"FII") | G24: =SUMIFS(G5:G20,$B$5:$B$20,"FII") | H24: =SUMIFS(H5:H20,$B$5:$B$20,"FII") | I24: =IF(E24>0,H24/E24,0) | J24: =SUMIFS(J5:J20,$B$5:$B$20,"FII") | L24: =SUMIFS(L5:L20,$B$5:$B$20,"FII") | P24: =SUMIFS(P5:P20,$B$5:$B$20,"FII") | V24: =SUMIFS(V5:V20,$B$5:$B$20,"FII")
A26: Como ler
A27: • Linhas em cinza: ativos do catálogo que você ainda não tem (a mesma lista serve de catálogo e de carteira).
A28: • Meta de renda: cotas p/ meta = meta mensal ÷ provento mensal por cota; aporte = cotas faltantes × cotação.
A29: • Tipo, segmento, cotação, provento 12m e peso ideal vêm de dados/ativos.csv (aba Ativos, oculta).

Sheet Análises
A1: InvestERP Análises Dinâmicas
A3: Tabelas dinâmicas sobre Carteira, Proventos e Lançamentos — use os filtros e a segmentação.
A5: As tabelas dinâmicas são criadas pelo Excel ao rodar gestao.py (requer Excel no Windows).

Sheet Meta
A1: InvestERP Meta de Renda por Ativo
A3: Amarelo = você decide: quanto cada ativo deve pagar por mês e em quantos meses (negrito = personalizado; vazio = padrão das Premissas). O resto é calculado.
A4: Ticker | B4: Tipo | C4: Segmento | D4: Valor da cota (R$) | E4: Provento mensal por cota (R$) | F4: Rendimento mensal | G4: Meta mensal (R$) | H4: Prazo (meses) | I4: Cotas necessárias | J4: Valor total a investir (R$) | K4: Cotas que você tem | L4: Preço médio pago (R$) | M4: Valor investido hoje (R$) | N4: Renda mensal atual (R$) | O4: % da meta | P4: Cotas faltantes | Q4: Valor faltante (R$) | R4: Cotas por mês | S4: Aporte mensal no prazo (R$) | T4: Aporte mensal reinvestindo proventos (R$) | U4: Data prevista
A5: =Carteira!A5 | B5: =Carteira!B5 | C5: =Carteira!AB5 | D5: =Carteira!F5 | E5: =Carteira!U5 | F5: =IF(D5>0,E5/D5,0) | G5: =IF(A5="","",META_MENSAL) | H5: =IF(A5="","",PRAZO_META) | I5: =IF(N(G5)=0,"",IF(E5>0,ROUNDUP(G5/E5,0),"sem proventos")) | J5: =IF(ISNUMBER(I5),I5*D5,"") | K5: =Carteira!C5 | L5: =Carteira!D5 | M5: =Carteira!E5 | N5: =Carteira!V5 | O5: =IF(N(G5)>0,MIN(1,N5/G5),0) | P5: =IF(ISNUMBER(I5),MAX(0,I5-K5),"") | Q5: =IF(ISNUMBER(P5),P5*D5,"") | R5: =IF(AND(ISNUMBER(P5),N(H5)>0),ROUNDUP(P5/H5,0),"") | S5: =IF(AND(ISNUMBER(Q5),N(H5)>0),Q5/H5,"") | T5: =IF(NOT(ISNUMBER(S5)),"",IF(F5>0,Q5*F5/((1+F5)^H5-1),S5)) | U5: =IF(N(H5)>0,EDATE(TODAY(),H5),"")
A6: =Carteira!A6 | B6: =Carteira!B6 | C6: =Carteira!AB6 | D6: =Carteira!F6 | E6: =Carteira!U6 | F6: =IF(D6>0,E6/D6,0) | G6: 300 | H6: 48 | I6: =IF(N(G6)=0,"",IF(E6>0,ROUNDUP(G6/E6,0),"sem proventos")) | J6: =IF(ISNUMBER(I6),I6*D6,"") | K6: =Carteira!C6 | L6: =Carteira!D6 | M6: =Carteira!E6 | N6: =Carteira!V6 | O6: =IF(N(G6)>0,MIN(1,N6/G6),0) | P6: =IF(ISNUMBER(I6),MAX(0,I6-K6),"") | Q6: =IF(ISNUMBER(P6),P6*D6,"") | R6: =IF(AND(ISNUMBER(P6),N(H6)>0),ROUNDUP(P6/H6,0),"") | S6: =IF(AND(ISNUMBER(Q6),N(H6)>0),Q6/H6,"") | T6: =IF(NOT(ISNUMBER(S6)),"",IF(F6>0,Q6*F6/((1+F6)^H6-1),S6)) | U6: =IF(N(H6)>0,EDATE(TODAY(),H6),"")
A7: =Carteira!A7 | B7: =Carteira!B7 | C7: =Carteira!AB7 | D7: =Carteira!F7 | E7: =Carteira!U7 | F7: =IF(D7>0,E7/D7,0) | G7: =IF(A7="","",META_MENSAL) | H7: =IF(A7="","",PRAZO_META) | I7: =IF(N(G7)=0,"",IF(E7>0,ROUNDUP(G7/E7,0),"sem proventos")) | J7: =IF(ISNUMBER(I7),I7*D7,"") | K7: =Carteira!C7 | L7: =Carteira!D7 | M7: =Carteira!E7 | N7: =Carteira!V7 | O7: =IF(N(G7)>0,MIN(1,N7/G7),0) | P7: =IF(ISNUMBER(I7),MAX(0,I7-K7),"") | Q7: =IF(ISNUMBER(P7),P7*D7,"") | R7: =IF(AND(ISNUMBER(P7),N(H7)>0),ROUNDUP(P7/H7,0),"") | S7: =IF(AND(ISNUMBER(Q7),N(H7)>0),Q7/H7,"") | T7: =IF(NOT(ISNUMBER(S7)),"",IF(F7>0,Q7*F7/((1+F7)^H7-1),S7)) | U7: =IF(N(H7)>0,EDATE(TODAY(),H7),"")
A8: =Carteira!A8 | B8: =Carteira!B8 | C8: =Carteira!AB8 | D8: =Carteira!F8 | E8: =Carteira!U8 | F8: =IF(D8>0,E8/D8,0) | G8: =IF(A8="","",META_MENSAL) | H8: =IF(A8="","",PRAZO_META) | I8: =IF(N(G8)=0,"",IF(E8>0,ROUNDUP(G8/E8,0),"sem proventos")) | J8: =IF(ISNUMBER(I8),I8*D8,"") | K8: =Carteira!C8 | L8: =Carteira!D8 | M8: =Carteira!E8 | N8: =Carteira!V8 | O8: =IF(N(G8)>0,MIN(1,N8/G8),0) | P8: =IF(ISNUMBER(I8),MAX(0,I8-K8),"") | Q8: =IF(ISNUMBER(P8),P8*D8,"") | R8: =IF(AND(ISNUMBER(P8),N(H8)>0),ROUNDUP(P8/H8,0),"") | S8: =IF(AND(ISNUMBER(Q8),N(H8)>0),Q8/H8,"") | T8: =IF(NOT(ISNUMBER(S8)),"",IF(F8>0,Q8*F8/((1+F8)^H8-1),S8)) | U8: =IF(N(H8)>0,EDATE(TODAY(),H8),"")
A9: =Carteira!A9 | B9: =Carteira!B9 | C9: =Carteira!AB9 | D9: =Carteira!F9 | E9: =Carteira!U9 | F9: =IF(D9>0,E9/D9,0) | G9: =IF(A9="","",META_MENSAL) | H9: =IF(A9="","",PRAZO_META) | I9: =IF(N(G9)=0,"",IF(E9>0,ROUNDUP(G9/E9,0),"sem proventos")) | J9: =IF(ISNUMBER(I9),I9*D9,"") | K9: =Carteira!C9 | L9: =Carteira!D9 | M9: =Carteira!E9 | N9: =Carteira!V9 | O9: =IF(N(G9)>0,MIN(1,N9/G9),0) | P9: =IF(ISNUMBER(I9),MAX(0,I9-K9),"") | Q9: =IF(ISNUMBER(P9),P9*D9,"") | R9: =IF(AND(ISNUMBER(P9),N(H9)>0),ROUNDUP(P9/H9,0),"") | S9: =IF(AND(ISNUMBER(Q9),N(H9)>0),Q9/H9,"") | T9: =IF(NOT(ISNUMBER(S9)),"",IF(F9>0,Q9*F9/((1+F9)^H9-1),S9)) | U9: =IF(N(H9)>0,EDATE(TODAY(),H9),"")
A10: =Carteira!A10 | B10: =Carteira!B10 | C10: =Carteira!AB10 | D10: =Carteira!F10 | E10: =Carteira!U10 | F10: =IF(D10>0,E10/D10,0) | G10: =IF(A10="","",META_MENSAL) | H10: =IF(A10="","",PRAZO_META) | I10: =IF(N(G10)=0,"",IF(E10>0,ROUNDUP(G10/E10,0),"sem proventos")) | J10: =IF(ISNUMBER(I10),I10*D10,"") | K10: =Carteira!C10 | L10: =Carteira!D10 | M10: =Carteira!E10 | N10: =Carteira!V10 | O10: =IF(N(G10)>0,MIN(1,N10/G10),0) | P10: =IF(ISNUMBER(I10),MAX(0,I10-K10),"") | Q10: =IF(ISNUMBER(P10),P10*D10,"") | R10: =IF(AND(ISNUMBER(P10),N(H10)>0),ROUNDUP(P10/H10,0),"") | S10: =IF(AND(ISNUMBER(Q10),N(H10)>0),Q10/H10,"") | T10: =IF(NOT(ISNUMBER(S10)),"",IF(F10>0,Q10*F10/((1+F10)^H10-1),S10)) | U10: =IF(N(H10)>0,EDATE(TODAY(),H10),"")
A11: =Carteira!A11 | B11: =Carteira!B11 | C11: =Carteira!AB11 | D11: =Carteira!F11 | E11: =Carteira!U11 | F11: =IF(D11>0,E11/D11,0) | G11: =IF(A11="","",META_MENSAL) | H11: =IF(A11="","",PRAZO_META) | I11: =IF(N(G11)=0,"",IF(E11>0,ROUNDUP(G11/E11,0),"sem proventos")) | J11: =IF(ISNUMBER(I11),I11*D11,"") | K11: =Carteira!C11 | L11: =Carteira!D11 | M11: =Carteira!E11 | N11: =Carteira!V11 | O11: =IF(N(G11)>0,MIN(1,N11/G11),0) | P11: =IF(ISNUMBER(I11),MAX(0,I11-K11),"") | Q11: =IF(ISNUMBER(P11),P11*D11,"") | R11: =IF(AND(ISNUMBER(P11),N(H11)>0),ROUNDUP(P11/H11,0),"") | S11: =IF(AND(ISNUMBER(Q11),N(H11)>0),Q11/H11,"") | T11: =IF(NOT(ISNUMBER(S11)),"",IF(F11>0,Q11*F11/((1+F11)^H11-1),S11)) | U11: =IF(N(H11)>0,EDATE(TODAY(),H11),"")
A12: =Carteira!A12 | B12: =Carteira!B12 | C12: =Carteira!AB12 | D12: =Carteira!F12 | E12: =Carteira!U12 | F12: =IF(D12>0,E12/D12,0) | G12: =IF(A12="","",META_MENSAL) | H12: =IF(A12="","",PRAZO_META) | I12: =IF(N(G12)=0,"",IF(E12>0,ROUNDUP(G12/E12,0),"sem proventos")) | J12: =IF(ISNUMBER(I12),I12*D12,"") | K12: =Carteira!C12 | L12: =Carteira!D12 | M12: =Carteira!E12 | N12: =Carteira!V12 | O12: =IF(N(G12)>0,MIN(1,N12/G12),0) | P12: =IF(ISNUMBER(I12),MAX(0,I12-K12),"") | Q12: =IF(ISNUMBER(P12),P12*D12,"") | R12: =IF(AND(ISNUMBER(P12),N(H12)>0),ROUNDUP(P12/H12,0),"") | S12: =IF(AND(ISNUMBER(Q12),N(H12)>0),Q12/H12,"") | T12: =IF(NOT(ISNUMBER(S12)),"",IF(F12>0,Q12*F12/((1+F12)^H12-1),S12)) | U12: =IF(N(H12)>0,EDATE(TODAY(),H12),"")
A13: =Carteira!A13 | B13: =Carteira!B13 | C13: =Carteira!AB13 | D13: =Carteira!F13 | E13: =Carteira!U13 | F13: =IF(D13>0,E13/D13,0) | G13: =IF(A13="","",META_MENSAL) | H13: =IF(A13="","",PRAZO_META) | I13: =IF(N(G13)=0,"",IF(E13>0,ROUNDUP(G13/E13,0),"sem proventos")) | J13: =IF(ISNUMBER(I13),I13*D13,"") | K13: =Carteira!C13 | L13: =Carteira!D13 | M13: =Carteira!E13 | N13: =Carteira!V13 | O13: =IF(N(G13)>0,MIN(1,N13/G13),0) | P13: =IF(ISNUMBER(I13),MAX(0,I13-K13),"") | Q13: =IF(ISNUMBER(P13),P13*D13,"") | R13: =IF(AND(ISNUMBER(P13),N(H13)>0),ROUNDUP(P13/H13,0),"") | S13: =IF(AND(ISNUMBER(Q13),N(H13)>0),Q13/H13,"") | T13: =IF(NOT(ISNUMBER(S13)),"",IF(F13>0,Q13*F13/((1+F13)^H13-1),S13)) | U13: =IF(N(H13)>0,EDATE(TODAY(),H13),"")
A14: =Carteira!A14 | B14: =Carteira!B14 | C14: =Carteira!AB14 | D14: =Carteira!F14 | E14: =Carteira!U14 | F14: =IF(D14>0,E14/D14,0) | G14: =IF(A14="","",META_MENSAL) | H14: =IF(A14="","",PRAZO_META) | I14: =IF(N(G14)=0,"",IF(E14>0,ROUNDUP(G14/E14,0),"sem proventos")) | J14: =IF(ISNUMBER(I14),I14*D14,"") | K14: =Carteira!C14 | L14: =Carteira!D14 | M14: =Carteira!E14 | N14: =Carteira!V14 | O14: =IF(N(G14)>0,MIN(1,N14/G14),0) | P14: =IF(ISNUMBER(I14),MAX(0,I14-K14),"") | Q14: =IF(ISNUMBER(P14),P14*D14,"") | R14: =IF(AND(ISNUMBER(P14),N(H14)>0),ROUNDUP(P14/H14,0),"") | S14: =IF(AND(ISNUMBER(Q14),N(H14)>0),Q14/H14,"") | T14: =IF(NOT(ISNUMBER(S14)),"",IF(F14>0,Q14*F14/((1+F14)^H14-1),S14)) | U14: =IF(N(H14)>0,EDATE(TODAY(),H14),"")
A15: =Carteira!A15 | B15: =Carteira!B15 | C15: =Carteira!AB15 | D15: =Carteira!F15 | E15: =Carteira!U15 | F15: =IF(D15>0,E15/D15,0) | G15: 500 | H15: 36 | I15: =IF(N(G15)=0,"",IF(E15>0,ROUNDUP(G15/E15,0),"sem proventos")) | J15: =IF(ISNUMBER(I15),I15*D15,"") | K15: =Carteira!C15 | L15: =Carteira!D15 | M15: =Carteira!E15 | N15: =Carteira!V15 | O15: =IF(N(G15)>0,MIN(1,N15/G15),0) | P15: =IF(ISNUMBER(I15),MAX(0,I15-K15),"") | Q15: =IF(ISNUMBER(P15),P15*D15,"") | R15: =IF(AND(ISNUMBER(P15),N(H15)>0),ROUNDUP(P15/H15,0),"") | S15: =IF(AND(ISNUMBER(Q15),N(H15)>0),Q15/H15,"") | T15: =IF(NOT(ISNUMBER(S15)),"",IF(F15>0,Q15*F15/((1+F15)^H15-1),S15)) | U15: =IF(N(H15)>0,EDATE(TODAY(),H15),"")
A16: =Carteira!A16 | B16: =Carteira!B16 | C16: =Carteira!AB16 | D16: =Carteira!F16 | E16: =Carteira!U16 | F16: =IF(D16>0,E16/D16,0) | G16: =IF(A16="","",META_MENSAL) | H16: =IF(A16="","",PRAZO_META) | I16: =IF(N(G16)=0,"",IF(E16>0,ROUNDUP(G16/E16,0),"sem proventos")) | J16: =IF(ISNUMBER(I16),I16*D16,"") | K16: =Carteira!C16 | L16: =Carteira!D16 | M16: =Carteira!E16 | N16: =Carteira!V16 | O16: =IF(N(G16)>0,MIN(1,N16/G16),0) | P16: =IF(ISNUMBER(I16),MAX(0,I16-K16),"") | Q16: =IF(ISNUMBER(P16),P16*D16,"") | R16: =IF(AND(ISNUMBER(P16),N(H16)>0),ROUNDUP(P16/H16,0),"") | S16: =IF(AND(ISNUMBER(Q16),N(H16)>0),Q16/H16,"") | T16: =IF(NOT(ISNUMBER(S16)),"",IF(F16>0,Q16*F16/((1+F16)^H16-1),S16)) | U16: =IF(N(H16)>0,EDATE(TODAY(),H16),"")
A17: =Carteira!A17 | B17: =Carteira!B17 | C17: =Carteira!AB17 | D17: =Carteira!F17 | E17: =Carteira!U17 | F17: =IF(D17>0,E17/D17,0) | G17: =IF(A17="","",META_MENSAL) | H17: =IF(A17="","",PRAZO_META) | I17: =IF(N(G17)=0,"",IF(E17>0,ROUNDUP(G17/E17,0),"sem proventos")) | J17: =IF(ISNUMBER(I17),I17*D17,"") | K17: =Carteira!C17 | L17: =Carteira!D17 | M17: =Carteira!E17 | N17: =Carteira!V17 | O17: =IF(N(G17)>0,MIN(1,N17/G17),0) | P17: =IF(ISNUMBER(I17),MAX(0,I17-K17),"") | Q17: =IF(ISNUMBER(P17),P17*D17,"") | R17: =IF(AND(ISNUMBER(P17),N(H17)>0),ROUNDUP(P17/H17,0),"") | S17: =IF(AND(ISNUMBER(Q17),N(H17)>0),Q17/H17,"") | T17: =IF(NOT(ISNUMBER(S17)),"",IF(F17>0,Q17*F17/((1+F17)^H17-1),S17)) | U17: =IF(N(H17)>0,EDATE(TODAY(),H17),"")
A18: =Carteira!A18 | B18: =Carteira!B18 | C18: =Carteira!AB18 | D18: =Carteira!F18 | E18: =Carteira!U18 | F18: =IF(D18>0,E18/D18,0) | G18: =IF(A18="","",META_MENSAL) | H18: =IF(A18="","",PRAZO_META) | I18: =IF(N(G18)=0,"",IF(E18>0,ROUNDUP(G18/E18,0),"sem proventos")) | J18: =IF(ISNUMBER(I18),I18*D18,"") | K18: =Carteira!C18 | L18: =Carteira!D18 | M18: =Carteira!E18 | N18: =Carteira!V18 | O18: =IF(N(G18)>0,MIN(1,N18/G18),0) | P18: =IF(ISNUMBER(I18),MAX(0,I18-K18),"") | Q18: =IF(ISNUMBER(P18),P18*D18,"") | R18: =IF(AND(ISNUMBER(P18),N(H18)>0),ROUNDUP(P18/H18,0),"") | S18: =IF(AND(ISNUMBER(Q18),N(H18)>0),Q18/H18,"") | T18: =IF(NOT(ISNUMBER(S18)),"",IF(F18>0,Q18*F18/((1+F18)^H18-1),S18)) | U18: =IF(N(H18)>0,EDATE(TODAY(),H18),"")
A19: =Carteira!A19 | B19: =Carteira!B19 | C19: =Carteira!AB19 | D19: =Carteira!F19 | E19: =Carteira!U19 | F19: =IF(D19>0,E19/D19,0) | G19: =IF(A19="","",META_MENSAL) | H19: =IF(A19="","",PRAZO_META) | I19: =IF(N(G19)=0,"",IF(E19>0,ROUNDUP(G19/E19,0),"sem proventos")) | J19: =IF(ISNUMBER(I19),I19*D19,"") | K19: =Carteira!C19 | L19: =Carteira!D19 | M19: =Carteira!E19 | N19: =Carteira!V19 | O19: =IF(N(G19)>0,MIN(1,N19/G19),0) | P19: =IF(ISNUMBER(I19),MAX(0,I19-K19),"") | Q19: =IF(ISNUMBER(P19),P19*D19,"") | R19: =IF(AND(ISNUMBER(P19),N(H19)>0),ROUNDUP(P19/H19,0),"") | S19: =IF(AND(ISNUMBER(Q19),N(H19)>0),Q19/H19,"") | T19: =IF(NOT(ISNUMBER(S19)),"",IF(F19>0,Q19*F19/((1+F19)^H19-1),S19)) | U19: =IF(N(H19)>0,EDATE(TODAY(),H19),"")
A20: =Carteira!A20 | B20: =Carteira!B20 | C20: =Carteira!AB20 | D20: =Carteira!F20 | E20: =Carteira!U20 | F20: =IF(D20>0,E20/D20,0) | G20: =IF(A20="","",META_MENSAL) | H20: =IF(A20="","",PRAZO_META) | I20: =IF(N(G20)=0,"",IF(E20>0,ROUNDUP(G20/E20,0),"sem proventos")) | J20: =IF(ISNUMBER(I20),I20*D20,"") | K20: =Carteira!C20 | L20: =Carteira!D20 | M20: =Carteira!E20 | N20: =Carteira!V20 | O20: =IF(N(G20)>0,MIN(1,N20/G20),0) | P20: =IF(ISNUMBER(I20),MAX(0,I20-K20),"") | Q20: =IF(ISNUMBER(P20),P20*D20,"") | R20: =IF(AND(ISNUMBER(P20),N(H20)>0),ROUNDUP(P20/H20,0),"") | S20: =IF(AND(ISNUMBER(Q20),N(H20)>0),Q20/H20,"") | T20: =IF(NOT(ISNUMBER(S20)),"",IF(F20>0,Q20*F20/((1+F20)^H20-1),S20)) | U20: =IF(N(H20)>0,EDATE(TODAY(),H20),"")
A21: TOTAL | G21: =SUM(G5:G20) | J21: =SUM(J5:J20) | M21: =SUM(M5:M20) | N21: =SUM(N5:N20) | O21: =IF(G21>0,N21/G21,0) | P21: =SUM(P5:P20) | Q21: =SUM(Q5:Q20) | R21: =SUM(R5:R20) | S21: =SUM(S5:S20) | T21: =SUM(T5:T20)
A23: Aporte mensal para cumprir todos os prazos | G23: =S21
A24: … reinvestindo os proventos | G24: =T21
A25: Aporte mensal disponível (Premissas) | G25: =APORTE_MENSAL
A26: Sobra (+) ou falta (−) por mês, reinvestindo | G26: =APORTE_MENSAL-T21
A27: Subtotal ações — renda desejada / a investir | G27: =SUMIFS(G5:G20,B5:B20,"AÇÃO") | J27: =SUMIFS(J5:J20,B5:B20,"AÇÃO")
A28: Subtotal FIIs — renda desejada / a investir | G28: =SUMIFS(G5:G20,B5:B20,"FII") | J28: =SUMIFS(J5:J20,B5:B20,"FII")
A31: Como ler
A32: • Cotas necessárias = meta mensal ÷ provento mensal por cota (proventos dos últimos 12 meses ÷ 12), arredondado para cima.
A33: • Valor total a investir = cotas necessárias × valor da cota hoje. Valor faltante desconta as cotas que você já tem.
A34: • Aporte mensal no prazo = valor faltante ÷ prazo. Reinvestindo proventos: cada cota comprada passa a pagar e o provento compra mais cotas (juros compostos à taxa do rendimento mensal) — o aporte necessário fica menor.
A35: • Para personalizar, digite por cima do campo amarelo; apague para voltar ao padrão. Salva em dados/metas.csv ao clicar em ⟳ Atualizar (ou rodar atualizar.bat).
A36: • Cálculo com a cotação e o provento de hoje; mudanças de preço e de proventos alteram o resultado.

Sheet Quant
A1: InvestERP Análise Quantitativa
A3: Histórico semanal até 28/09/2026 (Yahoo Finance) • pesos: carteira real (lançamentos) • calculado por gestao.py — não digite aqui.
A4: Ticker | B4: Tipo | C4: Posição atual (R$) | D4: Peso atual | E4: Qualidade dos dados | F4: Semanas de histórico | G4: Última cotação | H4: Retorno 12m (preço) | I4: Retorno 12m (c/ proventos) | J4: Volatilidade anual | K4: Sharpe (vs CDI) | L4: Queda máx. 3a | M4: Beta (Ibov) | N4: Correlação Ibov | O4: Volatilidade EWMA (λ) | P4: VaR 95% semanal | Q4: CVaR 95% semanal | R4: Sortino | S4: Retorno esperado CAPM | T4: Alfa de Jensen | U4: Assimetria | V4: Curtose (excesso) | W4: Normalidade (p Jarque-Bera) | X4: Autocorrelação 1 sem. | Y4: Taxa instantânea f′(t) (anual) | Z4: Curvatura f″(t) | AA4: R² polinômio grau 3 | AB4: Leitura da tendência | AC4: Tendência anual (regressão 3a) | AD4: R² da regressão | AE4: Preço vs tendência | AF4: Preço projetado 12m (R$) | AG4: Faixa mín. 12m (R$) | AH4: Faixa máx. 12m (R$) | AI4: Proventos 12m hist. (R$) | AJ4: Crescimento proventos a/a | AK4: Peso na análise | AL4: Contribuição ao risco
A5: =Carteira!A5 | B5: =Carteira!B5 | C5: =Carteira!G5 | D5: =Carteira!P5 | E5: Alta | F5: 262 | G5: 46293 | H5: 0.1880867 | I5: 0.28571539 | J5: 0.24327063 | K5: -0.12374745 | L5: -0.26970725 | M5: 0.86425068 | N5: 0.52453639 | O5: 0.25331574 | P5: 0.052114277 | Q5: 0.067914786 | R5: -0.1715654 | S5: 0.167715 | T5: -0.057819125 | U5: -0.12355527 | V5: 0.53252513 | W5: 0.32624667 | X5: 0.011632848 | Y5: -0.24166551 | Z5: 1.1587881 | AA5: 0.82625732 | AB5: Queda perdendo força | AC5: 0.066860181 | AD5: 0.13747866 | AE5: -0.025681041 | AF5: 76.221587 | AG5: 66.178062 | AH5: 87.789369 | AI5: 5.612493 | AJ5: 0.23141342 | AK5: 0.11651359 | AL5: 0.11444895
A6: =Carteira!A6 | B6: =Carteira!B6 | C6: =Carteira!G6 | D6: =Carteira!P6 | E6: Alta | F6: 262 | G6: 46293 | H6: 0.10517711 | I6: 0.18931022 | J6: 0.17837025 | K6: 0.072434012 | L6: -0.13054642 | M6: 0.78736559 | N6: 0.6517478 | O6: 0.21762484 | P6: 0.032745529 | Q6: 0.041154033 | R6: 0.11596661 | S6: 0.16524943 | T6: -0.012329361 | U6: 0.88612767 | V6: 2.3607363 | W6: 5.0189496e-13 | X6: 0.040380819 | Y6: 0.64012704 | Z6: 3.5950827 | AA6: 0.45019229 | AB6: Alta acelerando | AC6: 0.064927885 | AD6: 0.3888202 | AE6: 0.0060614778 | AF6: 42.933236 | AG6: 40.081004 | AH6: 45.988438 | AI6: 3.006456 | AJ6: 0.015729596 | AK6: 0 | AL6: 0
A7: =Carteira!A7 | B7: =Carteira!B7 | C7: =Carteira!G7 | D7: =Carteira!P7 | E7: Alta | F7: 262 | G7: 46293 | H7: 0.58387097 | I7: 0.73698091 | J7: 0.27688116 | K7: 0.58906558 | L7: -0.2112376 | M7: 0.60955149 | N7: 0.32504431 | O7: 0.28595814 | P7: 0.058028459 | Q7: 0.076908099 | R7: 0.8737731 | S7: 0.15954725 | T7: 0.14355391 | U7: -0.18530851 | V7: 0.15946181 | W7: 0.5891636 | X7: 0.096040774 | Y7: 0.12717164 | Z7: 0.17300971 | AA7: 0.72092734 | AB7: Alta acelerando | AC7: 0.025975207 | AD7: 0.029566001 | AE7: 0.28190602 | AF7: 39.297251 | AG7: 34.573994 | AH7: 44.665767 | AI7: 3.664347 | AJ7: -0.30041063 | AK7: 0.11458093 | AL7: 0.10282834
A8: =Carteira!A8 | B8: =Carteira!B8 | C8: =Carteira!G8 | D8: =Carteira!P8 | E8: Alta | F8: 262 | G8: 46293 | H8: 0.021316033 | I8: 0.050878511 | J8: 0.26226345 | K8: -0.46235733 | L8: -0.36644177 | M8: 1.1145574 | N8: 0.62746604 | O8: 0.37314599 | P8: 0.055538238 | Q8: 0.0804844 | R8: -0.65038898 | S8: 0.1757419 | T8: -0.15700133 | U8: 0.19891188 | V8: 2.3392525 | W8: 1.1297434e-08 | X8: 0.12924708 | Y8: 1.6821308 | Z8: 6.6634439 | AA8: 0.49343534 | AB8: Alta acelerando | AC8: -0.10369124 | AD8: 0.54825287 | AE8: 0.061485102 | AF8: 18.610384 | AG8: 17.066336 | AH8: 20.294127 | AI8: 0.654951 | AJ8: -0.62030109 | AK8: 0.078689992 | AL8: 0.10883186
A9: =Carteira!A9 | B9: =Carteira!B9 | C9: =Carteira!G9 | D9: =Carteira!P9 | E9: Alta | F9: 262 | G9: 46293 | H9: -0.18181818 | I9: -0.11651979 | J9: 0.27554984 | K9: 0.13354495 | L9: -0.41012388 | M9: 1.1368974 | N9: 0.60918144 | O9: 0.33167804 | P9: 0.057794338 | Q9: 0.070657136 | R9: 0.20043422 | S9: 0.17645831 | T9: 0.00033998299 | U9: 0.18553898 | V9: 0.086475283 | W9: 0.62386288 | X9: 0.052431925 | Y9: 0.015498417 | Z9: 4.0594249 | AA9: 0.83810142 | AB9: Alta acelerando | AC9: 0.065876158 | AD9: 0.17295031 | AE9: -0.14051983 | AF9: 18.192861 | AG9: 16.10984 | AH9: 20.545219 | AI9: 1.38 | AJ9: -0.33333333 | AK9: 0.039713101 | AL9: 0.054956883
A10: =Carteira!A10 | B10: =Carteira!B10 | C10: =Carteira!G10 | D10: =Carteira!P10 | E10: Alta | F10: 262 | G10: 46293 | H10: 0.039766082 | I10: 0.10937778 | J10: 0.26056562 | K10: 0.10726498 | L10: -0.28557296 | M10: 1.2341272 | N10: 0.69930782 | O10: 0.25701254 | P10: 0.052315952 | Q10: 0.074662996 | R10: 0.15905758 | S10: 0.1795763 | T10: -0.011626731 | U10: 0.31826293 | V10: 2.6144191 | W10: 6.0332761e-11 | X10: 0.16338656 | Y10: 0.34588756 | Z10: 3.2137375 | AA10: 0.49934519 | AB10: Alta acelerando | AC10: 0.12823102 | AD10: 0.39188278 | AE10: -0.044808682 | AF10: 21.000974 | AG10: 18.422435 | AH10: 23.940423 | AI10: 1.552753 | AJ10: 0.25016344 | AK10: 0.043110447 | AL10: 0.056197673
A11: =Carteira!A11 | B11: =Carteira!B11 | C11: =Carteira!G11 | D11: =Carteira!P11 | E11: Alta | F11: 262 | G11: 46293 | H11: 0.28727273 | I11: 0.41142751 | J11: 0.20531679 | K11: 0.90321704 | L11: -0.1897419 | M11: 1.1926073 | N11: 0.85762722 | O11: 0.24881427 | P11: 0.043839098 | Q11: 0.052612355 | R11: 1.4297931 | S11: 0.17824483 | T11: 0.1472008 | U11: 0.17359489 | V11: 0.62569572 | W11: 0.18935786 | X11: 0.19154086 | Y11: 0.42487245 | Z11: 2.4163129 | AA11: 0.66286094 | AB11: Alta acelerando | AC11: 0.18294403 | AD11: 0.77393576 | AE11: 0.03958537 | AF11: 16.112662 | AG11: 14.886614 | AH11: 17.439686 | AI11: 1.127801 | AJ11: 0.12695804 | AK11: 0.11378965 | AL11: 0.13946025
A12: =Carteira!A12 | B12: =Carteira!B12 | C12: =Carteira!G12 | D12: =Carteira!P12 | E12: Alta | F12: 262 | G12: 46293 | H12: 0.011070111 | I12: 0.1157565 | J12: 0.26000797 | K12: 0.23966851 | L12: -0.24347764 | M12: 0.95259275 | N12: 0.54093637 | O12: 0.25032342 | P12: 0.042310362 | Q12: 0.067321483 | R12: 0.33739587 | S12: 0.17054798 | T12: 0.031767743 | U12: -0.96954323 | V12: 6.9452921 | W12: 4.0576148e-74 | X12: -0.11996904 | Y12: -0.17169876 | Z12: 0.55654393 | AA12: 0.32298595 | AB12: Queda perdendo força | AC12: 0.073858217 | AD12: 0.42857758 | AE12: -0.077057557 | AF12: 12.752134 | AG12: 11.869616 | AH12: 13.700269 | AI12: 1.350748 | AJ12: -0.047122953 | AK12: 0.10046918 | AL12: 0.12669234
A13: =Carteira!A13 | B13: =Carteira!B13 | C13: =Carteira!G13 | D13: =Carteira!P13 | E13: Alta | F13: 262 | G13: 46293 | H13: 0.23322542 | I13: 0.40630545 | J13: 0.27672862 | K13: 0.38598105 | L13: -0.38054934 | M13: 1.0995943 | N13: 0.58668366 | O13: 0.32485637 | P13: 0.053882322 | Q13: 0.068431464 | R13: 0.63420041 | S13: 0.17526206 | T13: 0.071549938 | U13: 0.79754753 | V13: 2.6626523 | W13: 2.5232387e-14 | X13: 0.1277394 | Y13: -0.83110852 | Z13: -5.5346294 | AA13: 0.70641168 | AB13: Queda acelerando | AC13: 0.24157686 | AD13: 0.61542631 | AE13: -0.091549521 | AF13: 6.8198198 | AG13: 5.8752203 | AH13: 7.916289 | AI13: 0.681977 | AJ13: 1.7938541 | AK13: 0.12410731 | AL13: 0.18934177
A14: =Carteira!A14 | B14: =Carteira!B14 | C14: =Carteira!G14 | D14: =Carteira!P14 | E14: Alta | F14: 262 | G14: 46293 | H14: 0.011107237 | I14: 0.076463093 | J14: 0.20485336 | K14: -0.64007191 | L14: -0.23896582 | M14: 0.57154112 | N14: 0.4119362 | O14: 0.19835311 | P14: 0.047936771 | Q14: 0.056633125 | R14: -0.85235776 | S14: 0.15832832 | T14: -0.14944921 | U14: -0.026495037 | V14: -0.071632269 | W14: 0.97452786 | X14: 0.017420234 | Y14: 1.9459683 | Z14: 5.884261 | AA14: 0.51688634 | AB14: Alta acelerando | AC14: -0.05836423 | AD14: 0.42258993 | AE14: 0.027483695 | AF14: 16.743512 | AG14: 15.748436 | AH14: 17.801462 | AI14: 1.161121 | AJ14: 0.079965884 | AK14: 0.061231509 | AL14: 0.042313931
A15: =Carteira!A15 | B15: =Carteira!B15 | C15: =Carteira!G15 | D15: =Carteira!P15 | E15: Alta | F15: 262 | G15: 46293 | H15: -0.059917355 | I15: 0.052712639 | J15: 0.071602498 | K15: -1.120382 | L15: -0.095793756 | M15: 0.056125261 | N15: 0.11573262 | O15: 0.05299261 | P15: 0.013602987 | Q15: 0.019489887 | R15: -1.511649 | S15: 0.14179984 | T15: -0.082021987 | U15: 0.754201 | V15: 4.4081079 | W15: 2.3011015e-31 | X15: -0.01915768 | Y15: -0.45404252 | Z15: -2.2482762 | AA15: 0.85279155 | AB15: Queda acelerando | AC15: -0.035416341 | AD15: 0.38339326 | AE15: -0.017308074 | AF15: 8.9323124 | AG15: 8.58329 | AH15: 9.2955272 | AI15: 1.194302 | AJ15: 0.039333254 | AK15: 0.014146279 | AL15: 0.0017895969
A16: =Carteira!A16 | B16: =Carteira!B16 | C16: =Carteira!G16 | D16: =Carteira!P16 | E16: Alta | F16: 262 | G16: 46293 | H16: -0.035023041 | I16: 0.078840001 | J16: 0.1527426 | K16: -0.92392431 | L16: -0.27152602 | M16: 0.34884784 | N16: 0.33721076 | O16: 0.16728806 | P16: 0.036409018 | Q16: 0.044621749 | R16: -1.2275774 | S16: 0.15118694 | T16: -0.15230954 | U16: 0.18360706 | V16: 0.95092609 | W16: 0.034146454 | X16: 0.062497149 | Y16: 0.18630907 | Z16: 3.5498852 | AA16: 0.83263014 | AB16: Alta acelerando | AC16: -0.10356767 | AD16: 0.4845669 | AE16: 0.057011847 | AF16: 35.517659 | AG16: 32.192907 | AH16: 39.185776 | AI16: 4.92 | AJ16: -0.10054845 | AK16: 0.010248302 | AL16: 0.0043834855
... A20: =Carteira!A20 | B20: =Carteira!B20 | C20: =Carteira!G20 | D20: =Carteira!P20 | E20: Alta | F20: 262 | G20: 46293 | H20: -0.024707412 | I20: 0.12285816 | J20: 0.15770702 | K20: -0.79028705 | L20: -0.36416251 | M20: 0.21470514 | N20: 0.20100968 | O20: 0.074931019 | P20: 0.022214613 | Q20: 0.052662884 | R20: -0.92119489 | S20: 0.14688522 | T20: -0.13151904 | U20: -4.2795324 | V20: 41.068942 | W20: 0 | X20: 0.12549858 | Y20: -0.004076007 | Z20: 0.99928438 | AA20: 0.61038978 | AB20: Queda perdendo força | AC20: -0.11368184 | AD20: 0.42672436 | AE20: 0.097635588 | AF20: 6.0560957 | AG20: 5.3609879 | AH20: 6.8413315 | AI20: 1.08 | AJ20: 0.13445378 | AK20: 0.039318947 | AL20: 0.012699847
A21: CARTEIRA | C21: =SUM(C5:C20) | D21: =SUM(D5:D20) | I21: 0.24746381 | J21: 0.12977478 | K21: 0.15915627 | L21: -0.17600324 | M21: 0.80057412 | AC21: 0.054981986 | AD21: 0.38459541 | AK21: 1 | AL21: 1
A24: Resumo da carteira | B24: Valor | C24: Leitura
A25: Base dos pesos | B25: carteira real (lançamentos) | C25: Carteira real quando há lançamentos; senão, pesos ideais.
A26: Retorno anual médio (3a, c/ proventos) | B26: 0.16065447 | C26: Média geométrica ponderada pelos pesos.
A27: Volatilidade anual da carteira | B27: 0.12977478 | C27: Considera as correlações entre os ativos.
A28: Índice de diversificação | B28: 1.731816 | C28: Vol. média dos ativos ÷ vol. da carteira (>1 = diversificação ajuda).
A29: Sharpe da carteira | B29: 0.15915627 | C29: Retorno acima do CDI (14.00%) por unidade de risco.
A30: Beta da carteira | B30: 0.80057412 | C30: 1 = oscila como o Ibovespa; <1 = mais defensiva.
A31: Queda máxima (3a) | B31: -0.17600324 | C31: Pior perda do pico ao vale com os pesos atuais.
A32: Dividend yield da carteira | B32: 0.09583896 | C32: Provento 12m ÷ cotação, ponderado.
A33: Retorno 12m da carteira | B33: 0.24746381 | C33: Com proventos reinvestidos.
A34: Ibovespa 12m | B34: 0.2748011 | C34: Referência de mercado.
A35: TIR realizada (seus lançamentos) | B35: 0.13913375 | C35: Taxa anual do seu dinheiro: compras, vendas, proventos e posição de hoje.
A36: CDI anual (premissa) | B36: 0.14 | C36: dados/config.json → analise.cdi_anual
A38: Correlação dos retornos semanais (3 anos) — perto de 1 = andam juntos; perto de 0 = diversificam
A39: Correlação | B39: VALE3 | C39: TAEE11 | D39: PETR4 | E39: BBAS3 | F39: BRBI11 | G39: BBDC4 | H39: ITSA4 | I39: CMIG4 | J39: FIQE3 | K39: KLBN11 | L39: MXRF11 | M39: BRCR11 | N39: XPLG11 | O39: XPML11 | P39: SNAG11 | Q39: CPTS11
A40: VALE3 | B40: 1 | C40: 0.2053981 | D40: 0.024840799 | E40: 0.22135208 | F40: 0.23288065 | G40: 0.26055857 | H40: 0.36849342 | I40: 0.21989083 | J40: 0.1967395 | K40: 0.31826183 | L40: 0.081187759 | M40: 0.22336242 | N40: 0.15871804 | O40: 0.14635994 | P40: 0.11541489 | Q40: 0.12565422
A41: TAEE11 | B41: 0.2053981 | C41: 1 | D41: 0.080533187 | E41: 0.48215106 | F41: 0.43713506 | G41: 0.56457627 | H41: 0.53284762 | I41: 0.42250382 | J41: 0.41712421 | K41: 0.31422654 | L41: 0.15178145 | M41: 0.24852381 | N41: 0.078772421 | O41: 0.27537546 | P41: 0.10481254 | Q41: 0.1045903
A42: PETR4 | B42: 0.024840799 | C42: 0.080533187 | D42: 1 | E42: 0.17656214 | F42: 0.2875501 | G42: 0.12069434 | H42: 0.089771923 | I42: 0.096683028 | J42: 0.17034352 | K42: 0.10131363 | L42: 0.059187207 | M42: 0.046330775 | N42: 0.044188688 | O42: 0.16295651 | P42: 0.046810067 | Q42: 0.11582183
A43: BBAS3 | B43: 0.22135208 | C43: 0.48215106 | D43: 0.17656214 | E43: 1 | F43: 0.40941512 | G43: 0.45466952 | H43: 0.62531861 | I43: 0.42743077 | J43: 0.40847816 | K43: 0.23420576 | L43: 0.14298158 | M43: 0.22767974 | N43: 0.11412156 | O43: 0.30409786 | P43: 0.078844262 | Q43: 0.087262758
A44: BRBI11 | B44: 0.23288065 | C44: 0.43713506 | D44: 0.2875501 | E44: 0.40941512 | F44: 1 | G44: 0.57068934 | H44: 0.52696517 | I44: 0.31387157 | J44: 0.44427739 | K44: 0.25378551 | L44: 0.042419729 | M44: 0.24635468 | N44: 0.10291128 | O44: 0.31901171 | P44: 0.052813667 | Q44: 0.13005255
A45: BBDC4 | B45: 0.26055857 | C45: 0.56457627 | D45: 0.12069434 | E45: 0.45466952 | F45: 0.57068934 | G45: 1 | H45: 0.62845225 | I45: 0.30421174 | J45: 0.50061178 | K45: 0.17731248 | L45: 0.10746678 | M45: 0.20092359 | N45: 0.080863886 | O45: 0.31538751 | P45: 0.10494853 | Q45: 0.15965421
A46: ITSA4 | B46: 0.36849342 | C46: 0.53284762 | D46: 0.089771923 | E46: 0.62531861 | F46: 0.52696517 | G46: 0.62845225 | H46: 1 | I46: 0.45283929 | J46: 0.4993193 | K46: 0.30086974 | L46: 0.085223446 | M46: 0.32864031 | N46: 0.16513794 | O46: 0.37106358 | P46: 0.08555105 | Q46: 0.15971854
A47: CMIG4 | B47: 0.21989083 | C47: 0.42250382 | D47: 0.096683028 | E47: 0.42743077 | F47: 0.31387157 | G47: 0.30421174 | H47: 0.45283929 | I47: 1 | J47: 0.35595487 | K47: 0.30215297 | L47: 0.076161762 | M47: 0.068664862 | N47: 0.18421122 | O47: 0.29973102 | P47: 0.02844248 | Q47: 0.051111029
A48: FIQE3 | B48: 0.1967395 | C48: 0.41712421 | D48: 0.17034352 | E48: 0.40847816 | F48: 0.44427739 | G48: 0.50061178 | H48: 0.4993193 | I48: 0.35595487 | J48: 1 | K48: 0.16919977 | L48: 0.15351248 | M48: 0.26440302 | N48: 0.23678287 | O48: 0.25615353 | P48: 0.12055522 | Q48: 0.17260348
A49: KLBN11 | B49: 0.31826183 | C49: 0.31422654 | D49: 0.10131363 | E49: 0.23420576 | F49: 0.25378551 | G49: 0.17731248 | H49: 0.30086974 | I49: 0.30215297 | J49: 0.16919977 | K49: 1 | L49: 0.25171937 | M49: 0.22811842 | N49: 0.056741841 | O49: 0.10554761 | P49: -0.047407606 | Q49: 0.0042207214
A50: MXRF11 | B50: 0.081187759 | C50: 0.15178145 | D50: 0.059187207 | E50: 0.14298158 | F50: 0.042419729 | G50: 0.10746678 | H50: 0.085223446 | I50: 0.076161762 | J50: 0.15351248 | K50: 0.25171937 | L50: 1 | M50: 0.22707975 | N50: 0.36762511 | O50: 0.28619138 | P50: 0.2691193 | Q50: 0.26614371
A51: BRCR11 | B51: 0.22336242 | C51: 0.24852381 | D51: 0.046330775 | E51: 0.22767974 | F51: 0.24635468 | G51: 0.20092359 | H51: 0.32864031 | I51: 0.068664862 | J51: 0.26440302 | K51: 0.22811842 | L51: 0.22707975 | M51: 1 | N51: 0.31007478 | O51: 0.34448783 | P51: 0.13619632 | Q51: 0.22549877
... A55: CPTS11 | B55: 0.12565422 | C55: 0.1045903 | D55: 0.11582183 | E55: 0.087262758 | F55: 0.13005255 | G55: 0.15965421 | H55: 0.15971854 | I55: 0.051111029 | J55: 0.17260348 | K55: 0.0042207214 | L55: 0.26614371 | M55: 0.22549877 | N55: 0.2570238 | O55: 0.27256624 | P55: 0.24753208 | Q55: 1
A57: Como ler
A58: • Derivadas: polinômio f(t) de grau 3 ajustado ao log-preço de 12 meses; f′(hoje) = taxa instantânea (e^f′ − 1 ao ano), f″(hoje) = curvatura (>0 acelerando, <0 perdendo força).
A59: • EWMA: σ²ₜ = λσ²ₜ₋₁ + (1−λ)r²ₜ (λ em config.json) — pesa mais as semanas recentes. VaR/CVaR 95%: perda semanal superada em 5% das semanas / perda média nessas semanas.
A60: • Jarque-Bera: p < 0,05 = retornos não normais (caudas gordas se curtose > 0). CAPM = CDI + β·(Ibov − CDI); alfa = retorno obtido − CAPM.
A61: • Tendência/R²: regressão log-linear de 3 anos. R² baixo = preço sem tendência clara; não use a projeção 12m isoladamente.
A62: • Faixa 12m: tendência ± 1 desvio-padrão dos resíduos (~68% dos casos históricos). Não é recomendação de compra ou venda.
A63: • Contribuição ao risco: parcela da volatilidade da carteira que vem de cada ativo (soma 100%).
A64: • Qualidade dos dados: Alta = 2,5+ anos de histórico, cotação recente e sem lacunas; Baixa = pouco histórico ou desatualizado.

Sheet Modelos
A1: InvestERP Modelos Matemáticos
A3: Álgebra linear, Markowitz, Monte Carlo e economia — calculado por gestao.py a partir do histórico e da sua carteira.
A5: 1. Economia — retorno real (equação de Fisher: 1 + nominal = (1 + real)(1 + inflação))
A6: Indicador | B6: Valor | C6: Leitura
A7: Inflação anual (premissa) | B7: 0.045 | C7: config.json → analise.inflacao_anual
A8: CDI real | B8: 0.090909091 | C8: Ganho do CDI acima da inflação
A9: Retorno real da carteira (3a) | B9: 0.11067413 | C9: Retorno médio histórico acima da inflação
A10: Dividend yield real | B10: 0.048649723 | C10: Renda acima da inflação
A11: Prêmio de risco sobre o CDI | B11: 0.02065447 | C11: Quanto a renda variável pagou a mais que o CDI
A14: 2. Álgebra linear — autovalores da matriz de covariância Σ = VΛVᵀ (fatores de risco); número de condição 79 (alto = ativos redundantes)
A15: Fator | B15: Autovalor λ (variância) | C15: Volatilidade √λ | D15: % do risco | E15: % acumulado
A16: Fator 1 | B16: 0.25787976 | C16: 0.50781863 | D16: 0.36877955 | E16: 0.36877955
A17: Fator 2 | B17: 0.077141941 | C17: 0.27774438 | D17: 0.11031641 | E17: 0.47909596
A18: Fator 3 | B18: 0.058512742 | C18: 0.24189407 | D18: 0.083675828 | E18: 0.56277179
A19: Fator 4 | B19: 0.05394595 | C19: 0.23226267 | D19: 0.077145112 | E19: 0.6399169
A20: Fator 5 | B20: 0.044703237 | C20: 0.2114314 | D20: 0.06392762 | E20: 0.70384452
A23: Autovetores (cargas): quanto cada ativo pesa em cada fator — Fator 1 ≈ risco de mercado comum
A24: Ativo | B24: Fator 1 | C24: Fator 2 | D24: Fator 3
A25: VALE3 | B25: 0.20457266 | C25: -0.2441446 | D25: 0.51844546
A26: TAEE11 | B26: 0.23911923 | C26: -0.093693442 | D26: -0.041004493
A27: PETR4 | B27: 0.16289934 | C27: 0.90115378 | D27: 0.28646032
A28: BBAS3 | B28: 0.37437773 | C28: -0.064616831 | D28: 0.069828889
A29: BRBI11 | B29: 0.4075027 | C29: 0.21460448 | D29: -0.18587159
A30: BBDC4 | B30: 0.39425036 | C30: -0.064572968 | D30: -0.3660678
A31: ITSA4 | B31: 0.32693138 | C31: -0.14036252 | D31: -0.014527341
A32: CMIG4 | B32: 0.31041548 | C32: -0.18416217 | D32: 0.39441166
A33: FIQE3 | B33: 0.39046675 | C33: 0.013335917 | D33: -0.35835283
A34: KLBN11 | B34: 0.16328768 | C34: -0.085072657 | D34: 0.43214494
A35: MXRF11 | B35: 0.026294509 | C35: -0.0038793064 | D35: 0.02599701
A36: BRCR11 | B36: 0.10894163 | C36: -0.036440153 | D36: 0.01429773
... A40: CPTS11 | B40: 0.066852908 | C40: 0.046155875 | D40: -0.028243203
A43: 3. Otimização de Markowitz (sem venda a descoberto): mín. variância w ∝ Σ⁻¹1 • máx. Sharpe w ∝ Σ⁻¹(μ − CDI)
A44: Ativo | B44: μ esperado | C44: Pesos ideais | D44: Carteira analisada | E44: Mínima variância | F44: Máximo Sharpe
A45: VALE3 | B45: 0.13880544 | C45: 0.1 | D45: 0.11651359 | E45: 0.014585304 | F45: 0
A46: TAEE11 | B46: 0.15908475 | C46: 0.05 | D46: 0 | E46: 0.029649573 | F46: 0
A47: PETR4 | B47: 0.2313242 | C47: 0.07 | D47: 0.11458093 | E47: 0.024790651 | F47: 0.29162352
A48: BBAS3 | B48: 0.097241235 | C48: 0.06 | D48: 0.078689992 | E48: 0 | F48: 0
A49: BRBI11 | B49: 0.1766283 | C49: 0.05 | D49: 0.039713101 | E49: 0 | F49: 0
A50: BBDC4 | B50: 0.17376293 | C50: 0.05 | D50: 0.043110447 | E50: 0 | F50: 0
A51: ITSA4 | B51: 0.25184522 | C51: 0.1 | D51: 0.11378965 | E51: 0.0015950876 | F51: 0.70681925
A52: CMIG4 | B52: 0.18643185 | C52: 0.1 | D52: 0.10046918 | E52: 0.0057126114 | F52: 0
A53: FIQE3 | B53: 0.21103703 | C53: 0.05 | D53: 0.12410731 | E53: 0 | F53: 0
A54: KLBN11 | B54: 0.083603719 | C54: 0.07 | D54: 0.061231509 | E54: 0.016417569 | F54: 0
A55: MXRF11 | B55: 0.10078885 | C55: 0.05 | D55: 0.014146279 | E55: 0.52170482 | F55: 0
A56: BRCR11 | B56: 0.075032168 | C56: 0.04 | D56: 0.010248302 | E56: 0.025660571 | F56: 0
... A60: CPTS11 | B60: 0.0811257 | C60: 0.04 | D60: 0.039318947 | E60: 0.007602287 | F60: 0
A61: Retorno esperado | C61: 0.15165278 | D61: 0.16316374 | E61: 0.11387356 | F61: 0.24568277
A62: Volatilidade | C62: 0.11504828 | D62: 0.12977478 | E62: 0.060890885 | F62: 0.17230518
A63: Sharpe | C63: 0.10128599 | D63: 0.17849184 | E63: -0.42906973 | F63: 0.61334642
A66: 4. Monte Carlo — 3.000 trajetórias de movimento browniano geométrico (μ = 11,7%, σ = 13,0%, aporte mensal das Premissas)
A67: Patrimônio em ações + FIIs por percentil (5% dos cenários ficam abaixo de P5)
A68: Ano | B68: P5 (R$) | C68: P25 (R$) | D68: Mediana (R$) | E68: P75 (R$) | F68: P95 (R$) | G68: CDI (R$) | H68: Aportado (R$) | I68: Prob. vencer CDI | J68: Prob. abaixo do aportado
A69: 1 | B69: 124305.6 | C69: 138663.27 | D69: 149957.87 | E69: 161680.18 | F69: 181009.23 | G69: 153136.35 | H69: 136772.79 | I69: 0.42566667 | J69: 0.20666667
A70: 2 | B70: 160196.73 | C70: 183957.85 | D70: 203026.85 | E70: 224668.52 | F70: 260740.62 | G70: 212830.8 | H70: 172772.79 | I70: 0.38133333 | J70: 0.13133333
A71: 3 | B71: 196839.99 | C71: 232232.27 | D71: 262452.3 | E71: 295256.87 | F71: 354374.39 | G71: 280882.48 | H71: 208772.79 | I71: 0.346 | J71: 0.096666667
A72: 4 | B72: 239261.14 | C72: 287129.42 | D72: 326373.75 | E72: 376054.55 | F72: 455974.48 | G72: 358461.39 | H72: 244772.79 | I72: 0.332 | J72: 0.063
A73: 5 | B73: 284591.3 | C73: 348759.54 | D73: 402765.23 | E73: 466848.86 | F73: 589722.75 | G73: 446901.35 | H73: 280772.79 | I73: 0.319 | J73: 0.042
A74: 6 | B74: 333248.4 | C74: 414945.69 | D74: 485384.01 | E74: 568185.87 | F74: 728906.61 | G74: 547722.91 | H74: 316772.79 | I74: 0.30266667 | J74: 0.031666667
A75: 7 | B75: 386662.58 | C75: 484589.37 | D75: 574677.38 | E75: 686885.38 | F75: 891768.79 | G75: 662659.48 | H75: 352772.79 | I75: 0.29866667 | J75: 0.019
A76: 8 | B76: 442177 | C76: 565750.09 | D76: 674532.01 | E76: 816691.86 | F76: 1078419.7 | G76: 793687.18 | H76: 388772.79 | I76: 0.27933333 | J76: 0.013666667
A77: 9 | B77: 500164.65 | C77: 652508.83 | D77: 784010.37 | E77: 954768.6 | F77: 1266349.5 | G77: 943058.75 | H77: 424772.79 | I77: 0.268 | J77: 0.0096666667
A78: 10 | B78: 561413.59 | C78: 746614.35 | D78: 913430.79 | E78: 1119868.2 | F78: 1536247 | G78: 1113342.3 | H78: 460772.79 | I78: 0.256 | J78: 0.0076666667
A80: Probabilidade de atingir a meta de renda em 10 anos: 92% • mediana: 7.2 anos
A101: Como ler
A102: • μ esperado de cada ativo = 50% retorno histórico (3a) + 50% CAPM — o encolhimento reduz o erro de estimação.
A103: • Fatores: se o Fator 1 explica muito do risco, a carteira depende de um único movimento de mercado.
A104: • Markowitz usa o passado; trate as carteiras ótimas como referência para o peso ideal, não como ordem de compra.
A105: • Monte Carlo: μ = valorização base + DY (se reinvestir); σ = volatilidade da carteira. Não é garantia de retorno.

Sheet Projeção
A1: InvestERP Projeção Futura
A3: Parte da posição atual (Carteira) e do aporte mensal (Premissas). Parâmetros em amarelo podem ser alterados aqui.
A4: Parâmetro | B4: Valor | C4: Origem
A5: Patrimônio inicial (ações + FIIs) | B5: =Carteira!G21 | C5: Carteira (posição atual) | K5: Mês | L5: Data | M5: Pessimista (R$) | N5: Base (R$) | O5: Otimista (R$) | P5: CDI (R$) | Q5: Renda mensal base (R$) | R5: Total aportado (R$)
A6: Aporte mensal | B6: =APORTE_MENSAL | C6: Premissas | K6: 0 | L6: =EDATE(TODAY(),K6) | M6: =PJ_INICIAL | N6: =PJ_INICIAL | O6: =PJ_INICIAL | P6: =PJ_INICIAL | Q6: =N6*PJ_DY/12 | R6: =PJ_INICIAL
A7: Dividend yield anual | B7: 0.09583896 | C7: Proventos 12m ÷ cotação, ponderado pela carteira | K7: 1 | L7: =EDATE(TODAY(),K7) | M7: =M6*(1+PJ_G_PESS)^(1/12)+PJ_APORTE+PJ_REINV*M6*PJ_DY/12 | N7: =N6*(1+PJ_G_BASE)^(1/12)+PJ_APORTE+PJ_REINV*N6*PJ_DY/12 | O7: =O6*(1+PJ_G_OTIM)^(1/12)+PJ_APORTE+PJ_REINV*O6*PJ_DY/12 | P7: =P6*(1+PJ_CDI)^(1/12)+PJ_APORTE | Q7: =N7*PJ_DY/12 | R7: =R6+PJ_APORTE
A8: Reinvestir proventos (1 = sim) | B8: 1 | C8: config.json → analise | K8: 2 | L8: =EDATE(TODAY(),K8) | M8: =M7*(1+PJ_G_PESS)^(1/12)+PJ_APORTE+PJ_REINV*M7*PJ_DY/12 | N8: =N7*(1+PJ_G_BASE)^(1/12)+PJ_APORTE+PJ_REINV*N7*PJ_DY/12 | O8: =O7*(1+PJ_G_OTIM)^(1/12)+PJ_APORTE+PJ_REINV*O7*PJ_DY/12 | P8: =P7*(1+PJ_CDI)^(1/12)+PJ_APORTE | Q8: =N8*PJ_DY/12 | R8: =R7+PJ_APORTE
A9: Valorização anual — pessimista | B9: -0.019892569 | C9: Base − 1 desvio-padrão no horizonte | K9: 3 | L9: =EDATE(TODAY(),K9) | M9: =M8*(1+PJ_G_PESS)^(1/12)+PJ_APORTE+PJ_REINV*M8*PJ_DY/12 | N9: =N8*(1+PJ_G_BASE)^(1/12)+PJ_APORTE+PJ_REINV*N8*PJ_DY/12 | O9: =O8*(1+PJ_G_OTIM)^(1/12)+PJ_APORTE+PJ_REINV*O8*PJ_DY/12 | P9: =P8*(1+PJ_CDI)^(1/12)+PJ_APORTE | Q9: =N9*PJ_DY/12 | R9: =R8+PJ_APORTE
A10: Valorização anual — base | B10: 0.02114582 | C10: Tendência 3a × R² (limitada a −10%…+20%) | K10: 4 | L10: =EDATE(TODAY(),K10) | M10: =M9*(1+PJ_G_PESS)^(1/12)+PJ_APORTE+PJ_REINV*M9*PJ_DY/12 | N10: =N9*(1+PJ_G_BASE)^(1/12)+PJ_APORTE+PJ_REINV*N9*PJ_DY/12 | O10: =O9*(1+PJ_G_OTIM)^(1/12)+PJ_APORTE+PJ_REINV*O9*PJ_DY/12 | P10: =P9*(1+PJ_CDI)^(1/12)+PJ_APORTE | Q10: =N10*PJ_DY/12 | R10: =R9+PJ_APORTE
A11: Valorização anual — otimista | B11: 0.062184209 | C11: Base + 1 desvio-padrão no horizonte | K11: 5 | L11: =EDATE(TODAY(),K11) | M11: =M10*(1+PJ_G_PESS)^(1/12)+PJ_APORTE+PJ_REINV*M10*PJ_DY/12 | N11: =N10*(1+PJ_G_BASE)^(1/12)+PJ_APORTE+PJ_REINV*N10*PJ_DY/12 | O11: =O10*(1+PJ_G_OTIM)^(1/12)+PJ_APORTE+PJ_REINV*O10*PJ_DY/12 | P11: =P10*(1+PJ_CDI)^(1/12)+PJ_APORTE | Q11: =N11*PJ_DY/12 | R11: =R10+PJ_APORTE
A12: CDI anual (comparação) | B12: 0.14 | C12: config.json → analise.cdi_anual | K12: 6 | L12: =EDATE(TODAY(),K12) | M12: =M11*(1+PJ_G_PESS)^(1/12)+PJ_APORTE+PJ_REINV*M11*PJ_DY/12 | N12: =N11*(1+PJ_G_BASE)^(1/12)+PJ_APORTE+PJ_REINV*N11*PJ_DY/12 | O12: =O11*(1+PJ_G_OTIM)^(1/12)+PJ_APORTE+PJ_REINV*O11*PJ_DY/12 | P12: =P11*(1+PJ_CDI)^(1/12)+PJ_APORTE | Q12: =N12*PJ_DY/12 | R12: =R11+PJ_APORTE
A13: Meta de renda mensal total | B13: =SUM(Meta!G5:G20) | C13: Soma das metas de cada ativo (aba Meta) | K13: 7 | L13: =EDATE(TODAY(),K13) | M13: =M12*(1+PJ_G_PESS)^(1/12)+PJ_APORTE+PJ_REINV*M12*PJ_DY/12 | N13: =N12*(1+PJ_G_BASE)^(1/12)+PJ_APORTE+PJ_REINV*N12*PJ_DY/12 | O13: =O12*(1+PJ_G_OTIM)^(1/12)+PJ_APORTE+PJ_REINV*O12*PJ_DY/12 | P13: =P12*(1+PJ_CDI)^(1/12)+PJ_APORTE | Q13: =N13*PJ_DY/12 | R13: =R12+PJ_APORTE
K14: 8 | L14: =EDATE(TODAY(),K14) | M14: =M13*(1+PJ_G_PESS)^(1/12)+PJ_APORTE+PJ_REINV*M13*PJ_DY/12 | N14: =N13*(1+PJ_G_BASE)^(1/12)+PJ_APORTE+PJ_REINV*N13*PJ_DY/12 | O14: =O13*(1+PJ_G_OTIM)^(1/12)+PJ_APORTE+PJ_REINV*O13*PJ_DY/12 | P14: =P13*(1+PJ_CDI)^(1/12)+PJ_APORTE | Q14: =N14*PJ_DY/12 | R14: =R13+PJ_APORTE
K15: 9 | L15: =EDATE(TODAY(),K15) | M15: =M14*(1+PJ_G_PESS)^(1/12)+PJ_APORTE+PJ_REINV*M14*PJ_DY/12 | N15: =N14*(1+PJ_G_BASE)^(1/12)+PJ_APORTE+PJ_REINV*N14*PJ_DY/12 | O15: =O14*(1+PJ_G_OTIM)^(1/12)+PJ_APORTE+PJ_REINV*O14*PJ_DY/12 | P15: =P14*(1+PJ_CDI)^(1/12)+PJ_APORTE | Q15: =N15*PJ_DY/12 | R15: =R14+PJ_APORTE
A16: Ano | B16: Pessimista (R$) | C16: Base (R$) | D16: Otimista (R$) | E16: CDI (R$) | F16: Renda mensal base (R$) | G16: Total aportado (R$) | H16: Base − CDI (R$) | I16: % da meta de renda | K16: 10 | L16: =EDATE(TODAY(),K16) | M16: =M15*(1+PJ_G_PESS)^(1/12)+PJ_APORTE+PJ_REINV*M15*PJ_DY/12 | N16: =N15*(1+PJ_G_BASE)^(1/12)+PJ_APORTE+PJ_REINV*N15*PJ_DY/12 | O16: =O15*(1+PJ_G_OTIM)^(1/12)+PJ_APORTE+PJ_REINV*O15*PJ_DY/12 | P16: =P15*(1+PJ_CDI)^(1/12)+PJ_APORTE | Q16: =N16*PJ_DY/12 | R16: =R15+PJ_APORTE
A17: 1 | B17: =M18 | C17: =N18 | D17: =O18 | E17: =P18 | F17: =Q18 | G17: =R18 | H17: =C17-E17 | I17: =IF(PJ_META>0,F17/PJ_META,0) | K17: 11 | L17: =EDATE(TODAY(),K17) | M17: =M16*(1+PJ_G_PESS)^(1/12)+PJ_APORTE+PJ_REINV*M16*PJ_DY/12 | N17: =N16*(1+PJ_G_BASE)^(1/12)+PJ_APORTE+PJ_REINV*N16*PJ_DY/12 | O17: =O16*(1+PJ_G_OTIM)^(1/12)+PJ_APORTE+PJ_REINV*O16*PJ_DY/12 | P17: =P16*(1+PJ_CDI)^(1/12)+PJ_APORTE | Q17: =N17*PJ_DY/12 | R17: =R16+PJ_APORTE
A18: 2 | B18: =M30 | C18: =N30 | D18: =O30 | E18: =P30 | F18: =Q30 | G18: =R30 | H18: =C18-E18 | I18: =IF(PJ_META>0,F18/PJ_META,0) | K18: 12 | L18: =EDATE(TODAY(),K18) | M18: =M17*(1+PJ_G_PESS)^(1/12)+PJ_APORTE+PJ_REINV*M17*PJ_DY/12 | N18: =N17*(1+PJ_G_BASE)^(1/12)+PJ_APORTE+PJ_REINV*N17*PJ_DY/12 | O18: =O17*(1+PJ_G_OTIM)^(1/12)+PJ_APORTE+PJ_REINV*O17*PJ_DY/12 | P18: =P17*(1+PJ_CDI)^(1/12)+PJ_APORTE | Q18: =N18*PJ_DY/12 | R18: =R17+PJ_APORTE
A19: 3 | B19: =M42 | C19: =N42 | D19: =O42 | E19: =P42 | F19: =Q42 | G19: =R42 | H19: =C19-E19 | I19: =IF(PJ_META>0,F19/PJ_META,0) | K19: 13 | L19: =EDATE(TODAY(),K19) | M19: =M18*(1+PJ_G_PESS)^(1/12)+PJ_APORTE+PJ_REINV*M18*PJ_DY/12 | N19: =N18*(1+PJ_G_BASE)^(1/12)+PJ_APORTE+PJ_REINV*N18*PJ_DY/12 | O19: =O18*(1+PJ_G_OTIM)^(1/12)+PJ_APORTE+PJ_REINV*O18*PJ_DY/12 | P19: =P18*(1+PJ_CDI)^(1/12)+PJ_APORTE | Q19: =N19*PJ_DY/12 | R19: =R18+PJ_APORTE
A20: 4 | B20: =M54 | C20: =N54 | D20: =O54 | E20: =P54 | F20: =Q54 | G20: =R54 | H20: =C20-E20 | I20: =IF(PJ_META>0,F20/PJ_META,0) | K20: 14 | L20: =EDATE(TODAY(),K20) | M20: =M19*(1+PJ_G_PESS)^(1/12)+PJ_APORTE+PJ_REINV*M19*PJ_DY/12 | N20: =N19*(1+PJ_G_BASE)^(1/12)+PJ_APORTE+PJ_REINV*N19*PJ_DY/12 | O20: =O19*(1+PJ_G_OTIM)^(1/12)+PJ_APORTE+PJ_REINV*O19*PJ_DY/12 | P20: =P19*(1+PJ_CDI)^(1/12)+PJ_APORTE | Q20: =N20*PJ_DY/12 | R20: =R19+PJ_APORTE
A21: 5 | B21: =M66 | C21: =N66 | D21: =O66 | E21: =P66 | F21: =Q66 | G21: =R66 | H21: =C21-E21 | I21: =IF(PJ_META>0,F21/PJ_META,0) | K21: 15 | L21: =EDATE(TODAY(),K21) | M21: =M20*(1+PJ_G_PESS)^(1/12)+PJ_APORTE+PJ_REINV*M20*PJ_DY/12 | N21: =N20*(1+PJ_G_BASE)^(1/12)+PJ_APORTE+PJ_REINV*N20*PJ_DY/12 | O21: =O20*(1+PJ_G_OTIM)^(1/12)+PJ_APORTE+PJ_REINV*O20*PJ_DY/12 | P21: =P20*(1+PJ_CDI)^(1/12)+PJ_APORTE | Q21: =N21*PJ_DY/12 | R21: =R20+PJ_APORTE
A22: 6 | B22: =M78 | C22: =N78 | D22: =O78 | E22: =P78 | F22: =Q78 | G22: =R78 | H22: =C22-E22 | I22: =IF(PJ_META>0,F22/PJ_META,0) | K22: 16 | L22: =EDATE(TODAY(),K22) | M22: =M21*(1+PJ_G_PESS)^(1/12)+PJ_APORTE+PJ_REINV*M21*PJ_DY/12 | N22: =N21*(1+PJ_G_BASE)^(1/12)+PJ_APORTE+PJ_REINV*N21*PJ_DY/12 | O22: =O21*(1+PJ_G_OTIM)^(1/12)+PJ_APORTE+PJ_REINV*O21*PJ_DY/12 | P22: =P21*(1+PJ_CDI)^(1/12)+PJ_APORTE | Q22: =N22*PJ_DY/12 | R22: =R21+PJ_APORTE
A23: 7 | B23: =M90 | C23: =N90 | D23: =O90 | E23: =P90 | F23: =Q90 | G23: =R90 | H23: =C23-E23 | I23: =IF(PJ_META>0,F23/PJ_META,0) | K23: 17 | L23: =EDATE(TODAY(),K23) | M23: =M22*(1+PJ_G_PESS)^(1/12)+PJ_APORTE+PJ_REINV*M22*PJ_DY/12 | N23: =N22*(1+PJ_G_BASE)^(1/12)+PJ_APORTE+PJ_REINV*N22*PJ_DY/12 | O23: =O22*(1+PJ_G_OTIM)^(1/12)+PJ_APORTE+PJ_REINV*O22*PJ_DY/12 | P23: =P22*(1+PJ_CDI)^(1/12)+PJ_APORTE | Q23: =N23*PJ_DY/12 | R23: =R22+PJ_APORTE
A24: 8 | B24: =M102 | C24: =N102 | D24: =O102 | E24: =P102 | F24: =Q102 | G24: =R102 | H24: =C24-E24 | I24: =IF(PJ_META>0,F24/PJ_META,0) | K24: 18 | L24: =EDATE(TODAY(),K24) | M24: =M23*(1+PJ_G_PESS)^(1/12)+PJ_APORTE+PJ_REINV*M23*PJ_DY/12 | N24: =N23*(1+PJ_G_BASE)^(1/12)+PJ_APORTE+PJ_REINV*N23*PJ_DY/12 | O24: =O23*(1+PJ_G_OTIM)^(1/12)+PJ_APORTE+PJ_REINV*O23*PJ_DY/12 | P24: =P23*(1+PJ_CDI)^(1/12)+PJ_APORTE | Q24: =N24*PJ_DY/12 | R24: =R23+PJ_APORTE
A25: 9 | B25: =M114 | C25: =N114 | D25: =O114 | E25: =P114 | F25: =Q114 | G25: =R114 | H25: =C25-E25 | I25: =IF(PJ_META>0,F25/PJ_META,0) | K25: 19 | L25: =EDATE(TODAY(),K25) | M25: =M24*(1+PJ_G_PESS)^(1/12)+PJ_APORTE+PJ_REINV*M24*PJ_DY/12 | N25: =N24*(1+PJ_G_BASE)^(1/12)+PJ_APORTE+PJ_REINV*N24*PJ_DY/12 | O25: =O24*(1+PJ_G_OTIM)^(1/12)+PJ_APORTE+PJ_REINV*O24*PJ_DY/12 | P25: =P24*(1+PJ_CDI)^(1/12)+PJ_APORTE | Q25: =N25*PJ_DY/12 | R25: =R24+PJ_APORTE
A26: 10 | B26: =M126 | C26: =N126 | D26: =O126 | E26: =P126 | F26: =Q126 | G26: =R126 | H26: =C26-E26 | I26: =IF(PJ_META>0,F26/PJ_META,0) | K26: 20 | L26: =EDATE(TODAY(),K26) | M26: =M25*(1+PJ_G_PESS)^(1/12)+PJ_APORTE+PJ_REINV*M25*PJ_DY/12 | N26: =N25*(1+PJ_G_BASE)^(1/12)+PJ_APORTE+PJ_REINV*N25*PJ_DY/12 | O26: =O25*(1+PJ_G_OTIM)^(1/12)+PJ_APORTE+PJ_REINV*O25*PJ_DY/12 | P26: =P25*(1+PJ_CDI)^(1/12)+PJ_APORTE | Q26: =N26*PJ_DY/12 | R26: =R25+PJ_APORTE
K27: 21 | L27: =EDATE(TODAY(),K27) | M27: =M26*(1+PJ_G_PESS)^(1/12)+PJ_APORTE+PJ_REINV*M26*PJ_DY/12 | N27: =N26*(1+PJ_G_BASE)^(1/12)+PJ_APORTE+PJ_REINV*N26*PJ_DY/12 | O27: =O26*(1+PJ_G_OTIM)^(1/12)+PJ_APORTE+PJ_REINV*O26*PJ_DY/12 | P27: =P26*(1+PJ_CDI)^(1/12)+PJ_APORTE | Q27: =N27*PJ_DY/12 | R27: =R26+PJ_APORTE
A28: Meses até a meta de renda (base) | B28: =IF(PJ_META<=0,"-",IF(COUNTIF(Q6:Q126,"<"&PJ_META)>120,"além de 10 anos",COUNTIF(Q6:Q126,"<"&PJ_META))) | K28: 22 | L28: =EDATE(TODAY(),K28) | M28: =M27*(1+PJ_G_PESS)^(1/12)+PJ_APORTE+PJ_REINV*M27*PJ_DY/12 | N28: =N27*(1+PJ_G_BASE)^(1/12)+PJ_APORTE+PJ_REINV*N27*PJ_DY/12 | O28: =O27*(1+PJ_G_OTIM)^(1/12)+PJ_APORTE+PJ_REINV*O27*PJ_DY/12 | P28: =P27*(1+PJ_CDI)^(1/12)+PJ_APORTE | Q28: =N28*PJ_DY/12 | R28: =R27+PJ_APORTE
A29: Renda mensal base no fim do horizonte | B29: =Q126 | K29: 23 | L29: =EDATE(TODAY(),K29) | M29: =M28*(1+PJ_G_PESS)^(1/12)+PJ_APORTE+PJ_REINV*M28*PJ_DY/12 | N29: =N28*(1+PJ_G_BASE)^(1/12)+PJ_APORTE+PJ_REINV*N28*PJ_DY/12 | O29: =O28*(1+PJ_G_OTIM)^(1/12)+PJ_APORTE+PJ_REINV*O28*PJ_DY/12 | P29: =P28*(1+PJ_CDI)^(1/12)+PJ_APORTE | Q29: =N29*PJ_DY/12 | R29: =R28+PJ_APORTE
K30: 24 | L30: =EDATE(TODAY(),K30) | M30: =M29*(1+PJ_G_PESS)^(1/12)+PJ_APORTE+PJ_REINV*M29*PJ_DY/12 | N30: =N29*(1+PJ_G_BASE)^(1/12)+PJ_APORTE+PJ_REINV*N29*PJ_DY/12 | O30: =O29*(1+PJ_G_OTIM)^(1/12)+PJ_APORTE+PJ_REINV*O29*PJ_DY/12 | P30: =P29*(1+PJ_CDI)^(1/12)+PJ_APORTE | Q30: =N30*PJ_DY/12 | R30: =R29+PJ_APORTE
K31: 25 | L31: =EDATE(TODAY(),K31) | M31: =M30*(1+PJ_G_PESS)^(1/12)+PJ_APORTE+PJ_REINV*M30*PJ_DY/12 | N31: =N30*(1+PJ_G_BASE)^(1/12)+PJ_APORTE+PJ_REINV*N30*PJ_DY/12 | O31: =O30*(1+PJ_G_OTIM)^(1/12)+PJ_APORTE+PJ_REINV*O30*PJ_DY/12 | P31: =P30*(1+PJ_CDI)^(1/12)+PJ_APORTE | Q31: =N31*PJ_DY/12 | R31: =R30+PJ_APORTE
K32: 26 | L32: =EDATE(TODAY(),K32) | M32: =M31*(1+PJ_G_PESS)^(1/12)+PJ_APORTE+PJ_REINV*M31*PJ_DY/12 | N32: =N31*(1+PJ_G_BASE)^(1/12)+PJ_APORTE+PJ_REINV*N31*PJ_DY/12 | O32: =O31*(1+PJ_G_OTIM)^(1/12)+PJ_APORTE+PJ_REINV*O31*PJ_DY/12 | P32: =P31*(1+PJ_CDI)^(1/12)+PJ_APORTE | Q32: =N32*PJ_DY/12 | R32: =R31+PJ_APORTE
K33: 27 | L33: =EDATE(TODAY(),K33) | M33: =M32*(1+PJ_G_PESS)^(1/12)+PJ_APORTE+PJ_REINV*M32*PJ_DY/12 | N33: =N32*(1+PJ_G_BASE)^(1/12)+PJ_APORTE+PJ_REINV*N32*PJ_DY/12 | O33: =O32*(1+PJ_G_OTIM)^(1/12)+PJ_APORTE+PJ_REINV*O32*PJ_DY/12 | P33: =P32*(1+PJ_CDI)^(1/12)+PJ_APORTE | Q33: =N33*PJ_DY/12 | R33: =R32+PJ_APORTE
K34: 28 | L34: =EDATE(TODAY(),K34) | M34: =M33*(1+PJ_G_PESS)^(1/12)+PJ_APORTE+PJ_REINV*M33*PJ_DY/12 | N34: =N33*(1+PJ_G_BASE)^(1/12)+PJ_APORTE+PJ_REINV*N33*PJ_DY/12 | O34: =O33*(1+PJ_G_OTIM)^(1/12)+PJ_APORTE+PJ_REINV*O33*PJ_DY/12 | P34: =P33*(1+PJ_CDI)^(1/12)+PJ_APORTE | Q34: =N34*PJ_DY/12 | R34: =R33+PJ_APORTE
K35: 29 | L35: =EDATE(TODAY(),K35) | M35: =M34*(1+PJ_G_PESS)^(1/12)+PJ_APORTE+PJ_REINV*M34*PJ_DY/12 | N35: =N34*(1+PJ_G_BASE)^(1/12)+PJ_APORTE+PJ_REINV*N34*PJ_DY/12 | O35: =O34*(1+PJ_G_OTIM)^(1/12)+PJ_APORTE+PJ_REINV*O34*PJ_DY/12 | P35: =P34*(1+PJ_CDI)^(1/12)+PJ_APORTE | Q35: =N35*PJ_DY/12 | R35: =R34+PJ_APORTE
K36: 30 | L36: =EDATE(TODAY(),K36) | M36: =M35*(1+PJ_G_PESS)^(1/12)+PJ_APORTE+PJ_REINV*M35*PJ_DY/12 | N36: =N35*(1+PJ_G_BASE)^(1/12)+PJ_APORTE+PJ_REINV*N35*PJ_DY/12 | O36: =O35*(1+PJ_G_OTIM)^(1/12)+PJ_APORTE+PJ_REINV*O35*PJ_DY/12 | P36: =P35*(1+PJ_CDI)^(1/12)+PJ_APORTE | Q36: =N36*PJ_DY/12 | R36: =R35+PJ_APORTE
K37: 31 | L37: =EDATE(TODAY(),K37) | M37: =M36*(1+PJ_G_PESS)^(1/12)+PJ_APORTE+PJ_REINV*M36*PJ_DY/12 | N37: =N36*(1+PJ_G_BASE)^(1/12)+PJ_APORTE+PJ_REINV*N36*PJ_DY/12 | O37: =O36*(1+PJ_G_OTIM)^(1/12)+PJ_APORTE+PJ_REINV*O36*PJ_DY/12 | P37: =P36*(1+PJ_CDI)^(1/12)+PJ_APORTE | Q37: =N37*PJ_DY/12 | R37: =R36+PJ_APORTE
K38: 32 | L38: =EDATE(TODAY(),K38) | M38: =M37*(1+PJ_G_PESS)^(1/12)+PJ_APORTE+PJ_REINV*M37*PJ_DY/12 | N38: =N37*(1+PJ_G_BASE)^(1/12)+PJ_APORTE+PJ_REINV*N37*PJ_DY/12 | O38: =O37*(1+PJ_G_OTIM)^(1/12)+PJ_APORTE+PJ_REINV*O37*PJ_DY/12 | P38: =P37*(1+PJ_CDI)^(1/12)+PJ_APORTE | Q38: =N38*PJ_DY/12 | R38: =R37+PJ_APORTE
K39: 33 | L39: =EDATE(TODAY(),K39) | M39: =M38*(1+PJ_G_PESS)^(1/12)+PJ_APORTE+PJ_REINV*M38*PJ_DY/12 | N39: =N38*(1+PJ_G_BASE)^(1/12)+PJ_APORTE+PJ_REINV*N38*PJ_DY/12 | O39: =O38*(1+PJ_G_OTIM)^(1/12)+PJ_APORTE+PJ_REINV*O38*PJ_DY/12 | P39: =P38*(1+PJ_CDI)^(1/12)+PJ_APORTE | Q39: =N39*PJ_DY/12 | R39: =R38+PJ_APORTE
K40: 34 | L40: =EDATE(TODAY(),K40) | M40: =M39*(1+PJ_G_PESS)^(1/12)+PJ_APORTE+PJ_REINV*M39*PJ_DY/12 | N40: =N39*(1+PJ_G_BASE)^(1/12)+PJ_APORTE+PJ_REINV*N39*PJ_DY/12 | O40: =O39*(1+PJ_G_OTIM)^(1/12)+PJ_APORTE+PJ_REINV*O39*PJ_DY/12 | P40: =P39*(1+PJ_CDI)^(1/12)+PJ_APORTE | Q40: =N40*PJ_DY/12 | R40: =R39+PJ_APORTE
K41: 35 | L41: =EDATE(TODAY(),K41) | M41: =M40*(1+PJ_G_PESS)^(1/12)+PJ_APORTE+PJ_REINV*M40*PJ_DY/12 | N41: =N40*(1+PJ_G_BASE)^(1/12)+PJ_APORTE+PJ_REINV*N40*PJ_DY/12 | O41: =O40*(1+PJ_G_OTIM)^(1/12)+PJ_APORTE+PJ_REINV*O40*PJ_DY/12 | P41: =P40*(1+PJ_CDI)^(1/12)+PJ_APORTE | Q41: =N41*PJ_DY/12 | R41: =R40+PJ_APORTE
... K126: 120 | L126: =EDATE(TODAY(),K126) | M126: =M125*(1+PJ_G_PESS)^(1/12)+PJ_APORTE+PJ_REINV*M125*PJ_DY/12 | N126: =N125*(1+PJ_G_BASE)^(1/12)+PJ_APORTE+PJ_REINV*N125*PJ_DY/12 | O126: =O125*(1+PJ_G_OTIM)^(1/12)+PJ_APORTE+PJ_REINV*O125*PJ_DY/12 | P126: =P125*(1+PJ_CDI)^(1/12)+PJ_APORTE | Q126: =N126*PJ_DY/12 | R126: =R125+PJ_APORTE
A150: Como ler
A151: • Cada mês: patrimônio × (1 + valorização)^(1/12) + aporte + proventos reinvestidos (se PJ_REINV = 1).
A152: • Cenários: base = tendência de 3 anos ponderada pela confiança (R²); pessimista/otimista = ± 1 desvio-padrão do retorno médio no horizonte (volatilidade ÷ √anos).
A153: • CDI: mesmo aporte aplicado ao CDI da premissa, sem IR — serve de régua para o custo de oportunidade.
A154: • Projeção é estimativa estatística a partir do passado; não é garantia de retorno.

Sheet Cadastro
A1: InvestERP Novo Lançamento
A3: Escolha o ticker, informe a quantidade e clique em Registrar — o resto vem do cadastro do ativo. | L3: cadastro-formulario-v3
B5: Amarelo = você preenche • Cinza ⟲ = automático • Botão Registrar grava na hora (habilite as macros ao abrir o arquivo)
B7: ✚ Compra / venda de cotas | E7: ◈ Provento recebido | H7: Últimos lançamentos
B8: Data (vazio = hoje) | E8: Data pagamento (vazio = hoje) | H8: Data | I8: Ticker | J8: Operação | K8: Cotas | L8: Preço (R$)
B9: Ticker | E9: Ticker | H9: =IF((COUNTA('Lançamentos'!$B:$B)+3-0)<5,"",INDEX('Lançamentos'!$A:$A,(COUNTA('Lançamentos'!$B:$B)+3-0))) | I9: =IF((COUNTA('Lançamentos'!$B:$B)+3-0)<5,"",INDEX('Lançamentos'!$B:$B,(COUNTA('Lançamentos'!$B:$B)+3-0))) | J9: =IF((COUNTA('Lançamentos'!$B:$B)+3-0)<5,"",INDEX('Lançamentos'!$C:$C,(COUNTA('Lançamentos'!$B:$B)+3-0))) | K9: =IF((COUNTA('Lançamentos'!$B:$B)+3-0)<5,"",INDEX('Lançamentos'!$D:$D,(COUNTA('Lançamentos'!$B:$B)+3-0))) | L9: =IF((COUNTA('Lançamentos'!$B:$B)+3-0)<5,"",INDEX('Lançamentos'!$E:$E,(COUNTA('Lançamentos'!$B:$B)+3-0)))
B10: Operação (vazio = compra) | E10: Tipo de provento | H10: =IF((COUNTA('Lançamentos'!$B:$B)+3-1)<5,"",INDEX('Lançamentos'!$A:$A,(COUNTA('Lançamentos'!$B:$B)+3-1))) | I10: =IF((COUNTA('Lançamentos'!$B:$B)+3-1)<5,"",INDEX('Lançamentos'!$B:$B,(COUNTA('Lançamentos'!$B:$B)+3-1))) | J10: =IF((COUNTA('Lançamentos'!$B:$B)+3-1)<5,"",INDEX('Lançamentos'!$C:$C,(COUNTA('Lançamentos'!$B:$B)+3-1))) | K10: =IF((COUNTA('Lançamentos'!$B:$B)+3-1)<5,"",INDEX('Lançamentos'!$D:$D,(COUNTA('Lançamentos'!$B:$B)+3-1))) | L10: =IF((COUNTA('Lançamentos'!$B:$B)+3-1)<5,"",INDEX('Lançamentos'!$E:$E,(COUNTA('Lançamentos'!$B:$B)+3-1)))
B11: Quantidade de cotas | E11: Valor por cota (R$) | H11: =IF((COUNTA('Lançamentos'!$B:$B)+3-2)<5,"",INDEX('Lançamentos'!$A:$A,(COUNTA('Lançamentos'!$B:$B)+3-2))) | I11: =IF((COUNTA('Lançamentos'!$B:$B)+3-2)<5,"",INDEX('Lançamentos'!$B:$B,(COUNTA('Lançamentos'!$B:$B)+3-2))) | J11: =IF((COUNTA('Lançamentos'!$B:$B)+3-2)<5,"",INDEX('Lançamentos'!$C:$C,(COUNTA('Lançamentos'!$B:$B)+3-2))) | K11: =IF((COUNTA('Lançamentos'!$B:$B)+3-2)<5,"",INDEX('Lançamentos'!$D:$D,(COUNTA('Lançamentos'!$B:$B)+3-2))) | L11: =IF((COUNTA('Lançamentos'!$B:$B)+3-2)<5,"",INDEX('Lançamentos'!$E:$E,(COUNTA('Lançamentos'!$B:$B)+3-2)))
B12: Preço por cota (vazio = cotação) | E12: Qtd de cotas (vazio = suas cotas) | H12: =IF((COUNTA('Lançamentos'!$B:$B)+3-3)<5,"",INDEX('Lançamentos'!$A:$A,(COUNTA('Lançamentos'!$B:$B)+3-3))) | I12: =IF((COUNTA('Lançamentos'!$B:$B)+3-3)<5,"",INDEX('Lançamentos'!$B:$B,(COUNTA('Lançamentos'!$B:$B)+3-3))) | J12: =IF((COUNTA('Lançamentos'!$B:$B)+3-3)<5,"",INDEX('Lançamentos'!$C:$C,(COUNTA('Lançamentos'!$B:$B)+3-3))) | K12: =IF((COUNTA('Lançamentos'!$B:$B)+3-3)<5,"",INDEX('Lançamentos'!$D:$D,(COUNTA('Lançamentos'!$B:$B)+3-3))) | L12: =IF((COUNTA('Lançamentos'!$B:$B)+3-3)<5,"",INDEX('Lançamentos'!$E:$E,(COUNTA('Lançamentos'!$B:$B)+3-3)))
B13: Custos / taxas (R$) | E13: AUTOMÁTICO ⟲ | H13: =IF((COUNTA('Lançamentos'!$B:$B)+3-4)<5,"",INDEX('Lançamentos'!$A:$A,(COUNTA('Lançamentos'!$B:$B)+3-4))) | I13: =IF((COUNTA('Lançamentos'!$B:$B)+3-4)<5,"",INDEX('Lançamentos'!$B:$B,(COUNTA('Lançamentos'!$B:$B)+3-4))) | J13: =IF((COUNTA('Lançamentos'!$B:$B)+3-4)<5,"",INDEX('Lançamentos'!$C:$C,(COUNTA('Lançamentos'!$B:$B)+3-4))) | K13: =IF((COUNTA('Lançamentos'!$B:$B)+3-4)<5,"",INDEX('Lançamentos'!$D:$D,(COUNTA('Lançamentos'!$B:$B)+3-4))) | L13: =IF((COUNTA('Lançamentos'!$B:$B)+3-4)<5,"",INDEX('Lançamentos'!$E:$E,(COUNTA('Lançamentos'!$B:$B)+3-4)))
B14: DADOS DO ATIVO ⟲ automático | E14: Cotas que você tem | F14: =IF(pv_ticker="","",IFERROR(INDEX(Carteira!$C$5:$C$20,MATCH(pv_ticker,Carteira!$A$5:$A$20,0)),0)) | H14: =IF((COUNTA('Lançamentos'!$B:$B)+3-5)<5,"",INDEX('Lançamentos'!$A:$A,(COUNTA('Lançamentos'!$B:$B)+3-5))) | I14: =IF((COUNTA('Lançamentos'!$B:$B)+3-5)<5,"",INDEX('Lançamentos'!$B:$B,(COUNTA('Lançamentos'!$B:$B)+3-5))) | J14: =IF((COUNTA('Lançamentos'!$B:$B)+3-5)<5,"",INDEX('Lançamentos'!$C:$C,(COUNTA('Lançamentos'!$B:$B)+3-5))) | K14: =IF((COUNTA('Lançamentos'!$B:$B)+3-5)<5,"",INDEX('Lançamentos'!$D:$D,(COUNTA('Lançamentos'!$B:$B)+3-5))) | L14: =IF((COUNTA('Lançamentos'!$B:$B)+3-5)<5,"",INDEX('Lançamentos'!$E:$E,(COUNTA('Lançamentos'!$B:$B)+3-5)))
B15: Ativo | C15: =IF(lc_ticker="","",IFERROR(INDEX(Ativos!$B$5:$B$20,MATCH(lc_ticker,Ativos!$A$5:$A$20,0))&" • "&INDEX(Ativos!$C$5:$C$20,MATCH(lc_ticker,Ativos!$A$5:$A$20,0)),"Ticker novo — preencha Tipo e Segmento abaixo")) | E15: Total recebido | F15: =IF(pv_valor="","",pv_valor*IF(pv_qtd="",N(pv_tem),pv_qtd)) | H15: =IF((COUNTA('Lançamentos'!$B:$B)+3-6)<5,"",INDEX('Lançamentos'!$A:$A,(COUNTA('Lançamentos'!$B:$B)+3-6))) | I15: =IF((COUNTA('Lançamentos'!$B:$B)+3-6)<5,"",INDEX('Lançamentos'!$B:$B,(COUNTA('Lançamentos'!$B:$B)+3-6))) | J15: =IF((COUNTA('Lançamentos'!$B:$B)+3-6)<5,"",INDEX('Lançamentos'!$C:$C,(COUNTA('Lançamentos'!$B:$B)+3-6))) | K15: =IF((COUNTA('Lançamentos'!$B:$B)+3-6)<5,"",INDEX('Lançamentos'!$D:$D,(COUNTA('Lançamentos'!$B:$B)+3-6))) | L15: =IF((COUNTA('Lançamentos'!$B:$B)+3-6)<5,"",INDEX('Lançamentos'!$E:$E,(COUNTA('Lançamentos'!$B:$B)+3-6)))
B16: Cotação atual (R$) | C16: =IF(lc_ticker="","",IFERROR(INDEX(Ativos!$D$5:$D$20,MATCH(lc_ticker,Ativos!$A$5:$A$20,0)),"")) | H16: =IF((COUNTA('Lançamentos'!$B:$B)+3-7)<5,"",INDEX('Lançamentos'!$A:$A,(COUNTA('Lançamentos'!$B:$B)+3-7))) | I16: =IF((COUNTA('Lançamentos'!$B:$B)+3-7)<5,"",INDEX('Lançamentos'!$B:$B,(COUNTA('Lançamentos'!$B:$B)+3-7))) | J16: =IF((COUNTA('Lançamentos'!$B:$B)+3-7)<5,"",INDEX('Lançamentos'!$C:$C,(COUNTA('Lançamentos'!$B:$B)+3-7))) | K16: =IF((COUNTA('Lançamentos'!$B:$B)+3-7)<5,"",INDEX('Lançamentos'!$D:$D,(COUNTA('Lançamentos'!$B:$B)+3-7))) | L16: =IF((COUNTA('Lançamentos'!$B:$B)+3-7)<5,"",INDEX('Lançamentos'!$E:$E,(COUNTA('Lançamentos'!$B:$B)+3-7)))
B17: Cotas que você tem | C17: =IF(lc_ticker="","",IFERROR(INDEX(Carteira!$C$5:$C$20,MATCH(lc_ticker,Carteira!$A$5:$A$20,0)),0)) | H17: =IF((COUNTA('Lançamentos'!$B:$B)+3-8)<5,"",INDEX('Lançamentos'!$A:$A,(COUNTA('Lançamentos'!$B:$B)+3-8))) | I17: =IF((COUNTA('Lançamentos'!$B:$B)+3-8)<5,"",INDEX('Lançamentos'!$B:$B,(COUNTA('Lançamentos'!$B:$B)+3-8))) | J17: =IF((COUNTA('Lançamentos'!$B:$B)+3-8)<5,"",INDEX('Lançamentos'!$C:$C,(COUNTA('Lançamentos'!$B:$B)+3-8))) | K17: =IF((COUNTA('Lançamentos'!$B:$B)+3-8)<5,"",INDEX('Lançamentos'!$D:$D,(COUNTA('Lançamentos'!$B:$B)+3-8))) | L17: =IF((COUNTA('Lançamentos'!$B:$B)+3-8)<5,"",INDEX('Lançamentos'!$E:$E,(COUNTA('Lançamentos'!$B:$B)+3-8)))
B18: SÓ PARA TICKER NOVO | H18: =IF((COUNTA('Lançamentos'!$B:$B)+3-9)<5,"",INDEX('Lançamentos'!$A:$A,(COUNTA('Lançamentos'!$B:$B)+3-9))) | I18: =IF((COUNTA('Lançamentos'!$B:$B)+3-9)<5,"",INDEX('Lançamentos'!$B:$B,(COUNTA('Lançamentos'!$B:$B)+3-9))) | J18: =IF((COUNTA('Lançamentos'!$B:$B)+3-9)<5,"",INDEX('Lançamentos'!$C:$C,(COUNTA('Lançamentos'!$B:$B)+3-9))) | K18: =IF((COUNTA('Lançamentos'!$B:$B)+3-9)<5,"",INDEX('Lançamentos'!$D:$D,(COUNTA('Lançamentos'!$B:$B)+3-9))) | L18: =IF((COUNTA('Lançamentos'!$B:$B)+3-9)<5,"",INDEX('Lançamentos'!$E:$E,(COUNTA('Lançamentos'!$B:$B)+3-9)))
B19: Tipo do ativo (AÇÃO / FII) | H19: =IF((COUNTA('Lançamentos'!$B:$B)+3-10)<5,"",INDEX('Lançamentos'!$A:$A,(COUNTA('Lançamentos'!$B:$B)+3-10))) | I19: =IF((COUNTA('Lançamentos'!$B:$B)+3-10)<5,"",INDEX('Lançamentos'!$B:$B,(COUNTA('Lançamentos'!$B:$B)+3-10))) | J19: =IF((COUNTA('Lançamentos'!$B:$B)+3-10)<5,"",INDEX('Lançamentos'!$C:$C,(COUNTA('Lançamentos'!$B:$B)+3-10))) | K19: =IF((COUNTA('Lançamentos'!$B:$B)+3-10)<5,"",INDEX('Lançamentos'!$D:$D,(COUNTA('Lançamentos'!$B:$B)+3-10))) | L19: =IF((COUNTA('Lançamentos'!$B:$B)+3-10)<5,"",INDEX('Lançamentos'!$E:$E,(COUNTA('Lançamentos'!$B:$B)+3-10)))
B20: Segmento | H20: =IF((COUNTA('Lançamentos'!$B:$B)+3-11)<5,"",INDEX('Lançamentos'!$A:$A,(COUNTA('Lançamentos'!$B:$B)+3-11))) | I20: =IF((COUNTA('Lançamentos'!$B:$B)+3-11)<5,"",INDEX('Lançamentos'!$B:$B,(COUNTA('Lançamentos'!$B:$B)+3-11))) | J20: =IF((COUNTA('Lançamentos'!$B:$B)+3-11)<5,"",INDEX('Lançamentos'!$C:$C,(COUNTA('Lançamentos'!$B:$B)+3-11))) | K20: =IF((COUNTA('Lançamentos'!$B:$B)+3-11)<5,"",INDEX('Lançamentos'!$D:$D,(COUNTA('Lançamentos'!$B:$B)+3-11))) | L20: =IF((COUNTA('Lançamentos'!$B:$B)+3-11)<5,"",INDEX('Lançamentos'!$E:$E,(COUNTA('Lançamentos'!$B:$B)+3-11)))
B21: RESUMO | H21: =IF((COUNTA('Lançamentos'!$B:$B)+3-12)<5,"",INDEX('Lançamentos'!$A:$A,(COUNTA('Lançamentos'!$B:$B)+3-12))) | I21: =IF((COUNTA('Lançamentos'!$B:$B)+3-12)<5,"",INDEX('Lançamentos'!$B:$B,(COUNTA('Lançamentos'!$B:$B)+3-12))) | J21: =IF((COUNTA('Lançamentos'!$B:$B)+3-12)<5,"",INDEX('Lançamentos'!$C:$C,(COUNTA('Lançamentos'!$B:$B)+3-12))) | K21: =IF((COUNTA('Lançamentos'!$B:$B)+3-12)<5,"",INDEX('Lançamentos'!$D:$D,(COUNTA('Lançamentos'!$B:$B)+3-12))) | L21: =IF((COUNTA('Lançamentos'!$B:$B)+3-12)<5,"",INDEX('Lançamentos'!$E:$E,(COUNTA('Lançamentos'!$B:$B)+3-12)))
B22: Total do lançamento | C22: =IF(lc_qtd="","",lc_qtd*IF(lc_preco="",N(lc_cot),lc_preco)+N(lc_custos)) | H22: =IF((COUNTA('Lançamentos'!$B:$B)+3-13)<5,"",INDEX('Lançamentos'!$A:$A,(COUNTA('Lançamentos'!$B:$B)+3-13))) | I22: =IF((COUNTA('Lançamentos'!$B:$B)+3-13)<5,"",INDEX('Lançamentos'!$B:$B,(COUNTA('Lançamentos'!$B:$B)+3-13))) | J22: =IF((COUNTA('Lançamentos'!$B:$B)+3-13)<5,"",INDEX('Lançamentos'!$C:$C,(COUNTA('Lançamentos'!$B:$B)+3-13))) | K22: =IF((COUNTA('Lançamentos'!$B:$B)+3-13)<5,"",INDEX('Lançamentos'!$D:$D,(COUNTA('Lançamentos'!$B:$B)+3-13))) | L22: =IF((COUNTA('Lançamentos'!$B:$B)+3-13)<5,"",INDEX('Lançamentos'!$E:$E,(COUNTA('Lançamentos'!$B:$B)+3-13)))
B23: Cotas após o lançamento | C23: =IF(lc_qtd="","",N(lc_tem)+IF(UPPER(lc_op)="VENDA",-1,1)*lc_qtd) | H23: =IF((COUNTA('Lançamentos'!$B:$B)+3-14)<5,"",INDEX('Lançamentos'!$A:$A,(COUNTA('Lançamentos'!$B:$B)+3-14))) | I23: =IF((COUNTA('Lançamentos'!$B:$B)+3-14)<5,"",INDEX('Lançamentos'!$B:$B,(COUNTA('Lançamentos'!$B:$B)+3-14))) | J23: =IF((COUNTA('Lançamentos'!$B:$B)+3-14)<5,"",INDEX('Lançamentos'!$C:$C,(COUNTA('Lançamentos'!$B:$B)+3-14))) | K23: =IF((COUNTA('Lançamentos'!$B:$B)+3-14)<5,"",INDEX('Lançamentos'!$D:$D,(COUNTA('Lançamentos'!$B:$B)+3-14))) | L23: =IF((COUNTA('Lançamentos'!$B:$B)+3-14)<5,"",INDEX('Lançamentos'!$E:$E,(COUNTA('Lançamentos'!$B:$B)+3-14)))
H24: Histórico completo na aba Lançamentos • posição de cada ativo na aba Carteira

Sheet Ativos
A1: InvestERP Cadastro de Ativos
A3: Gerado a partir de dados/ativos.csv — edite lá e rode gestao.py (ou atualizar.bat).
A4: Ticker | B4: Tipo | C4: Segmento | D4: Cotação (R$) | E4: Provento 12m por cota (R$) | F4: Peso ideal | G4: Atualizado em
A5: VALE3 | B5: AÇÃO | C5: Mineração | D5: 71.16 | E5: 5.6125 | F5: 0.1 | G5: 28/09/2026
A6: TAEE11 | B6: AÇÃO | C6: Energia – Transmissão | D6: 40.22 | E6: 3.0065 | F6: 0.05 | G6: 28/09/2026
A7: PETR4 | B7: AÇÃO | C7: Petróleo & Gás | D7: 48.72 | E7: 3.6643 | F7: 0.07 | G7: 28/09/2026
A8: BBAS3 | B8: AÇÃO | C8: Bancos | D8: 21.49 | E8: 0.655 | F8: 0.06 | G8: 28/09/2026
A9: BRBI11 | B9: AÇÃO | C9: Banco de investimento | D9: 14.5 | E9: 1.38 | F9: 0.05 | G9: 28/09/2026
A10: BBDC4 | B10: AÇÃO | C10: Bancos | D10: 17.66 | E10: 1.5528 | F10: 0.05 | G10: 28/09/2026
A11: ITSA4 | B11: AÇÃO | C11: Holding – Bancos | D11: 13.95 | E11: 1.1278 | F11: 0.1 | G11: 28/09/2026
A12: CMIG4 | B12: AÇÃO | C12: Energia – Utilities | D12: 10.84 | E12: 1.3507 | F12: 0.1 | G12: 28/09/2026
A13: FIQE3 | B13: AÇÃO | C13: Telecom / Tecnologia | D13: 4.92 | E13: 0.682 | F13: 0.05 | G13: 28/09/2026
A14: KLBN11 | B14: AÇÃO | C14: Papel & Celulose | D14: 18.31 | E14: 1.1611 | F14: 0.07 | G14: 28/09/2026
A15: MXRF11 | B15: FII | C15: Papel (recebíveis) | D15: 9.08 | E15: 1.1943 | F15: 0.05 | G15: 28/09/2026
A16: BRCR11 | B16: FII | C16: Lajes corporativas | D16: 41.31 | E16: 4.92 | F16: 0.04 | G16: 28/09/2026
... A20: CPTS11 | B20: FII | C20: Híbrido (papel) | D20: 7.42 | E20: 1.08 | F20: 0.04 | G20: 28/09/2026
A21: TOTAL | F21: =SUM(F5:F20)
A23: Observações
A24: • Cotação, provento 12m e 'Atualizado em' são preenchidos pelo Yahoo Finance a cada execução; 'manual' = não atualizado online.
A25: • Peso ideal: participação desejada de cada ativo dentro da renda variável — deve somar 100%.

Sheet Lançamentos
A1: InvestERP Lançamentos de Compra e Venda
A3: Gerado a partir de dados/lancamentos.csv — edite lá e rode gestao.py (ou atualizar.bat).
A4: Data | B4: Ticker | C4: Operação | D4: Quantidade | E4: Preço (R$) | F4: Custos (R$) | G4: Total (R$)
A5: 45299 | B5: FIQE3 | C5: COMPRA | D5: 419 | E5: 3.57 | F5: 0.45 | G5: =D5*E5+F5
A6: 45299 | B6: XPML11 | C6: COMPRA | D6: 12 | E6: 115.5 | F6: 0.42 | G6: =D6*E6+F6
A7: 45327 | B7: BRCR11 | C7: COMPRA | D7: 25 | E7: 59.48 | F7: 0.45 | G7: =D7*E7+F7
A8: 45327 | B8: BBAS3 | C8: COMPRA | D8: 52 | E8: 28.78 | F8: 0.45 | G8: =D8*E8+F8
A9: 45355 | B9: BRBI11 | C9: COMPRA | D9: 88 | E9: 16.9 | F9: 0.45 | G9: =D9*E9+F9
A10: 45355 | B10: XPML11 | C10: COMPRA | D10: 12 | E10: 118.49 | F10: 0.43 | G10: =D10*E10+F10
A11: 45383 | B11: VALE3 | C11: COMPRA | D11: 25 | E11: 59.71 | F11: 0.45 | G11: =D11*E11+F11
A12: 45383 | B12: XPLG11 | C12: COMPRA | D12: 13 | E12: 108.8 | F12: 0.42 | G12: =D12*E12+F12
A13: 45418 | B13: XPLG11 | C13: COMPRA | D13: 14 | E13: 104.98 | F13: 0.44 | G13: =D13*E13+F13
A14: 45418 | B14: ITSA4 | C14: COMPRA | D14: 160 | E14: 9.33 | F14: 0.45 | G14: =D14*E14+F14
A15: 45446 | B15: BRBI11 | C15: COMPRA | D15: 108 | E15: 13.83 | F15: 0.45 | G15: =D15*E15+F15
A16: 45446 | B16: BBAS3 | C16: COMPRA | D16: 55 | E16: 27.18 | F16: 0.45 | G16: =D16*E16+F16
... A71: 46272 | B71: VALE3 | C71: COMPRA | D71: 19 | E71: 78.2 | F71: 0.45 | G71: =D71*E71+F71

Sheet Proventos
A1: InvestERP Proventos Recebidos
A3: Gerado a partir de dados/proventos.csv — edite lá e rode gestao.py (ou atualizar.bat).
A4: Data pagamento | B4: Ticker | C4: Tipo | D4: Valor por cota (R$) | E4: Qtd de cotas | F4: Total (R$)
A5: 45309 | B5: XPML11 | C5: RENDIMENTO | D5: 0.9198 | E5: 12 | F5: =D5*E5
A6: 45330 | B6: FIQE3 | C6: DIVIDENDO | D6: 0.0514 | E6: 419 | F6: =D6*E6
A7: 45344 | B7: XPML11 | C7: RENDIMENTO | D7: 0.8998 | E7: 12 | F7: =D7*E7
A8: 45358 | B8: BRCR11 | C8: RENDIMENTO | D8: 0.41 | E8: 25 | F8: =D8*E8
A9: 45365 | B9: BBAS3 | C9: JCP | D9: 0.205 | E9: 52 | F9: =D9*E9
A10: 45372 | B10: XPML11 | C10: RENDIMENTO | D10: 0.8998 | E10: 24 | F10: =D10*E10
A11: 45379 | B11: BRBI11 | C11: DIVIDENDO | D11: 0.12 | E11: 88 | F11: =D11*E11
A12: 45393 | B12: BRCR11 | C12: RENDIMENTO | D12: 0.5 | E12: 25 | F12: =D12*E12
A13: 45400 | B13: XPML11 | C13: RENDIMENTO | D13: 0.9098 | E13: 24 | F13: =D13*E13
A14: 45414 | B14: XPLG11 | C14: RENDIMENTO | D14: 0.78 | E14: 13 | F14: =D14*E14
A15: 45421 | B15: BRCR11 | C15: RENDIMENTO | D15: 0.5 | E15: 25 | F15: =D15*E15
A16: 45428 | B16: BRBI11 | C16: DIVIDENDO | D16: 0.3 | E16: 88 | F16: =D16*E16
... A254: 46289 | B254: XPML11 | C254: RENDIMENTO | D254: 0.95 | E254: 52 | F254: =D254*E254

Sheet Premissas
A1: InvestERP Premissas
A3: Gerado a partir de dados/config.json — edite lá e rode gestao.py (ou atualizar.bat).
A4: Parâmetro | B4: Valor | C4: Uso
A5: Meta mensal padrão por ativo | B5: 300 | C5: Renda que cada ativo deve pagar por mês (personalize por ativo na aba Meta)
A6: Prazo padrão da meta (meses) | B6: 60 | C6: Em quanto tempo cada ativo deve atingir a meta (personalize na aba Meta)
A7: Aporte mensal | B7: 3000 | C7: Quanto você investe por mês (tempo até a meta)
A8: Peso ideal da renda variável | B8: 0.32 | C8: Ações + FIIs no patrimônio total
A11: Outras classes | B11: Valor (R$) | C11: Peso ideal no patrimônio
A12: Renda fixa (CDB) | B12: 45000 | C12: 0.5
A13: Internacional | B13: 12000 | C13: 0.15
A14: Cripto | B14: 2500 | C14: 0.03

Sheet Verificar
A1: InvestERP Pontos a Conferir
A3: Checagens automáticas feitas a cada geração — corrija em dados/.
A4: Gravidade | B4: Ativo | C4: O que foi encontrado
A5: INFO | B5: VALE3 | C5: Tendência de 3 anos com R² de 0,14: projeção por regressão pouco confiável.
A6: AVISO | B6: PETR4 | C6: Proventos 12m caíram 30% sobre o ano anterior — o DY atual pode não se repetir.
A7: INFO | B7: PETR4 | C7: Tendência de 3 anos com R² de 0,03: projeção por regressão pouco confiável.
A8: AVISO | B8: BBAS3 | C8: Proventos 12m caíram 62% sobre o ano anterior — o DY atual pode não se repetir.
A9: AVISO | B9: BRBI11 | C9: Proventos 12m caíram 33% sobre o ano anterior — o DY atual pode não se repetir.
A10: INFO | B10: BRBI11 | C10: Tendência de 3 anos com R² de 0,17: projeção por regressão pouco confiável.
A11: INFO | B11: XPML11 | C11: 1 cotação(ões) espúria(s) do Yahoo no histórico foram ignoradas na análise.
A12: INFO | B12: SNAG11 | C12: Tendência de 3 anos com R² de 0,03: projeção por regressão pouco confiável.

Sheet Base Painel
A1: Mês | B1: Proventos
A2: =DATE(YEAR(TODAY()),MONTH(TODAY())-11,1) | B2: =SUMIFS(Proventos!$F:$F,Proventos!$A:$A,">="&A2,Proventos!$A:$A,"<"&DATE(YEAR(A2),MONTH(A2)+1,1))
A3: =DATE(YEAR(TODAY()),MONTH(TODAY())-10,1) | B3: =SUMIFS(Proventos!$F:$F,Proventos!$A:$A,">="&A3,Proventos!$A:$A,"<"&DATE(YEAR(A3),MONTH(A3)+1,1))
A4: =DATE(YEAR(TODAY()),MONTH(TODAY())-9,1) | B4: =SUMIFS(Proventos!$F:$F,Proventos!$A:$A,">="&A4,Proventos!$A:$A,"<"&DATE(YEAR(A4),MONTH(A4)+1,1)) | D4: Ticker | G4: Ticker | H4: Posição | K4: Ticker | L4: Valorização | M4: Lucro | P4: Ticker | Q4: Valorização | R4: Lucro | U4: Ticker | V4: % da meta | Y4: Ticker | Z4: Proventos
A5: =DATE(YEAR(TODAY()),MONTH(TODAY())-8,1) | B5: =SUMIFS(Proventos!$F:$F,Proventos!$A:$A,">="&A5,Proventos!$A:$A,"<"&DATE(YEAR(A5),MONTH(A5)+1,1)) | D5: =Carteira!A5 | F5: =IF(AND(Carteira!AC5=1,OR(Carteira!C5>0,SUMIFS(Carteira!$C$5:$C$20,Carteira!$AC$5:$AC$20,1)=0)),N(Carteira!G5)+ROW()/1E9,"") | G5: =IFERROR(INDEX($D$5:$D$20,MATCH(LARGE($F$5:$F$20,1),$F$5:$F$20,0)),"") | H5: =IFERROR(INDEX(Carteira!$G$5:$G$20,MATCH(G5,Carteira!$A$5:$A$20,0)),"") | J5: =IF(AND(Carteira!AC5=1,OR(Carteira!C5>0,SUMIFS(Carteira!$C$5:$C$20,Carteira!$AC$5:$AC$20,1)=0)),N(Carteira!I5)+ROW()/1E9,"") | K5: =IFERROR(INDEX($D$5:$D$20,MATCH(LARGE($J$5:$J$20,1),$J$5:$J$20,0)),"") | L5: =IFERROR(INDEX(Carteira!$I$5:$I$20,MATCH(K5,Carteira!$A$5:$A$20,0)),"") | M5: =IFERROR(INDEX(Carteira!$H$5:$H$20,MATCH(K5,Carteira!$A$5:$A$20,0)),"") | O5: =IF(AND(Carteira!AC5=1,OR(Carteira!C5>0,SUMIFS(Carteira!$C$5:$C$20,Carteira!$AC$5:$AC$20,1)=0)),N(Carteira!I5)+ROW()/1E9,"") | P5: =IFERROR(INDEX($D$5:$D$20,MATCH(SMALL($O$5:$O$20,1),$O$5:$O$20,0)),"") | Q5: =IFERROR(INDEX(Carteira!$I$5:$I$20,MATCH(P5,Carteira!$A$5:$A$20,0)),"") | R5: =IFERROR(INDEX(Carteira!$H$5:$H$20,MATCH(P5,Carteira!$A$5:$A$20,0)),"") | T5: =IF(AND(Carteira!AC5=1,OR(Carteira!C5>0,SUMIFS(Carteira!$C$5:$C$20,Carteira!$AC$5:$AC$20,1)=0)),N(Carteira!W5)+ROW()/1E9,"") | U5: =IFERROR(INDEX($D$5:$D$20,MATCH(LARGE($T$5:$T$20,1),$T$5:$T$20,0)),"") | V5: =IFERROR(INDEX(Carteira!$W$5:$W$20,MATCH(U5,Carteira!$A$5:$A$20,0)),"") | X5: =IF(AND(Carteira!AC5=1,OR(Carteira!C5>0,SUMIFS(Carteira!$C$5:$C$20,Carteira!$AC$5:$AC$20,1)=0)),N(Carteira!J5)+ROW()/1E9,"") | Y5: =IFERROR(INDEX($D$5:$D$20,MATCH(LARGE($X$5:$X$20,1),$X$5:$X$20,0)),"") | Z5: =IFERROR(INDEX(Carteira!$J$5:$J$20,MATCH(Y5,Carteira!$A$5:$A$20,0)),"")
A6: =DATE(YEAR(TODAY()),MONTH(TODAY())-7,1) | B6: =SUMIFS(Proventos!$F:$F,Proventos!$A:$A,">="&A6,Proventos!$A:$A,"<"&DATE(YEAR(A6),MONTH(A6)+1,1)) | D6: =Carteira!A6 | F6: =IF(AND(Carteira!AC6=1,OR(Carteira!C6>0,SUMIFS(Carteira!$C$5:$C$20,Carteira!$AC$5:$AC$20,1)=0)),N(Carteira!G6)+ROW()/1E9,"") | G6: =IFERROR(INDEX($D$5:$D$20,MATCH(LARGE($F$5:$F$20,2),$F$5:$F$20,0)),"") | H6: =IFERROR(INDEX(Carteira!$G$5:$G$20,MATCH(G6,Carteira!$A$5:$A$20,0)),"") | J6: =IF(AND(Carteira!AC6=1,OR(Carteira!C6>0,SUMIFS(Carteira!$C$5:$C$20,Carteira!$AC$5:$AC$20,1)=0)),N(Carteira!I6)+ROW()/1E9,"") | K6: =IFERROR(INDEX($D$5:$D$20,MATCH(LARGE($J$5:$J$20,2),$J$5:$J$20,0)),"") | L6: =IFERROR(INDEX(Carteira!$I$5:$I$20,MATCH(K6,Carteira!$A$5:$A$20,0)),"") | M6: =IFERROR(INDEX(Carteira!$H$5:$H$20,MATCH(K6,Carteira!$A$5:$A$20,0)),"") | O6: =IF(AND(Carteira!AC6=1,OR(Carteira!C6>0,SUMIFS(Carteira!$C$5:$C$20,Carteira!$AC$5:$AC$20,1)=0)),N(Carteira!I6)+ROW()/1E9,"") | P6: =IFERROR(INDEX($D$5:$D$20,MATCH(SMALL($O$5:$O$20,2),$O$5:$O$20,0)),"") | Q6: =IFERROR(INDEX(Carteira!$I$5:$I$20,MATCH(P6,Carteira!$A$5:$A$20,0)),"") | R6: =IFERROR(INDEX(Carteira!$H$5:$H$20,MATCH(P6,Carteira!$A$5:$A$20,0)),"") | T6: =IF(AND(Carteira!AC6=1,OR(Carteira!C6>0,SUMIFS(Carteira!$C$5:$C$20,Carteira!$AC$5:$AC$20,1)=0)),N(Carteira!W6)+ROW()/1E9,"") | U6: =IFERROR(INDEX($D$5:$D$20,MATCH(LARGE($T$5:$T$20,2),$T$5:$T$20,0)),"") | V6: =IFERROR(INDEX(Carteira!$W$5:$W$20,MATCH(U6,Carteira!$A$5:$A$20,0)),"") | X6: =IF(AND(Carteira!AC6=1,OR(Carteira!C6>0,SUMIFS(Carteira!$C$5:$C$20,Carteira!$AC$5:$AC$20,1)=0)),N(Carteira!J6)+ROW()/1E9,"") | Y6: =IFERROR(INDEX($D$5:$D$20,MATCH(LARGE($X$5:$X$20,2),$X$5:$X$20,0)),"") | Z6: =IFERROR(INDEX(Carteira!$J$5:$J$20,MATCH(Y6,Carteira!$A$5:$A$20,0)),"")
A7: =DATE(YEAR(TODAY()),MONTH(TODAY())-6,1) | B7: =SUMIFS(Proventos!$F:$F,Proventos!$A:$A,">="&A7,Proventos!$A:$A,"<"&DATE(YEAR(A7),MONTH(A7)+1,1)) | D7: =Carteira!A7 | F7: =IF(AND(Carteira!AC7=1,OR(Carteira!C7>0,SUMIFS(Carteira!$C$5:$C$20,Carteira!$AC$5:$AC$20,1)=0)),N(Carteira!G7)+ROW()/1E9,"") | G7: =IFERROR(INDEX($D$5:$D$20,MATCH(LARGE($F$5:$F$20,3),$F$5:$F$20,0)),"") | H7: =IFERROR(INDEX(Carteira!$G$5:$G$20,MATCH(G7,Carteira!$A$5:$A$20,0)),"") | J7: =IF(AND(Carteira!AC7=1,OR(Carteira!C7>0,SUMIFS(Carteira!$C$5:$C$20,Carteira!$AC$5:$AC$20,1)=0)),N(Carteira!I7)+ROW()/1E9,"") | K7: =IFERROR(INDEX($D$5:$D$20,MATCH(LARGE($J$5:$J$20,3),$J$5:$J$20,0)),"") | L7: =IFERROR(INDEX(Carteira!$I$5:$I$20,MATCH(K7,Carteira!$A$5:$A$20,0)),"") | M7: =IFERROR(INDEX(Carteira!$H$5:$H$20,MATCH(K7,Carteira!$A$5:$A$20,0)),"") | O7: =IF(AND(Carteira!AC7=1,OR(Carteira!C7>0,SUMIFS(Carteira!$C$5:$C$20,Carteira!$AC$5:$AC$20,1)=0)),N(Carteira!I7)+ROW()/1E9,"") | P7: =IFERROR(INDEX($D$5:$D$20,MATCH(SMALL($O$5:$O$20,3),$O$5:$O$20,0)),"") | Q7: =IFERROR(INDEX(Carteira!$I$5:$I$20,MATCH(P7,Carteira!$A$5:$A$20,0)),"") | R7: =IFERROR(INDEX(Carteira!$H$5:$H$20,MATCH(P7,Carteira!$A$5:$A$20,0)),"") | T7: =IF(AND(Carteira!AC7=1,OR(Carteira!C7>0,SUMIFS(Carteira!$C$5:$C$20,Carteira!$AC$5:$AC$20,1)=0)),N(Carteira!W7)+ROW()/1E9,"") | U7: =IFERROR(INDEX($D$5:$D$20,MATCH(LARGE($T$5:$T$20,3),$T$5:$T$20,0)),"") | V7: =IFERROR(INDEX(Carteira!$W$5:$W$20,MATCH(U7,Carteira!$A$5:$A$20,0)),"") | X7: =IF(AND(Carteira!AC7=1,OR(Carteira!C7>0,SUMIFS(Carteira!$C$5:$C$20,Carteira!$AC$5:$AC$20,1)=0)),N(Carteira!J7)+ROW()/1E9,"") | Y7: =IFERROR(INDEX($D$5:$D$20,MATCH(LARGE($X$5:$X$20,3),$X$5:$X$20,0)),"") | Z7: =IFERROR(INDEX(Carteira!$J$5:$J$20,MATCH(Y7,Carteira!$A$5:$A$20,0)),"")
A8: =DATE(YEAR(TODAY()),MONTH(TODAY())-5,1) | B8: =SUMIFS(Proventos!$F:$F,Proventos!$A:$A,">="&A8,Proventos!$A:$A,"<"&DATE(YEAR(A8),MONTH(A8)+1,1)) | D8: =Carteira!A8 | F8: =IF(AND(Carteira!AC8=1,OR(Carteira!C8>0,SUMIFS(Carteira!$C$5:$C$20,Carteira!$AC$5:$AC$20,1)=0)),N(Carteira!G8)+ROW()/1E9,"") | G8: =IFERROR(INDEX($D$5:$D$20,MATCH(LARGE($F$5:$F$20,4),$F$5:$F$20,0)),"") | H8: =IFERROR(INDEX(Carteira!$G$5:$G$20,MATCH(G8,Carteira!$A$5:$A$20,0)),"") | J8: =IF(AND(Carteira!AC8=1,OR(Carteira!C8>0,SUMIFS(Carteira!$C$5:$C$20,Carteira!$AC$5:$AC$20,1)=0)),N(Carteira!I8)+ROW()/1E9,"") | K8: =IFERROR(INDEX($D$5:$D$20,MATCH(LARGE($J$5:$J$20,4),$J$5:$J$20,0)),"") | L8: =IFERROR(INDEX(Carteira!$I$5:$I$20,MATCH(K8,Carteira!$A$5:$A$20,0)),"") | M8: =IFERROR(INDEX(Carteira!$H$5:$H$20,MATCH(K8,Carteira!$A$5:$A$20,0)),"") | O8: =IF(AND(Carteira!AC8=1,OR(Carteira!C8>0,SUMIFS(Carteira!$C$5:$C$20,Carteira!$AC$5:$AC$20,1)=0)),N(Carteira!I8)+ROW()/1E9,"") | P8: =IFERROR(INDEX($D$5:$D$20,MATCH(SMALL($O$5:$O$20,4),$O$5:$O$20,0)),"") | Q8: =IFERROR(INDEX(Carteira!$I$5:$I$20,MATCH(P8,Carteira!$A$5:$A$20,0)),"") | R8: =IFERROR(INDEX(Carteira!$H$5:$H$20,MATCH(P8,Carteira!$A$5:$A$20,0)),"") | T8: =IF(AND(Carteira!AC8=1,OR(Carteira!C8>0,SUMIFS(Carteira!$C$5:$C$20,Carteira!$AC$5:$AC$20,1)=0)),N(Carteira!W8)+ROW()/1E9,"") | U8: =IFERROR(INDEX($D$5:$D$20,MATCH(LARGE($T$5:$T$20,4),$T$5:$T$20,0)),"") | V8: =IFERROR(INDEX(Carteira!$W$5:$W$20,MATCH(U8,Carteira!$A$5:$A$20,0)),"") | X8: =IF(AND(Carteira!AC8=1,OR(Carteira!C8>0,SUMIFS(Carteira!$C$5:$C$20,Carteira!$AC$5:$AC$20,1)=0)),N(Carteira!J8)+ROW()/1E9,"") | Y8: =IFERROR(INDEX($D$5:$D$20,MATCH(LARGE($X$5:$X$20,4),$X$5:$X$20,0)),"") | Z8: =IFERROR(INDEX(Carteira!$J$5:$J$20,MATCH(Y8,Carteira!$A$5:$A$20,0)),"")
A9: =DATE(YEAR(TODAY()),MONTH(TODAY())-4,1) | B9: =SUMIFS(Proventos!$F:$F,Proventos!$A:$A,">="&A9,Proventos!$A:$A,"<"&DATE(YEAR(A9),MONTH(A9)+1,1)) | D9: =Carteira!A9 | F9: =IF(AND(Carteira!AC9=1,OR(Carteira!C9>0,SUMIFS(Carteira!$C$5:$C$20,Carteira!$AC$5:$AC$20,1)=0)),N(Carteira!G9)+ROW()/1E9,"") | G9: =IFERROR(INDEX($D$5:$D$20,MATCH(LARGE($F$5:$F$20,5),$F$5:$F$20,0)),"") | H9: =IFERROR(INDEX(Carteira!$G$5:$G$20,MATCH(G9,Carteira!$A$5:$A$20,0)),"") | J9: =IF(AND(Carteira!AC9=1,OR(Carteira!C9>0,SUMIFS(Carteira!$C$5:$C$20,Carteira!$AC$5:$AC$20,1)=0)),N(Carteira!I9)+ROW()/1E9,"") | K9: =IFERROR(INDEX($D$5:$D$20,MATCH(LARGE($J$5:$J$20,5),$J$5:$J$20,0)),"") | L9: =IFERROR(INDEX(Carteira!$I$5:$I$20,MATCH(K9,Carteira!$A$5:$A$20,0)),"") | M9: =IFERROR(INDEX(Carteira!$H$5:$H$20,MATCH(K9,Carteira!$A$5:$A$20,0)),"") | O9: =IF(AND(Carteira!AC9=1,OR(Carteira!C9>0,SUMIFS(Carteira!$C$5:$C$20,Carteira!$AC$5:$AC$20,1)=0)),N(Carteira!I9)+ROW()/1E9,"") | P9: =IFERROR(INDEX($D$5:$D$20,MATCH(SMALL($O$5:$O$20,5),$O$5:$O$20,0)),"") | Q9: =IFERROR(INDEX(Carteira!$I$5:$I$20,MATCH(P9,Carteira!$A$5:$A$20,0)),"") | R9: =IFERROR(INDEX(Carteira!$H$5:$H$20,MATCH(P9,Carteira!$A$5:$A$20,0)),"") | T9: =IF(AND(Carteira!AC9=1,OR(Carteira!C9>0,SUMIFS(Carteira!$C$5:$C$20,Carteira!$AC$5:$AC$20,1)=0)),N(Carteira!W9)+ROW()/1E9,"") | U9: =IFERROR(INDEX($D$5:$D$20,MATCH(LARGE($T$5:$T$20,5),$T$5:$T$20,0)),"") | V9: =IFERROR(INDEX(Carteira!$W$5:$W$20,MATCH(U9,Carteira!$A$5:$A$20,0)),"") | X9: =IF(AND(Carteira!AC9=1,OR(Carteira!C9>0,SUMIFS(Carteira!$C$5:$C$20,Carteira!$AC$5:$AC$20,1)=0)),N(Carteira!J9)+ROW()/1E9,"") | Y9: =IFERROR(INDEX($D$5:$D$20,MATCH(LARGE($X$5:$X$20,5),$X$5:$X$20,0)),"") | Z9: =IFERROR(INDEX(Carteira!$J$5:$J$20,MATCH(Y9,Carteira!$A$5:$A$20,0)),"")
A10: =DATE(YEAR(TODAY()),MONTH(TODAY())-3,1) | B10: =SUMIFS(Proventos!$F:$F,Proventos!$A:$A,">="&A10,Proventos!$A:$A,"<"&DATE(YEAR(A10),MONTH(A10)+1,1)) | D10: =Carteira!A10 | F10: =IF(AND(Carteira!AC10=1,OR(Carteira!C10>0,SUMIFS(Carteira!$C$5:$C$20,Carteira!$AC$5:$AC$20,1)=0)),N(Carteira!G10)+ROW()/1E9,"") | G10: =IFERROR(INDEX($D$5:$D$20,MATCH(LARGE($F$5:$F$20,6),$F$5:$F$20,0)),"") | H10: =IFERROR(INDEX(Carteira!$G$5:$G$20,MATCH(G10,Carteira!$A$5:$A$20,0)),"") | J10: =IF(AND(Carteira!AC10=1,OR(Carteira!C10>0,SUMIFS(Carteira!$C$5:$C$20,Carteira!$AC$5:$AC$20,1)=0)),N(Carteira!I10)+ROW()/1E9,"") | K10: =IFERROR(INDEX($D$5:$D$20,MATCH(LARGE($J$5:$J$20,6),$J$5:$J$20,0)),"") | L10: =IFERROR(INDEX(Carteira!$I$5:$I$20,MATCH(K10,Carteira!$A$5:$A$20,0)),"") | M10: =IFERROR(INDEX(Carteira!$H$5:$H$20,MATCH(K10,Carteira!$A$5:$A$20,0)),"") | O10: =IF(AND(Carteira!AC10=1,OR(Carteira!C10>0,SUMIFS(Carteira!$C$5:$C$20,Carteira!$AC$5:$AC$20,1)=0)),N(Carteira!I10)+ROW()/1E9,"") | P10: =IFERROR(INDEX($D$5:$D$20,MATCH(SMALL($O$5:$O$20,6),$O$5:$O$20,0)),"") | Q10: =IFERROR(INDEX(Carteira!$I$5:$I$20,MATCH(P10,Carteira!$A$5:$A$20,0)),"") | R10: =IFERROR(INDEX(Carteira!$H$5:$H$20,MATCH(P10,Carteira!$A$5:$A$20,0)),"") | T10: =IF(AND(Carteira!AC10=1,OR(Carteira!C10>0,SUMIFS(Carteira!$C$5:$C$20,Carteira!$AC$5:$AC$20,1)=0)),N(Carteira!W10)+ROW()/1E9,"") | U10: =IFERROR(INDEX($D$5:$D$20,MATCH(LARGE($T$5:$T$20,6),$T$5:$T$20,0)),"") | V10: =IFERROR(INDEX(Carteira!$W$5:$W$20,MATCH(U10,Carteira!$A$5:$A$20,0)),"") | X10: =IF(AND(Carteira!AC10=1,OR(Carteira!C10>0,SUMIFS(Carteira!$C$5:$C$20,Carteira!$AC$5:$AC$20,1)=0)),N(Carteira!J10)+ROW()/1E9,"") | Y10: =IFERROR(INDEX($D$5:$D$20,MATCH(LARGE($X$5:$X$20,6),$X$5:$X$20,0)),"") | Z10: =IFERROR(INDEX(Carteira!$J$5:$J$20,MATCH(Y10,Carteira!$A$5:$A$20,0)),"")
A11: =DATE(YEAR(TODAY()),MONTH(TODAY())-2,1) | B11: =SUMIFS(Proventos!$F:$F,Proventos!$A:$A,">="&A11,Proventos!$A:$A,"<"&DATE(YEAR(A11),MONTH(A11)+1,1)) | D11: =Carteira!A11 | F11: =IF(AND(Carteira!AC11=1,OR(Carteira!C11>0,SUMIFS(Carteira!$C$5:$C$20,Carteira!$AC$5:$AC$20,1)=0)),N(Carteira!G11)+ROW()/1E9,"") | G11: =IFERROR(INDEX($D$5:$D$20,MATCH(LARGE($F$5:$F$20,7),$F$5:$F$20,0)),"") | H11: =IFERROR(INDEX(Carteira!$G$5:$G$20,MATCH(G11,Carteira!$A$5:$A$20,0)),"") | J11: =IF(AND(Carteira!AC11=1,OR(Carteira!C11>0,SUMIFS(Carteira!$C$5:$C$20,Carteira!$AC$5:$AC$20,1)=0)),N(Carteira!I11)+ROW()/1E9,"") | K11: =IFERROR(INDEX($D$5:$D$20,MATCH(LARGE($J$5:$J$20,7),$J$5:$J$20,0)),"") | L11: =IFERROR(INDEX(Carteira!$I$5:$I$20,MATCH(K11,Carteira!$A$5:$A$20,0)),"") | M11: =IFERROR(INDEX(Carteira!$H$5:$H$20,MATCH(K11,Carteira!$A$5:$A$20,0)),"") | O11: =IF(AND(Carteira!AC11=1,OR(Carteira!C11>0,SUMIFS(Carteira!$C$5:$C$20,Carteira!$AC$5:$AC$20,1)=0)),N(Carteira!I11)+ROW()/1E9,"") | P11: =IFERROR(INDEX($D$5:$D$20,MATCH(SMALL($O$5:$O$20,7),$O$5:$O$20,0)),"") | Q11: =IFERROR(INDEX(Carteira!$I$5:$I$20,MATCH(P11,Carteira!$A$5:$A$20,0)),"") | R11: =IFERROR(INDEX(Carteira!$H$5:$H$20,MATCH(P11,Carteira!$A$5:$A$20,0)),"") | T11: =IF(AND(Carteira!AC11=1,OR(Carteira!C11>0,SUMIFS(Carteira!$C$5:$C$20,Carteira!$AC$5:$AC$20,1)=0)),N(Carteira!W11)+ROW()/1E9,"") | U11: =IFERROR(INDEX($D$5:$D$20,MATCH(LARGE($T$5:$T$20,7),$T$5:$T$20,0)),"") | V11: =IFERROR(INDEX(Carteira!$W$5:$W$20,MATCH(U11,Carteira!$A$5:$A$20,0)),"") | X11: =IF(AND(Carteira!AC11=1,OR(Carteira!C11>0,SUMIFS(Carteira!$C$5:$C$20,Carteira!$AC$5:$AC$20,1)=0)),N(Carteira!J11)+ROW()/1E9,"") | Y11: =IFERROR(INDEX($D$5:$D$20,MATCH(LARGE($X$5:$X$20,7),$X$5:$X$20,0)),"") | Z11: =IFERROR(INDEX(Carteira!$J$5:$J$20,MATCH(Y11,Carteira!$A$5:$A$20,0)),"")
A12: =DATE(YEAR(TODAY()),MONTH(TODAY())-1,1) | B12: =SUMIFS(Proventos!$F:$F,Proventos!$A:$A,">="&A12,Proventos!$A:$A,"<"&DATE(YEAR(A12),MONTH(A12)+1,1)) | D12: =Carteira!A12 | F12: =IF(AND(Carteira!AC12=1,OR(Carteira!C12>0,SUMIFS(Carteira!$C$5:$C$20,Carteira!$AC$5:$AC$20,1)=0)),N(Carteira!G12)+ROW()/1E9,"") | G12: =IFERROR(INDEX($D$5:$D$20,MATCH(LARGE($F$5:$F$20,8),$F$5:$F$20,0)),"") | H12: =IFERROR(INDEX(Carteira!$G$5:$G$20,MATCH(G12,Carteira!$A$5:$A$20,0)),"") | J12: =IF(AND(Carteira!AC12=1,OR(Carteira!C12>0,SUMIFS(Carteira!$C$5:$C$20,Carteira!$AC$5:$AC$20,1)=0)),N(Carteira!I12)+ROW()/1E9,"") | K12: =IFERROR(INDEX($D$5:$D$20,MATCH(LARGE($J$5:$J$20,8),$J$5:$J$20,0)),"") | L12: =IFERROR(INDEX(Carteira!$I$5:$I$20,MATCH(K12,Carteira!$A$5:$A$20,0)),"") | M12: =IFERROR(INDEX(Carteira!$H$5:$H$20,MATCH(K12,Carteira!$A$5:$A$20,0)),"") | O12: =IF(AND(Carteira!AC12=1,OR(Carteira!C12>0,SUMIFS(Carteira!$C$5:$C$20,Carteira!$AC$5:$AC$20,1)=0)),N(Carteira!I12)+ROW()/1E9,"") | P12: =IFERROR(INDEX($D$5:$D$20,MATCH(SMALL($O$5:$O$20,8),$O$5:$O$20,0)),"") | Q12: =IFERROR(INDEX(Carteira!$I$5:$I$20,MATCH(P12,Carteira!$A$5:$A$20,0)),"") | R12: =IFERROR(INDEX(Carteira!$H$5:$H$20,MATCH(P12,Carteira!$A$5:$A$20,0)),"") | T12: =IF(AND(Carteira!AC12=1,OR(Carteira!C12>0,SUMIFS(Carteira!$C$5:$C$20,Carteira!$AC$5:$AC$20,1)=0)),N(Carteira!W12)+ROW()/1E9,"") | U12: =IFERROR(INDEX($D$5:$D$20,MATCH(LARGE($T$5:$T$20,8),$T$5:$T$20,0)),"") | V12: =IFERROR(INDEX(Carteira!$W$5:$W$20,MATCH(U12,Carteira!$A$5:$A$20,0)),"") | X12: =IF(AND(Carteira!AC12=1,OR(Carteira!C12>0,SUMIFS(Carteira!$C$5:$C$20,Carteira!$AC$5:$AC$20,1)=0)),N(Carteira!J12)+ROW()/1E9,"") | Y12: =IFERROR(INDEX($D$5:$D$20,MATCH(LARGE($X$5:$X$20,8),$X$5:$X$20,0)),"") | Z12: =IFERROR(INDEX(Carteira!$J$5:$J$20,MATCH(Y12,Carteira!$A$5:$A$20,0)),"")
A13: =DATE(YEAR(TODAY()),MONTH(TODAY())-0,1) | B13: =SUMIFS(Proventos!$F:$F,Proventos!$A:$A,">="&A13,Proventos!$A:$A,"<"&DATE(YEAR(A13),MONTH(A13)+1,1)) | D13: =Carteira!A13 | F13: =IF(AND(Carteira!AC13=1,OR(Carteira!C13>0,SUMIFS(Carteira!$C$5:$C$20,Carteira!$AC$5:$AC$20,1)=0)),N(Carteira!G13)+ROW()/1E9,"") | G13: =IFERROR(INDEX($D$5:$D$20,MATCH(LARGE($F$5:$F$20,9),$F$5:$F$20,0)),"") | H13: =IFERROR(INDEX(Carteira!$G$5:$G$20,MATCH(G13,Carteira!$A$5:$A$20,0)),"") | J13: =IF(AND(Carteira!AC13=1,OR(Carteira!C13>0,SUMIFS(Carteira!$C$5:$C$20,Carteira!$AC$5:$AC$20,1)=0)),N(Carteira!I13)+ROW()/1E9,"") | K13: =IFERROR(INDEX($D$5:$D$20,MATCH(LARGE($J$5:$J$20,9),$J$5:$J$20,0)),"") | L13: =IFERROR(INDEX(Carteira!$I$5:$I$20,MATCH(K13,Carteira!$A$5:$A$20,0)),"") | M13: =IFERROR(INDEX(Carteira!$H$5:$H$20,MATCH(K13,Carteira!$A$5:$A$20,0)),"") | O13: =IF(AND(Carteira!AC13=1,OR(Carteira!C13>0,SUMIFS(Carteira!$C$5:$C$20,Carteira!$AC$5:$AC$20,1)=0)),N(Carteira!I13)+ROW()/1E9,"") | P13: =IFERROR(INDEX($D$5:$D$20,MATCH(SMALL($O$5:$O$20,9),$O$5:$O$20,0)),"") | Q13: =IFERROR(INDEX(Carteira!$I$5:$I$20,MATCH(P13,Carteira!$A$5:$A$20,0)),"") | R13: =IFERROR(INDEX(Carteira!$H$5:$H$20,MATCH(P13,Carteira!$A$5:$A$20,0)),"") | T13: =IF(AND(Carteira!AC13=1,OR(Carteira!C13>0,SUMIFS(Carteira!$C$5:$C$20,Carteira!$AC$5:$AC$20,1)=0)),N(Carteira!W13)+ROW()/1E9,"") | U13: =IFERROR(INDEX($D$5:$D$20,MATCH(LARGE($T$5:$T$20,9),$T$5:$T$20,0)),"") | V13: =IFERROR(INDEX(Carteira!$W$5:$W$20,MATCH(U13,Carteira!$A$5:$A$20,0)),"") | X13: =IF(AND(Carteira!AC13=1,OR(Carteira!C13>0,SUMIFS(Carteira!$C$5:$C$20,Carteira!$AC$5:$AC$20,1)=0)),N(Carteira!J13)+ROW()/1E9,"") | Y13: =IFERROR(INDEX($D$5:$D$20,MATCH(LARGE($X$5:$X$20,9),$X$5:$X$20,0)),"") | Z13: =IFERROR(INDEX(Carteira!$J$5:$J$20,MATCH(Y13,Carteira!$A$5:$A$20,0)),"")
D14: =Carteira!A14 | F14: =IF(AND(Carteira!AC14=1,OR(Carteira!C14>0,SUMIFS(Carteira!$C$5:$C$20,Carteira!$AC$5:$AC$20,1)=0)),N(Carteira!G14)+ROW()/1E9,"") | G14: =IFERROR(INDEX($D$5:$D$20,MATCH(LARGE($F$5:$F$20,10),$F$5:$F$20,0)),"") | H14: =IFERROR(INDEX(Carteira!$G$5:$G$20,MATCH(G14,Carteira!$A$5:$A$20,0)),"") | J14: =IF(AND(Carteira!AC14=1,OR(Carteira!C14>0,SUMIFS(Carteira!$C$5:$C$20,Carteira!$AC$5:$AC$20,1)=0)),N(Carteira!I14)+ROW()/1E9,"") | K14: =IFERROR(INDEX($D$5:$D$20,MATCH(LARGE($J$5:$J$20,10),$J$5:$J$20,0)),"") | L14: =IFERROR(INDEX(Carteira!$I$5:$I$20,MATCH(K14,Carteira!$A$5:$A$20,0)),"") | M14: =IFERROR(INDEX(Carteira!$H$5:$H$20,MATCH(K14,Carteira!$A$5:$A$20,0)),"") | O14: =IF(AND(Carteira!AC14=1,OR(Carteira!C14>0,SUMIFS(Carteira!$C$5:$C$20,Carteira!$AC$5:$AC$20,1)=0)),N(Carteira!I14)+ROW()/1E9,"") | P14: =IFERROR(INDEX($D$5:$D$20,MATCH(SMALL($O$5:$O$20,10),$O$5:$O$20,0)),"") | Q14: =IFERROR(INDEX(Carteira!$I$5:$I$20,MATCH(P14,Carteira!$A$5:$A$20,0)),"") | R14: =IFERROR(INDEX(Carteira!$H$5:$H$20,MATCH(P14,Carteira!$A$5:$A$20,0)),"") | T14: =IF(AND(Carteira!AC14=1,OR(Carteira!C14>0,SUMIFS(Carteira!$C$5:$C$20,Carteira!$AC$5:$AC$20,1)=0)),N(Carteira!W14)+ROW()/1E9,"") | U14: =IFERROR(INDEX($D$5:$D$20,MATCH(LARGE($T$5:$T$20,10),$T$5:$T$20,0)),"") | V14: =IFERROR(INDEX(Carteira!$W$5:$W$20,MATCH(U14,Carteira!$A$5:$A$20,0)),"") | X14: =IF(AND(Carteira!AC14=1,OR(Carteira!C14>0,SUMIFS(Carteira!$C$5:$C$20,Carteira!$AC$5:$AC$20,1)=0)),N(Carteira!J14)+ROW()/1E9,"") | Y14: =IFERROR(INDEX($D$5:$D$20,MATCH(LARGE($X$5:$X$20,10),$X$5:$X$20,0)),"") | Z14: =IFERROR(INDEX(Carteira!$J$5:$J$20,MATCH(Y14,Carteira!$A$5:$A$20,0)),"")
D15: =Carteira!A15 | F15: =IF(AND(Carteira!AC15=1,OR(Carteira!C15>0,SUMIFS(Carteira!$C$5:$C$20,Carteira!$AC$5:$AC$20,1)=0)),N(Carteira!G15)+ROW()/1E9,"") | G15: =IFERROR(INDEX($D$5:$D$20,MATCH(LARGE($F$5:$F$20,11),$F$5:$F$20,0)),"") | H15: =IFERROR(INDEX(Carteira!$G$5:$G$20,MATCH(G15,Carteira!$A$5:$A$20,0)),"") | J15: =IF(AND(Carteira!AC15=1,OR(Carteira!C15>0,SUMIFS(Carteira!$C$5:$C$20,Carteira!$AC$5:$AC$20,1)=0)),N(Carteira!I15)+ROW()/1E9,"") | K15: =IFERROR(INDEX($D$5:$D$20,MATCH(LARGE($J$5:$J$20,11),$J$5:$J$20,0)),"") | L15: =IFERROR(INDEX(Carteira!$I$5:$I$20,MATCH(K15,Carteira!$A$5:$A$20,0)),"") | M15: =IFERROR(INDEX(Carteira!$H$5:$H$20,MATCH(K15,Carteira!$A$5:$A$20,0)),"") | O15: =IF(AND(Carteira!AC15=1,OR(Carteira!C15>0,SUMIFS(Carteira!$C$5:$C$20,Carteira!$AC$5:$AC$20,1)=0)),N(Carteira!I15)+ROW()/1E9,"") | P15: =IFERROR(INDEX($D$5:$D$20,MATCH(SMALL($O$5:$O$20,11),$O$5:$O$20,0)),"") | Q15: =IFERROR(INDEX(Carteira!$I$5:$I$20,MATCH(P15,Carteira!$A$5:$A$20,0)),"") | R15: =IFERROR(INDEX(Carteira!$H$5:$H$20,MATCH(P15,Carteira!$A$5:$A$20,0)),"") | T15: =IF(AND(Carteira!AC15=1,OR(Carteira!C15>0,SUMIFS(Carteira!$C$5:$C$20,Carteira!$AC$5:$AC$20,1)=0)),N(Carteira!W15)+ROW()/1E9,"") | U15: =IFERROR(INDEX($D$5:$D$20,MATCH(LARGE($T$5:$T$20,11),$T$5:$T$20,0)),"") | V15: =IFERROR(INDEX(Carteira!$W$5:$W$20,MATCH(U15,Carteira!$A$5:$A$20,0)),"") | X15: =IF(AND(Carteira!AC15=1,OR(Carteira!C15>0,SUMIFS(Carteira!$C$5:$C$20,Carteira!$AC$5:$AC$20,1)=0)),N(Carteira!J15)+ROW()/1E9,"") | Y15: =IFERROR(INDEX($D$5:$D$20,MATCH(LARGE($X$5:$X$20,11),$X$5:$X$20,0)),"") | Z15: =IFERROR(INDEX(Carteira!$J$5:$J$20,MATCH(Y15,Carteira!$A$5:$A$20,0)),"")
A16: Tipo | B16: Posição | D16: =Carteira!A16 | F16: =IF(AND(Carteira!AC16=1,OR(Carteira!C16>0,SUMIFS(Carteira!$C$5:$C$20,Carteira!$AC$5:$AC$20,1)=0)),N(Carteira!G16)+ROW()/1E9,"") | G16: =IFERROR(INDEX($D$5:$D$20,MATCH(LARGE($F$5:$F$20,12),$F$5:$F$20,0)),"") | H16: =IFERROR(INDEX(Carteira!$G$5:$G$20,MATCH(G16,Carteira!$A$5:$A$20,0)),"") | J16: =IF(AND(Carteira!AC16=1,OR(Carteira!C16>0,SUMIFS(Carteira!$C$5:$C$20,Carteira!$AC$5:$AC$20,1)=0)),N(Carteira!I16)+ROW()/1E9,"") | K16: =IFERROR(INDEX($D$5:$D$20,MATCH(LARGE($J$5:$J$20,12),$J$5:$J$20,0)),"") | L16: =IFERROR(INDEX(Carteira!$I$5:$I$20,MATCH(K16,Carteira!$A$5:$A$20,0)),"") | M16: =IFERROR(INDEX(Carteira!$H$5:$H$20,MATCH(K16,Carteira!$A$5:$A$20,0)),"") | O16: =IF(AND(Carteira!AC16=1,OR(Carteira!C16>0,SUMIFS(Carteira!$C$5:$C$20,Carteira!$AC$5:$AC$20,1)=0)),N(Carteira!I16)+ROW()/1E9,"") | P16: =IFERROR(INDEX($D$5:$D$20,MATCH(SMALL($O$5:$O$20,12),$O$5:$O$20,0)),"") | Q16: =IFERROR(INDEX(Carteira!$I$5:$I$20,MATCH(P16,Carteira!$A$5:$A$20,0)),"") | R16: =IFERROR(INDEX(Carteira!$H$5:$H$20,MATCH(P16,Carteira!$A$5:$A$20,0)),"") | T16: =IF(AND(Carteira!AC16=1,OR(Carteira!C16>0,SUMIFS(Carteira!$C$5:$C$20,Carteira!$AC$5:$AC$20,1)=0)),N(Carteira!W16)+ROW()/1E9,"") | U16: =IFERROR(INDEX($D$5:$D$20,MATCH(LARGE($T$5:$T$20,12),$T$5:$T$20,0)),"") | V16: =IFERROR(INDEX(Carteira!$W$5:$W$20,MATCH(U16,Carteira!$A$5:$A$20,0)),"") | X16: =IF(AND(Carteira!AC16=1,OR(Carteira!C16>0,SUMIFS(Carteira!$C$5:$C$20,Carteira!$AC$5:$AC$20,1)=0)),N(Carteira!J16)+ROW()/1E9,"") | Y16: =IFERROR(INDEX($D$5:$D$20,MATCH(LARGE($X$5:$X$20,12),$X$5:$X$20,0)),"") | Z16: =IFERROR(INDEX(Carteira!$J$5:$J$20,MATCH(Y16,Carteira!$A$5:$A$20,0)),"")
A17: Ações | B17: =Carteira!G23 | D17: =Carteira!A17 | F17: =IF(AND(Carteira!AC17=1,OR(Carteira!C17>0,SUMIFS(Carteira!$C$5:$C$20,Carteira!$AC$5:$AC$20,1)=0)),N(Carteira!G17)+ROW()/1E9,"") | G17: =IFERROR(INDEX($D$5:$D$20,MATCH(LARGE($F$5:$F$20,13),$F$5:$F$20,0)),"") | H17: =IFERROR(INDEX(Carteira!$G$5:$G$20,MATCH(G17,Carteira!$A$5:$A$20,0)),"") | J17: =IF(AND(Carteira!AC17=1,OR(Carteira!C17>0,SUMIFS(Carteira!$C$5:$C$20,Carteira!$AC$5:$AC$20,1)=0)),N(Carteira!I17)+ROW()/1E9,"") | K17: =IFERROR(INDEX($D$5:$D$20,MATCH(LARGE($J$5:$J$20,13),$J$5:$J$20,0)),"") | L17: =IFERROR(INDEX(Carteira!$I$5:$I$20,MATCH(K17,Carteira!$A$5:$A$20,0)),"") | M17: =IFERROR(INDEX(Carteira!$H$5:$H$20,MATCH(K17,Carteira!$A$5:$A$20,0)),"") | O17: =IF(AND(Carteira!AC17=1,OR(Carteira!C17>0,SUMIFS(Carteira!$C$5:$C$20,Carteira!$AC$5:$AC$20,1)=0)),N(Carteira!I17)+ROW()/1E9,"") | P17: =IFERROR(INDEX($D$5:$D$20,MATCH(SMALL($O$5:$O$20,13),$O$5:$O$20,0)),"") | Q17: =IFERROR(INDEX(Carteira!$I$5:$I$20,MATCH(P17,Carteira!$A$5:$A$20,0)),"") | R17: =IFERROR(INDEX(Carteira!$H$5:$H$20,MATCH(P17,Carteira!$A$5:$A$20,0)),"") | T17: =IF(AND(Carteira!AC17=1,OR(Carteira!C17>0,SUMIFS(Carteira!$C$5:$C$20,Carteira!$AC$5:$AC$20,1)=0)),N(Carteira!W17)+ROW()/1E9,"") | U17: =IFERROR(INDEX($D$5:$D$20,MATCH(LARGE($T$5:$T$20,13),$T$5:$T$20,0)),"") | V17: =IFERROR(INDEX(Carteira!$W$5:$W$20,MATCH(U17,Carteira!$A$5:$A$20,0)),"") | X17: =IF(AND(Carteira!AC17=1,OR(Carteira!C17>0,SUMIFS(Carteira!$C$5:$C$20,Carteira!$AC$5:$AC$20,1)=0)),N(Carteira!J17)+ROW()/1E9,"") | Y17: =IFERROR(INDEX($D$5:$D$20,MATCH(LARGE($X$5:$X$20,13),$X$5:$X$20,0)),"") | Z17: =IFERROR(INDEX(Carteira!$J$5:$J$20,MATCH(Y17,Carteira!$A$5:$A$20,0)),"")
A18: FIIs | B18: =Carteira!G24 | D18: =Carteira!A18 | F18: =IF(AND(Carteira!AC18=1,OR(Carteira!C18>0,SUMIFS(Carteira!$C$5:$C$20,Carteira!$AC$5:$AC$20,1)=0)),N(Carteira!G18)+ROW()/1E9,"") | G18: =IFERROR(INDEX($D$5:$D$20,MATCH(LARGE($F$5:$F$20,14),$F$5:$F$20,0)),"") | H18: =IFERROR(INDEX(Carteira!$G$5:$G$20,MATCH(G18,Carteira!$A$5:$A$20,0)),"") | J18: =IF(AND(Carteira!AC18=1,OR(Carteira!C18>0,SUMIFS(Carteira!$C$5:$C$20,Carteira!$AC$5:$AC$20,1)=0)),N(Carteira!I18)+ROW()/1E9,"") | K18: =IFERROR(INDEX($D$5:$D$20,MATCH(LARGE($J$5:$J$20,14),$J$5:$J$20,0)),"") | L18: =IFERROR(INDEX(Carteira!$I$5:$I$20,MATCH(K18,Carteira!$A$5:$A$20,0)),"") | M18: =IFERROR(INDEX(Carteira!$H$5:$H$20,MATCH(K18,Carteira!$A$5:$A$20,0)),"") | O18: =IF(AND(Carteira!AC18=1,OR(Carteira!C18>0,SUMIFS(Carteira!$C$5:$C$20,Carteira!$AC$5:$AC$20,1)=0)),N(Carteira!I18)+ROW()/1E9,"") | P18: =IFERROR(INDEX($D$5:$D$20,MATCH(SMALL($O$5:$O$20,14),$O$5:$O$20,0)),"") | Q18: =IFERROR(INDEX(Carteira!$I$5:$I$20,MATCH(P18,Carteira!$A$5:$A$20,0)),"") | R18: =IFERROR(INDEX(Carteira!$H$5:$H$20,MATCH(P18,Carteira!$A$5:$A$20,0)),"") | T18: =IF(AND(Carteira!AC18=1,OR(Carteira!C18>0,SUMIFS(Carteira!$C$5:$C$20,Carteira!$AC$5:$AC$20,1)=0)),N(Carteira!W18)+ROW()/1E9,"") | U18: =IFERROR(INDEX($D$5:$D$20,MATCH(LARGE($T$5:$T$20,14),$T$5:$T$20,0)),"") | V18: =IFERROR(INDEX(Carteira!$W$5:$W$20,MATCH(U18,Carteira!$A$5:$A$20,0)),"") | X18: =IF(AND(Carteira!AC18=1,OR(Carteira!C18>0,SUMIFS(Carteira!$C$5:$C$20,Carteira!$AC$5:$AC$20,1)=0)),N(Carteira!J18)+ROW()/1E9,"") | Y18: =IFERROR(INDEX($D$5:$D$20,MATCH(LARGE($X$5:$X$20,14),$X$5:$X$20,0)),"") | Z18: =IFERROR(INDEX(Carteira!$J$5:$J$20,MATCH(Y18,Carteira!$A$5:$A$20,0)),"")
D19: =Carteira!A19 | F19: =IF(AND(Carteira!AC19=1,OR(Carteira!C19>0,SUMIFS(Carteira!$C$5:$C$20,Carteira!$AC$5:$AC$20,1)=0)),N(Carteira!G19)+ROW()/1E9,"") | G19: =IFERROR(INDEX($D$5:$D$20,MATCH(LARGE($F$5:$F$20,15),$F$5:$F$20,0)),"") | H19: =IFERROR(INDEX(Carteira!$G$5:$G$20,MATCH(G19,Carteira!$A$5:$A$20,0)),"") | J19: =IF(AND(Carteira!AC19=1,OR(Carteira!C19>0,SUMIFS(Carteira!$C$5:$C$20,Carteira!$AC$5:$AC$20,1)=0)),N(Carteira!I19)+ROW()/1E9,"") | K19: =IFERROR(INDEX($D$5:$D$20,MATCH(LARGE($J$5:$J$20,15),$J$5:$J$20,0)),"") | L19: =IFERROR(INDEX(Carteira!$I$5:$I$20,MATCH(K19,Carteira!$A$5:$A$20,0)),"") | M19: =IFERROR(INDEX(Carteira!$H$5:$H$20,MATCH(K19,Carteira!$A$5:$A$20,0)),"") | O19: =IF(AND(Carteira!AC19=1,OR(Carteira!C19>0,SUMIFS(Carteira!$C$5:$C$20,Carteira!$AC$5:$AC$20,1)=0)),N(Carteira!I19)+ROW()/1E9,"") | P19: =IFERROR(INDEX($D$5:$D$20,MATCH(SMALL($O$5:$O$20,15),$O$5:$O$20,0)),"") | Q19: =IFERROR(INDEX(Carteira!$I$5:$I$20,MATCH(P19,Carteira!$A$5:$A$20,0)),"") | R19: =IFERROR(INDEX(Carteira!$H$5:$H$20,MATCH(P19,Carteira!$A$5:$A$20,0)),"") | T19: =IF(AND(Carteira!AC19=1,OR(Carteira!C19>0,SUMIFS(Carteira!$C$5:$C$20,Carteira!$AC$5:$AC$20,1)=0)),N(Carteira!W19)+ROW()/1E9,"") | U19: =IFERROR(INDEX($D$5:$D$20,MATCH(LARGE($T$5:$T$20,15),$T$5:$T$20,0)),"") | V19: =IFERROR(INDEX(Carteira!$W$5:$W$20,MATCH(U19,Carteira!$A$5:$A$20,0)),"") | X19: =IF(AND(Carteira!AC19=1,OR(Carteira!C19>0,SUMIFS(Carteira!$C$5:$C$20,Carteira!$AC$5:$AC$20,1)=0)),N(Carteira!J19)+ROW()/1E9,"") | Y19: =IFERROR(INDEX($D$5:$D$20,MATCH(LARGE($X$5:$X$20,15),$X$5:$X$20,0)),"") | Z19: =IFERROR(INDEX(Carteira!$J$5:$J$20,MATCH(Y19,Carteira!$A$5:$A$20,0)),"")
D20: =Carteira!A20 | F20: =IF(AND(Carteira!AC20=1,OR(Carteira!C20>0,SUMIFS(Carteira!$C$5:$C$20,Carteira!$AC$5:$AC$20,1)=0)),N(Carteira!G20)+ROW()/1E9,"") | G20: =IFERROR(INDEX($D$5:$D$20,MATCH(LARGE($F$5:$F$20,16),$F$5:$F$20,0)),"") | H20: =IFERROR(INDEX(Carteira!$G$5:$G$20,MATCH(G20,Carteira!$A$5:$A$20,0)),"") | J20: =IF(AND(Carteira!AC20=1,OR(Carteira!C20>0,SUMIFS(Carteira!$C$5:$C$20,Carteira!$AC$5:$AC$20,1)=0)),N(Carteira!I20)+ROW()/1E9,"") | K20: =IFERROR(INDEX($D$5:$D$20,MATCH(LARGE($J$5:$J$20,16),$J$5:$J$20,0)),"") | L20: =IFERROR(INDEX(Carteira!$I$5:$I$20,MATCH(K20,Carteira!$A$5:$A$20,0)),"") | M20: =IFERROR(INDEX(Carteira!$H$5:$H$20,MATCH(K20,Carteira!$A$5:$A$20,0)),"") | O20: =IF(AND(Carteira!AC20=1,OR(Carteira!C20>0,SUMIFS(Carteira!$C$5:$C$20,Carteira!$AC$5:$AC$20,1)=0)),N(Carteira!I20)+ROW()/1E9,"") | P20: =IFERROR(INDEX($D$5:$D$20,MATCH(SMALL($O$5:$O$20,16),$O$5:$O$20,0)),"") | Q20: =IFERROR(INDEX(Carteira!$I$5:$I$20,MATCH(P20,Carteira!$A$5:$A$20,0)),"") | R20: =IFERROR(INDEX(Carteira!$H$5:$H$20,MATCH(P20,Carteira!$A$5:$A$20,0)),"") | T20: =IF(AND(Carteira!AC20=1,OR(Carteira!C20>0,SUMIFS(Carteira!$C$5:$C$20,Carteira!$AC$5:$AC$20,1)=0)),N(Carteira!W20)+ROW()/1E9,"") | U20: =IFERROR(INDEX($D$5:$D$20,MATCH(LARGE($T$5:$T$20,16),$T$5:$T$20,0)),"") | V20: =IFERROR(INDEX(Carteira!$W$5:$W$20,MATCH(U20,Carteira!$A$5:$A$20,0)),"") | X20: =IF(AND(Carteira!AC20=1,OR(Carteira!C20>0,SUMIFS(Carteira!$C$5:$C$20,Carteira!$AC$5:$AC$20,1)=0)),N(Carteira!J20)+ROW()/1E9,"") | Y20: =IFERROR(INDEX($D$5:$D$20,MATCH(LARGE($X$5:$X$20,16),$X$5:$X$20,0)),"") | Z20: =IFERROR(INDEX(Carteira!$J$5:$J$20,MATCH(Y20,Carteira!$A$5:$A$20,0)),"")
